# uncompyle6 version 3.9.0
# Python bytecode version base 3.7.0 (3394)
# Decompiled from: Python 3.7.16 (default, Dec  7 2022, 01:12:33) 
# [GCC 11.3.0]
# Embedded file name: T:\InGame\Gameplay\Scripts\Server\venues\zone_director_venue_proxy.py
# Compiled at: 2019-09-05 20:33:14
# Size of source mod 2**32: 1084 bytes

-- Stacks of completed symbols:
START ::= |- stmts . 
_ifstmts_jump ::= \e_c_stmts_opt . COME_FROM
_ifstmts_jump ::= \e_c_stmts_opt . ELSE
_ifstmts_jump ::= \e_c_stmts_opt . JUMP_ABSOLUTE JUMP_FORWARD \e__come_froms
_ifstmts_jump ::= \e_c_stmts_opt . JUMP_ABSOLUTE JUMP_FORWARD _come_froms
_ifstmts_jump ::= \e_c_stmts_opt . come_froms
_ifstmts_jump ::= c_stmts_opt . COME_FROM
_ifstmts_jump ::= c_stmts_opt . ELSE
_ifstmts_jump ::= c_stmts_opt . JUMP_ABSOLUTE JUMP_FORWARD \e__come_froms
_ifstmts_jump ::= c_stmts_opt . JUMP_ABSOLUTE JUMP_FORWARD _come_froms
_ifstmts_jump ::= c_stmts_opt . come_froms
_ifstmts_jump ::= c_stmts_opt COME_FROM . 
_ifstmts_jump ::= c_stmts_opt come_froms . 
_ifstmts_jumpl ::= _ifstmts_jump . 
_ifstmts_jumpl ::= c_stmts . JUMP_BACK
_stmts ::= _stmts . stmt
_stmts ::= _stmts stmt . 
_stmts ::= stmt . 
and ::= expr . JUMP_IF_FALSE_OR_POP expr \e_come_from_opt
and ::= expr . JUMP_IF_FALSE_OR_POP expr come_from_opt
and ::= expr . jifop_come_from expr
and ::= expr . jmp_false expr
and ::= expr . jmp_false expr COME_FROM
and ::= expr . jmp_false expr jmp_false
and ::= expr jmp_false . expr
and ::= expr jmp_false . expr COME_FROM
and ::= expr jmp_false . expr jmp_false
and ::= expr jmp_false expr . 
and ::= expr jmp_false expr . COME_FROM
and ::= expr jmp_false expr . jmp_false
and_not ::= expr . jmp_false expr POP_JUMP_IF_TRUE
and_not ::= expr jmp_false . expr POP_JUMP_IF_TRUE
and_not ::= expr jmp_false expr . POP_JUMP_IF_TRUE
assert2 ::= expr . jmp_true LOAD_GLOBAL expr CALL_FUNCTION_1 RAISE_VARARGS_1
assert2 ::= expr jmp_true . LOAD_GLOBAL expr CALL_FUNCTION_1 RAISE_VARARGS_1
assert2 ::= expr jmp_true LOAD_GLOBAL . expr CALL_FUNCTION_1 RAISE_VARARGS_1
assert_invert ::= testtrue . LOAD_GLOBAL RAISE_VARARGS_1
assert_invert ::= testtrue LOAD_GLOBAL . RAISE_VARARGS_1
assign ::= expr . DUP_TOP designList
assign ::= expr . store
assign ::= expr store . 
assign2 ::= expr . expr ROT_TWO store store
assign2 ::= expr expr . ROT_TWO store store
assign3 ::= expr . expr expr ROT_THREE ROT_TWO store store store
assign3 ::= expr expr . expr ROT_THREE ROT_TWO store store store
attribute ::= expr . LOAD_ATTR
attribute ::= expr LOAD_ATTR . 
attribute37 ::= expr . LOAD_METHOD
attribute37 ::= expr LOAD_METHOD . 
aug_assign1 ::= expr . expr inplace_op ROT_THREE STORE_SUBSCR
aug_assign1 ::= expr . expr inplace_op store
aug_assign1 ::= expr expr . inplace_op ROT_THREE STORE_SUBSCR
aug_assign1 ::= expr expr . inplace_op store
aug_assign2 ::= expr . DUP_TOP LOAD_ATTR expr inplace_op ROT_TWO STORE_ATTR
await_expr ::= expr . GET_AWAITABLE LOAD_CONST YIELD_FROM
bin_op ::= expr . expr binary_operator
bin_op ::= expr expr . binary_operator
build_class ::= LOAD_BUILD_CLASS . mkfunc CALL_FUNCTION_1
build_class ::= LOAD_BUILD_CLASS . mkfunc expr call CALL_FUNCTION_3
build_class ::= LOAD_BUILD_CLASS . mkfunc expr call expr CALL_FUNCTION_4
build_class ::= LOAD_BUILD_CLASS . mkfunc expr expr CALL_FUNCTION_3
build_class ::= LOAD_BUILD_CLASS mkfunc . CALL_FUNCTION_1
build_class ::= LOAD_BUILD_CLASS mkfunc . expr call CALL_FUNCTION_3
build_class ::= LOAD_BUILD_CLASS mkfunc . expr call expr CALL_FUNCTION_4
build_class ::= LOAD_BUILD_CLASS mkfunc . expr expr CALL_FUNCTION_3
build_class ::= LOAD_BUILD_CLASS mkfunc expr . call CALL_FUNCTION_3
build_class ::= LOAD_BUILD_CLASS mkfunc expr . call expr CALL_FUNCTION_4
build_class ::= LOAD_BUILD_CLASS mkfunc expr . expr CALL_FUNCTION_3
build_class ::= LOAD_BUILD_CLASS mkfunc expr expr . CALL_FUNCTION_3
build_map_unpack_with_call ::= expr . expr BUILD_MAP_UNPACK_WITH_CALL_2
build_map_unpack_with_call ::= expr expr . BUILD_MAP_UNPACK_WITH_CALL_2
c_stmts ::= _stmts . 
c_stmts ::= _stmts . lastc_stmt
c_stmts ::= _stmts lastc_stmt . 
c_stmts_opt ::= c_stmts . 
call ::= expr . CALL_FUNCTION_0
call ::= expr . CALL_METHOD_0
call ::= expr . pos_arg CALL_FUNCTION_1
call ::= expr . pos_arg pos_arg pos_arg CALL_FUNCTION_3
call ::= expr . pos_arg pos_arg pos_arg pos_arg CALL_FUNCTION_4
call ::= expr CALL_FUNCTION_0 . 
call ::= expr CALL_METHOD_0 . 
call ::= expr pos_arg . CALL_FUNCTION_1
call ::= expr pos_arg . pos_arg pos_arg CALL_FUNCTION_3
call ::= expr pos_arg . pos_arg pos_arg pos_arg CALL_FUNCTION_4
call ::= expr pos_arg CALL_FUNCTION_1 . 
call ::= expr pos_arg pos_arg . pos_arg CALL_FUNCTION_3
call ::= expr pos_arg pos_arg . pos_arg pos_arg CALL_FUNCTION_4
call ::= expr pos_arg pos_arg pos_arg . CALL_FUNCTION_3
call ::= expr pos_arg pos_arg pos_arg . pos_arg CALL_FUNCTION_4
call_ex_kw ::= expr . expr build_map_unpack_with_call CALL_FUNCTION_EX_KW
call_ex_kw ::= expr expr . build_map_unpack_with_call CALL_FUNCTION_EX_KW
call_ex_kw4 ::= expr . expr expr CALL_FUNCTION_EX_KW
call_ex_kw4 ::= expr expr . expr CALL_FUNCTION_EX_KW
call_ex_kw4 ::= expr expr expr . CALL_FUNCTION_EX_KW
call_stmt ::= expr . POP_TOP
cf_jf_else ::= come_froms . JUMP_FORWARD ELSE
cf_jump_back ::= COME_FROM . JUMP_BACK
classdefdeco1 ::= expr . classdefdeco1 CALL_FUNCTION_1
classdefdeco1 ::= expr . classdefdeco2 CALL_FUNCTION_1
come_from_opt ::= COME_FROM . 
come_froms ::= COME_FROM . 
come_froms ::= come_froms . COME_FROM
compare ::= compare_single . 
compare_chained ::= expr . compare_chained1 ROT_TWO POP_TOP \e__come_froms
compare_chained ::= expr . compare_chained1 ROT_TWO POP_TOP _come_froms
compare_chained1 ::= expr . DUP_TOP ROT_THREE COMPARE_OP JUMP_IF_FALSE_OR_POP compare_chained1 COME_FROM
compare_chained1 ::= expr . DUP_TOP ROT_THREE COMPARE_OP JUMP_IF_FALSE_OR_POP compare_chained2 COME_FROM
compare_chained1_false_37 ::= expr . DUP_TOP ROT_THREE COMPARE_OP POP_JUMP_IF_FALSE compare_chained2b_false_37 POP_TOP _jump COME_FROM
compare_chained1_false_37 ::= expr . DUP_TOP ROT_THREE COMPARE_OP POP_JUMP_IF_FALSE compare_chained2c_37 POP_TOP JUMP_FORWARD COME_FROM
compare_chained1a_37 ::= expr . DUP_TOP ROT_THREE COMPARE_OP POP_JUMP_IF_FALSE
compare_chained1a_37 ::= expr . DUP_TOP ROT_THREE COMPARE_OP POP_JUMP_IF_FALSE compare_chained2a_37 COME_FROM POP_TOP COME_FROM
compare_chained1b_false_37 ::= expr . DUP_TOP ROT_THREE COMPARE_OP POP_JUMP_IF_FALSE compare_chained2b_false_37 POP_TOP _jump COME_FROM
compare_chained1c_37 ::= expr . DUP_TOP ROT_THREE COMPARE_OP POP_JUMP_IF_FALSE compare_chained2a_37 POP_TOP
compare_chained2_false_37 ::= expr . DUP_TOP ROT_THREE COMPARE_OP POP_JUMP_IF_FALSE compare_chained2a_false_37 POP_TOP JUMP_BACK COME_FROM
compare_chained37 ::= expr . compare_chained1a_37
compare_chained37 ::= expr . compare_chained1c_37
compare_chained37_false ::= expr . compare_chained1_false_37
compare_chained37_false ::= expr . compare_chained1b_false_37
compare_chained37_false ::= expr . compare_chained2_false_37
compare_single ::= expr . expr COMPARE_OP
compare_single ::= expr expr . COMPARE_OP
compare_single ::= expr expr COMPARE_OP . 
continues ::= _stmts . lastl_stmt continue
continues ::= _stmts lastl_stmt . continue
dict ::= expr . LOAD_CONST BUILD_CONST_KEY_MAP_1
else_suite ::= suite_stmts . 
expr ::= LOAD_CODE . 
expr ::= LOAD_FAST . 
expr ::= LOAD_GLOBAL . 
expr ::= LOAD_STR . 
expr ::= attribute . 
expr ::= attribute37 . 
expr ::= call . 
expr ::= compare . 
expr ::= or . 
expr_jit ::= expr . JUMP_IF_TRUE
expr_jitop ::= expr . JUMP_IF_TRUE_OR_POP
expr_jt ::= expr . jmp_true
expr_jt ::= expr jmp_true . 
expr_pjit ::= expr . POP_JUMP_IF_TRUE
expr_pjit ::= expr POP_JUMP_IF_TRUE . 
expr_pjit_come_from ::= expr . POP_JUMP_IF_TRUE COME_FROM
expr_pjit_come_from ::= expr POP_JUMP_IF_TRUE . COME_FROM
expr_stmt ::= expr . POP_TOP
if_exp ::= expr . jmp_false expr jf_cf expr COME_FROM
if_exp ::= expr . jmp_false expr jump_absolute_else expr
if_exp ::= expr jmp_false . expr jf_cf expr COME_FROM
if_exp ::= expr jmp_false . expr jump_absolute_else expr
if_exp ::= expr jmp_false expr . jf_cf expr COME_FROM
if_exp ::= expr jmp_false expr . jump_absolute_else expr
if_exp37 ::= expr . expr jf_cfs expr COME_FROM
if_exp37 ::= expr expr . jf_cfs expr COME_FROM
if_exp_37b ::= expr . jmp_false expr POP_JUMP_IF_FALSE jump_forward_else expr
if_exp_37b ::= expr jmp_false . expr POP_JUMP_IF_FALSE jump_forward_else expr
if_exp_37b ::= expr jmp_false expr . POP_JUMP_IF_FALSE jump_forward_else expr
if_exp_lambda ::= expr . jmp_false expr return_if_lambda return_stmt_lambda LAMBDA_MARKER
if_exp_lambda ::= expr jmp_false . expr return_if_lambda return_stmt_lambda LAMBDA_MARKER
if_exp_lambda ::= expr jmp_false expr . return_if_lambda return_stmt_lambda LAMBDA_MARKER
if_exp_not ::= expr . jmp_true expr jump_forward_else expr COME_FROM
if_exp_not ::= expr jmp_true . expr jump_forward_else expr COME_FROM
if_exp_not ::= expr jmp_true expr . jump_forward_else expr COME_FROM
if_exp_not_lambda ::= expr . jmp_true expr return_if_lambda return_stmt_lambda LAMBDA_MARKER
if_exp_not_lambda ::= expr jmp_true . expr return_if_lambda return_stmt_lambda LAMBDA_MARKER
if_exp_not_lambda ::= expr jmp_true expr . return_if_lambda return_stmt_lambda LAMBDA_MARKER
if_exp_true ::= expr . JUMP_FORWARD expr COME_FROM
ifelsestmt ::= testexpr . c_stmts come_froms else_suite come_froms
ifelsestmt ::= testexpr . c_stmts_opt JUMP_FORWARD else_suite \e__come_froms
ifelsestmt ::= testexpr . c_stmts_opt JUMP_FORWARD else_suite \e_opt_come_from_except
ifelsestmt ::= testexpr . c_stmts_opt JUMP_FORWARD else_suite _come_froms
ifelsestmt ::= testexpr . c_stmts_opt JUMP_FORWARD else_suite opt_come_from_except
ifelsestmt ::= testexpr . c_stmts_opt jf_cfs else_suite \e_opt_come_from_except
ifelsestmt ::= testexpr . c_stmts_opt jf_cfs else_suite opt_come_from_except
ifelsestmt ::= testexpr . c_stmts_opt jump_forward_else else_suite \e__come_froms
ifelsestmt ::= testexpr . c_stmts_opt jump_forward_else else_suite _come_froms
ifelsestmt ::= testexpr . stmts jf_cfs \e_else_suite_opt \e_opt_come_from_except
ifelsestmt ::= testexpr . stmts jf_cfs \e_else_suite_opt opt_come_from_except
ifelsestmt ::= testexpr . stmts jf_cfs else_suite_opt \e_opt_come_from_except
ifelsestmt ::= testexpr . stmts jf_cfs else_suite_opt opt_come_from_except
ifelsestmt ::= testexpr \e_c_stmts_opt . JUMP_FORWARD else_suite \e__come_froms
ifelsestmt ::= testexpr \e_c_stmts_opt . JUMP_FORWARD else_suite \e_opt_come_from_except
ifelsestmt ::= testexpr \e_c_stmts_opt . JUMP_FORWARD else_suite _come_froms
ifelsestmt ::= testexpr \e_c_stmts_opt . JUMP_FORWARD else_suite opt_come_from_except
ifelsestmt ::= testexpr \e_c_stmts_opt . jf_cfs else_suite \e_opt_come_from_except
ifelsestmt ::= testexpr \e_c_stmts_opt . jf_cfs else_suite opt_come_from_except
ifelsestmt ::= testexpr \e_c_stmts_opt . jump_forward_else else_suite \e__come_froms
ifelsestmt ::= testexpr \e_c_stmts_opt . jump_forward_else else_suite _come_froms
ifelsestmt ::= testexpr c_stmts . come_froms else_suite come_froms
ifelsestmt ::= testexpr c_stmts come_froms . else_suite come_froms
ifelsestmt ::= testexpr c_stmts come_froms else_suite . come_froms
ifelsestmt ::= testexpr c_stmts come_froms else_suite come_froms . 
ifelsestmt ::= testexpr c_stmts_opt . JUMP_FORWARD else_suite \e__come_froms
ifelsestmt ::= testexpr c_stmts_opt . JUMP_FORWARD else_suite \e_opt_come_from_except
ifelsestmt ::= testexpr c_stmts_opt . JUMP_FORWARD else_suite _come_froms
ifelsestmt ::= testexpr c_stmts_opt . JUMP_FORWARD else_suite opt_come_from_except
ifelsestmt ::= testexpr c_stmts_opt . jf_cfs else_suite \e_opt_come_from_except
ifelsestmt ::= testexpr c_stmts_opt . jf_cfs else_suite opt_come_from_except
ifelsestmt ::= testexpr c_stmts_opt . jump_forward_else else_suite \e__come_froms
ifelsestmt ::= testexpr c_stmts_opt . jump_forward_else else_suite _come_froms
ifelsestmt ::= testexpr stmts . jf_cfs \e_else_suite_opt \e_opt_come_from_except
ifelsestmt ::= testexpr stmts . jf_cfs \e_else_suite_opt opt_come_from_except
ifelsestmt ::= testexpr stmts . jf_cfs else_suite_opt \e_opt_come_from_except
ifelsestmt ::= testexpr stmts . jf_cfs else_suite_opt opt_come_from_except
ifelsestmtc ::= testexpr . c_stmts_opt JUMP_ABSOLUTE else_suitec
ifelsestmtc ::= testexpr . c_stmts_opt JUMP_FORWARD else_suitec
ifelsestmtc ::= testexpr . c_stmts_opt jump_absolute_else else_suitec
ifelsestmtc ::= testexpr \e_c_stmts_opt . JUMP_ABSOLUTE else_suitec
ifelsestmtc ::= testexpr \e_c_stmts_opt . JUMP_FORWARD else_suitec
ifelsestmtc ::= testexpr \e_c_stmts_opt . jump_absolute_else else_suitec
ifelsestmtc ::= testexpr c_stmts_opt . JUMP_ABSOLUTE else_suitec
ifelsestmtc ::= testexpr c_stmts_opt . JUMP_FORWARD else_suitec
ifelsestmtc ::= testexpr c_stmts_opt . jump_absolute_else else_suitec
ifelsestmtl ::= testexpr . c_stmts_opt cf_jf_else else_suitel
ifelsestmtl ::= testexpr . c_stmts_opt cf_jump_back else_suitel
ifelsestmtl ::= testexpr . c_stmts_opt jb_cfs else_suitel
ifelsestmtl ::= testexpr . c_stmts_opt jb_else else_suitel
ifelsestmtl ::= testexpr . c_stmts_opt jump_forward_else else_suitec
ifelsestmtl ::= testexpr \e_c_stmts_opt . cf_jf_else else_suitel
ifelsestmtl ::= testexpr \e_c_stmts_opt . cf_jump_back else_suitel
ifelsestmtl ::= testexpr \e_c_stmts_opt . jb_cfs else_suitel
ifelsestmtl ::= testexpr \e_c_stmts_opt . jb_else else_suitel
ifelsestmtl ::= testexpr \e_c_stmts_opt . jump_forward_else else_suitec
ifelsestmtl ::= testexpr c_stmts_opt . cf_jf_else else_suitel
ifelsestmtl ::= testexpr c_stmts_opt . cf_jump_back else_suitel
ifelsestmtl ::= testexpr c_stmts_opt . jb_cfs else_suitel
ifelsestmtl ::= testexpr c_stmts_opt . jb_else else_suitel
ifelsestmtl ::= testexpr c_stmts_opt . jump_forward_else else_suitec
ifelsestmtr ::= testexpr . return_if_stmts returns
iflaststmt ::= testexpr . c_stmts
iflaststmt ::= testexpr . c_stmts JUMP_ABSOLUTE
iflaststmt ::= testexpr . c_stmts_opt JUMP_FORWARD
iflaststmt ::= testexpr \e_c_stmts_opt . JUMP_FORWARD
iflaststmt ::= testexpr c_stmts . 
iflaststmt ::= testexpr c_stmts . JUMP_ABSOLUTE
iflaststmt ::= testexpr c_stmts_opt . JUMP_FORWARD
iflaststmtl ::= testexpr . c_stmts
iflaststmtl ::= testexpr . c_stmts JUMP_BACK
iflaststmtl ::= testexpr . c_stmts JUMP_BACK COME_FROM_LOOP
iflaststmtl ::= testexpr . c_stmts JUMP_BACK POP_BLOCK
iflaststmtl ::= testexpr c_stmts . 
iflaststmtl ::= testexpr c_stmts . JUMP_BACK
iflaststmtl ::= testexpr c_stmts . JUMP_BACK COME_FROM_LOOP
iflaststmtl ::= testexpr c_stmts . JUMP_BACK POP_BLOCK
ifstmt ::= testexpr . _ifstmts_jump
ifstmt ::= testexpr _ifstmts_jump . 
ifstmtl ::= testexpr . _ifstmts_jumpl
ifstmtl ::= testexpr _ifstmts_jumpl . 
jb_cfs ::= \e_come_from_opt . JUMP_BACK come_froms
jb_cfs ::= come_from_opt . JUMP_BACK come_froms
jmp_false ::= POP_JUMP_IF_FALSE . 
jmp_true ::= POP_JUMP_IF_TRUE . 
jump_absolute_else ::= come_froms . _jump COME_FROM
kvlist_1 ::= expr . expr BUILD_MAP_1
kvlist_1 ::= expr expr . BUILD_MAP_1
lastc_stmt ::= iflaststmt . 
lastl_stmt ::= iflaststmtl . 
mkfunc ::= LOAD_CODE . LOAD_STR MAKE_FUNCTION_0
mkfunc ::= LOAD_CODE LOAD_STR . MAKE_FUNCTION_0
mkfunc ::= LOAD_CODE LOAD_STR MAKE_FUNCTION_0 . 
mkfunc ::= expr . load_closure LOAD_CODE LOAD_STR MAKE_FUNCTION_10
mkfuncdeco ::= expr . mkfuncdeco CALL_FUNCTION_1
mkfuncdeco ::= expr . mkfuncdeco0 CALL_FUNCTION_1
or ::= expr_jt . expr
or ::= expr_jt . expr COME_FROM
or ::= expr_jt expr . 
or ::= expr_jt expr . COME_FROM
or ::= expr_pjit . expr POP_JUMP_IF_FALSE COME_FROM
or ::= expr_pjit expr . POP_JUMP_IF_FALSE COME_FROM
pos_arg ::= expr . 
raise_stmt1 ::= expr . RAISE_VARARGS_1
raise_stmt1 ::= expr RAISE_VARARGS_1 . 
ret_and ::= expr . JUMP_IF_FALSE_OR_POP return_expr_or_cond COME_FROM
ret_or ::= expr . JUMP_IF_TRUE_OR_POP return_expr_or_cond COME_FROM
return ::= return_expr . RETURN_END_IF
return ::= return_expr . RETURN_VALUE
return ::= return_expr . RETURN_VALUE COME_FROM
return ::= return_expr RETURN_VALUE . 
return ::= return_expr RETURN_VALUE . COME_FROM
return ::= return_expr RETURN_VALUE COME_FROM . 
return_expr ::= expr . 
return_expr_lambda ::= return_expr . RETURN_VALUE_LAMBDA
return_expr_lambda ::= return_expr . RETURN_VALUE_LAMBDA LAMBDA_MARKER
return_if_stmt ::= return_expr . RETURN_END_IF
return_if_stmt ::= return_expr . RETURN_END_IF POP_BLOCK
return_if_stmts ::= _stmts . return_if_stmt \e__come_froms
return_if_stmts ::= _stmts . return_if_stmt _come_froms
returns ::= _stmts . return
returns ::= _stmts . return_if_stmt
sstmt ::= return . RETURN_LAST
sstmt ::= sstmt . RETURN_LAST
sstmt ::= stmt . 
stmt ::= assign . 
stmt ::= ifstmt . 
stmt ::= ifstmtl . 
stmt ::= raise_stmt1 . 
stmt ::= return . 
stmts ::= sstmt . 
stmts ::= stmts . sstmt
stmts ::= stmts sstmt . 
store ::= STORE_FAST . 
store ::= expr . STORE_ATTR
store_subscript ::= expr . expr STORE_SUBSCR
subscript ::= expr . expr BINARY_SUBSCR
subscript ::= expr expr . BINARY_SUBSCR
subscript2 ::= expr . expr DUP_TOP_TWO BINARY_SUBSCR
subscript2 ::= expr expr . DUP_TOP_TWO BINARY_SUBSCR
suite_stmts ::= _stmts . 
testexpr ::= testfalse . 
testexpr ::= testtrue . 
testexpr_cf ::= testexpr . come_froms
testfalse ::= expr . jmp_false
testfalse ::= expr jmp_false . 
testfalse ::= or . jmp_false COME_FROM
testfalse_not_and ::= expr . jmp_false expr jmp_true COME_FROM
testfalse_not_and ::= expr jmp_false . expr jmp_true COME_FROM
testfalse_not_and ::= expr jmp_false expr . jmp_true COME_FROM
testfalse_not_or ::= expr . jmp_false expr jmp_false COME_FROM
testfalse_not_or ::= expr jmp_false . expr jmp_false COME_FROM
testfalse_not_or ::= expr jmp_false expr . jmp_false COME_FROM
testfalsel ::= expr . jmp_true
testtrue ::= expr . jmp_true
testtrue ::= expr jmp_true . 
unary_not ::= expr . UNARY_NOT
unary_op ::= expr . unary_operator
yield ::= expr . YIELD_VALUE
yield_from ::= expr . GET_YIELD_FROM_ITER LOAD_CONST YIELD_FROM
Instruction context:
   
 L.  20        52  LOAD_BUILD_CLASS 
                  54  LOAD_CODE                <code_object _ZoneDirectorVenueProxy>
                  56  LOAD_STR                 '_ZoneDirectorVenueProxy'
                  58  MAKE_FUNCTION_0          'Neither defaults, keyword-only args, annotations, nor closures'
                  60  LOAD_STR                 '_ZoneDirectorVenueProxy'
                  62  LOAD_FAST                'cls'
                  64  LOAD_GLOBAL              type
                  66  LOAD_FAST                'venue_zone_director'
                  68  CALL_FUNCTION_1       1  '1 positional argument'
->                70  CALL_FUNCTION_4       4  '4 positional arguments'
                  72  STORE_FAST               '_ZoneDirectorVenueProxy'
from zone_director import ZoneDirectorBase
import services

class ZoneDirectorVenueProxy(ZoneDirectorBase):

    def __new__--- This code section failed: ---

 L.  14         0  LOAD_FAST                'proxy'
                2  POP_JUMP_IF_TRUE     38  'to 38'

 L.  15         4  LOAD_GLOBAL              super
                6  CALL_FUNCTION_0       0  '0 positional arguments'
                8  LOAD_ATTR                __new__
               10  STORE_FAST               'new'

 L.  16        12  LOAD_FAST                'new'
               14  LOAD_GLOBAL              object
               16  LOAD_ATTR                __new__
               18  COMPARE_OP               is
               20  POP_JUMP_IF_FALSE    30  'to 30'

 L.  17        22  LOAD_FAST                'new'
               24  LOAD_FAST                'cls'
               26  CALL_FUNCTION_1       1  '1 positional argument'
               28  RETURN_VALUE     
             30_0  COME_FROM            20  '20'

 L.  18        30  LOAD_GLOBAL              TypeError
               32  LOAD_STR                 'super() of _ZoneDirectorVenueProxy cannot override __new__'
               34  CALL_FUNCTION_1       1  '1 positional argument'
               36  RAISE_VARARGS_1       1  'exception instance'
             38_0  COME_FROM             2  '2'

 L.  19        38  LOAD_GLOBAL              services
               40  LOAD_METHOD              venue_service
               42  CALL_METHOD_0         0  '0 positional arguments'
               44  LOAD_ATTR                active_venue
               46  LOAD_METHOD              zone_director
               48  CALL_METHOD_0         0  '0 positional arguments'
               50  STORE_FAST               'venue_zone_director'

 L.  20        52  LOAD_BUILD_CLASS 
               54  LOAD_CODE                <code_object _ZoneDirectorVenueProxy>
               56  LOAD_STR                 '_ZoneDirectorVenueProxy'
               58  MAKE_FUNCTION_0          'Neither defaults, keyword-only args, annotations, nor closures'
               60  LOAD_STR                 '_ZoneDirectorVenueProxy'
               62  LOAD_FAST                'cls'
               64  LOAD_GLOBAL              type
               66  LOAD_FAST                'venue_zone_director'
               68  CALL_FUNCTION_1       1  '1 positional argument'
               70  CALL_FUNCTION_4       4  '4 positional arguments'
               72  STORE_FAST               '_ZoneDirectorVenueProxy'

 L.  25        74  LOAD_FAST                '_ZoneDirectorVenueProxy'
               76  LOAD_FAST                'args'
               78  LOAD_STR                 'proxy'
               80  LOAD_CONST               False
               82  BUILD_MAP_1           1 
               84  LOAD_FAST                'kwargs'
               86  BUILD_MAP_UNPACK_WITH_CALL_2     2 
               88  CALL_FUNCTION_EX_KW     1  'keyword and positional arguments'
               90  RETURN_VALUE     
               -1  RETURN_LAST      

Parse error at or near `CALL_FUNCTION_4' instruction at offset 70

    INSTANCE_SUBCLASSES_ONLY = True
