# uncompyle6 version 3.9.0
# Python bytecode version base 3.7.0 (3394)
# Decompiled from: Python 3.7.16 (default, Dec  7 2022, 01:12:33) 
# [GCC 11.3.0]
# Embedded file name: T:\InGame\Gameplay\Scripts\Server\socials\geometry.py
# Compiled at: 2017-06-29 18:59:38
# Size of source mod 2**32: 15320 bytes

-- Stacks of completed symbols:
START ::= |- stmts . 
_come_froms ::= \e__come_froms . COME_FROM
_come_froms ::= \e__come_froms . COME_FROM_LOOP
_come_froms ::= \e__come_froms COME_FROM . 
_come_froms ::= _come_froms . COME_FROM
_come_froms ::= _come_froms . COME_FROM_LOOP
_come_froms ::= _come_froms COME_FROM . 
_ifstmts_jump ::= COME_FROM . c_stmts come_froms
_ifstmts_jump ::= \e_c_stmts_opt . COME_FROM
_ifstmts_jump ::= \e_c_stmts_opt . ELSE
_ifstmts_jump ::= \e_c_stmts_opt . JUMP_ABSOLUTE JUMP_FORWARD \e__come_froms
_ifstmts_jump ::= \e_c_stmts_opt . JUMP_ABSOLUTE JUMP_FORWARD _come_froms
_ifstmts_jump ::= \e_c_stmts_opt . come_froms
_ifstmts_jump ::= \e_c_stmts_opt COME_FROM . 
_ifstmts_jump ::= \e_c_stmts_opt come_froms . 
_ifstmts_jump ::= c_stmts_opt . COME_FROM
_ifstmts_jump ::= c_stmts_opt . ELSE
_ifstmts_jump ::= c_stmts_opt . JUMP_ABSOLUTE JUMP_FORWARD \e__come_froms
_ifstmts_jump ::= c_stmts_opt . JUMP_ABSOLUTE JUMP_FORWARD _come_froms
_ifstmts_jump ::= c_stmts_opt . come_froms
_ifstmts_jump ::= c_stmts_opt COME_FROM . 
_ifstmts_jump ::= c_stmts_opt come_froms . 
_ifstmts_jumpl ::= COME_FROM . c_stmts JUMP_BACK
_ifstmts_jumpl ::= COME_FROM . c_stmts JUMP_FORWARD
_ifstmts_jumpl ::= _ifstmts_jump . 
_ifstmts_jumpl ::= c_stmts . JUMP_BACK
_ifstmts_jumpl ::= c_stmts JUMP_BACK . 
_stmts ::= _stmts . stmt
_stmts ::= _stmts stmt . 
_stmts ::= stmt . 
and ::= expr . JUMP_IF_FALSE_OR_POP expr \e_come_from_opt
and ::= expr . JUMP_IF_FALSE_OR_POP expr come_from_opt
and ::= expr . jifop_come_from expr
and ::= expr . jmp_false expr
and ::= expr . jmp_false expr COME_FROM
and ::= expr . jmp_false expr jmp_false
and ::= expr jmp_false . expr
and ::= expr jmp_false . expr COME_FROM
and ::= expr jmp_false . expr jmp_false
and ::= expr jmp_false expr . 
and ::= expr jmp_false expr . COME_FROM
and ::= expr jmp_false expr . jmp_false
and ::= expr jmp_false expr jmp_false . 
and_not ::= expr . jmp_false expr POP_JUMP_IF_TRUE
and_not ::= expr jmp_false . expr POP_JUMP_IF_TRUE
and_not ::= expr jmp_false expr . POP_JUMP_IF_TRUE
assert2 ::= expr . jmp_true LOAD_GLOBAL expr CALL_FUNCTION_1 RAISE_VARARGS_1
assert2 ::= expr jmp_true . LOAD_GLOBAL expr CALL_FUNCTION_1 RAISE_VARARGS_1
assert_invert ::= testtrue . LOAD_GLOBAL RAISE_VARARGS_1
assign ::= expr . DUP_TOP designList
assign ::= expr . store
assign ::= expr store . 
assign2 ::= expr . expr ROT_TWO store store
assign2 ::= expr expr . ROT_TWO store store
assign3 ::= expr . expr expr ROT_THREE ROT_TWO store store store
assign3 ::= expr expr . expr ROT_THREE ROT_TWO store store store
assign3 ::= expr expr expr . ROT_THREE ROT_TWO store store store
async_for_stmt ::= setup_loop . expr GET_AITER LOAD_CONST YIELD_FROM SETUP_EXCEPT GET_ANEXT LOAD_CONST YIELD_FROM store POP_BLOCK JUMP_FORWARD COME_FROM_EXCEPT DUP_TOP LOAD_GLOBAL COMPARE_OP POP_JUMP_IF_FALSE POP_TOP POP_TOP POP_TOP POP_EXCEPT POP_BLOCK JUMP_ABSOLUTE END_FINALLY COME_FROM for_block POP_BLOCK COME_FROM_LOOP
async_for_stmt ::= setup_loop . expr GET_AITER SETUP_EXCEPT GET_ANEXT LOAD_CONST YIELD_FROM store POP_BLOCK JUMP_FORWARD COME_FROM_EXCEPT DUP_TOP LOAD_GLOBAL COMPARE_OP POP_JUMP_IF_TRUE END_FINALLY COME_FROM for_block COME_FROM POP_TOP POP_TOP POP_TOP POP_EXCEPT POP_TOP POP_BLOCK COME_FROM_LOOP
async_for_stmt ::= setup_loop expr . GET_AITER LOAD_CONST YIELD_FROM SETUP_EXCEPT GET_ANEXT LOAD_CONST YIELD_FROM store POP_BLOCK JUMP_FORWARD COME_FROM_EXCEPT DUP_TOP LOAD_GLOBAL COMPARE_OP POP_JUMP_IF_FALSE POP_TOP POP_TOP POP_TOP POP_EXCEPT POP_BLOCK JUMP_ABSOLUTE END_FINALLY COME_FROM for_block POP_BLOCK COME_FROM_LOOP
async_for_stmt ::= setup_loop expr . GET_AITER SETUP_EXCEPT GET_ANEXT LOAD_CONST YIELD_FROM store POP_BLOCK JUMP_FORWARD COME_FROM_EXCEPT DUP_TOP LOAD_GLOBAL COMPARE_OP POP_JUMP_IF_TRUE END_FINALLY COME_FROM for_block COME_FROM POP_TOP POP_TOP POP_TOP POP_EXCEPT POP_TOP POP_BLOCK COME_FROM_LOOP
async_for_stmt37 ::= setup_loop . expr GET_AITER \e__come_froms SETUP_EXCEPT GET_ANEXT LOAD_CONST YIELD_FROM store POP_BLOCK JUMP_BACK COME_FROM_EXCEPT DUP_TOP LOAD_GLOBAL COMPARE_OP POP_JUMP_IF_TRUE END_FINALLY for_block COME_FROM POP_TOP POP_TOP POP_TOP POP_EXCEPT POP_TOP POP_BLOCK COME_FROM_LOOP
async_for_stmt37 ::= setup_loop . expr GET_AITER _come_froms SETUP_EXCEPT GET_ANEXT LOAD_CONST YIELD_FROM store POP_BLOCK JUMP_BACK COME_FROM_EXCEPT DUP_TOP LOAD_GLOBAL COMPARE_OP POP_JUMP_IF_TRUE END_FINALLY for_block COME_FROM POP_TOP POP_TOP POP_TOP POP_EXCEPT POP_TOP POP_BLOCK COME_FROM_LOOP
async_for_stmt37 ::= setup_loop expr . GET_AITER \e__come_froms SETUP_EXCEPT GET_ANEXT LOAD_CONST YIELD_FROM store POP_BLOCK JUMP_BACK COME_FROM_EXCEPT DUP_TOP LOAD_GLOBAL COMPARE_OP POP_JUMP_IF_TRUE END_FINALLY for_block COME_FROM POP_TOP POP_TOP POP_TOP POP_EXCEPT POP_TOP POP_BLOCK COME_FROM_LOOP
async_for_stmt37 ::= setup_loop expr . GET_AITER _come_froms SETUP_EXCEPT GET_ANEXT LOAD_CONST YIELD_FROM store POP_BLOCK JUMP_BACK COME_FROM_EXCEPT DUP_TOP LOAD_GLOBAL COMPARE_OP POP_JUMP_IF_TRUE END_FINALLY for_block COME_FROM POP_TOP POP_TOP POP_TOP POP_EXCEPT POP_TOP POP_BLOCK COME_FROM_LOOP
async_forelse_stmt ::= setup_loop . expr GET_AITER \e__come_froms SETUP_EXCEPT GET_ANEXT LOAD_CONST YIELD_FROM store POP_BLOCK JUMP_FORWARD COME_FROM_EXCEPT DUP_TOP LOAD_GLOBAL COMPARE_OP POP_JUMP_IF_TRUE END_FINALLY COME_FROM for_block COME_FROM POP_TOP POP_TOP POP_TOP POP_EXCEPT POP_TOP POP_BLOCK else_suite COME_FROM_LOOP
async_forelse_stmt ::= setup_loop . expr GET_AITER _come_froms SETUP_EXCEPT GET_ANEXT LOAD_CONST YIELD_FROM store POP_BLOCK JUMP_FORWARD COME_FROM_EXCEPT DUP_TOP LOAD_GLOBAL COMPARE_OP POP_JUMP_IF_TRUE END_FINALLY COME_FROM for_block COME_FROM POP_TOP POP_TOP POP_TOP POP_EXCEPT POP_TOP POP_BLOCK else_suite COME_FROM_LOOP
async_forelse_stmt ::= setup_loop expr . GET_AITER \e__come_froms SETUP_EXCEPT GET_ANEXT LOAD_CONST YIELD_FROM store POP_BLOCK JUMP_FORWARD COME_FROM_EXCEPT DUP_TOP LOAD_GLOBAL COMPARE_OP POP_JUMP_IF_TRUE END_FINALLY COME_FROM for_block COME_FROM POP_TOP POP_TOP POP_TOP POP_EXCEPT POP_TOP POP_BLOCK else_suite COME_FROM_LOOP
async_forelse_stmt ::= setup_loop expr . GET_AITER _come_froms SETUP_EXCEPT GET_ANEXT LOAD_CONST YIELD_FROM store POP_BLOCK JUMP_FORWARD COME_FROM_EXCEPT DUP_TOP LOAD_GLOBAL COMPARE_OP POP_JUMP_IF_TRUE END_FINALLY COME_FROM for_block COME_FROM POP_TOP POP_TOP POP_TOP POP_EXCEPT POP_TOP POP_BLOCK else_suite COME_FROM_LOOP
attribute ::= expr . LOAD_ATTR
attribute ::= expr LOAD_ATTR . 
attribute37 ::= expr . LOAD_METHOD
attribute37 ::= expr LOAD_METHOD . 
aug_assign1 ::= expr . expr inplace_op ROT_THREE STORE_SUBSCR
aug_assign1 ::= expr . expr inplace_op store
aug_assign1 ::= expr expr . inplace_op ROT_THREE STORE_SUBSCR
aug_assign1 ::= expr expr . inplace_op store
aug_assign2 ::= expr . DUP_TOP LOAD_ATTR expr inplace_op ROT_TWO STORE_ATTR
await_expr ::= expr . GET_AWAITABLE LOAD_CONST YIELD_FROM
bin_op ::= expr . expr binary_operator
bin_op ::= expr expr . binary_operator
bin_op ::= expr expr binary_operator . 
binary_operator ::= BINARY_MULTIPLY . 
c_stmts ::= _stmts . 
c_stmts ::= _stmts . lastc_stmt
c_stmts ::= _stmts lastc_stmt . 
c_stmts_opt ::= c_stmts . 
call ::= expr . CALL_FUNCTION_0
call ::= expr . CALL_METHOD_0
call ::= expr . expr CALL_METHOD_1
call ::= expr . expr expr CALL_METHOD_2
call ::= expr . expr expr expr CALL_METHOD_3
call ::= expr . pos_arg CALL_FUNCTION_1
call ::= expr . pos_arg pos_arg CALL_FUNCTION_2
call ::= expr . pos_arg pos_arg pos_arg CALL_FUNCTION_3
call ::= expr . pos_arg pos_arg pos_arg pos_arg CALL_FUNCTION_4
call ::= expr . pos_arg pos_arg pos_arg pos_arg pos_arg pos_arg CALL_FUNCTION_6
call ::= expr expr . CALL_METHOD_1
call ::= expr expr . expr CALL_METHOD_2
call ::= expr expr . expr expr CALL_METHOD_3
call ::= expr expr CALL_METHOD_1 . 
call ::= expr expr expr . CALL_METHOD_2
call ::= expr expr expr . expr CALL_METHOD_3
call ::= expr expr expr expr . CALL_METHOD_3
call ::= expr pos_arg . CALL_FUNCTION_1
call ::= expr pos_arg . pos_arg CALL_FUNCTION_2
call ::= expr pos_arg . pos_arg pos_arg CALL_FUNCTION_3
call ::= expr pos_arg . pos_arg pos_arg pos_arg CALL_FUNCTION_4
call ::= expr pos_arg . pos_arg pos_arg pos_arg pos_arg pos_arg CALL_FUNCTION_6
call ::= expr pos_arg CALL_FUNCTION_1 . 
call ::= expr pos_arg pos_arg . CALL_FUNCTION_2
call ::= expr pos_arg pos_arg . pos_arg CALL_FUNCTION_3
call ::= expr pos_arg pos_arg . pos_arg pos_arg CALL_FUNCTION_4
call ::= expr pos_arg pos_arg . pos_arg pos_arg pos_arg pos_arg CALL_FUNCTION_6
call ::= expr pos_arg pos_arg CALL_FUNCTION_2 . 
call ::= expr pos_arg pos_arg pos_arg . CALL_FUNCTION_3
call ::= expr pos_arg pos_arg pos_arg . pos_arg CALL_FUNCTION_4
call ::= expr pos_arg pos_arg pos_arg . pos_arg pos_arg pos_arg CALL_FUNCTION_6
call ::= expr pos_arg pos_arg pos_arg CALL_FUNCTION_3 . 
call ::= expr pos_arg pos_arg pos_arg pos_arg . CALL_FUNCTION_4
call ::= expr pos_arg pos_arg pos_arg pos_arg . pos_arg pos_arg CALL_FUNCTION_6
call ::= expr pos_arg pos_arg pos_arg pos_arg pos_arg . pos_arg CALL_FUNCTION_6
call ::= expr pos_arg pos_arg pos_arg pos_arg pos_arg pos_arg . CALL_FUNCTION_6
call ::= expr pos_arg pos_arg pos_arg pos_arg pos_arg pos_arg CALL_FUNCTION_6 . 
call_kw36 ::= expr . expr LOAD_CONST CALL_FUNCTION_KW_1
call_kw36 ::= expr . expr expr expr LOAD_CONST CALL_FUNCTION_KW_3
call_kw36 ::= expr . expr expr expr expr expr LOAD_CONST CALL_FUNCTION_KW_5
call_kw36 ::= expr expr . LOAD_CONST CALL_FUNCTION_KW_1
call_kw36 ::= expr expr . expr expr LOAD_CONST CALL_FUNCTION_KW_3
call_kw36 ::= expr expr . expr expr expr expr LOAD_CONST CALL_FUNCTION_KW_5
call_kw36 ::= expr expr expr . expr LOAD_CONST CALL_FUNCTION_KW_3
call_kw36 ::= expr expr expr . expr expr expr LOAD_CONST CALL_FUNCTION_KW_5
call_kw36 ::= expr expr expr expr . LOAD_CONST CALL_FUNCTION_KW_3
call_kw36 ::= expr expr expr expr . expr expr LOAD_CONST CALL_FUNCTION_KW_5
call_kw36 ::= expr expr expr expr expr . expr LOAD_CONST CALL_FUNCTION_KW_5
call_kw36 ::= expr expr expr expr expr expr . LOAD_CONST CALL_FUNCTION_KW_5
call_stmt ::= expr . POP_TOP
call_stmt ::= expr POP_TOP . 
cf_jf_else ::= come_froms . JUMP_FORWARD ELSE
cf_jump_back ::= COME_FROM . JUMP_BACK
classdefdeco1 ::= expr . classdefdeco1 CALL_FUNCTION_1
classdefdeco1 ::= expr . classdefdeco2 CALL_FUNCTION_1
come_from_loops ::= \e_come_from_loops . COME_FROM_LOOP
come_from_opt ::= COME_FROM . 
come_froms ::= COME_FROM . 
come_froms ::= come_froms . COME_FROM
come_froms ::= come_froms COME_FROM . 
compare ::= compare_single . 
compare_chained ::= expr . compare_chained1 ROT_TWO POP_TOP \e__come_froms
compare_chained ::= expr . compare_chained1 ROT_TWO POP_TOP _come_froms
compare_chained1 ::= expr . DUP_TOP ROT_THREE COMPARE_OP JUMP_IF_FALSE_OR_POP compare_chained1 COME_FROM
compare_chained1 ::= expr . DUP_TOP ROT_THREE COMPARE_OP JUMP_IF_FALSE_OR_POP compare_chained2 COME_FROM
compare_chained1_false_37 ::= expr . DUP_TOP ROT_THREE COMPARE_OP POP_JUMP_IF_FALSE compare_chained2b_false_37 POP_TOP _jump COME_FROM
compare_chained1_false_37 ::= expr . DUP_TOP ROT_THREE COMPARE_OP POP_JUMP_IF_FALSE compare_chained2c_37 POP_TOP JUMP_FORWARD COME_FROM
compare_chained1a_37 ::= expr . DUP_TOP ROT_THREE COMPARE_OP POP_JUMP_IF_FALSE
compare_chained1a_37 ::= expr . DUP_TOP ROT_THREE COMPARE_OP POP_JUMP_IF_FALSE compare_chained2a_37 COME_FROM POP_TOP COME_FROM
compare_chained1b_false_37 ::= expr . DUP_TOP ROT_THREE COMPARE_OP POP_JUMP_IF_FALSE compare_chained2b_false_37 POP_TOP _jump COME_FROM
compare_chained1c_37 ::= expr . DUP_TOP ROT_THREE COMPARE_OP POP_JUMP_IF_FALSE compare_chained2a_37 POP_TOP
compare_chained2_false_37 ::= expr . DUP_TOP ROT_THREE COMPARE_OP POP_JUMP_IF_FALSE compare_chained2a_false_37 POP_TOP JUMP_BACK COME_FROM
compare_chained37 ::= expr . compare_chained1a_37
compare_chained37 ::= expr . compare_chained1c_37
compare_chained37_false ::= expr . compare_chained1_false_37
compare_chained37_false ::= expr . compare_chained1b_false_37
compare_chained37_false ::= expr . compare_chained2_false_37
compare_single ::= expr . expr COMPARE_OP
compare_single ::= expr expr . COMPARE_OP
compare_single ::= expr expr COMPARE_OP . 
continues ::= _stmts . lastl_stmt continue
continues ::= _stmts lastl_stmt . continue
continues ::= lastl_stmt . continue
delete_subscript ::= expr . expr DELETE_SUBSCR
delete_subscript ::= expr expr . DELETE_SUBSCR
else_suite ::= suite_stmts . 
else_suitel ::= l_stmts . 
expr ::= LOAD_CONST . 
expr ::= LOAD_FAST . 
expr ::= LOAD_GLOBAL . 
expr ::= and . 
expr ::= attribute . 
expr ::= attribute37 . 
expr ::= bin_op . 
expr ::= call . 
expr ::= compare . 
expr ::= get_iter . 
expr ::= if_exp . 
expr ::= list . 
expr ::= or . 
expr ::= subscript . 
expr ::= tuple . 
expr_jit ::= expr . JUMP_IF_TRUE
expr_jitop ::= expr . JUMP_IF_TRUE_OR_POP
expr_jt ::= expr . jmp_true
expr_jt ::= expr jmp_true . 
expr_or_arg ::= expr . 
expr_pjit ::= expr . POP_JUMP_IF_TRUE
expr_pjit ::= expr POP_JUMP_IF_TRUE . 
expr_pjit_come_from ::= expr . POP_JUMP_IF_TRUE COME_FROM
expr_pjit_come_from ::= expr POP_JUMP_IF_TRUE . COME_FROM
expr_pjit_come_from ::= expr POP_JUMP_IF_TRUE COME_FROM . 
expr_stmt ::= expr . POP_TOP
expr_stmt ::= expr POP_TOP . 
for ::= setup_loop . expr get_for_iter store for_block POP_BLOCK
for ::= setup_loop . expr get_for_iter store for_block POP_BLOCK COME_FROM_LOOP
for ::= setup_loop . expr get_for_iter store for_block POP_BLOCK NOP COME_FROM_LOOP
for ::= setup_loop expr . get_for_iter store for_block POP_BLOCK
for ::= setup_loop expr . get_for_iter store for_block POP_BLOCK COME_FROM_LOOP
for ::= setup_loop expr . get_for_iter store for_block POP_BLOCK NOP COME_FROM_LOOP
for ::= setup_loop expr get_for_iter . store for_block POP_BLOCK
for ::= setup_loop expr get_for_iter . store for_block POP_BLOCK COME_FROM_LOOP
for ::= setup_loop expr get_for_iter . store for_block POP_BLOCK NOP COME_FROM_LOOP
for ::= setup_loop expr get_for_iter store . for_block POP_BLOCK
for ::= setup_loop expr get_for_iter store . for_block POP_BLOCK COME_FROM_LOOP
for ::= setup_loop expr get_for_iter store . for_block POP_BLOCK NOP COME_FROM_LOOP
for ::= setup_loop expr get_for_iter store for_block . POP_BLOCK
for ::= setup_loop expr get_for_iter store for_block . POP_BLOCK COME_FROM_LOOP
for ::= setup_loop expr get_for_iter store for_block . POP_BLOCK NOP COME_FROM_LOOP
for ::= setup_loop expr get_for_iter store for_block POP_BLOCK . 
for ::= setup_loop expr get_for_iter store for_block POP_BLOCK . COME_FROM_LOOP
for ::= setup_loop expr get_for_iter store for_block POP_BLOCK . NOP COME_FROM_LOOP
for ::= setup_loop expr get_for_iter store for_block POP_BLOCK COME_FROM_LOOP . 
for_block ::= \e_l_stmts_opt . COME_FROM_LOOP JUMP_BACK
for_block ::= \e_l_stmts_opt . _come_froms JUMP_BACK
for_block ::= \e_l_stmts_opt . come_from_loops JUMP_BACK
for_block ::= \e_l_stmts_opt \e__come_froms . JUMP_BACK
for_block ::= \e_l_stmts_opt \e_come_from_loops . JUMP_BACK
for_block ::= l_stmts . 
for_block ::= l_stmts . JUMP_BACK
for_block ::= l_stmts JUMP_BACK . 
for_block ::= l_stmts_opt . COME_FROM_LOOP JUMP_BACK
for_block ::= l_stmts_opt . _come_froms JUMP_BACK
for_block ::= l_stmts_opt . come_from_loops JUMP_BACK
for_block ::= l_stmts_opt \e__come_froms . JUMP_BACK
for_block ::= l_stmts_opt \e__come_froms JUMP_BACK . 
for_block ::= l_stmts_opt \e_come_from_loops . JUMP_BACK
for_block ::= l_stmts_opt \e_come_from_loops JUMP_BACK . 
for_block ::= l_stmts_opt _come_froms . JUMP_BACK
for_iter ::= \e__come_froms . FOR_ITER
forelselaststmt ::= SETUP_LOOP . expr get_for_iter store for_block POP_BLOCK else_suitec \e__come_froms
forelselaststmt ::= SETUP_LOOP . expr get_for_iter store for_block POP_BLOCK else_suitec _come_froms
forelselaststmt ::= SETUP_LOOP expr . get_for_iter store for_block POP_BLOCK else_suitec \e__come_froms
forelselaststmt ::= SETUP_LOOP expr . get_for_iter store for_block POP_BLOCK else_suitec _come_froms
forelselaststmt ::= SETUP_LOOP expr get_for_iter . store for_block POP_BLOCK else_suitec \e__come_froms
forelselaststmt ::= SETUP_LOOP expr get_for_iter . store for_block POP_BLOCK else_suitec _come_froms
forelselaststmt ::= SETUP_LOOP expr get_for_iter store . for_block POP_BLOCK else_suitec \e__come_froms
forelselaststmt ::= SETUP_LOOP expr get_for_iter store . for_block POP_BLOCK else_suitec _come_froms
forelselaststmt ::= SETUP_LOOP expr get_for_iter store for_block . POP_BLOCK else_suitec \e__come_froms
forelselaststmt ::= SETUP_LOOP expr get_for_iter store for_block . POP_BLOCK else_suitec _come_froms
forelselaststmt ::= SETUP_LOOP expr get_for_iter store for_block POP_BLOCK . else_suitec \e__come_froms
forelselaststmt ::= SETUP_LOOP expr get_for_iter store for_block POP_BLOCK . else_suitec _come_froms
forelselaststmt ::= setup_loop . expr get_for_iter store for_block POP_BLOCK else_suitec COME_FROM_LOOP
forelselaststmt ::= setup_loop expr . get_for_iter store for_block POP_BLOCK else_suitec COME_FROM_LOOP
forelselaststmt ::= setup_loop expr get_for_iter . store for_block POP_BLOCK else_suitec COME_FROM_LOOP
forelselaststmt ::= setup_loop expr get_for_iter store . for_block POP_BLOCK else_suitec COME_FROM_LOOP
forelselaststmt ::= setup_loop expr get_for_iter store for_block . POP_BLOCK else_suitec COME_FROM_LOOP
forelselaststmt ::= setup_loop expr get_for_iter store for_block POP_BLOCK . else_suitec COME_FROM_LOOP
forelselaststmtl ::= SETUP_LOOP . expr get_for_iter store for_block POP_BLOCK else_suitel \e__come_froms
forelselaststmtl ::= SETUP_LOOP . expr get_for_iter store for_block POP_BLOCK else_suitel _come_froms
forelselaststmtl ::= SETUP_LOOP expr . get_for_iter store for_block POP_BLOCK else_suitel \e__come_froms
forelselaststmtl ::= SETUP_LOOP expr . get_for_iter store for_block POP_BLOCK else_suitel _come_froms
forelselaststmtl ::= SETUP_LOOP expr get_for_iter . store for_block POP_BLOCK else_suitel \e__come_froms
forelselaststmtl ::= SETUP_LOOP expr get_for_iter . store for_block POP_BLOCK else_suitel _come_froms
forelselaststmtl ::= SETUP_LOOP expr get_for_iter store . for_block POP_BLOCK else_suitel \e__come_froms
forelselaststmtl ::= SETUP_LOOP expr get_for_iter store . for_block POP_BLOCK else_suitel _come_froms
forelselaststmtl ::= SETUP_LOOP expr get_for_iter store for_block . POP_BLOCK else_suitel \e__come_froms
forelselaststmtl ::= SETUP_LOOP expr get_for_iter store for_block . POP_BLOCK else_suitel _come_froms
forelselaststmtl ::= SETUP_LOOP expr get_for_iter store for_block POP_BLOCK . else_suitel \e__come_froms
forelselaststmtl ::= SETUP_LOOP expr get_for_iter store for_block POP_BLOCK . else_suitel _come_froms
forelselaststmtl ::= setup_loop . expr get_for_iter store for_block POP_BLOCK else_suitel COME_FROM_LOOP
forelselaststmtl ::= setup_loop expr . get_for_iter store for_block POP_BLOCK else_suitel COME_FROM_LOOP
forelselaststmtl ::= setup_loop expr get_for_iter . store for_block POP_BLOCK else_suitel COME_FROM_LOOP
forelselaststmtl ::= setup_loop expr get_for_iter store . for_block POP_BLOCK else_suitel COME_FROM_LOOP
forelselaststmtl ::= setup_loop expr get_for_iter store for_block . POP_BLOCK else_suitel COME_FROM_LOOP
forelselaststmtl ::= setup_loop expr get_for_iter store for_block POP_BLOCK . else_suitel COME_FROM_LOOP
forelsestmt ::= SETUP_LOOP . expr get_for_iter store for_block POP_BLOCK else_suite \e__come_froms
forelsestmt ::= SETUP_LOOP . expr get_for_iter store for_block POP_BLOCK else_suite _come_froms
forelsestmt ::= SETUP_LOOP expr . get_for_iter store for_block POP_BLOCK else_suite \e__come_froms
forelsestmt ::= SETUP_LOOP expr . get_for_iter store for_block POP_BLOCK else_suite _come_froms
forelsestmt ::= SETUP_LOOP expr get_for_iter . store for_block POP_BLOCK else_suite \e__come_froms
forelsestmt ::= SETUP_LOOP expr get_for_iter . store for_block POP_BLOCK else_suite _come_froms
forelsestmt ::= SETUP_LOOP expr get_for_iter store . for_block POP_BLOCK else_suite \e__come_froms
forelsestmt ::= SETUP_LOOP expr get_for_iter store . for_block POP_BLOCK else_suite _come_froms
forelsestmt ::= SETUP_LOOP expr get_for_iter store for_block . POP_BLOCK else_suite \e__come_froms
forelsestmt ::= SETUP_LOOP expr get_for_iter store for_block . POP_BLOCK else_suite _come_froms
forelsestmt ::= SETUP_LOOP expr get_for_iter store for_block POP_BLOCK . else_suite \e__come_froms
forelsestmt ::= SETUP_LOOP expr get_for_iter store for_block POP_BLOCK . else_suite _come_froms
forelsestmt ::= setup_loop . expr get_for_iter store for_block POP_BLOCK else_suite COME_FROM_LOOP
forelsestmt ::= setup_loop expr . get_for_iter store for_block POP_BLOCK else_suite COME_FROM_LOOP
forelsestmt ::= setup_loop expr get_for_iter . store for_block POP_BLOCK else_suite COME_FROM_LOOP
forelsestmt ::= setup_loop expr get_for_iter store . for_block POP_BLOCK else_suite COME_FROM_LOOP
forelsestmt ::= setup_loop expr get_for_iter store for_block . POP_BLOCK else_suite COME_FROM_LOOP
forelsestmt ::= setup_loop expr get_for_iter store for_block POP_BLOCK . else_suite COME_FROM_LOOP
get_for_iter ::= GET_ITER . _come_froms FOR_ITER
get_for_iter ::= GET_ITER \e__come_froms . FOR_ITER
get_for_iter ::= GET_ITER \e__come_froms FOR_ITER . 
get_iter ::= expr . GET_ITER
get_iter ::= expr GET_ITER . 
if_exp ::= expr . jmp_false expr jf_cf expr COME_FROM
if_exp ::= expr . jmp_false expr jump_absolute_else expr
if_exp ::= expr jmp_false . expr jf_cf expr COME_FROM
if_exp ::= expr jmp_false . expr jump_absolute_else expr
if_exp ::= expr jmp_false expr . jf_cf expr COME_FROM
if_exp ::= expr jmp_false expr . jump_absolute_else expr
if_exp ::= expr jmp_false expr jf_cf . expr COME_FROM
if_exp ::= expr jmp_false expr jf_cf expr . COME_FROM
if_exp ::= expr jmp_false expr jf_cf expr COME_FROM . 
if_exp37 ::= expr . expr jf_cfs expr COME_FROM
if_exp37 ::= expr expr . jf_cfs expr COME_FROM
if_exp_37b ::= expr . jmp_false expr POP_JUMP_IF_FALSE jump_forward_else expr
if_exp_37b ::= expr jmp_false . expr POP_JUMP_IF_FALSE jump_forward_else expr
if_exp_37b ::= expr jmp_false expr . POP_JUMP_IF_FALSE jump_forward_else expr
if_exp_37b ::= expr jmp_false expr POP_JUMP_IF_FALSE . jump_forward_else expr
if_exp_lambda ::= expr . jmp_false expr return_if_lambda return_stmt_lambda LAMBDA_MARKER
if_exp_lambda ::= expr jmp_false . expr return_if_lambda return_stmt_lambda LAMBDA_MARKER
if_exp_lambda ::= expr jmp_false expr . return_if_lambda return_stmt_lambda LAMBDA_MARKER
if_exp_not ::= expr . jmp_true expr jump_forward_else expr COME_FROM
if_exp_not ::= expr jmp_true . expr jump_forward_else expr COME_FROM
if_exp_not ::= expr jmp_true expr . jump_forward_else expr COME_FROM
if_exp_not_lambda ::= expr . jmp_true expr return_if_lambda return_stmt_lambda LAMBDA_MARKER
if_exp_not_lambda ::= expr jmp_true . expr return_if_lambda return_stmt_lambda LAMBDA_MARKER
if_exp_not_lambda ::= expr jmp_true expr . return_if_lambda return_stmt_lambda LAMBDA_MARKER
if_exp_true ::= expr . JUMP_FORWARD expr COME_FROM
if_exp_true ::= expr JUMP_FORWARD . expr COME_FROM
ifelsestmt ::= testexpr . c_stmts come_froms else_suite come_froms
ifelsestmt ::= testexpr . c_stmts_opt JUMP_FORWARD else_suite \e__come_froms
ifelsestmt ::= testexpr . c_stmts_opt JUMP_FORWARD else_suite \e_opt_come_from_except
ifelsestmt ::= testexpr . c_stmts_opt JUMP_FORWARD else_suite _come_froms
ifelsestmt ::= testexpr . c_stmts_opt JUMP_FORWARD else_suite opt_come_from_except
ifelsestmt ::= testexpr . c_stmts_opt jf_cfs else_suite \e_opt_come_from_except
ifelsestmt ::= testexpr . c_stmts_opt jf_cfs else_suite opt_come_from_except
ifelsestmt ::= testexpr . c_stmts_opt jump_forward_else else_suite \e__come_froms
ifelsestmt ::= testexpr . c_stmts_opt jump_forward_else else_suite _come_froms
ifelsestmt ::= testexpr . stmts jf_cfs \e_else_suite_opt \e_opt_come_from_except
ifelsestmt ::= testexpr . stmts jf_cfs \e_else_suite_opt opt_come_from_except
ifelsestmt ::= testexpr . stmts jf_cfs else_suite_opt \e_opt_come_from_except
ifelsestmt ::= testexpr . stmts jf_cfs else_suite_opt opt_come_from_except
ifelsestmt ::= testexpr \e_c_stmts_opt . JUMP_FORWARD else_suite \e__come_froms
ifelsestmt ::= testexpr \e_c_stmts_opt . JUMP_FORWARD else_suite \e_opt_come_from_except
ifelsestmt ::= testexpr \e_c_stmts_opt . JUMP_FORWARD else_suite _come_froms
ifelsestmt ::= testexpr \e_c_stmts_opt . JUMP_FORWARD else_suite opt_come_from_except
ifelsestmt ::= testexpr \e_c_stmts_opt . jf_cfs else_suite \e_opt_come_from_except
ifelsestmt ::= testexpr \e_c_stmts_opt . jf_cfs else_suite opt_come_from_except
ifelsestmt ::= testexpr \e_c_stmts_opt . jump_forward_else else_suite \e__come_froms
ifelsestmt ::= testexpr \e_c_stmts_opt . jump_forward_else else_suite _come_froms
ifelsestmt ::= testexpr c_stmts . come_froms else_suite come_froms
ifelsestmt ::= testexpr c_stmts come_froms . else_suite come_froms
ifelsestmt ::= testexpr c_stmts come_froms else_suite . come_froms
ifelsestmt ::= testexpr c_stmts come_froms else_suite come_froms . 
ifelsestmt ::= testexpr c_stmts_opt . JUMP_FORWARD else_suite \e__come_froms
ifelsestmt ::= testexpr c_stmts_opt . JUMP_FORWARD else_suite \e_opt_come_from_except
ifelsestmt ::= testexpr c_stmts_opt . JUMP_FORWARD else_suite _come_froms
ifelsestmt ::= testexpr c_stmts_opt . JUMP_FORWARD else_suite opt_come_from_except
ifelsestmt ::= testexpr c_stmts_opt . jf_cfs else_suite \e_opt_come_from_except
ifelsestmt ::= testexpr c_stmts_opt . jf_cfs else_suite opt_come_from_except
ifelsestmt ::= testexpr c_stmts_opt . jump_forward_else else_suite \e__come_froms
ifelsestmt ::= testexpr c_stmts_opt . jump_forward_else else_suite _come_froms
ifelsestmt ::= testexpr stmts . jf_cfs \e_else_suite_opt \e_opt_come_from_except
ifelsestmt ::= testexpr stmts . jf_cfs \e_else_suite_opt opt_come_from_except
ifelsestmt ::= testexpr stmts . jf_cfs else_suite_opt \e_opt_come_from_except
ifelsestmt ::= testexpr stmts . jf_cfs else_suite_opt opt_come_from_except
ifelsestmtc ::= testexpr . c_stmts_opt JUMP_ABSOLUTE else_suitec
ifelsestmtc ::= testexpr . c_stmts_opt JUMP_FORWARD else_suitec
ifelsestmtc ::= testexpr . c_stmts_opt jump_absolute_else else_suitec
ifelsestmtc ::= testexpr \e_c_stmts_opt . JUMP_ABSOLUTE else_suitec
ifelsestmtc ::= testexpr \e_c_stmts_opt . JUMP_FORWARD else_suitec
ifelsestmtc ::= testexpr \e_c_stmts_opt . jump_absolute_else else_suitec
ifelsestmtc ::= testexpr c_stmts_opt . JUMP_ABSOLUTE else_suitec
ifelsestmtc ::= testexpr c_stmts_opt . JUMP_FORWARD else_suitec
ifelsestmtc ::= testexpr c_stmts_opt . jump_absolute_else else_suitec
ifelsestmtl ::= testexpr . c_stmts_opt cf_jf_else else_suitel
ifelsestmtl ::= testexpr . c_stmts_opt cf_jump_back else_suitel
ifelsestmtl ::= testexpr . c_stmts_opt jb_cfs else_suitel
ifelsestmtl ::= testexpr . c_stmts_opt jb_else else_suitel
ifelsestmtl ::= testexpr . c_stmts_opt jump_forward_else else_suitec
ifelsestmtl ::= testexpr \e_c_stmts_opt . cf_jf_else else_suitel
ifelsestmtl ::= testexpr \e_c_stmts_opt . cf_jump_back else_suitel
ifelsestmtl ::= testexpr \e_c_stmts_opt . jb_cfs else_suitel
ifelsestmtl ::= testexpr \e_c_stmts_opt . jb_else else_suitel
ifelsestmtl ::= testexpr \e_c_stmts_opt . jump_forward_else else_suitec
ifelsestmtl ::= testexpr c_stmts_opt . cf_jf_else else_suitel
ifelsestmtl ::= testexpr c_stmts_opt . cf_jump_back else_suitel
ifelsestmtl ::= testexpr c_stmts_opt . jb_cfs else_suitel
ifelsestmtl ::= testexpr c_stmts_opt . jb_else else_suitel
ifelsestmtl ::= testexpr c_stmts_opt . jump_forward_else else_suitec
ifelsestmtl ::= testexpr c_stmts_opt jb_cfs . else_suitel
ifelsestmtl ::= testexpr c_stmts_opt jb_cfs else_suitel . 
ifelsestmtl ::= testexpr c_stmts_opt jb_else . else_suitel
ifelsestmtl ::= testexpr c_stmts_opt jb_else else_suitel . 
ifelsestmtl ::= testexpr_cf . c_stmts_opt jb_else else_suitel
ifelsestmtl ::= testexpr_cf \e_c_stmts_opt . jb_else else_suitel
ifelsestmtl ::= testexpr_cf c_stmts_opt . jb_else else_suitel
ifelsestmtr ::= testexpr . return_if_stmts returns
iflaststmt ::= testexpr . c_stmts
iflaststmt ::= testexpr . c_stmts JUMP_ABSOLUTE
iflaststmt ::= testexpr . c_stmts_opt JUMP_FORWARD
iflaststmt ::= testexpr \e_c_stmts_opt . JUMP_FORWARD
iflaststmt ::= testexpr c_stmts . 
iflaststmt ::= testexpr c_stmts . JUMP_ABSOLUTE
iflaststmt ::= testexpr c_stmts_opt . JUMP_FORWARD
iflaststmtl ::= testexpr . c_stmts
iflaststmtl ::= testexpr . c_stmts JUMP_BACK
iflaststmtl ::= testexpr . c_stmts JUMP_BACK COME_FROM_LOOP
iflaststmtl ::= testexpr . c_stmts JUMP_BACK POP_BLOCK
iflaststmtl ::= testexpr c_stmts . 
iflaststmtl ::= testexpr c_stmts . JUMP_BACK
iflaststmtl ::= testexpr c_stmts . JUMP_BACK COME_FROM_LOOP
iflaststmtl ::= testexpr c_stmts . JUMP_BACK POP_BLOCK
iflaststmtl ::= testexpr c_stmts JUMP_BACK . 
iflaststmtl ::= testexpr c_stmts JUMP_BACK . COME_FROM_LOOP
iflaststmtl ::= testexpr c_stmts JUMP_BACK . POP_BLOCK
iflaststmtl ::= testexpr c_stmts JUMP_BACK POP_BLOCK . 
iflaststmtl ::= testexprl . c_stmts JUMP_BACK
iflaststmtl ::= testexprl . c_stmts JUMP_BACK COME_FROM_LOOP
iflaststmtl ::= testexprl . c_stmts JUMP_BACK POP_BLOCK
ifstmt ::= testexpr . _ifstmts_jump
ifstmt ::= testexpr _ifstmts_jump . 
ifstmtl ::= testexpr . _ifstmts_jumpl
ifstmtl ::= testexpr _ifstmts_jumpl . 
import ::= LOAD_CONST . LOAD_CONST alias
import_as37 ::= LOAD_CONST . LOAD_CONST importlist37 store POP_TOP
import_from ::= LOAD_CONST . LOAD_CONST IMPORT_NAME importlist POP_TOP
import_from ::= LOAD_CONST . LOAD_CONST importlist POP_TOP
import_from37 ::= LOAD_CONST . LOAD_CONST IMPORT_NAME_ATTR importlist37 POP_TOP
import_from_as37 ::= LOAD_CONST . LOAD_CONST import_from_attr37 store POP_TOP
import_from_star ::= LOAD_CONST . LOAD_CONST IMPORT_NAME IMPORT_STAR
import_from_star ::= LOAD_CONST . LOAD_CONST IMPORT_NAME_ATTR IMPORT_STAR
importmultiple ::= LOAD_CONST . LOAD_CONST alias imports_cont
jb_cfs ::= \e_come_from_opt . JUMP_BACK come_froms
jb_cfs ::= \e_come_from_opt JUMP_BACK . come_froms
jb_cfs ::= \e_come_from_opt JUMP_BACK come_froms . 
jb_cfs ::= come_from_opt . JUMP_BACK come_froms
jb_else ::= JUMP_BACK . COME_FROM
jb_else ::= JUMP_BACK . ELSE
jb_else ::= JUMP_BACK COME_FROM . 
jf_cf ::= JUMP_FORWARD . COME_FROM
jf_cf ::= JUMP_FORWARD COME_FROM . 
jmp_false ::= POP_JUMP_IF_FALSE . 
jmp_true ::= POP_JUMP_IF_TRUE . 
jump_absolute_else ::= come_froms . _jump COME_FROM
l_stmts ::= _stmts . 
l_stmts ::= _stmts . lastl_stmt
l_stmts ::= _stmts lastl_stmt . 
l_stmts ::= l_stmts . lstmt
l_stmts ::= l_stmts lstmt . 
l_stmts ::= lastl_stmt . 
l_stmts ::= lastl_stmt . come_froms l_stmts
l_stmts ::= lastl_stmt come_froms . l_stmts
l_stmts ::= lastl_stmt come_froms l_stmts . 
l_stmts ::= lstmt . 
l_stmts_opt ::= l_stmts . 
lambda_body ::= expr . LOAD_LAMBDA LOAD_STR MAKE_FUNCTION_1
lastc_stmt ::= iflaststmt . 
lastl_stmt ::= ifelsestmtl . 
lastl_stmt ::= iflaststmtl . 
lc_body ::= expr . LIST_APPEND
list ::= BUILD_LIST_0 . 
list ::= expr . BUILD_LIST_1
list ::= expr . expr BUILD_LIST_2
list ::= expr expr . BUILD_LIST_2
list_comp ::= BUILD_LIST_0 . list_iter
list_for ::= expr_or_arg . for_iter store list_iter jb_or_c \e__come_froms
list_for ::= expr_or_arg . for_iter store list_iter jb_or_c _come_froms
list_if ::= expr . jmp_false list_iter
list_if ::= expr . jmp_false list_iter COME_FROM
list_if ::= expr . jmp_false37 list_iter
list_if_not ::= expr . jmp_true list_iter
list_if_not ::= expr . jmp_true list_iter COME_FROM
lstmt ::= stmt . 
mkfunc ::= expr . LOAD_CODE LOAD_STR MAKE_FUNCTION_1
mkfuncdeco ::= expr . mkfuncdeco CALL_FUNCTION_1
mkfuncdeco ::= expr . mkfuncdeco0 CALL_FUNCTION_1
or ::= and . jitop_come_from_expr COME_FROM
or ::= expr_jt . expr
or ::= expr_jt . expr COME_FROM
or ::= expr_jt expr . 
or ::= expr_jt expr . COME_FROM
or ::= expr_pjit . expr POP_JUMP_IF_FALSE COME_FROM
or ::= expr_pjit expr . POP_JUMP_IF_FALSE COME_FROM
or ::= expr_pjit_come_from . expr
pos_arg ::= expr . 
ret_and ::= expr . JUMP_IF_FALSE_OR_POP return_expr_or_cond COME_FROM
ret_or ::= expr . JUMP_IF_TRUE_OR_POP return_expr_or_cond COME_FROM
return ::= return_expr . RETURN_END_IF
return ::= return_expr . RETURN_VALUE
return ::= return_expr . RETURN_VALUE COME_FROM
return ::= return_expr RETURN_VALUE . 
return ::= return_expr RETURN_VALUE . COME_FROM
return ::= return_expr RETURN_VALUE COME_FROM . 
return_expr ::= expr . 
return_expr_lambda ::= return_expr . RETURN_VALUE_LAMBDA
return_expr_lambda ::= return_expr . RETURN_VALUE_LAMBDA LAMBDA_MARKER
return_if_stmt ::= return_expr . RETURN_END_IF
return_if_stmt ::= return_expr . RETURN_END_IF POP_BLOCK
return_if_stmts ::= _stmts . return_if_stmt \e__come_froms
return_if_stmts ::= _stmts . return_if_stmt _come_froms
returns ::= _stmts . return
returns ::= _stmts . return_if_stmt
returns ::= _stmts return . 
returns ::= return . 
setup_loop ::= SETUP_LOOP . _come_froms
setup_loop ::= SETUP_LOOP \e__come_froms . 
sstmt ::= sstmt . RETURN_LAST
sstmt ::= stmt . 
stmt ::= assign . 
stmt ::= call_stmt . 
stmt ::= expr_stmt . 
stmt ::= for . 
stmt ::= ifelsestmt . 
stmt ::= ifstmt . 
stmt ::= ifstmtl . 
stmt ::= return . 
stmts ::= sstmt . 
stmts ::= stmts . sstmt
stmts ::= stmts sstmt . 
store ::= STORE_FAST . 
store ::= expr . STORE_ATTR
store ::= unpack . 
store_subscript ::= expr . expr STORE_SUBSCR
store_subscript ::= expr expr . STORE_SUBSCR
subscript ::= expr . expr BINARY_SUBSCR
subscript ::= expr expr . BINARY_SUBSCR
subscript ::= expr expr BINARY_SUBSCR . 
subscript2 ::= expr . expr DUP_TOP_TWO BINARY_SUBSCR
subscript2 ::= expr expr . DUP_TOP_TWO BINARY_SUBSCR
suite_stmts ::= _stmts . 
suite_stmts ::= returns . 
testexpr ::= testfalse . 
testexpr ::= testtrue . 
testexpr_cf ::= testexpr . come_froms
testexpr_cf ::= testexpr come_froms . 
testexprl ::= testfalsel . 
testfalse ::= expr . jmp_false
testfalse ::= expr jmp_false . 
testfalse ::= or . jmp_false COME_FROM
testfalse_not_and ::= and . jmp_true come_froms
testfalse_not_and ::= expr . jmp_false expr jmp_true COME_FROM
testfalse_not_and ::= expr jmp_false . expr jmp_true COME_FROM
testfalse_not_and ::= expr jmp_false expr . jmp_true COME_FROM
testfalse_not_or ::= expr . jmp_false expr jmp_false COME_FROM
testfalse_not_or ::= expr jmp_false . expr jmp_false COME_FROM
testfalse_not_or ::= expr jmp_false expr . jmp_false COME_FROM
testfalse_not_or ::= expr jmp_false expr jmp_false . COME_FROM
testfalsel ::= expr . jmp_true
testfalsel ::= expr jmp_true . 
testtrue ::= expr . jmp_true
testtrue ::= expr jmp_true . 
tuple ::= expr . expr BUILD_TUPLE_2
tuple ::= expr expr . BUILD_TUPLE_2
tuple ::= expr expr BUILD_TUPLE_2 . 
unary_not ::= expr . UNARY_NOT
unary_op ::= expr . unary_operator
unpack ::= UNPACK_SEQUENCE_2 . store store
unpack ::= UNPACK_SEQUENCE_2 store . store
unpack ::= UNPACK_SEQUENCE_2 store store . 
while1elsestmt ::= setup_loop . l_stmts JUMP_BACK POP_BLOCK else_suite COME_FROM_LOOP
while1elsestmt ::= setup_loop . l_stmts JUMP_BACK \e__come_froms POP_BLOCK else_suitel COME_FROM_LOOP
while1elsestmt ::= setup_loop . l_stmts JUMP_BACK _come_froms POP_BLOCK else_suitel COME_FROM_LOOP
while1elsestmt ::= setup_loop . l_stmts JUMP_BACK else_suite COME_FROM_LOOP
while1elsestmt ::= setup_loop . l_stmts JUMP_BACK else_suitel
while1stmt ::= setup_loop . l_stmts COME_FROM JUMP_BACK COME_FROM_LOOP
while1stmt ::= setup_loop . l_stmts COME_FROM JUMP_BACK POP_BLOCK COME_FROM_LOOP
while1stmt ::= setup_loop . l_stmts COME_FROM_LOOP
while1stmt ::= setup_loop . l_stmts COME_FROM_LOOP JUMP_BACK POP_BLOCK COME_FROM_LOOP
while1stmt ::= setup_loop . l_stmts POP_BLOCK COME_FROM_LOOP
whileTruestmt ::= SETUP_LOOP . l_stmts_opt JUMP_BACK COME_FROM_LOOP
whileTruestmt ::= SETUP_LOOP \e_l_stmts_opt . JUMP_BACK COME_FROM_LOOP
whileTruestmt ::= setup_loop . l_stmts_opt JUMP_BACK POP_BLOCK \e__come_froms
whileTruestmt ::= setup_loop . l_stmts_opt JUMP_BACK POP_BLOCK _come_froms
whileTruestmt ::= setup_loop \e_l_stmts_opt . JUMP_BACK POP_BLOCK \e__come_froms
whileTruestmt ::= setup_loop \e_l_stmts_opt . JUMP_BACK POP_BLOCK _come_froms
whileelsestmt ::= setup_loop . testexpr \e_l_stmts_opt JUMP_BACK POP_BLOCK else_suitel COME_FROM
whileelsestmt ::= setup_loop . testexpr \e_l_stmts_opt JUMP_BACK POP_BLOCK else_suitel COME_FROM_LOOP
whileelsestmt ::= setup_loop . testexpr l_stmts_opt JUMP_BACK POP_BLOCK else_suitel COME_FROM
whileelsestmt ::= setup_loop . testexpr l_stmts_opt JUMP_BACK POP_BLOCK else_suitel COME_FROM_LOOP
whilestmt ::= setup_loop . testexpr \e_l_stmts_opt COME_FROM JUMP_BACK POP_BLOCK COME_FROM_LOOP
whilestmt ::= setup_loop . testexpr \e_l_stmts_opt JUMP_BACK POP_BLOCK COME_FROM_LOOP
whilestmt ::= setup_loop . testexpr \e_l_stmts_opt JUMP_BACK come_froms POP_BLOCK
whilestmt ::= setup_loop . testexpr \e_l_stmts_opt JUMP_BACK come_froms POP_BLOCK COME_FROM_LOOP
whilestmt ::= setup_loop . testexpr \e_l_stmts_opt come_froms JUMP_BACK come_froms POP_BLOCK COME_FROM_LOOP
whilestmt ::= setup_loop . testexpr l_stmts_opt COME_FROM JUMP_BACK POP_BLOCK COME_FROM_LOOP
whilestmt ::= setup_loop . testexpr l_stmts_opt JUMP_BACK POP_BLOCK COME_FROM_LOOP
whilestmt ::= setup_loop . testexpr l_stmts_opt JUMP_BACK come_froms POP_BLOCK
whilestmt ::= setup_loop . testexpr l_stmts_opt JUMP_BACK come_froms POP_BLOCK COME_FROM_LOOP
whilestmt ::= setup_loop . testexpr l_stmts_opt come_froms JUMP_BACK come_froms POP_BLOCK COME_FROM_LOOP
whilestmt ::= setup_loop . testexpr returns POP_BLOCK COME_FROM_LOOP
whilestmt ::= setup_loop . testexpr returns come_froms POP_BLOCK COME_FROM_LOOP
with ::= expr . SETUP_WITH POP_TOP \e_suite_stmts_opt COME_FROM_WITH WITH_CLEANUP_START WITH_CLEANUP_FINISH END_FINALLY
with ::= expr . SETUP_WITH POP_TOP \e_suite_stmts_opt COME_FROM_WITH with_suffix
with ::= expr . SETUP_WITH POP_TOP \e_suite_stmts_opt POP_BLOCK LOAD_CONST COME_FROM_WITH with_suffix
with ::= expr . SETUP_WITH POP_TOP \e_suite_stmts_opt POP_BLOCK LOAD_CONST WITH_CLEANUP_START WITH_CLEANUP_FINISH END_FINALLY
with ::= expr . SETUP_WITH POP_TOP \e_suite_stmts_opt POP_BLOCK LOAD_CONST with_suffix
with ::= expr . SETUP_WITH POP_TOP suite_stmts_opt COME_FROM_WITH WITH_CLEANUP_START WITH_CLEANUP_FINISH END_FINALLY
with ::= expr . SETUP_WITH POP_TOP suite_stmts_opt COME_FROM_WITH with_suffix
with ::= expr . SETUP_WITH POP_TOP suite_stmts_opt POP_BLOCK LOAD_CONST COME_FROM_WITH with_suffix
with ::= expr . SETUP_WITH POP_TOP suite_stmts_opt POP_BLOCK LOAD_CONST WITH_CLEANUP_START WITH_CLEANUP_FINISH END_FINALLY
with ::= expr . SETUP_WITH POP_TOP suite_stmts_opt POP_BLOCK LOAD_CONST with_suffix
withasstmt ::= expr . SETUP_WITH store \e_suite_stmts_opt COME_FROM_WITH WITH_CLEANUP_START WITH_CLEANUP_FINISH END_FINALLY
withasstmt ::= expr . SETUP_WITH store \e_suite_stmts_opt COME_FROM_WITH with_suffix
withasstmt ::= expr . SETUP_WITH store \e_suite_stmts_opt POP_BLOCK LOAD_CONST COME_FROM_WITH with_suffix
withasstmt ::= expr . SETUP_WITH store suite_stmts_opt COME_FROM_WITH WITH_CLEANUP_START WITH_CLEANUP_FINISH END_FINALLY
withasstmt ::= expr . SETUP_WITH store suite_stmts_opt COME_FROM_WITH with_suffix
withasstmt ::= expr . SETUP_WITH store suite_stmts_opt POP_BLOCK LOAD_CONST COME_FROM_WITH with_suffix
yield ::= expr . YIELD_VALUE
yield_from ::= expr . GET_YIELD_FROM_ITER LOAD_CONST YIELD_FROM
Instruction context:
   
 L. 351       262  LOAD_FAST                'results'
                 264  LOAD_FAST                'rejected'
                 266  BUILD_TUPLE_2         2 
->               268  RETURN_VALUE     
import collections, contextlib
from sims4.tuning.geometric import TunableCurve
from sims4.tuning.tunable import Tunable, TunableRange
import accumulator, placement, sims4.geometry, sims4.log, sims4.math
__all__ = [
 'SocialGeometry', 'make']
logger = sims4.log.Logger('SocialGeometry')

class SocialGeometry:
    __slots__ = ('focus', 'field', '_area', 'transform')
    GROUP_DISTANCE_CURVE = TunableCurve(description='\n    A curve defining the score for standing a given distance away from other\n    Sims in the social group.\n    \n    Higher values (on the y-axis) encourage standing at that distance (on the\n    x-axis) away from other Sims.')
    NON_GROUP_DISTANCE_CURVE = TunableCurve(description='\n    A curve defining the score for standing a given distance away from other\n    Sims *not* in the social group.\n    \n    Higher values (on the y-axis) encourage standing at that distance (on the\n     x-axis) away from other Sims.')
    GROUP_ANGLE_CURVE = TunableCurve(description='\n    A curve defining the score for two Sims with this facing angle (in radians).\n    \n    An angle of zero (on the x-axis) means a Sims is facing another Sim, while\n    PI means a Sim is facing away.  Higher values (on the y-axis) encourage\n    that angular facing.')
    OVERLAP_SCORE_MULTIPLIER = Tunable(float, 1.0, description='p\n    Higher values raise the importance of the "personal space" component of the\n    social scoring function.')
    DEFAULT_SCORE_CUTOFF = TunableRange(float, 0.8, minimum=0, maximum=1.0, description='\n    Transforms scoring below cutoff * max_score are filtered out when joining / adjusting position')
    NON_OVERLAPPING_SCORE_MULTIPLIER = Tunable(float, 0.05, description='Minimum score multiplier for non-overlapping fields')
    SCORE_STRENGTH_MULTIPLIER = Tunable(float, 3, description='\n    Values > 1 will cause Sims to go further out of their way to be in perfect social arrangements.\n    This helps overcome distance attenuation for social adjustment since we want Sims to care more\n    about where they are positioned than how far they have to go to improve that position.')
    SCORE_OFFSET_FOR_CURRENT_POSITION = Tunable(float, 0.5, description="\n    An additional score to apply to points that are virtually identical to the\n    Sim's current position if the Sim already has an entry in the geometry.\n    \n    Larger numbers provide more friction that will prevent Sims from moving\n    away from their current position unless the score of the new point makes\n    moving worthwhile.")

    def __init__(self, focus, field, transform):
        self.focus = focus
        self.field = field
        self.transform = transform
        self._area = None

    def __repr__(self):
        return 'SocialGeometry[Focus:{}]'.format(self.focus)

    @property
    def area(self):
        if self._area is None:
            self._area = self.field.area()
        return self._area


class SocialGroupGeometry(collections.MutableMapping):

    def __init__(self):
        self.members = {}
        self.aggregate = None
        self._total_focus = None
        self._lockout = 0
        self._dirty = False

    def __repr__(self):
        return 'SocialGroupGeometry[focus:{}, Members:{}]'.format(self.focus, len(self.members))

    @property
    def focus(self):
        if self.aggregate is None:
            return
        return self.aggregate.focus

    @property
    def field(self):
        if self.aggregate is None:
            return
        return self.aggregate.field

    @property
    def area(self):
        if self.aggregate is None:
            return
        return self.aggregate.area

    def minimum_distance(self, p, sim_list, skip=None):
        sim_positions = [sim.intended_position for sim in sim_list if sim is not skip]
        if not sim_positions:
            return
        return sims4.math.minimum_distance(p, sim_positions)

    @contextlib.contextmanager
    def lock(self):
        try:
            self._lockout += 1
            self.aggregate = None
            self._total_focus = None
            yield self
        finally:
            self._lockout -= 1
            if self._lockout == 0:
                if self._dirty:
                    self._reconstruct()

    def score_placement(self, sim_list, group):
        scores = []
        for sim in sim_list:
            remainder = SocialGroupGeometry()
            with remainder.lock():
                for other, other_geometry in self.members.items():
                    if other is sim:
                        continue
                    remainder[other] = other_geometry

            valid, _ = score_transforms([sim.transform], sim, group, remainder)
            if valid:
                scores.append((sim, valid[0][1]))
            else:
                scores.append((sim, 0))

        return scores

    def __len__(self):
        return len(self.members)

    def __iter__(self):
        return iter(self.members)

    def __bool__(self):
        return bool(self.members)

    def __getitem__(self, key):
        return self.members[key]

    def __setitem__(self, key, value):
        existed = key in self.members
        self.members[key] = value
        if existed:
            self._reconstruct()
        else:
            self._merge(value)

    def __delitem__(self, key):
        existed = key in self.members
        del self.members[key]
        if existed:
            self._reconstruct()

    def __contains__(self, key):
        return key in self.members

    def _reconstruct(self):
        if self._lockout:
            self._dirty = True
            return
        n = len(self.members)
        if n == 0:
            self._total_focus = None
            self.aggregate = None
            return
        total_focus = None
        field = None
        for geometry in self.members.values():
            if total_focus is None:
                total_focus = geometry.focus
                field = geometry.field
            else:
                total_focus = total_focus + geometry.focus
                field = field.intersect(geometry.field)
            if not field.convex:
                field = sims4.geometry.CompoundPolygon(sims4.geometry.Polygon())

        focus = total_focus * (1.0 / n)
        self._total_focus = total_focus
        self.aggregate = SocialGeometry(focus, field, None)

    def _merge(self, geometry):
        if self._lockout:
            self._dirty = True
            return
        if self.aggregate is None:
            self._total_focus = geometry.focus
            self.aggregate = geometry
            return
        n = len(self.members)
        self._total_focus = self._total_focus + geometry.focus
        focus = self._total_focus * (1.0 / n)
        field = self.aggregate.field.intersect(geometry.field)
        self.aggregate = SocialGeometry(focus, field, None)


def create_from_transform(base_transform, base_focus, base_field, focal_dist):
    offset = sims4.math.Transform(sims4.math.Vector3(0, 0, focal_dist), sims4.math.Quaternion.IDENTITY())
    transform = sims4.math.Transform.concatenate(offset, base_transform)
    transform.translation = sims4.math.vector_flatten(transform.translation)
    focus = transform.transform_point(base_focus)
    vertices = [transform.transform_point(v) for v in base_field]
    field = sims4.geometry.CompoundPolygon(sims4.geometry.Polygon(vertices))
    return SocialGeometry(focus, field, base_transform)


def _get_social_geometry_for_sim(sim):
    tuning = sim.posture.social_geometry
    if tuning is None:
        return (None, None)
    base_focus = tuning.focal_point
    base_field = tuning.social_space
    if base_field is None:
        return (None, None)
    social_space_override, focal_point_override = sim.si_state.get_social_geometry_override()
    if social_space_override is not None:
        if focal_point_override is not None:
            base_focus = focal_point_override
            base_field = social_space_override
    return (
     base_focus, base_field)


def create(sim, group, transform_override=None):
    base_focus, base_field = _get_social_geometry_for_sim(sim)
    if base_focus is None or base_field is None:
        return
    r = group.group_radius
    transform = transform_override or sim.intended_transform
    return create_from_transform(transform, base_focus, base_field, r)


def score_transforms--- This code section failed: ---

 L. 320         0  LOAD_GLOBAL              _get_social_geometry_for_sim
                2  LOAD_FAST                'sim'
                4  CALL_FUNCTION_1       1  '1 positional argument'
                6  UNPACK_SEQUENCE_2     2 
                8  STORE_FAST               'base_focus'
               10  STORE_FAST               'base_field'

 L. 321        12  LOAD_FAST                'base_focus'
               14  LOAD_CONST               None
               16  COMPARE_OP               is
               18  POP_JUMP_IF_TRUE     32  'to 32'
               20  LOAD_FAST                'base_field'
               22  LOAD_CONST               None
               24  COMPARE_OP               is
               26  POP_JUMP_IF_TRUE     32  'to 32'
               28  LOAD_FAST                'group_geometry'
               30  POP_JUMP_IF_TRUE     40  'to 40'
             32_0  COME_FROM            26  '26'
             32_1  COME_FROM            18  '18'

 L. 322        32  BUILD_LIST_0          0 
               34  BUILD_LIST_0          0 
               36  BUILD_TUPLE_2         2 
               38  RETURN_VALUE     
             40_0  COME_FROM            30  '30'

 L. 324        40  LOAD_FAST                'group'
               42  LOAD_ATTR                group_radius
               44  STORE_FAST               'r'

 L. 326        46  BUILD_LIST_0          0 
               48  STORE_FAST               'scored'

 L. 327        50  BUILD_LIST_0          0 
               52  STORE_FAST               'results'

 L. 328        54  BUILD_LIST_0          0 
               56  STORE_FAST               'rejected'

 L. 329        58  LOAD_CONST               None
               60  STORE_FAST               'max_score'

 L. 330        62  SETUP_LOOP          182  'to 182'
               64  LOAD_FAST                'transforms'
               66  GET_ITER         
               68  FOR_ITER            180  'to 180'
               70  STORE_FAST               'transform'

 L. 331        72  LOAD_GLOBAL              score_transform
               74  LOAD_FAST                'transform'
               76  LOAD_FAST                'sim'
               78  LOAD_FAST                'group_geometry'
               80  LOAD_FAST                'r'
               82  LOAD_FAST                'base_focus'
               84  LOAD_FAST                'base_field'
               86  CALL_FUNCTION_6       6  '6 positional arguments'
               88  STORE_FAST               'score'

 L. 332        90  LOAD_FAST                'score'
               92  LOAD_CONST               0
               94  COMPARE_OP               >
               96  POP_JUMP_IF_FALSE   118  'to 118'
               98  LOAD_FAST                'modifier'
              100  LOAD_CONST               None
              102  COMPARE_OP               is-not
              104  POP_JUMP_IF_FALSE   118  'to 118'

 L. 333       106  LOAD_FAST                'modifier'
              108  LOAD_FAST                'score'
              110  LOAD_FAST                'transform'
              112  LOAD_FAST                'sim'
              114  CALL_FUNCTION_3       3  '3 positional arguments'
              116  STORE_FAST               'score'
            118_0  COME_FROM           104  '104'
            118_1  COME_FROM            96  '96'

 L. 334       118  LOAD_FAST                'score'
              120  LOAD_CONST               0
              122  COMPARE_OP               >
              124  POP_JUMP_IF_FALSE   164  'to 164'

 L. 335       126  LOAD_FAST                'scored'
              128  LOAD_METHOD              append
              130  LOAD_FAST                'transform'
              132  LOAD_FAST                'score'
              134  BUILD_TUPLE_2         2 
              136  CALL_METHOD_1         1  '1 positional argument'
              138  POP_TOP          

 L. 336       140  LOAD_FAST                'max_score'
              142  LOAD_CONST               None
              144  COMPARE_OP               is-not
              146  POP_JUMP_IF_FALSE   158  'to 158'
              148  LOAD_GLOBAL              max
              150  LOAD_FAST                'score'
              152  LOAD_FAST                'max_score'
              154  CALL_FUNCTION_2       2  '2 positional arguments'
              156  JUMP_FORWARD        160  'to 160'
            158_0  COME_FROM           146  '146'
              158  LOAD_FAST                'score'
            160_0  COME_FROM           156  '156'
              160  STORE_FAST               'max_score'
              162  JUMP_BACK            68  'to 68'
            164_0  COME_FROM           124  '124'

 L. 338       164  LOAD_FAST                'rejected'
              166  LOAD_METHOD              append
              168  LOAD_FAST                'transform'
              170  LOAD_FAST                'score'
              172  BUILD_TUPLE_2         2 
              174  CALL_METHOD_1         1  '1 positional argument'
              176  POP_TOP          
              178  JUMP_BACK            68  'to 68'
              180  POP_BLOCK        
            182_0  COME_FROM_LOOP       62  '62'

 L. 340       182  LOAD_FAST                'cutoff'
              184  LOAD_CONST               None
              186  COMPARE_OP               is
              188  POP_JUMP_IF_FALSE   196  'to 196'

 L. 341       190  LOAD_GLOBAL              SocialGeometry
              192  LOAD_ATTR                DEFAULT_SCORE_CUTOFF
              194  STORE_FAST               'cutoff'
            196_0  COME_FROM           188  '188'

 L. 343       196  LOAD_FAST                'max_score'
              198  LOAD_CONST               None
              200  COMPARE_OP               is-not
          202_204  POP_JUMP_IF_FALSE   262  'to 262'

 L. 344       206  LOAD_FAST                'max_score'
              208  LOAD_FAST                'cutoff'
              210  BINARY_MULTIPLY  
              212  STORE_FAST               'cutoff_score'

 L. 345       214  SETUP_LOOP          262  'to 262'
              216  LOAD_FAST                'scored'
              218  GET_ITER         
              220  FOR_ITER            260  'to 260'
              222  STORE_FAST               'score_data'

 L. 346       224  LOAD_FAST                'score_data'
              226  LOAD_CONST               1
              228  BINARY_SUBSCR    
              230  LOAD_FAST                'cutoff_score'
              232  COMPARE_OP               >=
              234  POP_JUMP_IF_FALSE   248  'to 248'

 L. 347       236  LOAD_FAST                'results'
              238  LOAD_METHOD              append
              240  LOAD_FAST                'score_data'
              242  CALL_METHOD_1         1  '1 positional argument'
              244  POP_TOP          
              246  JUMP_BACK           220  'to 220'
            248_0  COME_FROM           234  '234'

 L. 349       248  LOAD_FAST                'rejected'
              250  LOAD_METHOD              append
              252  LOAD_FAST                'score_data'
              254  CALL_METHOD_1         1  '1 positional argument'
              256  POP_TOP          
              258  JUMP_BACK           220  'to 220'
              260  POP_BLOCK        
            262_0  COME_FROM_LOOP      214  '214'
            262_1  COME_FROM           202  '202'

 L. 351       262  LOAD_FAST                'results'
              264  LOAD_FAST                'rejected'
              266  BUILD_TUPLE_2         2 
              268  RETURN_VALUE     
               -1  RETURN_LAST      

Parse error at or near `RETURN_VALUE' instruction at offset 268


def score_transform(transform, sim, group_geometry, r, base_focus, base_field):
    accum = accumulator.HarmonicMeanAccumulator()
    dist = group_geometry.minimum_distance((transform.translation), (group_geometry.members), skip=sim)
    in_group_dist_score = SocialGeometry.GROUP_DISTANCE_CURVE.get(dist)
    accum.add(in_group_dist_score)
    if accum.fault():
        return 0
    candidate_geometry = create_from_transform(transform, base_focus, base_field, r)
    candidate_area = candidate_geometry.field.area()
    if candidate_area <= sims4.math.EPSILON:
        return 0
    candidate_facing = sims4.math.yaw_quaternion_to_angle(transform.orientation)
    for other_sim, geometry in group_geometry.members.items():
        if other_sim is sim:
            continue
        other_facing = sims4.math.yaw_quaternion_to_angle(geometry.transform.orientation)
        delta = geometry.transform.translation - transform.translation
        score_facing(accum, candidate_facing, other_facing, delta)
        intersection = geometry.field.intersect(candidate_geometry.field)
        fraction = intersection.area() / candidate_area
        fraction = SocialGeometry.OVERLAP_SCORE_MULTIPLIER * max(fraction, SocialGeometry.NON_OVERLAPPING_SCORE_MULTIPLIER)
        accum.add(fraction)
        if accum.fault():
            return 0

    nearby_non_members = list(placement.get_nearby_sims_gen((transform.translation), (sim.routing_surface), exclude=group_geometry, check_all_surfaces_on_level=True))
    if sim in nearby_non_members:
        nearby_non_members.remove(sim)
    if nearby_non_members:
        nearest = group_geometry.minimum_distance(transform.translation, nearby_non_members)
        not_in_group_score = SocialGeometry.NON_GROUP_DISTANCE_CURVE.get(nearest)
        accum.add(not_in_group_score)
    return accum.value()


def score_facing(accum, sim_facing, other_facing, delta):
    facing_angle = sims4.math.vector3_angle(delta)
    angle_ab = sims4.math.angle_abs_difference(sim_facing, facing_angle)
    score_ab = SocialGeometry.GROUP_ANGLE_CURVE.get(angle_ab)
    angle_ba = sims4.math.angle_abs_difference(other_facing, facing_angle + sims4.math.PI)
    score_ba = SocialGeometry.GROUP_ANGLE_CURVE.get(angle_ba)
    accum.add(score_ab * score_ba)
