# uncompyle6 version 3.9.0
# Python bytecode version base 3.7.0 (3394)
# Decompiled from: Python 3.7.16 (default, Dec  7 2022, 01:12:33) 
# [GCC 11.3.0]
# Embedded file name: T:\InGame\Gameplay\Scripts\Server\sims\baby\baby_utils.py
# Compiled at: 2016-10-06 19:13:48
# Size of source mod 2**32: 6997 bytes

-- Stacks of completed symbols:
START ::= |- stmts . 
_come_froms ::= \e__come_froms . COME_FROM
_come_froms ::= \e__come_froms . COME_FROM_LOOP
_come_froms ::= \e__come_froms COME_FROM . 
_come_froms ::= _come_froms . COME_FROM
_come_froms ::= _come_froms . COME_FROM_LOOP
_ifstmts_jump ::= \e_c_stmts_opt . COME_FROM
_ifstmts_jump ::= \e_c_stmts_opt . ELSE
_ifstmts_jump ::= \e_c_stmts_opt . JUMP_ABSOLUTE JUMP_FORWARD \e__come_froms
_ifstmts_jump ::= \e_c_stmts_opt . JUMP_ABSOLUTE JUMP_FORWARD _come_froms
_ifstmts_jump ::= \e_c_stmts_opt . come_froms
_stmts ::= _stmts . stmt
_stmts ::= stmt . 
and ::= expr . JUMP_IF_FALSE_OR_POP expr \e_come_from_opt
and ::= expr . JUMP_IF_FALSE_OR_POP expr come_from_opt
and ::= expr . jifop_come_from expr
and ::= expr . jmp_false expr
and ::= expr . jmp_false expr COME_FROM
and ::= expr . jmp_false expr jmp_false
and ::= expr jmp_false . expr
and ::= expr jmp_false . expr COME_FROM
and ::= expr jmp_false . expr jmp_false
and_not ::= expr . jmp_false expr POP_JUMP_IF_TRUE
and_not ::= expr jmp_false . expr POP_JUMP_IF_TRUE
assert2 ::= expr . jmp_true LOAD_GLOBAL expr CALL_FUNCTION_1 RAISE_VARARGS_1
assert2 ::= expr jmp_true . LOAD_GLOBAL expr CALL_FUNCTION_1 RAISE_VARARGS_1
assert_invert ::= testtrue . LOAD_GLOBAL RAISE_VARARGS_1
assign ::= expr . DUP_TOP designList
assign ::= expr . store
assign ::= expr store . 
assign2 ::= expr . expr ROT_TWO store store
assign2 ::= expr expr . ROT_TWO store store
assign3 ::= expr . expr expr ROT_THREE ROT_TWO store store store
assign3 ::= expr expr . expr ROT_THREE ROT_TWO store store store
assign3 ::= expr expr expr . ROT_THREE ROT_TWO store store store
async_for_stmt ::= setup_loop . expr GET_AITER LOAD_CONST YIELD_FROM SETUP_EXCEPT GET_ANEXT LOAD_CONST YIELD_FROM store POP_BLOCK JUMP_FORWARD COME_FROM_EXCEPT DUP_TOP LOAD_GLOBAL COMPARE_OP POP_JUMP_IF_FALSE POP_TOP POP_TOP POP_TOP POP_EXCEPT POP_BLOCK JUMP_ABSOLUTE END_FINALLY COME_FROM for_block POP_BLOCK COME_FROM_LOOP
async_for_stmt ::= setup_loop . expr GET_AITER SETUP_EXCEPT GET_ANEXT LOAD_CONST YIELD_FROM store POP_BLOCK JUMP_FORWARD COME_FROM_EXCEPT DUP_TOP LOAD_GLOBAL COMPARE_OP POP_JUMP_IF_TRUE END_FINALLY COME_FROM for_block COME_FROM POP_TOP POP_TOP POP_TOP POP_EXCEPT POP_TOP POP_BLOCK COME_FROM_LOOP
async_for_stmt ::= setup_loop expr . GET_AITER LOAD_CONST YIELD_FROM SETUP_EXCEPT GET_ANEXT LOAD_CONST YIELD_FROM store POP_BLOCK JUMP_FORWARD COME_FROM_EXCEPT DUP_TOP LOAD_GLOBAL COMPARE_OP POP_JUMP_IF_FALSE POP_TOP POP_TOP POP_TOP POP_EXCEPT POP_BLOCK JUMP_ABSOLUTE END_FINALLY COME_FROM for_block POP_BLOCK COME_FROM_LOOP
async_for_stmt ::= setup_loop expr . GET_AITER SETUP_EXCEPT GET_ANEXT LOAD_CONST YIELD_FROM store POP_BLOCK JUMP_FORWARD COME_FROM_EXCEPT DUP_TOP LOAD_GLOBAL COMPARE_OP POP_JUMP_IF_TRUE END_FINALLY COME_FROM for_block COME_FROM POP_TOP POP_TOP POP_TOP POP_EXCEPT POP_TOP POP_BLOCK COME_FROM_LOOP
async_for_stmt37 ::= setup_loop . expr GET_AITER \e__come_froms SETUP_EXCEPT GET_ANEXT LOAD_CONST YIELD_FROM store POP_BLOCK JUMP_BACK COME_FROM_EXCEPT DUP_TOP LOAD_GLOBAL COMPARE_OP POP_JUMP_IF_TRUE END_FINALLY for_block COME_FROM POP_TOP POP_TOP POP_TOP POP_EXCEPT POP_TOP POP_BLOCK COME_FROM_LOOP
async_for_stmt37 ::= setup_loop . expr GET_AITER _come_froms SETUP_EXCEPT GET_ANEXT LOAD_CONST YIELD_FROM store POP_BLOCK JUMP_BACK COME_FROM_EXCEPT DUP_TOP LOAD_GLOBAL COMPARE_OP POP_JUMP_IF_TRUE END_FINALLY for_block COME_FROM POP_TOP POP_TOP POP_TOP POP_EXCEPT POP_TOP POP_BLOCK COME_FROM_LOOP
async_for_stmt37 ::= setup_loop expr . GET_AITER \e__come_froms SETUP_EXCEPT GET_ANEXT LOAD_CONST YIELD_FROM store POP_BLOCK JUMP_BACK COME_FROM_EXCEPT DUP_TOP LOAD_GLOBAL COMPARE_OP POP_JUMP_IF_TRUE END_FINALLY for_block COME_FROM POP_TOP POP_TOP POP_TOP POP_EXCEPT POP_TOP POP_BLOCK COME_FROM_LOOP
async_for_stmt37 ::= setup_loop expr . GET_AITER _come_froms SETUP_EXCEPT GET_ANEXT LOAD_CONST YIELD_FROM store POP_BLOCK JUMP_BACK COME_FROM_EXCEPT DUP_TOP LOAD_GLOBAL COMPARE_OP POP_JUMP_IF_TRUE END_FINALLY for_block COME_FROM POP_TOP POP_TOP POP_TOP POP_EXCEPT POP_TOP POP_BLOCK COME_FROM_LOOP
async_forelse_stmt ::= setup_loop . expr GET_AITER \e__come_froms SETUP_EXCEPT GET_ANEXT LOAD_CONST YIELD_FROM store POP_BLOCK JUMP_FORWARD COME_FROM_EXCEPT DUP_TOP LOAD_GLOBAL COMPARE_OP POP_JUMP_IF_TRUE END_FINALLY COME_FROM for_block COME_FROM POP_TOP POP_TOP POP_TOP POP_EXCEPT POP_TOP POP_BLOCK else_suite COME_FROM_LOOP
async_forelse_stmt ::= setup_loop . expr GET_AITER _come_froms SETUP_EXCEPT GET_ANEXT LOAD_CONST YIELD_FROM store POP_BLOCK JUMP_FORWARD COME_FROM_EXCEPT DUP_TOP LOAD_GLOBAL COMPARE_OP POP_JUMP_IF_TRUE END_FINALLY COME_FROM for_block COME_FROM POP_TOP POP_TOP POP_TOP POP_EXCEPT POP_TOP POP_BLOCK else_suite COME_FROM_LOOP
async_forelse_stmt ::= setup_loop expr . GET_AITER \e__come_froms SETUP_EXCEPT GET_ANEXT LOAD_CONST YIELD_FROM store POP_BLOCK JUMP_FORWARD COME_FROM_EXCEPT DUP_TOP LOAD_GLOBAL COMPARE_OP POP_JUMP_IF_TRUE END_FINALLY COME_FROM for_block COME_FROM POP_TOP POP_TOP POP_TOP POP_EXCEPT POP_TOP POP_BLOCK else_suite COME_FROM_LOOP
async_forelse_stmt ::= setup_loop expr . GET_AITER _come_froms SETUP_EXCEPT GET_ANEXT LOAD_CONST YIELD_FROM store POP_BLOCK JUMP_FORWARD COME_FROM_EXCEPT DUP_TOP LOAD_GLOBAL COMPARE_OP POP_JUMP_IF_TRUE END_FINALLY COME_FROM for_block COME_FROM POP_TOP POP_TOP POP_TOP POP_EXCEPT POP_TOP POP_BLOCK else_suite COME_FROM_LOOP
attribute ::= expr . LOAD_ATTR
attribute ::= expr LOAD_ATTR . 
attribute37 ::= expr . LOAD_METHOD
attribute37 ::= expr LOAD_METHOD . 
aug_assign1 ::= expr . expr inplace_op ROT_THREE STORE_SUBSCR
aug_assign1 ::= expr . expr inplace_op store
aug_assign1 ::= expr expr . inplace_op ROT_THREE STORE_SUBSCR
aug_assign1 ::= expr expr . inplace_op store
aug_assign2 ::= expr . DUP_TOP LOAD_ATTR expr inplace_op ROT_TWO STORE_ATTR
await_expr ::= expr . GET_AWAITABLE LOAD_CONST YIELD_FROM
bin_op ::= expr . expr binary_operator
bin_op ::= expr expr . binary_operator
call ::= expr . CALL_METHOD_0
call ::= expr . expr CALL_METHOD_1
call ::= expr . pos_arg CALL_FUNCTION_1
call ::= expr . pos_arg pos_arg CALL_FUNCTION_2
call ::= expr CALL_METHOD_0 . 
call ::= expr expr . CALL_METHOD_1
call ::= expr expr CALL_METHOD_1 . 
call ::= expr pos_arg . CALL_FUNCTION_1
call ::= expr pos_arg . pos_arg CALL_FUNCTION_2
call ::= expr pos_arg CALL_FUNCTION_1 . 
call ::= expr pos_arg pos_arg . CALL_FUNCTION_2
call ::= expr pos_arg pos_arg CALL_FUNCTION_2 . 
call_ex ::= expr . starred CALL_FUNCTION_EX
call_ex ::= expr starred . CALL_FUNCTION_EX
call_ex_kw4 ::= expr . expr expr CALL_FUNCTION_EX
call_ex_kw4 ::= expr . expr expr CALL_FUNCTION_EX_KW
call_ex_kw4 ::= expr expr . expr CALL_FUNCTION_EX
call_ex_kw4 ::= expr expr . expr CALL_FUNCTION_EX_KW
call_ex_kw4 ::= expr expr expr . CALL_FUNCTION_EX
call_ex_kw4 ::= expr expr expr . CALL_FUNCTION_EX_KW
call_kw36 ::= expr . expr expr LOAD_CONST CALL_FUNCTION_KW_2
call_kw36 ::= expr expr . expr LOAD_CONST CALL_FUNCTION_KW_2
call_kw36 ::= expr expr expr . LOAD_CONST CALL_FUNCTION_KW_2
call_stmt ::= expr . POP_TOP
classdefdeco1 ::= expr . classdefdeco1 CALL_FUNCTION_1
classdefdeco1 ::= expr . classdefdeco2 CALL_FUNCTION_1
come_from_loops ::= \e_come_from_loops . COME_FROM_LOOP
compare ::= compare_single . 
compare_chained ::= expr . compare_chained1 ROT_TWO POP_TOP \e__come_froms
compare_chained ::= expr . compare_chained1 ROT_TWO POP_TOP _come_froms
compare_chained1 ::= expr . DUP_TOP ROT_THREE COMPARE_OP JUMP_IF_FALSE_OR_POP compare_chained1 COME_FROM
compare_chained1 ::= expr . DUP_TOP ROT_THREE COMPARE_OP JUMP_IF_FALSE_OR_POP compare_chained2 COME_FROM
compare_chained1_false_37 ::= expr . DUP_TOP ROT_THREE COMPARE_OP POP_JUMP_IF_FALSE compare_chained2b_false_37 POP_TOP _jump COME_FROM
compare_chained1_false_37 ::= expr . DUP_TOP ROT_THREE COMPARE_OP POP_JUMP_IF_FALSE compare_chained2c_37 POP_TOP JUMP_FORWARD COME_FROM
compare_chained1a_37 ::= expr . DUP_TOP ROT_THREE COMPARE_OP POP_JUMP_IF_FALSE
compare_chained1a_37 ::= expr . DUP_TOP ROT_THREE COMPARE_OP POP_JUMP_IF_FALSE compare_chained2a_37 COME_FROM POP_TOP COME_FROM
compare_chained1b_false_37 ::= expr . DUP_TOP ROT_THREE COMPARE_OP POP_JUMP_IF_FALSE compare_chained2b_false_37 POP_TOP _jump COME_FROM
compare_chained1c_37 ::= expr . DUP_TOP ROT_THREE COMPARE_OP POP_JUMP_IF_FALSE compare_chained2a_37 POP_TOP
compare_chained2_false_37 ::= expr . DUP_TOP ROT_THREE COMPARE_OP POP_JUMP_IF_FALSE compare_chained2a_false_37 POP_TOP JUMP_BACK COME_FROM
compare_chained37 ::= expr . compare_chained1a_37
compare_chained37 ::= expr . compare_chained1c_37
compare_chained37_false ::= expr . compare_chained1_false_37
compare_chained37_false ::= expr . compare_chained1b_false_37
compare_chained37_false ::= expr . compare_chained2_false_37
compare_single ::= expr . expr COMPARE_OP
compare_single ::= expr expr . COMPARE_OP
compare_single ::= expr expr COMPARE_OP . 
continues ::= _stmts . lastl_stmt continue
expr ::= LOAD_CONST . 
expr ::= LOAD_FAST . 
expr ::= LOAD_GLOBAL . 
expr ::= attribute . 
expr ::= attribute37 . 
expr ::= call . 
expr ::= compare . 
expr ::= generator_exp . 
expr ::= get_iter . 
expr ::= or . 
expr_jit ::= expr . JUMP_IF_TRUE
expr_jitop ::= expr . JUMP_IF_TRUE_OR_POP
expr_jt ::= expr . jmp_true
expr_jt ::= expr jmp_true . 
expr_pjit ::= expr . POP_JUMP_IF_TRUE
expr_pjit ::= expr POP_JUMP_IF_TRUE . 
expr_pjit_come_from ::= expr . POP_JUMP_IF_TRUE COME_FROM
expr_pjit_come_from ::= expr POP_JUMP_IF_TRUE . COME_FROM
expr_pjit_come_from ::= expr POP_JUMP_IF_TRUE COME_FROM . 
expr_stmt ::= expr . POP_TOP
for ::= setup_loop . expr get_for_iter store for_block POP_BLOCK
for ::= setup_loop . expr get_for_iter store for_block POP_BLOCK COME_FROM_LOOP
for ::= setup_loop . expr get_for_iter store for_block POP_BLOCK NOP COME_FROM_LOOP
for ::= setup_loop expr . get_for_iter store for_block POP_BLOCK
for ::= setup_loop expr . get_for_iter store for_block POP_BLOCK COME_FROM_LOOP
for ::= setup_loop expr . get_for_iter store for_block POP_BLOCK NOP COME_FROM_LOOP
for ::= setup_loop expr get_for_iter . store for_block POP_BLOCK
for ::= setup_loop expr get_for_iter . store for_block POP_BLOCK COME_FROM_LOOP
for ::= setup_loop expr get_for_iter . store for_block POP_BLOCK NOP COME_FROM_LOOP
for ::= setup_loop expr get_for_iter store . for_block POP_BLOCK
for ::= setup_loop expr get_for_iter store . for_block POP_BLOCK COME_FROM_LOOP
for ::= setup_loop expr get_for_iter store . for_block POP_BLOCK NOP COME_FROM_LOOP
for ::= setup_loop expr get_for_iter store for_block . POP_BLOCK
for ::= setup_loop expr get_for_iter store for_block . POP_BLOCK COME_FROM_LOOP
for ::= setup_loop expr get_for_iter store for_block . POP_BLOCK NOP COME_FROM_LOOP
for_block ::= \e_l_stmts_opt . COME_FROM_LOOP JUMP_BACK
for_block ::= \e_l_stmts_opt . _come_froms JUMP_BACK
for_block ::= \e_l_stmts_opt . come_from_loops JUMP_BACK
for_block ::= \e_l_stmts_opt \e__come_froms . JUMP_BACK
for_block ::= \e_l_stmts_opt \e_come_from_loops . JUMP_BACK
for_block ::= l_stmts . 
for_block ::= l_stmts . JUMP_BACK
for_block ::= l_stmts_opt . COME_FROM_LOOP JUMP_BACK
for_block ::= l_stmts_opt . _come_froms JUMP_BACK
for_block ::= l_stmts_opt . come_from_loops JUMP_BACK
for_block ::= l_stmts_opt \e__come_froms . JUMP_BACK
for_block ::= l_stmts_opt \e_come_from_loops . JUMP_BACK
forelselaststmt ::= SETUP_LOOP . expr get_for_iter store for_block POP_BLOCK else_suitec \e__come_froms
forelselaststmt ::= SETUP_LOOP . expr get_for_iter store for_block POP_BLOCK else_suitec _come_froms
forelselaststmt ::= SETUP_LOOP expr . get_for_iter store for_block POP_BLOCK else_suitec \e__come_froms
forelselaststmt ::= SETUP_LOOP expr . get_for_iter store for_block POP_BLOCK else_suitec _come_froms
forelselaststmt ::= SETUP_LOOP expr get_for_iter . store for_block POP_BLOCK else_suitec \e__come_froms
forelselaststmt ::= SETUP_LOOP expr get_for_iter . store for_block POP_BLOCK else_suitec _come_froms
forelselaststmt ::= SETUP_LOOP expr get_for_iter store . for_block POP_BLOCK else_suitec \e__come_froms
forelselaststmt ::= SETUP_LOOP expr get_for_iter store . for_block POP_BLOCK else_suitec _come_froms
forelselaststmt ::= SETUP_LOOP expr get_for_iter store for_block . POP_BLOCK else_suitec \e__come_froms
forelselaststmt ::= SETUP_LOOP expr get_for_iter store for_block . POP_BLOCK else_suitec _come_froms
forelselaststmt ::= setup_loop . expr get_for_iter store for_block POP_BLOCK else_suitec COME_FROM_LOOP
forelselaststmt ::= setup_loop expr . get_for_iter store for_block POP_BLOCK else_suitec COME_FROM_LOOP
forelselaststmt ::= setup_loop expr get_for_iter . store for_block POP_BLOCK else_suitec COME_FROM_LOOP
forelselaststmt ::= setup_loop expr get_for_iter store . for_block POP_BLOCK else_suitec COME_FROM_LOOP
forelselaststmt ::= setup_loop expr get_for_iter store for_block . POP_BLOCK else_suitec COME_FROM_LOOP
forelselaststmtl ::= SETUP_LOOP . expr get_for_iter store for_block POP_BLOCK else_suitel \e__come_froms
forelselaststmtl ::= SETUP_LOOP . expr get_for_iter store for_block POP_BLOCK else_suitel _come_froms
forelselaststmtl ::= SETUP_LOOP expr . get_for_iter store for_block POP_BLOCK else_suitel \e__come_froms
forelselaststmtl ::= SETUP_LOOP expr . get_for_iter store for_block POP_BLOCK else_suitel _come_froms
forelselaststmtl ::= SETUP_LOOP expr get_for_iter . store for_block POP_BLOCK else_suitel \e__come_froms
forelselaststmtl ::= SETUP_LOOP expr get_for_iter . store for_block POP_BLOCK else_suitel _come_froms
forelselaststmtl ::= SETUP_LOOP expr get_for_iter store . for_block POP_BLOCK else_suitel \e__come_froms
forelselaststmtl ::= SETUP_LOOP expr get_for_iter store . for_block POP_BLOCK else_suitel _come_froms
forelselaststmtl ::= SETUP_LOOP expr get_for_iter store for_block . POP_BLOCK else_suitel \e__come_froms
forelselaststmtl ::= SETUP_LOOP expr get_for_iter store for_block . POP_BLOCK else_suitel _come_froms
forelselaststmtl ::= setup_loop . expr get_for_iter store for_block POP_BLOCK else_suitel COME_FROM_LOOP
forelselaststmtl ::= setup_loop expr . get_for_iter store for_block POP_BLOCK else_suitel COME_FROM_LOOP
forelselaststmtl ::= setup_loop expr get_for_iter . store for_block POP_BLOCK else_suitel COME_FROM_LOOP
forelselaststmtl ::= setup_loop expr get_for_iter store . for_block POP_BLOCK else_suitel COME_FROM_LOOP
forelselaststmtl ::= setup_loop expr get_for_iter store for_block . POP_BLOCK else_suitel COME_FROM_LOOP
forelsestmt ::= SETUP_LOOP . expr get_for_iter store for_block POP_BLOCK else_suite \e__come_froms
forelsestmt ::= SETUP_LOOP . expr get_for_iter store for_block POP_BLOCK else_suite _come_froms
forelsestmt ::= SETUP_LOOP expr . get_for_iter store for_block POP_BLOCK else_suite \e__come_froms
forelsestmt ::= SETUP_LOOP expr . get_for_iter store for_block POP_BLOCK else_suite _come_froms
forelsestmt ::= SETUP_LOOP expr get_for_iter . store for_block POP_BLOCK else_suite \e__come_froms
forelsestmt ::= SETUP_LOOP expr get_for_iter . store for_block POP_BLOCK else_suite _come_froms
forelsestmt ::= SETUP_LOOP expr get_for_iter store . for_block POP_BLOCK else_suite \e__come_froms
forelsestmt ::= SETUP_LOOP expr get_for_iter store . for_block POP_BLOCK else_suite _come_froms
forelsestmt ::= SETUP_LOOP expr get_for_iter store for_block . POP_BLOCK else_suite \e__come_froms
forelsestmt ::= SETUP_LOOP expr get_for_iter store for_block . POP_BLOCK else_suite _come_froms
forelsestmt ::= setup_loop . expr get_for_iter store for_block POP_BLOCK else_suite COME_FROM_LOOP
forelsestmt ::= setup_loop expr . get_for_iter store for_block POP_BLOCK else_suite COME_FROM_LOOP
forelsestmt ::= setup_loop expr get_for_iter . store for_block POP_BLOCK else_suite COME_FROM_LOOP
forelsestmt ::= setup_loop expr get_for_iter store . for_block POP_BLOCK else_suite COME_FROM_LOOP
forelsestmt ::= setup_loop expr get_for_iter store for_block . POP_BLOCK else_suite COME_FROM_LOOP
generator_exp ::= load_genexpr . LOAD_STR MAKE_FUNCTION_0 expr GET_ITER CALL_FUNCTION_1
generator_exp ::= load_genexpr LOAD_STR . MAKE_FUNCTION_0 expr GET_ITER CALL_FUNCTION_1
generator_exp ::= load_genexpr LOAD_STR MAKE_FUNCTION_0 . expr GET_ITER CALL_FUNCTION_1
generator_exp ::= load_genexpr LOAD_STR MAKE_FUNCTION_0 expr . GET_ITER CALL_FUNCTION_1
generator_exp ::= load_genexpr LOAD_STR MAKE_FUNCTION_0 expr GET_ITER . CALL_FUNCTION_1
generator_exp ::= load_genexpr LOAD_STR MAKE_FUNCTION_0 expr GET_ITER CALL_FUNCTION_1 . 
get_for_iter ::= GET_ITER . _come_froms FOR_ITER
get_for_iter ::= GET_ITER \e__come_froms . FOR_ITER
get_for_iter ::= GET_ITER _come_froms . FOR_ITER
get_for_iter ::= GET_ITER _come_froms FOR_ITER . 
get_iter ::= expr . GET_ITER
get_iter ::= expr GET_ITER . 
if_exp ::= expr . jmp_false expr jf_cf expr COME_FROM
if_exp ::= expr . jmp_false expr jump_absolute_else expr
if_exp ::= expr jmp_false . expr jf_cf expr COME_FROM
if_exp ::= expr jmp_false . expr jump_absolute_else expr
if_exp37 ::= expr . expr jf_cfs expr COME_FROM
if_exp37 ::= expr expr . jf_cfs expr COME_FROM
if_exp_37b ::= expr . jmp_false expr POP_JUMP_IF_FALSE jump_forward_else expr
if_exp_37b ::= expr jmp_false . expr POP_JUMP_IF_FALSE jump_forward_else expr
if_exp_lambda ::= expr . jmp_false expr return_if_lambda return_stmt_lambda LAMBDA_MARKER
if_exp_lambda ::= expr jmp_false . expr return_if_lambda return_stmt_lambda LAMBDA_MARKER
if_exp_not ::= expr . jmp_true expr jump_forward_else expr COME_FROM
if_exp_not ::= expr jmp_true . expr jump_forward_else expr COME_FROM
if_exp_not ::= expr jmp_true expr . jump_forward_else expr COME_FROM
if_exp_not_lambda ::= expr . jmp_true expr return_if_lambda return_stmt_lambda LAMBDA_MARKER
if_exp_not_lambda ::= expr jmp_true . expr return_if_lambda return_stmt_lambda LAMBDA_MARKER
if_exp_not_lambda ::= expr jmp_true expr . return_if_lambda return_stmt_lambda LAMBDA_MARKER
if_exp_true ::= expr . JUMP_FORWARD expr COME_FROM
ifelsestmt ::= testexpr . c_stmts come_froms else_suite come_froms
ifelsestmt ::= testexpr . c_stmts_opt JUMP_FORWARD else_suite \e__come_froms
ifelsestmt ::= testexpr . c_stmts_opt JUMP_FORWARD else_suite \e_opt_come_from_except
ifelsestmt ::= testexpr . c_stmts_opt JUMP_FORWARD else_suite _come_froms
ifelsestmt ::= testexpr . c_stmts_opt JUMP_FORWARD else_suite opt_come_from_except
ifelsestmt ::= testexpr . c_stmts_opt jf_cfs else_suite \e_opt_come_from_except
ifelsestmt ::= testexpr . c_stmts_opt jf_cfs else_suite opt_come_from_except
ifelsestmt ::= testexpr . c_stmts_opt jump_forward_else else_suite \e__come_froms
ifelsestmt ::= testexpr . c_stmts_opt jump_forward_else else_suite _come_froms
ifelsestmt ::= testexpr . stmts jf_cfs \e_else_suite_opt \e_opt_come_from_except
ifelsestmt ::= testexpr . stmts jf_cfs \e_else_suite_opt opt_come_from_except
ifelsestmt ::= testexpr . stmts jf_cfs else_suite_opt \e_opt_come_from_except
ifelsestmt ::= testexpr . stmts jf_cfs else_suite_opt opt_come_from_except
ifelsestmt ::= testexpr \e_c_stmts_opt . JUMP_FORWARD else_suite \e__come_froms
ifelsestmt ::= testexpr \e_c_stmts_opt . JUMP_FORWARD else_suite \e_opt_come_from_except
ifelsestmt ::= testexpr \e_c_stmts_opt . JUMP_FORWARD else_suite _come_froms
ifelsestmt ::= testexpr \e_c_stmts_opt . JUMP_FORWARD else_suite opt_come_from_except
ifelsestmt ::= testexpr \e_c_stmts_opt . jf_cfs else_suite \e_opt_come_from_except
ifelsestmt ::= testexpr \e_c_stmts_opt . jf_cfs else_suite opt_come_from_except
ifelsestmt ::= testexpr \e_c_stmts_opt . jump_forward_else else_suite \e__come_froms
ifelsestmt ::= testexpr \e_c_stmts_opt . jump_forward_else else_suite _come_froms
ifelsestmtc ::= testexpr . c_stmts_opt JUMP_ABSOLUTE else_suitec
ifelsestmtc ::= testexpr . c_stmts_opt JUMP_FORWARD else_suitec
ifelsestmtc ::= testexpr . c_stmts_opt jump_absolute_else else_suitec
ifelsestmtc ::= testexpr \e_c_stmts_opt . JUMP_ABSOLUTE else_suitec
ifelsestmtc ::= testexpr \e_c_stmts_opt . JUMP_FORWARD else_suitec
ifelsestmtc ::= testexpr \e_c_stmts_opt . jump_absolute_else else_suitec
ifelsestmtl ::= testexpr . c_stmts_opt cf_jf_else else_suitel
ifelsestmtl ::= testexpr . c_stmts_opt cf_jump_back else_suitel
ifelsestmtl ::= testexpr . c_stmts_opt jb_cfs else_suitel
ifelsestmtl ::= testexpr . c_stmts_opt jb_else else_suitel
ifelsestmtl ::= testexpr . c_stmts_opt jump_forward_else else_suitec
ifelsestmtl ::= testexpr \e_c_stmts_opt . cf_jf_else else_suitel
ifelsestmtl ::= testexpr \e_c_stmts_opt . cf_jump_back else_suitel
ifelsestmtl ::= testexpr \e_c_stmts_opt . jb_cfs else_suitel
ifelsestmtl ::= testexpr \e_c_stmts_opt . jb_else else_suitel
ifelsestmtl ::= testexpr \e_c_stmts_opt . jump_forward_else else_suitec
ifelsestmtr ::= testexpr . return_if_stmts returns
iflaststmt ::= testexpr . c_stmts
iflaststmt ::= testexpr . c_stmts JUMP_ABSOLUTE
iflaststmt ::= testexpr . c_stmts_opt JUMP_FORWARD
iflaststmt ::= testexpr \e_c_stmts_opt . JUMP_FORWARD
iflaststmtl ::= testexpr . c_stmts
iflaststmtl ::= testexpr . c_stmts JUMP_BACK
iflaststmtl ::= testexpr . c_stmts JUMP_BACK COME_FROM_LOOP
iflaststmtl ::= testexpr . c_stmts JUMP_BACK POP_BLOCK
iflaststmtl ::= testexprl . c_stmts JUMP_BACK
iflaststmtl ::= testexprl . c_stmts JUMP_BACK COME_FROM_LOOP
iflaststmtl ::= testexprl . c_stmts JUMP_BACK POP_BLOCK
ifstmt ::= testexpr . _ifstmts_jump
ifstmtl ::= testexpr . _ifstmts_jumpl
jb_cfs ::= \e_come_from_opt . JUMP_BACK come_froms
jmp_false ::= POP_JUMP_IF_FALSE . 
jmp_true ::= POP_JUMP_IF_TRUE . 
l_stmts ::= _stmts . 
l_stmts ::= _stmts . lastl_stmt
l_stmts ::= l_stmts . lstmt
l_stmts ::= lstmt . 
l_stmts_opt ::= l_stmts . 
lambda_body ::= expr . LOAD_LAMBDA LOAD_STR MAKE_FUNCTION_1
load_genexpr ::= LOAD_GENEXPR . 
lstmt ::= stmt . 
mkfunc ::= expr . LOAD_CODE LOAD_STR MAKE_FUNCTION_1
mkfuncdeco ::= expr . mkfuncdeco CALL_FUNCTION_1
mkfuncdeco ::= expr . mkfuncdeco0 CALL_FUNCTION_1
or ::= expr_jt . expr
or ::= expr_jt . expr COME_FROM
or ::= expr_jt expr . 
or ::= expr_jt expr . COME_FROM
or ::= expr_pjit . expr POP_JUMP_IF_FALSE COME_FROM
or ::= expr_pjit expr . POP_JUMP_IF_FALSE COME_FROM
or ::= expr_pjit_come_from . expr
pos_arg ::= expr . 
ret_and ::= expr . JUMP_IF_FALSE_OR_POP return_expr_or_cond COME_FROM
ret_or ::= expr . JUMP_IF_TRUE_OR_POP return_expr_or_cond COME_FROM
return ::= return_expr . RETURN_END_IF
return ::= return_expr . RETURN_VALUE
return ::= return_expr . RETURN_VALUE COME_FROM
return_expr ::= expr . 
return_expr_lambda ::= return_expr . RETURN_VALUE_LAMBDA
return_expr_lambda ::= return_expr . RETURN_VALUE_LAMBDA LAMBDA_MARKER
return_if_stmt ::= return_expr . RETURN_END_IF
return_if_stmt ::= return_expr . RETURN_END_IF POP_BLOCK
returns ::= _stmts . return
returns ::= _stmts . return_if_stmt
setup_loop ::= SETUP_LOOP . _come_froms
setup_loop ::= SETUP_LOOP \e__come_froms . 
starred ::= expr . 
stmt ::= assign . 
store ::= STORE_FAST . 
store ::= expr . STORE_ATTR
store_subscript ::= expr . expr STORE_SUBSCR
store_subscript ::= expr expr . STORE_SUBSCR
subscript ::= expr . expr BINARY_SUBSCR
subscript ::= expr expr . BINARY_SUBSCR
subscript2 ::= expr . expr DUP_TOP_TWO BINARY_SUBSCR
subscript2 ::= expr expr . DUP_TOP_TWO BINARY_SUBSCR
testexpr ::= testfalse . 
testexpr ::= testtrue . 
testexpr_cf ::= testexpr . come_froms
testexprl ::= testfalsel . 
testfalse ::= expr . jmp_false
testfalse ::= expr jmp_false . 
testfalse ::= or . jmp_false COME_FROM
testfalse_not_and ::= expr . jmp_false expr jmp_true COME_FROM
testfalse_not_and ::= expr jmp_false . expr jmp_true COME_FROM
testfalse_not_or ::= expr . jmp_false expr jmp_false COME_FROM
testfalse_not_or ::= expr jmp_false . expr jmp_false COME_FROM
testfalsel ::= expr . jmp_true
testfalsel ::= expr jmp_true . 
testtrue ::= expr . jmp_true
testtrue ::= expr jmp_true . 
tuple ::= expr . BUILD_TUPLE_1
unary_not ::= expr . UNARY_NOT
unary_op ::= expr . unary_operator
while1elsestmt ::= setup_loop . l_stmts JUMP_BACK POP_BLOCK else_suite COME_FROM_LOOP
while1elsestmt ::= setup_loop . l_stmts JUMP_BACK \e__come_froms POP_BLOCK else_suitel COME_FROM_LOOP
while1elsestmt ::= setup_loop . l_stmts JUMP_BACK _come_froms POP_BLOCK else_suitel COME_FROM_LOOP
while1elsestmt ::= setup_loop . l_stmts JUMP_BACK else_suite COME_FROM_LOOP
while1elsestmt ::= setup_loop . l_stmts JUMP_BACK else_suitel
while1stmt ::= setup_loop . l_stmts COME_FROM JUMP_BACK COME_FROM_LOOP
while1stmt ::= setup_loop . l_stmts COME_FROM JUMP_BACK POP_BLOCK COME_FROM_LOOP
while1stmt ::= setup_loop . l_stmts COME_FROM_LOOP
while1stmt ::= setup_loop . l_stmts COME_FROM_LOOP JUMP_BACK POP_BLOCK COME_FROM_LOOP
while1stmt ::= setup_loop . l_stmts POP_BLOCK COME_FROM_LOOP
whileTruestmt ::= SETUP_LOOP . l_stmts_opt JUMP_BACK COME_FROM_LOOP
whileTruestmt ::= SETUP_LOOP \e_l_stmts_opt . JUMP_BACK COME_FROM_LOOP
whileTruestmt ::= setup_loop . l_stmts_opt JUMP_BACK POP_BLOCK \e__come_froms
whileTruestmt ::= setup_loop . l_stmts_opt JUMP_BACK POP_BLOCK _come_froms
whileTruestmt ::= setup_loop \e_l_stmts_opt . JUMP_BACK POP_BLOCK \e__come_froms
whileTruestmt ::= setup_loop \e_l_stmts_opt . JUMP_BACK POP_BLOCK _come_froms
whileelsestmt ::= setup_loop . testexpr \e_l_stmts_opt JUMP_BACK POP_BLOCK else_suitel COME_FROM
whileelsestmt ::= setup_loop . testexpr \e_l_stmts_opt JUMP_BACK POP_BLOCK else_suitel COME_FROM_LOOP
whileelsestmt ::= setup_loop . testexpr l_stmts_opt JUMP_BACK POP_BLOCK else_suitel COME_FROM
whileelsestmt ::= setup_loop . testexpr l_stmts_opt JUMP_BACK POP_BLOCK else_suitel COME_FROM_LOOP
whilestmt ::= setup_loop . testexpr \e_l_stmts_opt COME_FROM JUMP_BACK POP_BLOCK COME_FROM_LOOP
whilestmt ::= setup_loop . testexpr \e_l_stmts_opt JUMP_BACK POP_BLOCK COME_FROM_LOOP
whilestmt ::= setup_loop . testexpr \e_l_stmts_opt JUMP_BACK come_froms POP_BLOCK
whilestmt ::= setup_loop . testexpr \e_l_stmts_opt JUMP_BACK come_froms POP_BLOCK COME_FROM_LOOP
whilestmt ::= setup_loop . testexpr \e_l_stmts_opt come_froms JUMP_BACK come_froms POP_BLOCK COME_FROM_LOOP
whilestmt ::= setup_loop . testexpr l_stmts_opt COME_FROM JUMP_BACK POP_BLOCK COME_FROM_LOOP
whilestmt ::= setup_loop . testexpr l_stmts_opt JUMP_BACK POP_BLOCK COME_FROM_LOOP
whilestmt ::= setup_loop . testexpr l_stmts_opt JUMP_BACK come_froms POP_BLOCK
whilestmt ::= setup_loop . testexpr l_stmts_opt JUMP_BACK come_froms POP_BLOCK COME_FROM_LOOP
whilestmt ::= setup_loop . testexpr l_stmts_opt come_froms JUMP_BACK come_froms POP_BLOCK COME_FROM_LOOP
whilestmt ::= setup_loop . testexpr returns POP_BLOCK COME_FROM_LOOP
whilestmt ::= setup_loop . testexpr returns come_froms POP_BLOCK COME_FROM_LOOP
yield ::= expr . YIELD_VALUE
yield_from ::= expr . GET_YIELD_FROM_ITER LOAD_CONST YIELD_FROM
Instruction context:
   
 L.  83        60  LOAD_FAST                'sim_info'
                  62  LOAD_CONST               None
                  64  COMPARE_OP               is
                  66  POP_JUMP_IF_TRUE     84  'to 84'
                  68  LOAD_FAST                'sim_info'
                  70  LOAD_ATTR                household
                  72  LOAD_FAST                'household'
                  74  COMPARE_OP               is-not
                  76  POP_JUMP_IF_TRUE     84  'to 84'
                  78  LOAD_FAST                'sim_info'
                  80  LOAD_ATTR                is_baby
                  82  POP_JUMP_IF_TRUE     42  'to 42'
                84_0  COME_FROM            76  '76'
->              84_1  COME_FROM            66  '66'
from build_buy import find_objects_in_household_inventory, remove_object_from_household_inventory, object_exists_in_household_inventory
from objects import HiddenReasonFlag
from objects.object_enums import ResetReason
from objects.system import create_object
from sims.baby.baby_tuning import BabyTuning
import services, sims4.log
logger = sims4.log.Logger('Baby')

def assign_bassinet_for_baby(sim_info):
    object_manager = services.object_manager()
    for bassinet in (object_manager.get_objects_of_type_gen)(*BabyTuning.BABY_BASSINET_DEFINITION_MAP.values()):
        if not bassinet.transient:
            set_baby_sim_info_with_switch_id(bassinet, sim_info)
            bassinet.destroy(source=sim_info, cause='Assigned bassinet for baby.')
            return True

    return False


def assign_to_bassinet(sim_info):
    if object_exists_in_household_inventory(sim_info.id, sim_info.household_id):
        return
    bassinet = services.object_manager().get(sim_info.sim_id)
    if bassinet is None:
        if assign_bassinet_for_baby(sim_info):
            return
        create_and_place_baby(sim_info)


def create_and_place_baby(sim_info, position=None, routing_surface=None, **kwargs):
    bassinet = create_object((BabyTuning.get_default_definition(sim_info)), obj_id=(sim_info.sim_id))
    (bassinet.set_sim_info)(sim_info, **kwargs)
    bassinet.place_in_good_location(position=position, routing_surface=routing_surface)
    sim_info.suppress_aging()


def remove_stale_babies--- This code section failed: ---

 L.  80         0  LOAD_FAST                'household'
                2  LOAD_GLOBAL              services
                4  LOAD_METHOD              active_household
                6  CALL_METHOD_0         0  '0 positional arguments'
                8  COMPARE_OP               is
               10  POP_JUMP_IF_FALSE    98  'to 98'

 L.  81        12  SETUP_LOOP           98  'to 98'
               14  LOAD_GLOBAL              find_objects_in_household_inventory
               16  LOAD_GLOBAL              tuple
               18  LOAD_GENEXPR             '<code_object <genexpr>>'
               20  LOAD_STR                 'remove_stale_babies.<locals>.<genexpr>'
               22  MAKE_FUNCTION_0          'Neither defaults, keyword-only args, annotations, nor closures'
               24  LOAD_GLOBAL              BabyTuning
               26  LOAD_ATTR                BABY_BASSINET_DEFINITION_MAP
               28  GET_ITER         
               30  CALL_FUNCTION_1       1  '1 positional argument'
               32  CALL_FUNCTION_1       1  '1 positional argument'
               34  LOAD_FAST                'household'
               36  LOAD_ATTR                id
               38  CALL_FUNCTION_2       2  '2 positional arguments'
               40  GET_ITER         
             42_0  COME_FROM            82  '82'
               42  FOR_ITER             96  'to 96'
               44  STORE_FAST               'obj_id'

 L.  82        46  LOAD_GLOBAL              services
               48  LOAD_METHOD              sim_info_manager
               50  CALL_METHOD_0         0  '0 positional arguments'
               52  LOAD_METHOD              get
               54  LOAD_FAST                'obj_id'
               56  CALL_METHOD_1         1  '1 positional argument'
               58  STORE_FAST               'sim_info'

 L.  83        60  LOAD_FAST                'sim_info'
               62  LOAD_CONST               None
               64  COMPARE_OP               is
               66  POP_JUMP_IF_TRUE     84  'to 84'
               68  LOAD_FAST                'sim_info'
               70  LOAD_ATTR                household
               72  LOAD_FAST                'household'
               74  COMPARE_OP               is-not
               76  POP_JUMP_IF_TRUE     84  'to 84'
               78  LOAD_FAST                'sim_info'
               80  LOAD_ATTR                is_baby
               82  POP_JUMP_IF_TRUE     42  'to 42'
             84_0  COME_FROM            76  '76'
             84_1  COME_FROM            66  '66'

 L.  84        84  LOAD_GLOBAL              remove_object_from_household_inventory
               86  LOAD_FAST                'obj_id'
               88  LOAD_FAST                'household'
               90  CALL_FUNCTION_2       2  '2 positional arguments'
               92  POP_TOP          
               94  JUMP_BACK            42  'to 42'
               96  POP_BLOCK        
             98_0  COME_FROM_LOOP       12  '12'
             98_1  COME_FROM            10  '10'

Parse error at or near `COME_FROM' instruction at offset 84_1


def replace_bassinet(sim_info, bassinet=None, safe_destroy=False):
    bassinet = bassinet if bassinet is not None else services.object_manager().get(sim_info.sim_id)
    if bassinet is not None:
        empty_bassinet = create_object(BabyTuning.get_corresponding_definition(bassinet.definition))
        empty_bassinet.location = bassinet.location
        if safe_destroy:
            bassinet.make_transient()
        else:
            bassinet.reset(ResetReason.RESET_EXPECTED, None, 'Replacing Bassinet with child')
            bassinet.destroy(source=sim_info, cause='Replaced bassinet with empty version')
        return empty_bassinet


def run_baby_spawn_behavior(sim_info):
    sim_info.set_zone_on_spawn()
    if sim_info.is_baby:
        assign_to_bassinet(sim_info)
    else:
        replace_bassinet(sim_info)
    return True


def set_baby_sim_info_with_switch_id(bassinet, sim_info, **kwargs):
    if bassinet.id != sim_info.sim_id:
        new_bassinet = None
        try:
            try:
                bassinet_definition = BabyTuning.get_corresponding_definition(bassinet.definition)
                new_bassinet = create_object(bassinet_definition, obj_id=(sim_info.sim_id))
                (new_bassinet.set_sim_info)(sim_info, **kwargs)
                new_bassinet.location = bassinet.location
            except:
                logger.exception('{} fail to set sim_info {}', bassinet, sim_info)
                if new_bassinet is not None:
                    new_bassinet.destroy(source=sim_info, cause='Failed to set sim_info on bassinet')

        finally:
            sim_info.suppress_aging()
            bassinet.hide(HiddenReasonFlag.REPLACEMENT)

        return new_bassinet
