# uncompyle6 version 3.9.0
# Python bytecode version base 3.7.0 (3394)
# Decompiled from: Python 3.7.16 (default, Dec  7 2022, 01:12:33) 
# [GCC 11.3.0]
# Embedded file name: T:\InGame\Gameplay\Scripts\Server\drama_scheduler\dialog_drama_node.py
# Compiled at: 2021-10-28 01:46:57
# Size of source mod 2**32: 16660 bytes

-- Stacks of completed symbols:
START ::= |- stmts . 
_come_froms ::= \e__come_froms . COME_FROM
_come_froms ::= \e__come_froms . COME_FROM_LOOP
_come_froms ::= \e__come_froms COME_FROM . 
_come_froms ::= _come_froms . COME_FROM
_come_froms ::= _come_froms . COME_FROM_LOOP
_ifstmts_jump ::= \e_c_stmts_opt . COME_FROM
_ifstmts_jump ::= \e_c_stmts_opt . ELSE
_ifstmts_jump ::= \e_c_stmts_opt . JUMP_ABSOLUTE JUMP_FORWARD \e__come_froms
_ifstmts_jump ::= \e_c_stmts_opt . JUMP_ABSOLUTE JUMP_FORWARD _come_froms
_ifstmts_jump ::= \e_c_stmts_opt . come_froms
_ifstmts_jump ::= c_stmts_opt . COME_FROM
_ifstmts_jump ::= c_stmts_opt . ELSE
_ifstmts_jump ::= c_stmts_opt . JUMP_ABSOLUTE JUMP_FORWARD \e__come_froms
_ifstmts_jump ::= c_stmts_opt . JUMP_ABSOLUTE JUMP_FORWARD _come_froms
_ifstmts_jump ::= c_stmts_opt . come_froms
_ifstmts_jump ::= c_stmts_opt COME_FROM . 
_ifstmts_jump ::= c_stmts_opt come_froms . 
_ifstmts_jumpl ::= _ifstmts_jump . 
_ifstmts_jumpl ::= c_stmts . JUMP_BACK
_stmts ::= _stmts . stmt
_stmts ::= stmt . 
and ::= expr . JUMP_IF_FALSE_OR_POP expr \e_come_from_opt
and ::= expr . JUMP_IF_FALSE_OR_POP expr come_from_opt
and ::= expr . jifop_come_from expr
and ::= expr . jmp_false expr
and ::= expr . jmp_false expr COME_FROM
and ::= expr . jmp_false expr jmp_false
and ::= expr jmp_false . expr
and ::= expr jmp_false . expr COME_FROM
and ::= expr jmp_false . expr jmp_false
and ::= expr jmp_false expr . 
and ::= expr jmp_false expr . COME_FROM
and ::= expr jmp_false expr . jmp_false
and ::= expr jmp_false expr jmp_false . 
and_not ::= expr . jmp_false expr POP_JUMP_IF_TRUE
and_not ::= expr jmp_false . expr POP_JUMP_IF_TRUE
and_not ::= expr jmp_false expr . POP_JUMP_IF_TRUE
assert2 ::= expr . jmp_true LOAD_GLOBAL expr CALL_FUNCTION_1 RAISE_VARARGS_1
assign ::= expr . DUP_TOP designList
assign ::= expr . store
assign ::= expr store . 
assign2 ::= expr . expr ROT_TWO store store
assign2 ::= expr expr . ROT_TWO store store
assign3 ::= expr . expr expr ROT_THREE ROT_TWO store store store
assign3 ::= expr expr . expr ROT_THREE ROT_TWO store store store
assign3 ::= expr expr expr . ROT_THREE ROT_TWO store store store
async_for_stmt ::= setup_loop . expr GET_AITER LOAD_CONST YIELD_FROM SETUP_EXCEPT GET_ANEXT LOAD_CONST YIELD_FROM store POP_BLOCK JUMP_FORWARD COME_FROM_EXCEPT DUP_TOP LOAD_GLOBAL COMPARE_OP POP_JUMP_IF_FALSE POP_TOP POP_TOP POP_TOP POP_EXCEPT POP_BLOCK JUMP_ABSOLUTE END_FINALLY COME_FROM for_block POP_BLOCK COME_FROM_LOOP
async_for_stmt ::= setup_loop . expr GET_AITER SETUP_EXCEPT GET_ANEXT LOAD_CONST YIELD_FROM store POP_BLOCK JUMP_FORWARD COME_FROM_EXCEPT DUP_TOP LOAD_GLOBAL COMPARE_OP POP_JUMP_IF_TRUE END_FINALLY COME_FROM for_block COME_FROM POP_TOP POP_TOP POP_TOP POP_EXCEPT POP_TOP POP_BLOCK COME_FROM_LOOP
async_for_stmt ::= setup_loop expr . GET_AITER LOAD_CONST YIELD_FROM SETUP_EXCEPT GET_ANEXT LOAD_CONST YIELD_FROM store POP_BLOCK JUMP_FORWARD COME_FROM_EXCEPT DUP_TOP LOAD_GLOBAL COMPARE_OP POP_JUMP_IF_FALSE POP_TOP POP_TOP POP_TOP POP_EXCEPT POP_BLOCK JUMP_ABSOLUTE END_FINALLY COME_FROM for_block POP_BLOCK COME_FROM_LOOP
async_for_stmt ::= setup_loop expr . GET_AITER SETUP_EXCEPT GET_ANEXT LOAD_CONST YIELD_FROM store POP_BLOCK JUMP_FORWARD COME_FROM_EXCEPT DUP_TOP LOAD_GLOBAL COMPARE_OP POP_JUMP_IF_TRUE END_FINALLY COME_FROM for_block COME_FROM POP_TOP POP_TOP POP_TOP POP_EXCEPT POP_TOP POP_BLOCK COME_FROM_LOOP
async_for_stmt37 ::= setup_loop . expr GET_AITER \e__come_froms SETUP_EXCEPT GET_ANEXT LOAD_CONST YIELD_FROM store POP_BLOCK JUMP_BACK COME_FROM_EXCEPT DUP_TOP LOAD_GLOBAL COMPARE_OP POP_JUMP_IF_TRUE END_FINALLY for_block COME_FROM POP_TOP POP_TOP POP_TOP POP_EXCEPT POP_TOP POP_BLOCK COME_FROM_LOOP
async_for_stmt37 ::= setup_loop . expr GET_AITER _come_froms SETUP_EXCEPT GET_ANEXT LOAD_CONST YIELD_FROM store POP_BLOCK JUMP_BACK COME_FROM_EXCEPT DUP_TOP LOAD_GLOBAL COMPARE_OP POP_JUMP_IF_TRUE END_FINALLY for_block COME_FROM POP_TOP POP_TOP POP_TOP POP_EXCEPT POP_TOP POP_BLOCK COME_FROM_LOOP
async_for_stmt37 ::= setup_loop expr . GET_AITER \e__come_froms SETUP_EXCEPT GET_ANEXT LOAD_CONST YIELD_FROM store POP_BLOCK JUMP_BACK COME_FROM_EXCEPT DUP_TOP LOAD_GLOBAL COMPARE_OP POP_JUMP_IF_TRUE END_FINALLY for_block COME_FROM POP_TOP POP_TOP POP_TOP POP_EXCEPT POP_TOP POP_BLOCK COME_FROM_LOOP
async_for_stmt37 ::= setup_loop expr . GET_AITER _come_froms SETUP_EXCEPT GET_ANEXT LOAD_CONST YIELD_FROM store POP_BLOCK JUMP_BACK COME_FROM_EXCEPT DUP_TOP LOAD_GLOBAL COMPARE_OP POP_JUMP_IF_TRUE END_FINALLY for_block COME_FROM POP_TOP POP_TOP POP_TOP POP_EXCEPT POP_TOP POP_BLOCK COME_FROM_LOOP
async_forelse_stmt ::= setup_loop . expr GET_AITER \e__come_froms SETUP_EXCEPT GET_ANEXT LOAD_CONST YIELD_FROM store POP_BLOCK JUMP_FORWARD COME_FROM_EXCEPT DUP_TOP LOAD_GLOBAL COMPARE_OP POP_JUMP_IF_TRUE END_FINALLY COME_FROM for_block COME_FROM POP_TOP POP_TOP POP_TOP POP_EXCEPT POP_TOP POP_BLOCK else_suite COME_FROM_LOOP
async_forelse_stmt ::= setup_loop . expr GET_AITER _come_froms SETUP_EXCEPT GET_ANEXT LOAD_CONST YIELD_FROM store POP_BLOCK JUMP_FORWARD COME_FROM_EXCEPT DUP_TOP LOAD_GLOBAL COMPARE_OP POP_JUMP_IF_TRUE END_FINALLY COME_FROM for_block COME_FROM POP_TOP POP_TOP POP_TOP POP_EXCEPT POP_TOP POP_BLOCK else_suite COME_FROM_LOOP
async_forelse_stmt ::= setup_loop expr . GET_AITER \e__come_froms SETUP_EXCEPT GET_ANEXT LOAD_CONST YIELD_FROM store POP_BLOCK JUMP_FORWARD COME_FROM_EXCEPT DUP_TOP LOAD_GLOBAL COMPARE_OP POP_JUMP_IF_TRUE END_FINALLY COME_FROM for_block COME_FROM POP_TOP POP_TOP POP_TOP POP_EXCEPT POP_TOP POP_BLOCK else_suite COME_FROM_LOOP
async_forelse_stmt ::= setup_loop expr . GET_AITER _come_froms SETUP_EXCEPT GET_ANEXT LOAD_CONST YIELD_FROM store POP_BLOCK JUMP_FORWARD COME_FROM_EXCEPT DUP_TOP LOAD_GLOBAL COMPARE_OP POP_JUMP_IF_TRUE END_FINALLY COME_FROM for_block COME_FROM POP_TOP POP_TOP POP_TOP POP_EXCEPT POP_TOP POP_BLOCK else_suite COME_FROM_LOOP
attribute ::= expr . LOAD_ATTR
attribute ::= expr LOAD_ATTR . 
attribute37 ::= expr . LOAD_METHOD
attribute37 ::= expr LOAD_METHOD . 
aug_assign1 ::= expr . expr inplace_op ROT_THREE STORE_SUBSCR
aug_assign1 ::= expr . expr inplace_op store
aug_assign1 ::= expr expr . inplace_op ROT_THREE STORE_SUBSCR
aug_assign1 ::= expr expr . inplace_op store
aug_assign2 ::= expr . DUP_TOP LOAD_ATTR expr inplace_op ROT_TWO STORE_ATTR
await_expr ::= expr . GET_AWAITABLE LOAD_CONST YIELD_FROM
bin_op ::= expr . expr binary_operator
bin_op ::= expr expr . binary_operator
c_stmts ::= _stmts . 
c_stmts ::= _stmts . lastc_stmt
c_stmts ::= lastc_stmt . 
c_stmts_opt ::= c_stmts . 
call ::= expr . CALL_METHOD_0
call ::= expr . expr CALL_METHOD_1
call ::= expr . expr expr CALL_METHOD_2
call ::= expr . pos_arg pos_arg pos_arg CALL_FUNCTION_3
call ::= expr . pos_arg pos_arg pos_arg pos_arg CALL_FUNCTION_4
call ::= expr CALL_METHOD_0 . 
call ::= expr expr . CALL_METHOD_1
call ::= expr expr . expr CALL_METHOD_2
call ::= expr expr CALL_METHOD_1 . 
call ::= expr expr expr . CALL_METHOD_2
call ::= expr pos_arg . pos_arg pos_arg CALL_FUNCTION_3
call ::= expr pos_arg . pos_arg pos_arg pos_arg CALL_FUNCTION_4
call ::= expr pos_arg pos_arg . pos_arg CALL_FUNCTION_3
call ::= expr pos_arg pos_arg . pos_arg pos_arg CALL_FUNCTION_4
call ::= expr pos_arg pos_arg pos_arg . CALL_FUNCTION_3
call ::= expr pos_arg pos_arg pos_arg . pos_arg CALL_FUNCTION_4
call ::= expr pos_arg pos_arg pos_arg pos_arg . CALL_FUNCTION_4
call_kw36 ::= expr . expr LOAD_CONST CALL_FUNCTION_KW_1
call_kw36 ::= expr . expr expr LOAD_CONST CALL_FUNCTION_KW_2
call_kw36 ::= expr . expr expr expr LOAD_CONST CALL_FUNCTION_KW_3
call_kw36 ::= expr expr . LOAD_CONST CALL_FUNCTION_KW_1
call_kw36 ::= expr expr . expr LOAD_CONST CALL_FUNCTION_KW_2
call_kw36 ::= expr expr . expr expr LOAD_CONST CALL_FUNCTION_KW_3
call_kw36 ::= expr expr LOAD_CONST . CALL_FUNCTION_KW_1
call_kw36 ::= expr expr LOAD_CONST CALL_FUNCTION_KW_1 . 
call_kw36 ::= expr expr expr . LOAD_CONST CALL_FUNCTION_KW_2
call_kw36 ::= expr expr expr . expr LOAD_CONST CALL_FUNCTION_KW_3
call_kw36 ::= expr expr expr LOAD_CONST . CALL_FUNCTION_KW_2
call_kw36 ::= expr expr expr LOAD_CONST CALL_FUNCTION_KW_2 . 
call_kw36 ::= expr expr expr expr . LOAD_CONST CALL_FUNCTION_KW_3
call_kw36 ::= expr expr expr expr LOAD_CONST . CALL_FUNCTION_KW_3
call_kw36 ::= expr expr expr expr LOAD_CONST CALL_FUNCTION_KW_3 . 
call_stmt ::= expr . POP_TOP
call_stmt ::= expr POP_TOP . 
cf_jf_else ::= come_froms . JUMP_FORWARD ELSE
cf_jump_back ::= COME_FROM . JUMP_BACK
come_from_loops ::= \e_come_from_loops . COME_FROM_LOOP
come_from_opt ::= COME_FROM . 
come_froms ::= COME_FROM . 
come_froms ::= come_froms . COME_FROM
come_froms ::= come_froms COME_FROM . 
compare ::= compare_single . 
compare_chained ::= expr . compare_chained1 ROT_TWO POP_TOP \e__come_froms
compare_chained ::= expr . compare_chained1 ROT_TWO POP_TOP _come_froms
compare_chained1 ::= expr . DUP_TOP ROT_THREE COMPARE_OP JUMP_IF_FALSE_OR_POP compare_chained1 COME_FROM
compare_chained1 ::= expr . DUP_TOP ROT_THREE COMPARE_OP JUMP_IF_FALSE_OR_POP compare_chained2 COME_FROM
compare_chained1_false_37 ::= expr . DUP_TOP ROT_THREE COMPARE_OP POP_JUMP_IF_FALSE compare_chained2b_false_37 POP_TOP _jump COME_FROM
compare_chained1_false_37 ::= expr . DUP_TOP ROT_THREE COMPARE_OP POP_JUMP_IF_FALSE compare_chained2c_37 POP_TOP JUMP_FORWARD COME_FROM
compare_chained1a_37 ::= expr . DUP_TOP ROT_THREE COMPARE_OP POP_JUMP_IF_FALSE
compare_chained1a_37 ::= expr . DUP_TOP ROT_THREE COMPARE_OP POP_JUMP_IF_FALSE compare_chained2a_37 COME_FROM POP_TOP COME_FROM
compare_chained1b_false_37 ::= expr . DUP_TOP ROT_THREE COMPARE_OP POP_JUMP_IF_FALSE compare_chained2b_false_37 POP_TOP _jump COME_FROM
compare_chained1c_37 ::= expr . DUP_TOP ROT_THREE COMPARE_OP POP_JUMP_IF_FALSE compare_chained2a_37 POP_TOP
compare_chained2_false_37 ::= expr . DUP_TOP ROT_THREE COMPARE_OP POP_JUMP_IF_FALSE compare_chained2a_false_37 POP_TOP JUMP_BACK COME_FROM
compare_chained37 ::= expr . compare_chained1a_37
compare_chained37 ::= expr . compare_chained1c_37
compare_chained37_false ::= expr . compare_chained1_false_37
compare_chained37_false ::= expr . compare_chained1b_false_37
compare_chained37_false ::= expr . compare_chained2_false_37
compare_single ::= expr . expr COMPARE_OP
compare_single ::= expr expr . COMPARE_OP
compare_single ::= expr expr COMPARE_OP . 
continues ::= _stmts . lastl_stmt continue
continues ::= lastl_stmt . continue
dict ::= expr . expr LOAD_CONST BUILD_CONST_KEY_MAP_2
dict ::= expr . expr expr LOAD_CONST BUILD_CONST_KEY_MAP_3
dict ::= expr . expr expr expr expr LOAD_CONST BUILD_CONST_KEY_MAP_5
dict ::= expr expr . LOAD_CONST BUILD_CONST_KEY_MAP_2
dict ::= expr expr . expr LOAD_CONST BUILD_CONST_KEY_MAP_3
dict ::= expr expr . expr expr expr LOAD_CONST BUILD_CONST_KEY_MAP_5
dict ::= expr expr LOAD_CONST . BUILD_CONST_KEY_MAP_2
dict ::= expr expr expr . LOAD_CONST BUILD_CONST_KEY_MAP_3
dict ::= expr expr expr . expr expr LOAD_CONST BUILD_CONST_KEY_MAP_5
dict ::= expr expr expr LOAD_CONST . BUILD_CONST_KEY_MAP_3
dict ::= expr expr expr expr . expr LOAD_CONST BUILD_CONST_KEY_MAP_5
dict ::= expr expr expr expr expr . LOAD_CONST BUILD_CONST_KEY_MAP_5
dict ::= expr expr expr expr expr LOAD_CONST . BUILD_CONST_KEY_MAP_5
dict ::= expr expr expr expr expr LOAD_CONST BUILD_CONST_KEY_MAP_5 . 
else_suitec ::= c_stmts . 
expr ::= LOAD_CODE . 
expr ::= LOAD_CONST . 
expr ::= LOAD_DEREF . 
expr ::= LOAD_FAST . 
expr ::= LOAD_GLOBAL . 
expr ::= LOAD_NAME . 
expr ::= LOAD_STR . 
expr ::= attribute . 
expr ::= attribute37 . 
expr ::= call . 
expr ::= call_kw36 . 
expr ::= compare . 
expr ::= dict . 
expr ::= get_iter . 
expr ::= if_exp . 
expr_jit ::= expr . JUMP_IF_TRUE
expr_jitop ::= expr . JUMP_IF_TRUE_OR_POP
expr_jt ::= expr . jmp_true
expr_pjit ::= expr . POP_JUMP_IF_TRUE
expr_pjit_come_from ::= expr . POP_JUMP_IF_TRUE COME_FROM
expr_stmt ::= expr . POP_TOP
expr_stmt ::= expr POP_TOP . 
for ::= setup_loop . expr get_for_iter store for_block POP_BLOCK
for ::= setup_loop . expr get_for_iter store for_block POP_BLOCK COME_FROM_LOOP
for ::= setup_loop . expr get_for_iter store for_block POP_BLOCK NOP COME_FROM_LOOP
for ::= setup_loop expr . get_for_iter store for_block POP_BLOCK
for ::= setup_loop expr . get_for_iter store for_block POP_BLOCK COME_FROM_LOOP
for ::= setup_loop expr . get_for_iter store for_block POP_BLOCK NOP COME_FROM_LOOP
for ::= setup_loop expr get_for_iter . store for_block POP_BLOCK
for ::= setup_loop expr get_for_iter . store for_block POP_BLOCK COME_FROM_LOOP
for ::= setup_loop expr get_for_iter . store for_block POP_BLOCK NOP COME_FROM_LOOP
for ::= setup_loop expr get_for_iter store . for_block POP_BLOCK
for ::= setup_loop expr get_for_iter store . for_block POP_BLOCK COME_FROM_LOOP
for ::= setup_loop expr get_for_iter store . for_block POP_BLOCK NOP COME_FROM_LOOP
for ::= setup_loop expr get_for_iter store for_block . POP_BLOCK
for ::= setup_loop expr get_for_iter store for_block . POP_BLOCK COME_FROM_LOOP
for ::= setup_loop expr get_for_iter store for_block . POP_BLOCK NOP COME_FROM_LOOP
for ::= setup_loop expr get_for_iter store for_block POP_BLOCK . 
for ::= setup_loop expr get_for_iter store for_block POP_BLOCK . COME_FROM_LOOP
for ::= setup_loop expr get_for_iter store for_block POP_BLOCK . NOP COME_FROM_LOOP
for ::= setup_loop expr get_for_iter store for_block POP_BLOCK COME_FROM_LOOP . 
for_block ::= \e_l_stmts_opt . COME_FROM_LOOP JUMP_BACK
for_block ::= \e_l_stmts_opt . _come_froms JUMP_BACK
for_block ::= \e_l_stmts_opt . come_from_loops JUMP_BACK
for_block ::= \e_l_stmts_opt \e__come_froms . JUMP_BACK
for_block ::= \e_l_stmts_opt \e_come_from_loops . JUMP_BACK
for_block ::= l_stmts . 
for_block ::= l_stmts . JUMP_BACK
for_block ::= l_stmts JUMP_BACK . 
for_block ::= l_stmts_opt . COME_FROM_LOOP JUMP_BACK
for_block ::= l_stmts_opt . _come_froms JUMP_BACK
for_block ::= l_stmts_opt . come_from_loops JUMP_BACK
for_block ::= l_stmts_opt \e__come_froms . JUMP_BACK
for_block ::= l_stmts_opt \e__come_froms JUMP_BACK . 
for_block ::= l_stmts_opt \e_come_from_loops . JUMP_BACK
for_block ::= l_stmts_opt \e_come_from_loops JUMP_BACK . 
forelselaststmt ::= SETUP_LOOP . expr get_for_iter store for_block POP_BLOCK else_suitec \e__come_froms
forelselaststmt ::= SETUP_LOOP . expr get_for_iter store for_block POP_BLOCK else_suitec _come_froms
forelselaststmt ::= SETUP_LOOP expr . get_for_iter store for_block POP_BLOCK else_suitec \e__come_froms
forelselaststmt ::= SETUP_LOOP expr . get_for_iter store for_block POP_BLOCK else_suitec _come_froms
forelselaststmt ::= SETUP_LOOP expr get_for_iter . store for_block POP_BLOCK else_suitec \e__come_froms
forelselaststmt ::= SETUP_LOOP expr get_for_iter . store for_block POP_BLOCK else_suitec _come_froms
forelselaststmt ::= SETUP_LOOP expr get_for_iter store . for_block POP_BLOCK else_suitec \e__come_froms
forelselaststmt ::= SETUP_LOOP expr get_for_iter store . for_block POP_BLOCK else_suitec _come_froms
forelselaststmt ::= SETUP_LOOP expr get_for_iter store for_block . POP_BLOCK else_suitec \e__come_froms
forelselaststmt ::= SETUP_LOOP expr get_for_iter store for_block . POP_BLOCK else_suitec _come_froms
forelselaststmt ::= SETUP_LOOP expr get_for_iter store for_block POP_BLOCK . else_suitec \e__come_froms
forelselaststmt ::= SETUP_LOOP expr get_for_iter store for_block POP_BLOCK . else_suitec _come_froms
forelselaststmt ::= setup_loop . expr get_for_iter store for_block POP_BLOCK else_suitec COME_FROM_LOOP
forelselaststmt ::= setup_loop expr . get_for_iter store for_block POP_BLOCK else_suitec COME_FROM_LOOP
forelselaststmt ::= setup_loop expr get_for_iter . store for_block POP_BLOCK else_suitec COME_FROM_LOOP
forelselaststmt ::= setup_loop expr get_for_iter store . for_block POP_BLOCK else_suitec COME_FROM_LOOP
forelselaststmt ::= setup_loop expr get_for_iter store for_block . POP_BLOCK else_suitec COME_FROM_LOOP
forelselaststmt ::= setup_loop expr get_for_iter store for_block POP_BLOCK . else_suitec COME_FROM_LOOP
forelselaststmtl ::= SETUP_LOOP . expr get_for_iter store for_block POP_BLOCK else_suitel \e__come_froms
forelselaststmtl ::= SETUP_LOOP . expr get_for_iter store for_block POP_BLOCK else_suitel _come_froms
forelselaststmtl ::= SETUP_LOOP expr . get_for_iter store for_block POP_BLOCK else_suitel \e__come_froms
forelselaststmtl ::= SETUP_LOOP expr . get_for_iter store for_block POP_BLOCK else_suitel _come_froms
forelselaststmtl ::= SETUP_LOOP expr get_for_iter . store for_block POP_BLOCK else_suitel \e__come_froms
forelselaststmtl ::= SETUP_LOOP expr get_for_iter . store for_block POP_BLOCK else_suitel _come_froms
forelselaststmtl ::= SETUP_LOOP expr get_for_iter store . for_block POP_BLOCK else_suitel \e__come_froms
forelselaststmtl ::= SETUP_LOOP expr get_for_iter store . for_block POP_BLOCK else_suitel _come_froms
forelselaststmtl ::= SETUP_LOOP expr get_for_iter store for_block . POP_BLOCK else_suitel \e__come_froms
forelselaststmtl ::= SETUP_LOOP expr get_for_iter store for_block . POP_BLOCK else_suitel _come_froms
forelselaststmtl ::= SETUP_LOOP expr get_for_iter store for_block POP_BLOCK . else_suitel \e__come_froms
forelselaststmtl ::= SETUP_LOOP expr get_for_iter store for_block POP_BLOCK . else_suitel _come_froms
forelselaststmtl ::= setup_loop . expr get_for_iter store for_block POP_BLOCK else_suitel COME_FROM_LOOP
forelselaststmtl ::= setup_loop expr . get_for_iter store for_block POP_BLOCK else_suitel COME_FROM_LOOP
forelselaststmtl ::= setup_loop expr get_for_iter . store for_block POP_BLOCK else_suitel COME_FROM_LOOP
forelselaststmtl ::= setup_loop expr get_for_iter store . for_block POP_BLOCK else_suitel COME_FROM_LOOP
forelselaststmtl ::= setup_loop expr get_for_iter store for_block . POP_BLOCK else_suitel COME_FROM_LOOP
forelselaststmtl ::= setup_loop expr get_for_iter store for_block POP_BLOCK . else_suitel COME_FROM_LOOP
forelsestmt ::= SETUP_LOOP . expr get_for_iter store for_block POP_BLOCK else_suite \e__come_froms
forelsestmt ::= SETUP_LOOP . expr get_for_iter store for_block POP_BLOCK else_suite _come_froms
forelsestmt ::= SETUP_LOOP expr . get_for_iter store for_block POP_BLOCK else_suite \e__come_froms
forelsestmt ::= SETUP_LOOP expr . get_for_iter store for_block POP_BLOCK else_suite _come_froms
forelsestmt ::= SETUP_LOOP expr get_for_iter . store for_block POP_BLOCK else_suite \e__come_froms
forelsestmt ::= SETUP_LOOP expr get_for_iter . store for_block POP_BLOCK else_suite _come_froms
forelsestmt ::= SETUP_LOOP expr get_for_iter store . for_block POP_BLOCK else_suite \e__come_froms
forelsestmt ::= SETUP_LOOP expr get_for_iter store . for_block POP_BLOCK else_suite _come_froms
forelsestmt ::= SETUP_LOOP expr get_for_iter store for_block . POP_BLOCK else_suite \e__come_froms
forelsestmt ::= SETUP_LOOP expr get_for_iter store for_block . POP_BLOCK else_suite _come_froms
forelsestmt ::= SETUP_LOOP expr get_for_iter store for_block POP_BLOCK . else_suite \e__come_froms
forelsestmt ::= SETUP_LOOP expr get_for_iter store for_block POP_BLOCK . else_suite _come_froms
forelsestmt ::= setup_loop . expr get_for_iter store for_block POP_BLOCK else_suite COME_FROM_LOOP
forelsestmt ::= setup_loop expr . get_for_iter store for_block POP_BLOCK else_suite COME_FROM_LOOP
forelsestmt ::= setup_loop expr get_for_iter . store for_block POP_BLOCK else_suite COME_FROM_LOOP
forelsestmt ::= setup_loop expr get_for_iter store . for_block POP_BLOCK else_suite COME_FROM_LOOP
forelsestmt ::= setup_loop expr get_for_iter store for_block . POP_BLOCK else_suite COME_FROM_LOOP
forelsestmt ::= setup_loop expr get_for_iter store for_block POP_BLOCK . else_suite COME_FROM_LOOP
function_def ::= mkfunc . store
function_def ::= mkfunc store . 
get_for_iter ::= GET_ITER . _come_froms FOR_ITER
get_for_iter ::= GET_ITER \e__come_froms . FOR_ITER
get_for_iter ::= GET_ITER \e__come_froms FOR_ITER . 
get_iter ::= expr . GET_ITER
get_iter ::= expr GET_ITER . 
if_exp ::= expr . jmp_false expr jf_cf expr COME_FROM
if_exp ::= expr . jmp_false expr jump_absolute_else expr
if_exp ::= expr jmp_false . expr jf_cf expr COME_FROM
if_exp ::= expr jmp_false . expr jump_absolute_else expr
if_exp ::= expr jmp_false expr . jf_cf expr COME_FROM
if_exp ::= expr jmp_false expr . jump_absolute_else expr
if_exp ::= expr jmp_false expr jf_cf . expr COME_FROM
if_exp ::= expr jmp_false expr jf_cf expr . COME_FROM
if_exp ::= expr jmp_false expr jf_cf expr COME_FROM . 
if_exp37 ::= expr . expr jf_cfs expr COME_FROM
if_exp37 ::= expr expr . jf_cfs expr COME_FROM
if_exp_37b ::= expr . jmp_false expr POP_JUMP_IF_FALSE jump_forward_else expr
if_exp_37b ::= expr jmp_false . expr POP_JUMP_IF_FALSE jump_forward_else expr
if_exp_37b ::= expr jmp_false expr . POP_JUMP_IF_FALSE jump_forward_else expr
if_exp_37b ::= expr jmp_false expr POP_JUMP_IF_FALSE . jump_forward_else expr
if_exp_lambda ::= expr . jmp_false expr return_if_lambda return_stmt_lambda LAMBDA_MARKER
if_exp_lambda ::= expr jmp_false . expr return_if_lambda return_stmt_lambda LAMBDA_MARKER
if_exp_lambda ::= expr jmp_false expr . return_if_lambda return_stmt_lambda LAMBDA_MARKER
if_exp_not ::= expr . jmp_true expr jump_forward_else expr COME_FROM
if_exp_not_lambda ::= expr . jmp_true expr return_if_lambda return_stmt_lambda LAMBDA_MARKER
if_exp_true ::= expr . JUMP_FORWARD expr COME_FROM
if_exp_true ::= expr JUMP_FORWARD . expr COME_FROM
ifelsestmt ::= testexpr . c_stmts come_froms else_suite come_froms
ifelsestmt ::= testexpr . c_stmts_opt JUMP_FORWARD else_suite \e__come_froms
ifelsestmt ::= testexpr . c_stmts_opt JUMP_FORWARD else_suite \e_opt_come_from_except
ifelsestmt ::= testexpr . c_stmts_opt JUMP_FORWARD else_suite _come_froms
ifelsestmt ::= testexpr . c_stmts_opt JUMP_FORWARD else_suite opt_come_from_except
ifelsestmt ::= testexpr . c_stmts_opt jf_cfs else_suite \e_opt_come_from_except
ifelsestmt ::= testexpr . c_stmts_opt jf_cfs else_suite opt_come_from_except
ifelsestmt ::= testexpr . c_stmts_opt jump_forward_else else_suite \e__come_froms
ifelsestmt ::= testexpr . c_stmts_opt jump_forward_else else_suite _come_froms
ifelsestmt ::= testexpr . stmts jf_cfs \e_else_suite_opt \e_opt_come_from_except
ifelsestmt ::= testexpr . stmts jf_cfs \e_else_suite_opt opt_come_from_except
ifelsestmt ::= testexpr . stmts jf_cfs else_suite_opt \e_opt_come_from_except
ifelsestmt ::= testexpr . stmts jf_cfs else_suite_opt opt_come_from_except
ifelsestmt ::= testexpr \e_c_stmts_opt . JUMP_FORWARD else_suite \e__come_froms
ifelsestmt ::= testexpr \e_c_stmts_opt . JUMP_FORWARD else_suite \e_opt_come_from_except
ifelsestmt ::= testexpr \e_c_stmts_opt . JUMP_FORWARD else_suite _come_froms
ifelsestmt ::= testexpr \e_c_stmts_opt . JUMP_FORWARD else_suite opt_come_from_except
ifelsestmt ::= testexpr \e_c_stmts_opt . jf_cfs else_suite \e_opt_come_from_except
ifelsestmt ::= testexpr \e_c_stmts_opt . jf_cfs else_suite opt_come_from_except
ifelsestmt ::= testexpr \e_c_stmts_opt . jump_forward_else else_suite \e__come_froms
ifelsestmt ::= testexpr \e_c_stmts_opt . jump_forward_else else_suite _come_froms
ifelsestmt ::= testexpr c_stmts . come_froms else_suite come_froms
ifelsestmt ::= testexpr c_stmts come_froms . else_suite come_froms
ifelsestmt ::= testexpr c_stmts_opt . JUMP_FORWARD else_suite \e__come_froms
ifelsestmt ::= testexpr c_stmts_opt . JUMP_FORWARD else_suite \e_opt_come_from_except
ifelsestmt ::= testexpr c_stmts_opt . JUMP_FORWARD else_suite _come_froms
ifelsestmt ::= testexpr c_stmts_opt . JUMP_FORWARD else_suite opt_come_from_except
ifelsestmt ::= testexpr c_stmts_opt . jf_cfs else_suite \e_opt_come_from_except
ifelsestmt ::= testexpr c_stmts_opt . jf_cfs else_suite opt_come_from_except
ifelsestmt ::= testexpr c_stmts_opt . jump_forward_else else_suite \e__come_froms
ifelsestmt ::= testexpr c_stmts_opt . jump_forward_else else_suite _come_froms
ifelsestmt ::= testexpr c_stmts_opt JUMP_FORWARD . else_suite \e__come_froms
ifelsestmt ::= testexpr c_stmts_opt JUMP_FORWARD . else_suite \e_opt_come_from_except
ifelsestmt ::= testexpr c_stmts_opt JUMP_FORWARD . else_suite _come_froms
ifelsestmt ::= testexpr c_stmts_opt JUMP_FORWARD . else_suite opt_come_from_except
ifelsestmt ::= testexpr c_stmts_opt jf_cfs . else_suite \e_opt_come_from_except
ifelsestmt ::= testexpr c_stmts_opt jf_cfs . else_suite opt_come_from_except
ifelsestmt ::= testexpr c_stmts_opt jump_forward_else . else_suite \e__come_froms
ifelsestmt ::= testexpr c_stmts_opt jump_forward_else . else_suite _come_froms
ifelsestmt ::= testexpr stmts . jf_cfs \e_else_suite_opt \e_opt_come_from_except
ifelsestmt ::= testexpr stmts . jf_cfs \e_else_suite_opt opt_come_from_except
ifelsestmt ::= testexpr stmts . jf_cfs else_suite_opt \e_opt_come_from_except
ifelsestmt ::= testexpr stmts . jf_cfs else_suite_opt opt_come_from_except
ifelsestmt ::= testexpr stmts jf_cfs . else_suite_opt \e_opt_come_from_except
ifelsestmt ::= testexpr stmts jf_cfs . else_suite_opt opt_come_from_except
ifelsestmt ::= testexpr stmts jf_cfs \e_else_suite_opt . opt_come_from_except
ifelsestmt ::= testexpr stmts jf_cfs \e_else_suite_opt \e_opt_come_from_except . 
ifelsestmt ::= testexpr stmts jf_cfs \e_else_suite_opt opt_come_from_except . 
ifelsestmtc ::= testexpr . c_stmts_opt JUMP_ABSOLUTE else_suitec
ifelsestmtc ::= testexpr . c_stmts_opt JUMP_FORWARD else_suitec
ifelsestmtc ::= testexpr . c_stmts_opt jump_absolute_else else_suitec
ifelsestmtc ::= testexpr \e_c_stmts_opt . JUMP_ABSOLUTE else_suitec
ifelsestmtc ::= testexpr \e_c_stmts_opt . JUMP_FORWARD else_suitec
ifelsestmtc ::= testexpr \e_c_stmts_opt . jump_absolute_else else_suitec
ifelsestmtc ::= testexpr c_stmts_opt . JUMP_ABSOLUTE else_suitec
ifelsestmtc ::= testexpr c_stmts_opt . JUMP_FORWARD else_suitec
ifelsestmtc ::= testexpr c_stmts_opt . jump_absolute_else else_suitec
ifelsestmtc ::= testexpr c_stmts_opt JUMP_FORWARD . else_suitec
ifelsestmtl ::= testexpr . c_stmts_opt cf_jf_else else_suitel
ifelsestmtl ::= testexpr . c_stmts_opt cf_jump_back else_suitel
ifelsestmtl ::= testexpr . c_stmts_opt jb_cfs else_suitel
ifelsestmtl ::= testexpr . c_stmts_opt jb_else else_suitel
ifelsestmtl ::= testexpr . c_stmts_opt jump_forward_else else_suitec
ifelsestmtl ::= testexpr \e_c_stmts_opt . cf_jf_else else_suitel
ifelsestmtl ::= testexpr \e_c_stmts_opt . cf_jump_back else_suitel
ifelsestmtl ::= testexpr \e_c_stmts_opt . jb_cfs else_suitel
ifelsestmtl ::= testexpr \e_c_stmts_opt . jb_else else_suitel
ifelsestmtl ::= testexpr \e_c_stmts_opt . jump_forward_else else_suitec
ifelsestmtl ::= testexpr c_stmts_opt . cf_jf_else else_suitel
ifelsestmtl ::= testexpr c_stmts_opt . cf_jump_back else_suitel
ifelsestmtl ::= testexpr c_stmts_opt . jb_cfs else_suitel
ifelsestmtl ::= testexpr c_stmts_opt . jb_else else_suitel
ifelsestmtl ::= testexpr c_stmts_opt . jump_forward_else else_suitec
ifelsestmtl ::= testexpr c_stmts_opt jump_forward_else . else_suitec
ifelsestmtl ::= testexpr c_stmts_opt jump_forward_else else_suitec . 
ifelsestmtr ::= testexpr . return_if_stmts returns
iflaststmt ::= testexpr . c_stmts
iflaststmt ::= testexpr . c_stmts JUMP_ABSOLUTE
iflaststmt ::= testexpr . c_stmts_opt JUMP_FORWARD
iflaststmt ::= testexpr \e_c_stmts_opt . JUMP_FORWARD
iflaststmt ::= testexpr c_stmts . 
iflaststmt ::= testexpr c_stmts . JUMP_ABSOLUTE
iflaststmt ::= testexpr c_stmts_opt . JUMP_FORWARD
iflaststmt ::= testexpr c_stmts_opt JUMP_FORWARD . 
iflaststmtl ::= testexpr . c_stmts
iflaststmtl ::= testexpr . c_stmts JUMP_BACK
iflaststmtl ::= testexpr . c_stmts JUMP_BACK COME_FROM_LOOP
iflaststmtl ::= testexpr . c_stmts JUMP_BACK POP_BLOCK
iflaststmtl ::= testexpr c_stmts . 
iflaststmtl ::= testexpr c_stmts . JUMP_BACK
iflaststmtl ::= testexpr c_stmts . JUMP_BACK COME_FROM_LOOP
iflaststmtl ::= testexpr c_stmts . JUMP_BACK POP_BLOCK
ifstmt ::= testexpr . _ifstmts_jump
ifstmt ::= testexpr _ifstmts_jump . 
ifstmtl ::= testexpr . _ifstmts_jumpl
ifstmtl ::= testexpr _ifstmts_jumpl . 
jb_cfs ::= \e_come_from_opt . JUMP_BACK come_froms
jb_cfs ::= come_from_opt . JUMP_BACK come_froms
jf_cf ::= JUMP_FORWARD . COME_FROM
jf_cf ::= JUMP_FORWARD COME_FROM . 
jf_cfs ::= JUMP_FORWARD . _come_froms
jf_cfs ::= JUMP_FORWARD \e__come_froms . 
jf_cfs ::= JUMP_FORWARD _come_froms . 
jmp_false ::= POP_JUMP_IF_FALSE . 
jump_absolute_else ::= come_froms . _jump COME_FROM
jump_forward_else ::= JUMP_FORWARD . 
jump_forward_else ::= JUMP_FORWARD . COME_FROM
jump_forward_else ::= JUMP_FORWARD . ELSE
jump_forward_else ::= JUMP_FORWARD COME_FROM . 
kvlist_1 ::= expr . expr BUILD_MAP_1
kvlist_1 ::= expr expr . BUILD_MAP_1
l_stmts ::= _stmts . 
l_stmts ::= _stmts . lastl_stmt
l_stmts ::= l_stmts . lstmt
l_stmts ::= lstmt . 
l_stmts_opt ::= l_stmts . 
lambda_body ::= load_closure . LOAD_LAMBDA LOAD_STR MAKE_FUNCTION_8
lastc_stmt ::= iflaststmt . 
lastl_stmt ::= ifelsestmtl . 
lastl_stmt ::= iflaststmtl . 
load_closure ::= LOAD_CLOSURE . 
load_closure ::= LOAD_CLOSURE . LOAD_CLOSURE LOAD_CLOSURE BUILD_TUPLE_3
load_closure ::= LOAD_CLOSURE LOAD_CLOSURE . LOAD_CLOSURE BUILD_TUPLE_3
load_closure ::= LOAD_CLOSURE LOAD_CLOSURE LOAD_CLOSURE . BUILD_TUPLE_3
load_closure ::= LOAD_CLOSURE LOAD_CLOSURE LOAD_CLOSURE BUILD_TUPLE_3 . 
load_closure ::= load_closure . LOAD_CLOSURE
load_closure ::= load_closure LOAD_CLOSURE . 
lstmt ::= stmt . 
mkfunc ::= LOAD_CODE . LOAD_STR MAKE_FUNCTION_0
mkfunc ::= LOAD_CODE LOAD_STR . MAKE_FUNCTION_0
mkfunc ::= LOAD_CODE LOAD_STR MAKE_FUNCTION_0 . 
mkfunc ::= load_closure . LOAD_CODE LOAD_STR MAKE_FUNCTION_8
mkfunc ::= load_closure LOAD_CODE . LOAD_STR MAKE_FUNCTION_8
mkfunc ::= load_closure LOAD_CODE LOAD_STR . MAKE_FUNCTION_8
mkfunc ::= load_closure LOAD_CODE LOAD_STR MAKE_FUNCTION_8 . 
mkfuncdeco ::= expr . mkfuncdeco CALL_FUNCTION_1
mkfuncdeco ::= expr . mkfuncdeco0 CALL_FUNCTION_1
opt_come_from_except ::= _come_froms . 
pos_arg ::= expr . 
raise_stmt1 ::= expr . RAISE_VARARGS_1
ret_and ::= expr . JUMP_IF_FALSE_OR_POP return_expr_or_cond COME_FROM
ret_or ::= expr . JUMP_IF_TRUE_OR_POP return_expr_or_cond COME_FROM
return ::= return_expr . RETURN_END_IF
return ::= return_expr . RETURN_VALUE
return ::= return_expr . RETURN_VALUE COME_FROM
return_closure ::= LOAD_CLOSURE . DUP_TOP STORE_NAME RETURN_VALUE RETURN_LAST
return_closure ::= LOAD_CLOSURE . RETURN_VALUE RETURN_LAST
return_expr ::= expr . 
return_expr_lambda ::= return_expr . RETURN_VALUE_LAMBDA
return_expr_lambda ::= return_expr . RETURN_VALUE_LAMBDA LAMBDA_MARKER
return_if_stmt ::= return_expr . RETURN_END_IF
return_if_stmt ::= return_expr . RETURN_END_IF POP_BLOCK
return_if_stmts ::= _stmts . return_if_stmt \e__come_froms
return_if_stmts ::= _stmts . return_if_stmt _come_froms
returns ::= _stmts . return
returns ::= _stmts . return_if_stmt
setup_loop ::= SETUP_LOOP . _come_froms
setup_loop ::= SETUP_LOOP \e__come_froms . 
sstmt ::= sstmt . RETURN_LAST
sstmt ::= stmt . 
stmt ::= assign . 
stmt ::= call_stmt . 
stmt ::= expr_stmt . 
stmt ::= for . 
stmt ::= function_def . 
stmts ::= sstmt . 
stmts ::= stmts . sstmt
stmts ::= stmts sstmt . 
store ::= STORE_DEREF . 
store ::= STORE_FAST . 
store ::= STORE_NAME . 
store ::= expr . STORE_ATTR
store_subscript ::= expr . expr STORE_SUBSCR
store_subscript ::= expr expr . STORE_SUBSCR
subscript ::= expr . expr BINARY_SUBSCR
subscript ::= expr expr . BINARY_SUBSCR
subscript2 ::= expr . expr DUP_TOP_TWO BINARY_SUBSCR
subscript2 ::= expr expr . DUP_TOP_TWO BINARY_SUBSCR
testexpr ::= testfalse . 
testexpr_cf ::= testexpr . come_froms
testfalse ::= expr . jmp_false
testfalse ::= expr jmp_false . 
testfalse_not_and ::= expr . jmp_false expr jmp_true COME_FROM
testfalse_not_and ::= expr jmp_false . expr jmp_true COME_FROM
testfalse_not_and ::= expr jmp_false expr . jmp_true COME_FROM
testfalse_not_or ::= expr . jmp_false expr jmp_false COME_FROM
testfalse_not_or ::= expr jmp_false . expr jmp_false COME_FROM
testfalse_not_or ::= expr jmp_false expr . jmp_false COME_FROM
testfalse_not_or ::= expr jmp_false expr jmp_false . COME_FROM
testfalsel ::= expr . jmp_true
testtrue ::= expr . jmp_true
unary_not ::= expr . UNARY_NOT
unary_op ::= expr . unary_operator
while1elsestmt ::= setup_loop . l_stmts JUMP_BACK POP_BLOCK else_suite COME_FROM_LOOP
while1elsestmt ::= setup_loop . l_stmts JUMP_BACK \e__come_froms POP_BLOCK else_suitel COME_FROM_LOOP
while1elsestmt ::= setup_loop . l_stmts JUMP_BACK _come_froms POP_BLOCK else_suitel COME_FROM_LOOP
while1elsestmt ::= setup_loop . l_stmts JUMP_BACK else_suite COME_FROM_LOOP
while1elsestmt ::= setup_loop . l_stmts JUMP_BACK else_suitel
while1stmt ::= setup_loop . l_stmts COME_FROM JUMP_BACK COME_FROM_LOOP
while1stmt ::= setup_loop . l_stmts COME_FROM JUMP_BACK POP_BLOCK COME_FROM_LOOP
while1stmt ::= setup_loop . l_stmts COME_FROM_LOOP
while1stmt ::= setup_loop . l_stmts COME_FROM_LOOP JUMP_BACK POP_BLOCK COME_FROM_LOOP
while1stmt ::= setup_loop . l_stmts POP_BLOCK COME_FROM_LOOP
whileTruestmt ::= SETUP_LOOP . l_stmts_opt JUMP_BACK COME_FROM_LOOP
whileTruestmt ::= SETUP_LOOP \e_l_stmts_opt . JUMP_BACK COME_FROM_LOOP
whileTruestmt ::= setup_loop . l_stmts_opt JUMP_BACK POP_BLOCK \e__come_froms
whileTruestmt ::= setup_loop . l_stmts_opt JUMP_BACK POP_BLOCK _come_froms
whileTruestmt ::= setup_loop \e_l_stmts_opt . JUMP_BACK POP_BLOCK \e__come_froms
whileTruestmt ::= setup_loop \e_l_stmts_opt . JUMP_BACK POP_BLOCK _come_froms
whileelsestmt ::= setup_loop . testexpr \e_l_stmts_opt JUMP_BACK POP_BLOCK else_suitel COME_FROM
whileelsestmt ::= setup_loop . testexpr \e_l_stmts_opt JUMP_BACK POP_BLOCK else_suitel COME_FROM_LOOP
whileelsestmt ::= setup_loop . testexpr l_stmts_opt JUMP_BACK POP_BLOCK else_suitel COME_FROM
whileelsestmt ::= setup_loop . testexpr l_stmts_opt JUMP_BACK POP_BLOCK else_suitel COME_FROM_LOOP
whilestmt ::= setup_loop . testexpr \e_l_stmts_opt COME_FROM JUMP_BACK POP_BLOCK COME_FROM_LOOP
whilestmt ::= setup_loop . testexpr \e_l_stmts_opt JUMP_BACK POP_BLOCK COME_FROM_LOOP
whilestmt ::= setup_loop . testexpr \e_l_stmts_opt JUMP_BACK come_froms POP_BLOCK
whilestmt ::= setup_loop . testexpr \e_l_stmts_opt JUMP_BACK come_froms POP_BLOCK COME_FROM_LOOP
whilestmt ::= setup_loop . testexpr \e_l_stmts_opt come_froms JUMP_BACK come_froms POP_BLOCK COME_FROM_LOOP
whilestmt ::= setup_loop . testexpr l_stmts_opt COME_FROM JUMP_BACK POP_BLOCK COME_FROM_LOOP
whilestmt ::= setup_loop . testexpr l_stmts_opt JUMP_BACK POP_BLOCK COME_FROM_LOOP
whilestmt ::= setup_loop . testexpr l_stmts_opt JUMP_BACK come_froms POP_BLOCK
whilestmt ::= setup_loop . testexpr l_stmts_opt JUMP_BACK come_froms POP_BLOCK COME_FROM_LOOP
whilestmt ::= setup_loop . testexpr l_stmts_opt come_froms JUMP_BACK come_froms POP_BLOCK COME_FROM_LOOP
whilestmt ::= setup_loop . testexpr returns POP_BLOCK COME_FROM_LOOP
whilestmt ::= setup_loop . testexpr returns come_froms POP_BLOCK COME_FROM_LOOP
yield ::= expr . YIELD_VALUE
yield_from ::= expr . GET_YIELD_FROM_ITER LOAD_CONST YIELD_FROM
Instruction context:
   
 L. 210       140  LOAD_FAST                'loot_action'
                 142  LOAD_METHOD              apply_to_resolver
                 144  LOAD_DEREF               'resolver'
                 146  CALL_METHOD_1         1  '1 positional argument'
                 148  POP_TOP          
                 150  JUMP_BACK           136  'to 136'
                 152  POP_BLOCK        
               154_0  COME_FROM_LOOP      128  '128'
               154_1  COME_FROM           126  '126'
               154_2  COME_FROM           114  '114'
->             154_3  COME_FROM_LOOP       88  '88'
               154_4  COME_FROM            74  '74'
               154_5  COME_FROM_LOOP       48  '48'
               154_6  COME_FROM            34  '34'
from live_events.live_event_service import LiveEventName
from live_events.live_event_telemetry import LiveEventTelemetry
from drama_scheduler.drama_node import BaseDramaNode, CooldownOption, DramaNodeRunOutcome
from drama_scheduler.drama_node_types import DramaNodeType
from sims4.localization import TunableLocalizedStringFactory
from sims4.tuning.tunable import TunableVariant, TunableList, TunableReference, HasTunableSingletonFactory, AutoFactoryInit, TunableTuple, Tunable, OptionalTunable, TunableEnumEntry
from sims4.utils import classproperty
from tunable_utils.tested_list import TunableTestedList
from ui.ui_dialog import UiDialogOk, UiDialogOkCancel, ButtonType, UiDialog, UiDialogResponse
from ui.ui_dialog_notification import UiDialogNotification
import services, sims4.resources

class _dialog_and_loot(HasTunableSingletonFactory, AutoFactoryInit):

    def on_node_run(self, drama_node):
        raise NotImplementedError


class _notification_and_loot(_dialog_and_loot):
    FACTORY_TUNABLES = {'notification':UiDialogNotification.TunableFactory(description='\n            The notification that will display to the drama node.\n            '), 
     'loot_list':TunableList(description='\n            A list of loot operations to apply when this notification is given.\n            ',
       tunable=TunableReference(manager=(services.get_instance_manager(sims4.resources.Types.ACTION)),
       class_restrictions=('LootActions', 'RandomWeightedLoot'),
       pack_safe=True))}

    def on_node_run(self, drama_node):
        resolver = drama_node._get_resolver()
        target_sim_id = drama_node._sender_sim_info.id if drama_node._sender_sim_info is not None else None
        dialog = self.notification((drama_node._receiver_sim_info), target_sim_id=target_sim_id,
          resolver=resolver)
        dialog.show_dialog()
        for loot_action in self.loot_list:
            loot_action.apply_to_resolver(resolver)


class _dialog_ok_and_loot(_dialog_and_loot):
    FACTORY_TUNABLES = {'dialog':UiDialogOk.TunableFactory(description='\n            The dialog with an ok button that we will display to the user.\n            '), 
     'on_dialog_complete_loot_list':TunableList(description='\n            A list of loot that will be applied when the player responds to the\n            dialog or, if the dialog is a phone ring or text message, when the\n            dialog times out due to the player ignoring it for too long.\n            ',
       tunable=TunableReference(manager=(services.get_instance_manager(sims4.resources.Types.ACTION)),
       class_restrictions=('LootActions', 'RandomWeightedLoot'),
       pack_safe=True)), 
     'on_dialog_seen_loot_list':TunableList(description='\n            A list of loot that will be applied when player responds to the\n            message.  If the dialog is a phone ring or text message then this\n            loot will not be triggered when the dialog times out due to the\n            player ignoring it for too long.\n            ',
       tunable=TunableReference(manager=(services.get_instance_manager(sims4.resources.Types.ACTION)),
       class_restrictions=('LootActions', ),
       pack_safe=True))}

    def on_node_run(self, drama_node):
        resolver = drama_node._get_resolver()
        target_sim_id = drama_node._sender_sim_info.id if drama_node._sender_sim_info is not None else None
        dialog = self.dialog((drama_node._receiver_sim_info), target_sim_id=target_sim_id,
          resolver=resolver)

        def response(dialog):
            for loot_action in self.on_dialog_complete_loot_list:
                loot_action.apply_to_resolver(resolver)

            if dialog.response is not None:
                if dialog.response != ButtonType.DIALOG_RESPONSE_NO_RESPONSE:
                    for loot_action in self.on_dialog_seen_loot_list:
                        loot_action.apply_to_resolver(resolver)

            DialogDramaNode.apply_cooldown_on_response(drama_node)
            DialogDramaNode.send_dialog_telemetry(drama_node, dialog)

        dialog.show_dialog(on_response=response)


class _loot_only(_dialog_and_loot):
    FACTORY_TUNABLES = {'on_drama_node_run_loot': TunableList(description='\n            A list of loot operations to apply when the drama node runs.\n            ',
                                 tunable=TunableReference(manager=(services.get_instance_manager(sims4.resources.Types.ACTION)),
                                 class_restrictions=('LootActions', 'RandomWeightedLoot'),
                                 pack_safe=True))}

    def on_node_run(self, drama_node):
        resolver = drama_node._get_resolver()
        for loot_action in self.on_drama_node_run_loot:
            loot_action.apply_to_resolver(resolver)


class _dialog_ok_cancel_and_loot(_dialog_and_loot):
    FACTORY_TUNABLES = {'dialog':UiDialogOkCancel.TunableFactory(description='\n            The ok cancel dialog that will display to the user.\n            '), 
     'on_dialog_complete_loot_list':TunableList(description='\n            A list of loot that will be applied when the player responds to the\n            dialog or, if the dialog is a phone ring or text message, when the\n            dialog times out due to the player ignoring it for too long.\n            ',
       tunable=TunableReference(manager=(services.get_instance_manager(sims4.resources.Types.ACTION)),
       class_restrictions=('LootActions', 'RandomWeightedLoot'),
       pack_safe=True)), 
     'on_dialog_accetped_loot_list':TunableList(description='\n            A list of loot operations to apply when the player chooses ok.\n            ',
       tunable=TunableReference(manager=(services.get_instance_manager(sims4.resources.Types.ACTION)),
       class_restrictions=('LootActions', 'RandomWeightedLoot'),
       pack_safe=True)), 
     'on_dialog_canceled_loot_list':TunableList(description='\n            A list of loot operations to apply when the player chooses cancel.\n            ',
       tunable=TunableReference(manager=(services.get_instance_manager(sims4.resources.Types.ACTION)),
       class_restrictions=('LootActions', 'RandomWeightedLoot'),
       pack_safe=True)), 
     'on_dialog_no_response_loot_list':TunableList(description="\n            A list of loot operations to apply when the player ignores and doesn't respond, timing out the dialog.\n            ",
       tunable=TunableReference(manager=(services.get_instance_manager(sims4.resources.Types.ACTION)),
       class_restrictions=('LootActions', 'RandomWeightedLoot'),
       pack_safe=True))}

    def on_node_run(self, drama_node):
        resolver = drama_node._get_resolver()
        target_sim_id = drama_node._sender_sim_info.id if drama_node._sender_sim_info is not None else None
        dialog = self.dialog((drama_node._receiver_sim_info), target_sim_id=target_sim_id,
          resolver=resolver)

        def response--- This code section failed: ---

 L. 196         0  SETUP_LOOP           26  'to 26'
                2  LOAD_DEREF               'self'
                4  LOAD_ATTR                on_dialog_complete_loot_list
                6  GET_ITER         
                8  FOR_ITER             24  'to 24'
               10  STORE_FAST               'loot_action'

 L. 197        12  LOAD_FAST                'loot_action'
               14  LOAD_METHOD              apply_to_resolver
               16  LOAD_DEREF               'resolver'
               18  CALL_METHOD_1         1  '1 positional argument'
               20  POP_TOP          
               22  JUMP_BACK             8  'to 8'
               24  POP_BLOCK        
             26_0  COME_FROM_LOOP        0  '0'

 L. 201        26  LOAD_FAST                'dialog'
               28  LOAD_ATTR                response
               30  LOAD_CONST               None
               32  COMPARE_OP               is-not
               34  POP_JUMP_IF_FALSE   154  'to 154'

 L. 202        36  LOAD_FAST                'dialog'
               38  LOAD_ATTR                response
               40  LOAD_GLOBAL              ButtonType
               42  LOAD_ATTR                DIALOG_RESPONSE_OK
               44  COMPARE_OP               ==
               46  POP_JUMP_IF_FALSE    76  'to 76'

 L. 203        48  SETUP_LOOP          154  'to 154'
               50  LOAD_DEREF               'self'
               52  LOAD_ATTR                on_dialog_accetped_loot_list
               54  GET_ITER         
               56  FOR_ITER             72  'to 72'
               58  STORE_FAST               'loot_action'

 L. 204        60  LOAD_FAST                'loot_action'
               62  LOAD_METHOD              apply_to_resolver
               64  LOAD_DEREF               'resolver'
               66  CALL_METHOD_1         1  '1 positional argument'
               68  POP_TOP          
               70  JUMP_BACK            56  'to 56'
               72  POP_BLOCK        
               74  JUMP_FORWARD        154  'to 154'
             76_0  COME_FROM            46  '46'

 L. 205        76  LOAD_FAST                'dialog'
               78  LOAD_ATTR                response
               80  LOAD_GLOBAL              ButtonType
               82  LOAD_ATTR                DIALOG_RESPONSE_CANCEL
               84  COMPARE_OP               ==
               86  POP_JUMP_IF_FALSE   116  'to 116'

 L. 206        88  SETUP_LOOP          154  'to 154'
               90  LOAD_DEREF               'self'
               92  LOAD_ATTR                on_dialog_canceled_loot_list
               94  GET_ITER         
               96  FOR_ITER            112  'to 112'
               98  STORE_FAST               'loot_action'

 L. 207       100  LOAD_FAST                'loot_action'
              102  LOAD_METHOD              apply_to_resolver
              104  LOAD_DEREF               'resolver'
              106  CALL_METHOD_1         1  '1 positional argument'
              108  POP_TOP          
              110  JUMP_BACK            96  'to 96'
              112  POP_BLOCK        
              114  JUMP_FORWARD        154  'to 154'
            116_0  COME_FROM            86  '86'

 L. 208       116  LOAD_FAST                'dialog'
              118  LOAD_ATTR                response
              120  LOAD_GLOBAL              ButtonType
              122  LOAD_ATTR                DIALOG_RESPONSE_NO_RESPONSE
              124  COMPARE_OP               ==
              126  POP_JUMP_IF_FALSE   154  'to 154'

 L. 209       128  SETUP_LOOP          154  'to 154'
              130  LOAD_DEREF               'self'
              132  LOAD_ATTR                on_dialog_no_response_loot_list
              134  GET_ITER         
              136  FOR_ITER            152  'to 152'
              138  STORE_FAST               'loot_action'

 L. 210       140  LOAD_FAST                'loot_action'
              142  LOAD_METHOD              apply_to_resolver
              144  LOAD_DEREF               'resolver'
              146  CALL_METHOD_1         1  '1 positional argument'
              148  POP_TOP          
              150  JUMP_BACK           136  'to 136'
              152  POP_BLOCK        
            154_0  COME_FROM_LOOP      128  '128'
            154_1  COME_FROM           126  '126'
            154_2  COME_FROM           114  '114'
            154_3  COME_FROM_LOOP       88  '88'
            154_4  COME_FROM            74  '74'
            154_5  COME_FROM_LOOP       48  '48'
            154_6  COME_FROM            34  '34'

 L. 212       154  LOAD_GLOBAL              DialogDramaNode
              156  LOAD_METHOD              apply_cooldown_on_response
              158  LOAD_DEREF               'drama_node'
              160  CALL_METHOD_1         1  '1 positional argument'
              162  POP_TOP          

 L. 213       164  LOAD_GLOBAL              DialogDramaNode
              166  LOAD_METHOD              send_dialog_telemetry
              168  LOAD_DEREF               'drama_node'
              170  LOAD_FAST                'dialog'
              172  CALL_METHOD_2         2  '2 positional arguments'
              174  POP_TOP          

Parse error at or near `COME_FROM_LOOP' instruction at offset 154_3

        dialog.show_dialog(on_response=response)


class _dialog_multi_tested_response(_dialog_and_loot):
    FACTORY_TUNABLES = {'dialog':UiDialog.TunableFactory(description='\n            The dialog that will display to the user.\n            '), 
     'on_dialog_complete_loot_list':TunableList(description='\n            A list of loot that will be applied when the player responds to the\n            dialog or, if the dialog is a phone ring or text message, when the\n            dialog times out due to the player ignoring it for too long.\n            ',
       tunable=TunableReference(manager=(services.get_instance_manager(sims4.resources.Types.ACTION)),
       class_restrictions=('LootActions', 'RandomWeightedLoot'),
       pack_safe=True)), 
     'possible_responses':TunableTestedList(description='\n            A tunable tested list of the possible responses to this dialog.\n            ',
       tunable_type=TunableTuple(description='\n                A possible response for this dialog.\n                ',
       text=TunableLocalizedStringFactory(description='\n                    The text of the response field.\n                    '),
       loot=TunableList(description='\n                    A list of loot that will be applied when the player selects this response.\n                    ',
       tunable=TunableReference(manager=(services.get_instance_manager(sims4.resources.Types.ACTION)),
       class_restrictions=('LootActions', 'RandomWeightedLoot'),
       pack_safe=True))))}

    def on_node_run(self, drama_node):
        resolver = drama_node._get_resolver()
        responses = []
        for index, possible_response in self.possible_responses(resolver=resolver, yield_index=True):
            responses.append(UiDialogResponse(dialog_response_id=index, text=(possible_response.text),
              ui_request=(UiDialogResponse.UiDialogUiRequest.NO_REQUEST)))

        target_sim_id = drama_node._sender_sim_info.id if drama_node._sender_sim_info is not None else None
        dialog = self.dialog((drama_node._receiver_sim_info), target_sim_id=target_sim_id,
          resolver=resolver)
        dialog.set_responses(responses)

        def response(dialog):
            for loot_action in self.on_dialog_complete_loot_list:
                loot_action.apply_to_resolver(resolver)

            if 0 <= dialog.response < len(self.possible_responses):
                for loot_action in self.possible_responses[dialog.response].item.loot:
                    loot_action.apply_to_resolver(resolver)

            DialogDramaNode.apply_cooldown_on_response(drama_node)
            DialogDramaNode.send_dialog_telemetry(drama_node, dialog)

        dialog.show_dialog(on_response=response)


class DialogDramaNode(BaseDramaNode):
    INSTANCE_TUNABLES = {'dialog_and_loot':TunableVariant(description='\n            The type of dialog and loot that will be applied.\n            ',
       notification=_notification_and_loot.TunableFactory(),
       dialog_ok=_dialog_ok_and_loot.TunableFactory(),
       dialog_ok_cancel=_dialog_ok_cancel_and_loot.TunableFactory(),
       dialog_multi_response=_dialog_multi_tested_response.TunableFactory(),
       loot_only=_loot_only.TunableFactory(),
       default='notification'), 
     'is_simless':Tunable(description='\n            If checked, this drama node will not be linked to any specific sim. \n            ',
       tunable_type=bool,
       default=False), 
     'live_event_telemetry_name':OptionalTunable(description='\n            If tuned, the dialog shown by this drama node will send telemetry about the live event that opened it.\n            ',
       tunable=TunableEnumEntry(description='\n                Name of the live event that triggered this drama node.\n                ',
       tunable_type=LiveEventName,
       default=(LiveEventName.DEFAULT),
       invalid_enums=(
      LiveEventName.DEFAULT,)))}

    @classproperty
    def drama_node_type(cls):
        return DramaNodeType.DIALOG

    @classproperty
    def simless(cls):
        return cls.is_simless

    def run(self):
        if self.simless:
            self._receiver_sim_info = services.active_sim_info()
        return super().run()

    def _run(self):
        self.dialog_and_loot.on_node_run(self)
        return DramaNodeRunOutcome.SUCCESS_NODE_COMPLETE

    @classmethod
    def apply_cooldown_on_response(cls, drama_node):
        if drama_node.cooldown is not None:
            if drama_node.cooldown.cooldown_option == CooldownOption.ON_DIALOG_RESPONSE:
                services.drama_scheduler_service().start_cooldown(drama_node)

    @classmethod
    def send_dialog_telemetry(cls, drama_node, dialog):
        if drama_node.live_event_telemetry_name is not None:
            LiveEventTelemetry.send_live_event_dialog_telemetry(drama_node.live_event_telemetry_name, dialog.owner, dialog.response)
