# uncompyle6 version 3.9.0
# Python bytecode version base 3.7.0 (3394)
# Decompiled from: Python 3.7.16 (default, Dec  7 2022, 01:12:33) 
# [GCC 11.3.0]
# Embedded file name: T:\InGame\Gameplay\Scripts\Server\statistics\statistic_tracker.py
# Compiled at: 2020-10-24 22:33:02
# Size of source mod 2**32: 6681 bytes

-- Stacks of completed symbols:
START ::= |- stmts . 
_come_froms ::= \e__come_froms . COME_FROM
_come_froms ::= \e__come_froms . COME_FROM_LOOP
_come_froms ::= \e__come_froms COME_FROM . 
_come_froms ::= _come_froms . COME_FROM
_come_froms ::= _come_froms . COME_FROM_LOOP
_ifstmts_jump ::= \e_c_stmts_opt . COME_FROM
_ifstmts_jump ::= \e_c_stmts_opt . ELSE
_ifstmts_jump ::= \e_c_stmts_opt . JUMP_ABSOLUTE JUMP_FORWARD \e__come_froms
_ifstmts_jump ::= \e_c_stmts_opt . JUMP_ABSOLUTE JUMP_FORWARD _come_froms
_ifstmts_jump ::= \e_c_stmts_opt . come_froms
_ifstmts_jump ::= c_stmts_opt . COME_FROM
_ifstmts_jump ::= c_stmts_opt . ELSE
_ifstmts_jump ::= c_stmts_opt . JUMP_ABSOLUTE JUMP_FORWARD \e__come_froms
_ifstmts_jump ::= c_stmts_opt . JUMP_ABSOLUTE JUMP_FORWARD _come_froms
_ifstmts_jump ::= c_stmts_opt . come_froms
_ifstmts_jump ::= c_stmts_opt COME_FROM . 
_ifstmts_jump ::= c_stmts_opt come_froms . 
_ifstmts_jumpl ::= _ifstmts_jump . 
_ifstmts_jumpl ::= c_stmts . JUMP_BACK
_jump ::= JUMP_BACK . 
_stmts ::= _stmts . stmt
_stmts ::= _stmts stmt . 
_stmts ::= stmt . 
and ::= expr . JUMP_IF_FALSE_OR_POP expr \e_come_from_opt
and ::= expr . JUMP_IF_FALSE_OR_POP expr come_from_opt
and ::= expr . jifop_come_from expr
and ::= expr . jmp_false expr
and ::= expr . jmp_false expr COME_FROM
and ::= expr . jmp_false expr jmp_false
and ::= expr jmp_false . expr
and ::= expr jmp_false . expr COME_FROM
and ::= expr jmp_false . expr jmp_false
and ::= expr jmp_false expr . 
and ::= expr jmp_false expr . COME_FROM
and ::= expr jmp_false expr . jmp_false
and ::= expr jmp_false expr jmp_false . 
and_not ::= expr . jmp_false expr POP_JUMP_IF_TRUE
and_not ::= expr jmp_false . expr POP_JUMP_IF_TRUE
and_not ::= expr jmp_false expr . POP_JUMP_IF_TRUE
and_not ::= expr jmp_false expr POP_JUMP_IF_TRUE . 
assert2 ::= expr . jmp_true LOAD_GLOBAL expr CALL_FUNCTION_1 RAISE_VARARGS_1
assert2 ::= expr jmp_true . LOAD_GLOBAL expr CALL_FUNCTION_1 RAISE_VARARGS_1
assert_invert ::= testtrue . LOAD_GLOBAL RAISE_VARARGS_1
assign ::= expr . DUP_TOP designList
assign ::= expr . store
assign ::= expr store . 
assign2 ::= expr . expr ROT_TWO store store
assign2 ::= expr expr . ROT_TWO store store
assign3 ::= expr . expr expr ROT_THREE ROT_TWO store store store
assign3 ::= expr expr . expr ROT_THREE ROT_TWO store store store
assign3 ::= expr expr expr . ROT_THREE ROT_TWO store store store
async_for_stmt ::= setup_loop . expr GET_AITER LOAD_CONST YIELD_FROM SETUP_EXCEPT GET_ANEXT LOAD_CONST YIELD_FROM store POP_BLOCK JUMP_FORWARD COME_FROM_EXCEPT DUP_TOP LOAD_GLOBAL COMPARE_OP POP_JUMP_IF_FALSE POP_TOP POP_TOP POP_TOP POP_EXCEPT POP_BLOCK JUMP_ABSOLUTE END_FINALLY COME_FROM for_block POP_BLOCK COME_FROM_LOOP
async_for_stmt ::= setup_loop . expr GET_AITER SETUP_EXCEPT GET_ANEXT LOAD_CONST YIELD_FROM store POP_BLOCK JUMP_FORWARD COME_FROM_EXCEPT DUP_TOP LOAD_GLOBAL COMPARE_OP POP_JUMP_IF_TRUE END_FINALLY COME_FROM for_block COME_FROM POP_TOP POP_TOP POP_TOP POP_EXCEPT POP_TOP POP_BLOCK COME_FROM_LOOP
async_for_stmt ::= setup_loop expr . GET_AITER LOAD_CONST YIELD_FROM SETUP_EXCEPT GET_ANEXT LOAD_CONST YIELD_FROM store POP_BLOCK JUMP_FORWARD COME_FROM_EXCEPT DUP_TOP LOAD_GLOBAL COMPARE_OP POP_JUMP_IF_FALSE POP_TOP POP_TOP POP_TOP POP_EXCEPT POP_BLOCK JUMP_ABSOLUTE END_FINALLY COME_FROM for_block POP_BLOCK COME_FROM_LOOP
async_for_stmt ::= setup_loop expr . GET_AITER SETUP_EXCEPT GET_ANEXT LOAD_CONST YIELD_FROM store POP_BLOCK JUMP_FORWARD COME_FROM_EXCEPT DUP_TOP LOAD_GLOBAL COMPARE_OP POP_JUMP_IF_TRUE END_FINALLY COME_FROM for_block COME_FROM POP_TOP POP_TOP POP_TOP POP_EXCEPT POP_TOP POP_BLOCK COME_FROM_LOOP
async_for_stmt37 ::= setup_loop . expr GET_AITER \e__come_froms SETUP_EXCEPT GET_ANEXT LOAD_CONST YIELD_FROM store POP_BLOCK JUMP_BACK COME_FROM_EXCEPT DUP_TOP LOAD_GLOBAL COMPARE_OP POP_JUMP_IF_TRUE END_FINALLY for_block COME_FROM POP_TOP POP_TOP POP_TOP POP_EXCEPT POP_TOP POP_BLOCK COME_FROM_LOOP
async_for_stmt37 ::= setup_loop . expr GET_AITER _come_froms SETUP_EXCEPT GET_ANEXT LOAD_CONST YIELD_FROM store POP_BLOCK JUMP_BACK COME_FROM_EXCEPT DUP_TOP LOAD_GLOBAL COMPARE_OP POP_JUMP_IF_TRUE END_FINALLY for_block COME_FROM POP_TOP POP_TOP POP_TOP POP_EXCEPT POP_TOP POP_BLOCK COME_FROM_LOOP
async_for_stmt37 ::= setup_loop expr . GET_AITER \e__come_froms SETUP_EXCEPT GET_ANEXT LOAD_CONST YIELD_FROM store POP_BLOCK JUMP_BACK COME_FROM_EXCEPT DUP_TOP LOAD_GLOBAL COMPARE_OP POP_JUMP_IF_TRUE END_FINALLY for_block COME_FROM POP_TOP POP_TOP POP_TOP POP_EXCEPT POP_TOP POP_BLOCK COME_FROM_LOOP
async_for_stmt37 ::= setup_loop expr . GET_AITER _come_froms SETUP_EXCEPT GET_ANEXT LOAD_CONST YIELD_FROM store POP_BLOCK JUMP_BACK COME_FROM_EXCEPT DUP_TOP LOAD_GLOBAL COMPARE_OP POP_JUMP_IF_TRUE END_FINALLY for_block COME_FROM POP_TOP POP_TOP POP_TOP POP_EXCEPT POP_TOP POP_BLOCK COME_FROM_LOOP
async_forelse_stmt ::= setup_loop . expr GET_AITER \e__come_froms SETUP_EXCEPT GET_ANEXT LOAD_CONST YIELD_FROM store POP_BLOCK JUMP_FORWARD COME_FROM_EXCEPT DUP_TOP LOAD_GLOBAL COMPARE_OP POP_JUMP_IF_TRUE END_FINALLY COME_FROM for_block COME_FROM POP_TOP POP_TOP POP_TOP POP_EXCEPT POP_TOP POP_BLOCK else_suite COME_FROM_LOOP
async_forelse_stmt ::= setup_loop . expr GET_AITER _come_froms SETUP_EXCEPT GET_ANEXT LOAD_CONST YIELD_FROM store POP_BLOCK JUMP_FORWARD COME_FROM_EXCEPT DUP_TOP LOAD_GLOBAL COMPARE_OP POP_JUMP_IF_TRUE END_FINALLY COME_FROM for_block COME_FROM POP_TOP POP_TOP POP_TOP POP_EXCEPT POP_TOP POP_BLOCK else_suite COME_FROM_LOOP
async_forelse_stmt ::= setup_loop expr . GET_AITER \e__come_froms SETUP_EXCEPT GET_ANEXT LOAD_CONST YIELD_FROM store POP_BLOCK JUMP_FORWARD COME_FROM_EXCEPT DUP_TOP LOAD_GLOBAL COMPARE_OP POP_JUMP_IF_TRUE END_FINALLY COME_FROM for_block COME_FROM POP_TOP POP_TOP POP_TOP POP_EXCEPT POP_TOP POP_BLOCK else_suite COME_FROM_LOOP
async_forelse_stmt ::= setup_loop expr . GET_AITER _come_froms SETUP_EXCEPT GET_ANEXT LOAD_CONST YIELD_FROM store POP_BLOCK JUMP_FORWARD COME_FROM_EXCEPT DUP_TOP LOAD_GLOBAL COMPARE_OP POP_JUMP_IF_TRUE END_FINALLY COME_FROM for_block COME_FROM POP_TOP POP_TOP POP_TOP POP_EXCEPT POP_TOP POP_BLOCK else_suite COME_FROM_LOOP
attribute ::= expr . LOAD_ATTR
attribute ::= expr LOAD_ATTR . 
attribute37 ::= expr . LOAD_METHOD
attribute37 ::= expr LOAD_METHOD . 
aug_assign1 ::= expr . expr inplace_op ROT_THREE STORE_SUBSCR
aug_assign1 ::= expr . expr inplace_op store
aug_assign1 ::= expr expr . inplace_op ROT_THREE STORE_SUBSCR
aug_assign1 ::= expr expr . inplace_op store
aug_assign2 ::= expr . DUP_TOP LOAD_ATTR expr inplace_op ROT_TWO STORE_ATTR
await_expr ::= expr . GET_AWAITABLE LOAD_CONST YIELD_FROM
bin_op ::= expr . expr binary_operator
bin_op ::= expr expr . binary_operator
c_stmts ::= _stmts . 
c_stmts ::= _stmts . lastc_stmt
c_stmts ::= _stmts lastc_stmt . 
c_stmts ::= continues . 
c_stmts ::= lastc_stmt . 
c_stmts_opt ::= c_stmts . 
call ::= expr . CALL_FUNCTION_0
call ::= expr . CALL_METHOD_0
call ::= expr . expr CALL_METHOD_1
call ::= expr . expr expr CALL_METHOD_2
call ::= expr . pos_arg pos_arg CALL_FUNCTION_2
call ::= expr . pos_arg pos_arg pos_arg CALL_FUNCTION_3
call ::= expr CALL_FUNCTION_0 . 
call ::= expr expr . CALL_METHOD_1
call ::= expr expr . expr CALL_METHOD_2
call ::= expr expr CALL_METHOD_1 . 
call ::= expr expr expr . CALL_METHOD_2
call ::= expr expr expr CALL_METHOD_2 . 
call ::= expr pos_arg . pos_arg CALL_FUNCTION_2
call ::= expr pos_arg . pos_arg pos_arg CALL_FUNCTION_3
call ::= expr pos_arg pos_arg . CALL_FUNCTION_2
call ::= expr pos_arg pos_arg . pos_arg CALL_FUNCTION_3
call ::= expr pos_arg pos_arg CALL_FUNCTION_2 . 
call ::= expr pos_arg pos_arg pos_arg . CALL_FUNCTION_3
call_kw36 ::= expr . expr expr expr LOAD_CONST CALL_FUNCTION_KW_3
call_kw36 ::= expr . expr expr expr expr LOAD_CONST CALL_FUNCTION_KW_4
call_kw36 ::= expr expr . expr expr LOAD_CONST CALL_FUNCTION_KW_3
call_kw36 ::= expr expr . expr expr expr LOAD_CONST CALL_FUNCTION_KW_4
call_kw36 ::= expr expr expr . expr LOAD_CONST CALL_FUNCTION_KW_3
call_kw36 ::= expr expr expr . expr expr LOAD_CONST CALL_FUNCTION_KW_4
call_kw36 ::= expr expr expr expr . LOAD_CONST CALL_FUNCTION_KW_3
call_kw36 ::= expr expr expr expr . expr LOAD_CONST CALL_FUNCTION_KW_4
call_kw36 ::= expr expr expr expr LOAD_CONST . CALL_FUNCTION_KW_3
call_kw36 ::= expr expr expr expr LOAD_CONST CALL_FUNCTION_KW_3 . 
call_kw36 ::= expr expr expr expr expr . LOAD_CONST CALL_FUNCTION_KW_4
call_stmt ::= expr . POP_TOP
call_stmt ::= expr POP_TOP . 
cf_jf_else ::= come_froms . JUMP_FORWARD ELSE
cf_jump_back ::= COME_FROM . JUMP_BACK
cf_jump_back ::= COME_FROM JUMP_BACK . 
come_from_loops ::= \e_come_from_loops . COME_FROM_LOOP
come_from_opt ::= COME_FROM . 
come_froms ::= COME_FROM . 
come_froms ::= come_froms . COME_FROM
come_froms ::= come_froms COME_FROM . 
compare ::= compare_single . 
compare_chained ::= expr . compare_chained1 ROT_TWO POP_TOP \e__come_froms
compare_chained ::= expr . compare_chained1 ROT_TWO POP_TOP _come_froms
compare_chained1 ::= expr . DUP_TOP ROT_THREE COMPARE_OP JUMP_IF_FALSE_OR_POP compare_chained1 COME_FROM
compare_chained1 ::= expr . DUP_TOP ROT_THREE COMPARE_OP JUMP_IF_FALSE_OR_POP compare_chained2 COME_FROM
compare_chained1_false_37 ::= expr . DUP_TOP ROT_THREE COMPARE_OP POP_JUMP_IF_FALSE compare_chained2b_false_37 POP_TOP _jump COME_FROM
compare_chained1_false_37 ::= expr . DUP_TOP ROT_THREE COMPARE_OP POP_JUMP_IF_FALSE compare_chained2c_37 POP_TOP JUMP_FORWARD COME_FROM
compare_chained1a_37 ::= expr . DUP_TOP ROT_THREE COMPARE_OP POP_JUMP_IF_FALSE
compare_chained1a_37 ::= expr . DUP_TOP ROT_THREE COMPARE_OP POP_JUMP_IF_FALSE compare_chained2a_37 COME_FROM POP_TOP COME_FROM
compare_chained1b_false_37 ::= expr . DUP_TOP ROT_THREE COMPARE_OP POP_JUMP_IF_FALSE compare_chained2b_false_37 POP_TOP _jump COME_FROM
compare_chained1c_37 ::= expr . DUP_TOP ROT_THREE COMPARE_OP POP_JUMP_IF_FALSE compare_chained2a_37 POP_TOP
compare_chained2_false_37 ::= expr . DUP_TOP ROT_THREE COMPARE_OP POP_JUMP_IF_FALSE compare_chained2a_false_37 POP_TOP JUMP_BACK COME_FROM
compare_chained37 ::= expr . compare_chained1a_37
compare_chained37 ::= expr . compare_chained1c_37
compare_chained37_false ::= expr . compare_chained1_false_37
compare_chained37_false ::= expr . compare_chained1b_false_37
compare_chained37_false ::= expr . compare_chained2_false_37
compare_single ::= expr . expr COMPARE_OP
compare_single ::= expr expr . COMPARE_OP
compare_single ::= expr expr COMPARE_OP . 
continue ::= CONTINUE . 
continues ::= _stmts . lastl_stmt continue
continues ::= _stmts lastl_stmt . continue
continues ::= continue . 
continues ::= lastl_stmt . continue
continues ::= lastl_stmt continue . 
dict ::= kvlist_0 . 
dict_comp_func ::= BUILD_MAP_0 . LOAD_ARG for_iter store comp_iter JUMP_BACK RETURN_VALUE RETURN_LAST
else_suite ::= suite_stmts . 
else_suite_opt ::= else_suite . 
else_suitec ::= c_stmts . 
else_suitel ::= l_stmts . 
expr ::= LOAD_CONST . 
expr ::= LOAD_FAST . 
expr ::= LOAD_GLOBAL . 
expr ::= LOAD_STR . 
expr ::= and . 
expr ::= attribute . 
expr ::= attribute37 . 
expr ::= call . 
expr ::= call_kw36 . 
expr ::= compare . 
expr ::= dict . 
expr ::= get_iter . 
expr ::= if_exp . 
expr ::= tuple . 
expr_jit ::= expr . JUMP_IF_TRUE
expr_jitop ::= expr . JUMP_IF_TRUE_OR_POP
expr_jt ::= expr . jmp_true
expr_jt ::= expr jmp_true . 
expr_pjit ::= expr . POP_JUMP_IF_TRUE
expr_pjit ::= expr POP_JUMP_IF_TRUE . 
expr_pjit_come_from ::= expr . POP_JUMP_IF_TRUE COME_FROM
expr_pjit_come_from ::= expr POP_JUMP_IF_TRUE . COME_FROM
expr_stmt ::= expr . POP_TOP
expr_stmt ::= expr POP_TOP . 
for ::= setup_loop . expr get_for_iter store for_block POP_BLOCK
for ::= setup_loop . expr get_for_iter store for_block POP_BLOCK COME_FROM_LOOP
for ::= setup_loop . expr get_for_iter store for_block POP_BLOCK NOP COME_FROM_LOOP
for ::= setup_loop expr . get_for_iter store for_block POP_BLOCK
for ::= setup_loop expr . get_for_iter store for_block POP_BLOCK COME_FROM_LOOP
for ::= setup_loop expr . get_for_iter store for_block POP_BLOCK NOP COME_FROM_LOOP
for ::= setup_loop expr get_for_iter . store for_block POP_BLOCK
for ::= setup_loop expr get_for_iter . store for_block POP_BLOCK COME_FROM_LOOP
for ::= setup_loop expr get_for_iter . store for_block POP_BLOCK NOP COME_FROM_LOOP
for ::= setup_loop expr get_for_iter store . for_block POP_BLOCK
for ::= setup_loop expr get_for_iter store . for_block POP_BLOCK COME_FROM_LOOP
for ::= setup_loop expr get_for_iter store . for_block POP_BLOCK NOP COME_FROM_LOOP
for ::= setup_loop expr get_for_iter store for_block . POP_BLOCK
for ::= setup_loop expr get_for_iter store for_block . POP_BLOCK COME_FROM_LOOP
for ::= setup_loop expr get_for_iter store for_block . POP_BLOCK NOP COME_FROM_LOOP
for_block ::= \e_l_stmts_opt . COME_FROM_LOOP JUMP_BACK
for_block ::= \e_l_stmts_opt . _come_froms JUMP_BACK
for_block ::= \e_l_stmts_opt . come_from_loops JUMP_BACK
for_block ::= \e_l_stmts_opt \e__come_froms . JUMP_BACK
for_block ::= \e_l_stmts_opt \e_come_from_loops . JUMP_BACK
for_block ::= l_stmts . 
for_block ::= l_stmts . JUMP_BACK
for_block ::= l_stmts_opt . COME_FROM_LOOP JUMP_BACK
for_block ::= l_stmts_opt . _come_froms JUMP_BACK
for_block ::= l_stmts_opt . come_from_loops JUMP_BACK
for_block ::= l_stmts_opt \e__come_froms . JUMP_BACK
for_block ::= l_stmts_opt \e_come_from_loops . JUMP_BACK
for_block ::= l_stmts_opt _come_froms . JUMP_BACK
forelselaststmtl ::= SETUP_LOOP . expr get_for_iter store for_block POP_BLOCK else_suitel \e__come_froms
forelselaststmtl ::= SETUP_LOOP . expr get_for_iter store for_block POP_BLOCK else_suitel _come_froms
forelselaststmtl ::= SETUP_LOOP expr . get_for_iter store for_block POP_BLOCK else_suitel \e__come_froms
forelselaststmtl ::= SETUP_LOOP expr . get_for_iter store for_block POP_BLOCK else_suitel _come_froms
forelselaststmtl ::= SETUP_LOOP expr get_for_iter . store for_block POP_BLOCK else_suitel \e__come_froms
forelselaststmtl ::= SETUP_LOOP expr get_for_iter . store for_block POP_BLOCK else_suitel _come_froms
forelselaststmtl ::= SETUP_LOOP expr get_for_iter store . for_block POP_BLOCK else_suitel \e__come_froms
forelselaststmtl ::= SETUP_LOOP expr get_for_iter store . for_block POP_BLOCK else_suitel _come_froms
forelselaststmtl ::= SETUP_LOOP expr get_for_iter store for_block . POP_BLOCK else_suitel \e__come_froms
forelselaststmtl ::= SETUP_LOOP expr get_for_iter store for_block . POP_BLOCK else_suitel _come_froms
forelselaststmtl ::= setup_loop . expr get_for_iter store for_block POP_BLOCK else_suitel COME_FROM_LOOP
forelselaststmtl ::= setup_loop expr . get_for_iter store for_block POP_BLOCK else_suitel COME_FROM_LOOP
forelselaststmtl ::= setup_loop expr get_for_iter . store for_block POP_BLOCK else_suitel COME_FROM_LOOP
forelselaststmtl ::= setup_loop expr get_for_iter store . for_block POP_BLOCK else_suitel COME_FROM_LOOP
forelselaststmtl ::= setup_loop expr get_for_iter store for_block . POP_BLOCK else_suitel COME_FROM_LOOP
forelsestmt ::= SETUP_LOOP . expr get_for_iter store for_block POP_BLOCK else_suite \e__come_froms
forelsestmt ::= SETUP_LOOP . expr get_for_iter store for_block POP_BLOCK else_suite _come_froms
forelsestmt ::= SETUP_LOOP expr . get_for_iter store for_block POP_BLOCK else_suite \e__come_froms
forelsestmt ::= SETUP_LOOP expr . get_for_iter store for_block POP_BLOCK else_suite _come_froms
forelsestmt ::= SETUP_LOOP expr get_for_iter . store for_block POP_BLOCK else_suite \e__come_froms
forelsestmt ::= SETUP_LOOP expr get_for_iter . store for_block POP_BLOCK else_suite _come_froms
forelsestmt ::= SETUP_LOOP expr get_for_iter store . for_block POP_BLOCK else_suite \e__come_froms
forelsestmt ::= SETUP_LOOP expr get_for_iter store . for_block POP_BLOCK else_suite _come_froms
forelsestmt ::= SETUP_LOOP expr get_for_iter store for_block . POP_BLOCK else_suite \e__come_froms
forelsestmt ::= SETUP_LOOP expr get_for_iter store for_block . POP_BLOCK else_suite _come_froms
forelsestmt ::= setup_loop . expr get_for_iter store for_block POP_BLOCK else_suite COME_FROM_LOOP
forelsestmt ::= setup_loop expr . get_for_iter store for_block POP_BLOCK else_suite COME_FROM_LOOP
forelsestmt ::= setup_loop expr get_for_iter . store for_block POP_BLOCK else_suite COME_FROM_LOOP
forelsestmt ::= setup_loop expr get_for_iter store . for_block POP_BLOCK else_suite COME_FROM_LOOP
forelsestmt ::= setup_loop expr get_for_iter store for_block . POP_BLOCK else_suite COME_FROM_LOOP
get_for_iter ::= GET_ITER . _come_froms FOR_ITER
get_for_iter ::= GET_ITER \e__come_froms . FOR_ITER
get_for_iter ::= GET_ITER _come_froms . FOR_ITER
get_for_iter ::= GET_ITER _come_froms FOR_ITER . 
get_iter ::= expr . GET_ITER
get_iter ::= expr GET_ITER . 
if_exp ::= expr . jmp_false expr jf_cf expr COME_FROM
if_exp ::= expr . jmp_false expr jump_absolute_else expr
if_exp ::= expr jmp_false . expr jf_cf expr COME_FROM
if_exp ::= expr jmp_false . expr jump_absolute_else expr
if_exp ::= expr jmp_false expr . jf_cf expr COME_FROM
if_exp ::= expr jmp_false expr . jump_absolute_else expr
if_exp ::= expr jmp_false expr jf_cf . expr COME_FROM
if_exp ::= expr jmp_false expr jf_cf expr . COME_FROM
if_exp ::= expr jmp_false expr jf_cf expr COME_FROM . 
if_exp37 ::= expr . expr jf_cfs expr COME_FROM
if_exp37 ::= expr expr . jf_cfs expr COME_FROM
if_exp_37a ::= and_not . expr JUMP_FORWARD come_froms expr COME_FROM
if_exp_37b ::= expr . jmp_false expr POP_JUMP_IF_FALSE jump_forward_else expr
if_exp_37b ::= expr jmp_false . expr POP_JUMP_IF_FALSE jump_forward_else expr
if_exp_37b ::= expr jmp_false expr . POP_JUMP_IF_FALSE jump_forward_else expr
if_exp_37b ::= expr jmp_false expr POP_JUMP_IF_FALSE . jump_forward_else expr
if_exp_lambda ::= expr . jmp_false expr return_if_lambda return_stmt_lambda LAMBDA_MARKER
if_exp_lambda ::= expr jmp_false . expr return_if_lambda return_stmt_lambda LAMBDA_MARKER
if_exp_lambda ::= expr jmp_false expr . return_if_lambda return_stmt_lambda LAMBDA_MARKER
if_exp_not ::= expr . jmp_true expr jump_forward_else expr COME_FROM
if_exp_not ::= expr jmp_true . expr jump_forward_else expr COME_FROM
if_exp_not_lambda ::= expr . jmp_true expr return_if_lambda return_stmt_lambda LAMBDA_MARKER
if_exp_not_lambda ::= expr jmp_true . expr return_if_lambda return_stmt_lambda LAMBDA_MARKER
if_exp_true ::= expr . JUMP_FORWARD expr COME_FROM
if_exp_true ::= expr JUMP_FORWARD . expr COME_FROM
ifelsestmt ::= testexpr . c_stmts come_froms else_suite come_froms
ifelsestmt ::= testexpr . c_stmts_opt JUMP_FORWARD else_suite \e__come_froms
ifelsestmt ::= testexpr . c_stmts_opt JUMP_FORWARD else_suite \e_opt_come_from_except
ifelsestmt ::= testexpr . c_stmts_opt JUMP_FORWARD else_suite _come_froms
ifelsestmt ::= testexpr . c_stmts_opt JUMP_FORWARD else_suite opt_come_from_except
ifelsestmt ::= testexpr . c_stmts_opt jf_cfs else_suite \e_opt_come_from_except
ifelsestmt ::= testexpr . c_stmts_opt jf_cfs else_suite opt_come_from_except
ifelsestmt ::= testexpr . c_stmts_opt jump_forward_else else_suite \e__come_froms
ifelsestmt ::= testexpr . c_stmts_opt jump_forward_else else_suite _come_froms
ifelsestmt ::= testexpr . stmts jf_cfs \e_else_suite_opt \e_opt_come_from_except
ifelsestmt ::= testexpr . stmts jf_cfs \e_else_suite_opt opt_come_from_except
ifelsestmt ::= testexpr . stmts jf_cfs else_suite_opt \e_opt_come_from_except
ifelsestmt ::= testexpr . stmts jf_cfs else_suite_opt opt_come_from_except
ifelsestmt ::= testexpr \e_c_stmts_opt . JUMP_FORWARD else_suite \e__come_froms
ifelsestmt ::= testexpr \e_c_stmts_opt . JUMP_FORWARD else_suite \e_opt_come_from_except
ifelsestmt ::= testexpr \e_c_stmts_opt . JUMP_FORWARD else_suite _come_froms
ifelsestmt ::= testexpr \e_c_stmts_opt . JUMP_FORWARD else_suite opt_come_from_except
ifelsestmt ::= testexpr \e_c_stmts_opt . jf_cfs else_suite \e_opt_come_from_except
ifelsestmt ::= testexpr \e_c_stmts_opt . jf_cfs else_suite opt_come_from_except
ifelsestmt ::= testexpr \e_c_stmts_opt . jump_forward_else else_suite \e__come_froms
ifelsestmt ::= testexpr \e_c_stmts_opt . jump_forward_else else_suite _come_froms
ifelsestmt ::= testexpr c_stmts . come_froms else_suite come_froms
ifelsestmt ::= testexpr c_stmts come_froms . else_suite come_froms
ifelsestmt ::= testexpr c_stmts come_froms else_suite . come_froms
ifelsestmt ::= testexpr c_stmts come_froms else_suite come_froms . 
ifelsestmt ::= testexpr c_stmts_opt . JUMP_FORWARD else_suite \e__come_froms
ifelsestmt ::= testexpr c_stmts_opt . JUMP_FORWARD else_suite \e_opt_come_from_except
ifelsestmt ::= testexpr c_stmts_opt . JUMP_FORWARD else_suite _come_froms
ifelsestmt ::= testexpr c_stmts_opt . JUMP_FORWARD else_suite opt_come_from_except
ifelsestmt ::= testexpr c_stmts_opt . jf_cfs else_suite \e_opt_come_from_except
ifelsestmt ::= testexpr c_stmts_opt . jf_cfs else_suite opt_come_from_except
ifelsestmt ::= testexpr c_stmts_opt . jump_forward_else else_suite \e__come_froms
ifelsestmt ::= testexpr c_stmts_opt . jump_forward_else else_suite _come_froms
ifelsestmt ::= testexpr c_stmts_opt JUMP_FORWARD . else_suite \e__come_froms
ifelsestmt ::= testexpr c_stmts_opt JUMP_FORWARD . else_suite \e_opt_come_from_except
ifelsestmt ::= testexpr c_stmts_opt JUMP_FORWARD . else_suite _come_froms
ifelsestmt ::= testexpr c_stmts_opt JUMP_FORWARD . else_suite opt_come_from_except
ifelsestmt ::= testexpr c_stmts_opt jf_cfs . else_suite \e_opt_come_from_except
ifelsestmt ::= testexpr c_stmts_opt jf_cfs . else_suite opt_come_from_except
ifelsestmt ::= testexpr c_stmts_opt jf_cfs else_suite . opt_come_from_except
ifelsestmt ::= testexpr c_stmts_opt jf_cfs else_suite \e_opt_come_from_except . 
ifelsestmt ::= testexpr c_stmts_opt jump_forward_else . else_suite \e__come_froms
ifelsestmt ::= testexpr c_stmts_opt jump_forward_else . else_suite _come_froms
ifelsestmt ::= testexpr c_stmts_opt jump_forward_else else_suite . _come_froms
ifelsestmt ::= testexpr c_stmts_opt jump_forward_else else_suite \e__come_froms . 
ifelsestmt ::= testexpr stmts . jf_cfs \e_else_suite_opt \e_opt_come_from_except
ifelsestmt ::= testexpr stmts . jf_cfs \e_else_suite_opt opt_come_from_except
ifelsestmt ::= testexpr stmts . jf_cfs else_suite_opt \e_opt_come_from_except
ifelsestmt ::= testexpr stmts . jf_cfs else_suite_opt opt_come_from_except
ifelsestmt ::= testexpr stmts jf_cfs . else_suite_opt \e_opt_come_from_except
ifelsestmt ::= testexpr stmts jf_cfs . else_suite_opt opt_come_from_except
ifelsestmt ::= testexpr stmts jf_cfs \e_else_suite_opt . opt_come_from_except
ifelsestmt ::= testexpr stmts jf_cfs \e_else_suite_opt \e_opt_come_from_except . 
ifelsestmt ::= testexpr stmts jf_cfs \e_else_suite_opt opt_come_from_except . 
ifelsestmt ::= testexpr stmts jf_cfs else_suite_opt . opt_come_from_except
ifelsestmt ::= testexpr stmts jf_cfs else_suite_opt \e_opt_come_from_except . 
ifelsestmtc ::= testexpr . c_stmts_opt JUMP_ABSOLUTE else_suitec
ifelsestmtc ::= testexpr . c_stmts_opt JUMP_FORWARD else_suitec
ifelsestmtc ::= testexpr . c_stmts_opt jump_absolute_else else_suitec
ifelsestmtc ::= testexpr \e_c_stmts_opt . JUMP_ABSOLUTE else_suitec
ifelsestmtc ::= testexpr \e_c_stmts_opt . JUMP_FORWARD else_suitec
ifelsestmtc ::= testexpr \e_c_stmts_opt . jump_absolute_else else_suitec
ifelsestmtc ::= testexpr c_stmts_opt . JUMP_ABSOLUTE else_suitec
ifelsestmtc ::= testexpr c_stmts_opt . JUMP_FORWARD else_suitec
ifelsestmtc ::= testexpr c_stmts_opt . jump_absolute_else else_suitec
ifelsestmtc ::= testexpr c_stmts_opt JUMP_FORWARD . else_suitec
ifelsestmtc ::= testexpr c_stmts_opt jump_absolute_else . else_suitec
ifelsestmtc ::= testexpr c_stmts_opt jump_absolute_else else_suitec . 
ifelsestmtl ::= testexpr . c_stmts_opt cf_jf_else else_suitel
ifelsestmtl ::= testexpr . c_stmts_opt cf_jump_back else_suitel
ifelsestmtl ::= testexpr . c_stmts_opt jb_cfs else_suitel
ifelsestmtl ::= testexpr . c_stmts_opt jb_else else_suitel
ifelsestmtl ::= testexpr . c_stmts_opt jump_forward_else else_suitec
ifelsestmtl ::= testexpr \e_c_stmts_opt . cf_jf_else else_suitel
ifelsestmtl ::= testexpr \e_c_stmts_opt . cf_jump_back else_suitel
ifelsestmtl ::= testexpr \e_c_stmts_opt . jb_cfs else_suitel
ifelsestmtl ::= testexpr \e_c_stmts_opt . jb_else else_suitel
ifelsestmtl ::= testexpr \e_c_stmts_opt . jump_forward_else else_suitec
ifelsestmtl ::= testexpr c_stmts_opt . cf_jf_else else_suitel
ifelsestmtl ::= testexpr c_stmts_opt . cf_jump_back else_suitel
ifelsestmtl ::= testexpr c_stmts_opt . jb_cfs else_suitel
ifelsestmtl ::= testexpr c_stmts_opt . jb_else else_suitel
ifelsestmtl ::= testexpr c_stmts_opt . jump_forward_else else_suitec
ifelsestmtl ::= testexpr c_stmts_opt cf_jump_back . else_suitel
ifelsestmtl ::= testexpr c_stmts_opt jb_cfs . else_suitel
ifelsestmtl ::= testexpr c_stmts_opt jb_cfs else_suitel . 
ifelsestmtl ::= testexpr c_stmts_opt jump_forward_else . else_suitec
ifelsestmtl ::= testexpr c_stmts_opt jump_forward_else else_suitec . 
ifelsestmtr ::= testexpr . return_if_stmts returns
iflaststmt ::= testexpr . c_stmts
iflaststmt ::= testexpr . c_stmts JUMP_ABSOLUTE
iflaststmt ::= testexpr . c_stmts_opt JUMP_FORWARD
iflaststmt ::= testexpr \e_c_stmts_opt . JUMP_FORWARD
iflaststmt ::= testexpr c_stmts . 
iflaststmt ::= testexpr c_stmts . JUMP_ABSOLUTE
iflaststmt ::= testexpr c_stmts_opt . JUMP_FORWARD
iflaststmt ::= testexpr c_stmts_opt JUMP_FORWARD . 
iflaststmtl ::= testexpr . c_stmts
iflaststmtl ::= testexpr . c_stmts JUMP_BACK
iflaststmtl ::= testexpr . c_stmts JUMP_BACK COME_FROM_LOOP
iflaststmtl ::= testexpr . c_stmts JUMP_BACK POP_BLOCK
iflaststmtl ::= testexpr c_stmts . 
iflaststmtl ::= testexpr c_stmts . JUMP_BACK
iflaststmtl ::= testexpr c_stmts . JUMP_BACK COME_FROM_LOOP
iflaststmtl ::= testexpr c_stmts . JUMP_BACK POP_BLOCK
iflaststmtl ::= testexprl . c_stmts JUMP_BACK
iflaststmtl ::= testexprl . c_stmts JUMP_BACK COME_FROM_LOOP
iflaststmtl ::= testexprl . c_stmts JUMP_BACK POP_BLOCK
iflaststmtl ::= testexprl c_stmts . JUMP_BACK
iflaststmtl ::= testexprl c_stmts . JUMP_BACK COME_FROM_LOOP
iflaststmtl ::= testexprl c_stmts . JUMP_BACK POP_BLOCK
ifstmt ::= testexpr . _ifstmts_jump
ifstmt ::= testexpr _ifstmts_jump . 
ifstmtl ::= testexpr . _ifstmts_jumpl
ifstmtl ::= testexpr _ifstmts_jumpl . 
import ::= LOAD_CONST . LOAD_CONST alias
import_as37 ::= LOAD_CONST . LOAD_CONST importlist37 store POP_TOP
import_from ::= LOAD_CONST . LOAD_CONST IMPORT_NAME importlist POP_TOP
import_from ::= LOAD_CONST . LOAD_CONST importlist POP_TOP
import_from37 ::= LOAD_CONST . LOAD_CONST IMPORT_NAME_ATTR importlist37 POP_TOP
import_from_as37 ::= LOAD_CONST . LOAD_CONST import_from_attr37 store POP_TOP
import_from_star ::= LOAD_CONST . LOAD_CONST IMPORT_NAME IMPORT_STAR
import_from_star ::= LOAD_CONST . LOAD_CONST IMPORT_NAME_ATTR IMPORT_STAR
importmultiple ::= LOAD_CONST . LOAD_CONST alias imports_cont
jb_cfs ::= \e_come_from_opt . JUMP_BACK come_froms
jb_cfs ::= come_from_opt . JUMP_BACK come_froms
jb_cfs ::= come_from_opt JUMP_BACK . come_froms
jb_cfs ::= come_from_opt JUMP_BACK come_froms . 
jf_cf ::= JUMP_FORWARD . COME_FROM
jf_cf ::= JUMP_FORWARD COME_FROM . 
jf_cfs ::= JUMP_FORWARD . _come_froms
jf_cfs ::= JUMP_FORWARD \e__come_froms . 
jf_cfs ::= JUMP_FORWARD _come_froms . 
jmp_false ::= POP_JUMP_IF_FALSE . 
jmp_true ::= POP_JUMP_IF_TRUE . 
jump_absolute_else ::= CONTINUE . ELSE
jump_absolute_else ::= come_froms . _jump COME_FROM
jump_absolute_else ::= come_froms _jump . COME_FROM
jump_absolute_else ::= come_froms _jump COME_FROM . 
jump_forward_else ::= JUMP_FORWARD . 
jump_forward_else ::= JUMP_FORWARD . COME_FROM
jump_forward_else ::= JUMP_FORWARD . ELSE
jump_forward_else ::= JUMP_FORWARD COME_FROM . 
kvlist_0 ::= BUILD_MAP_0 . 
l_stmts ::= _stmts . 
l_stmts ::= _stmts . lastl_stmt
l_stmts ::= _stmts lastl_stmt . 
l_stmts ::= l_stmts . lstmt
l_stmts ::= lstmt . 
l_stmts_opt ::= l_stmts . 
lambda_body ::= expr . LOAD_LAMBDA LOAD_STR MAKE_FUNCTION_1
lambda_body ::= expr . load_closure BUILD_TUPLE_1 LOAD_LAMBDA LOAD_STR MAKE_FUNCTION_9
lastc_stmt ::= ifelsestmtc . 
lastc_stmt ::= iflaststmt . 
lastl_stmt ::= ifelsestmtl . 
lastl_stmt ::= iflaststmtl . 
lstmt ::= stmt . 
mkfunc ::= expr . LOAD_CODE LOAD_STR MAKE_FUNCTION_1
mkfunc ::= expr . load_closure LOAD_CODE LOAD_STR MAKE_FUNCTION_9
mkfuncdeco ::= expr . mkfuncdeco CALL_FUNCTION_1
mkfuncdeco ::= expr . mkfuncdeco0 CALL_FUNCTION_1
opt_come_from_except ::= _come_froms . 
or ::= and . jitop_come_from_expr COME_FROM
or ::= expr_jt . expr
or ::= expr_jt . expr COME_FROM
or ::= expr_pjit . expr POP_JUMP_IF_FALSE COME_FROM
pos_arg ::= expr . 
ret_and ::= expr . JUMP_IF_FALSE_OR_POP return_expr_or_cond COME_FROM
ret_or ::= expr . JUMP_IF_TRUE_OR_POP return_expr_or_cond COME_FROM
return ::= return_expr . RETURN_END_IF
return ::= return_expr . RETURN_VALUE
return ::= return_expr . RETURN_VALUE COME_FROM
return_expr ::= expr . 
return_expr_lambda ::= return_expr . RETURN_VALUE_LAMBDA
return_expr_lambda ::= return_expr . RETURN_VALUE_LAMBDA LAMBDA_MARKER
return_if_stmt ::= return_expr . RETURN_END_IF
return_if_stmt ::= return_expr . RETURN_END_IF POP_BLOCK
return_if_stmts ::= _stmts . return_if_stmt \e__come_froms
return_if_stmts ::= _stmts . return_if_stmt _come_froms
returns ::= _stmts . return
returns ::= _stmts . return_if_stmt
setup_loop ::= SETUP_LOOP . _come_froms
setup_loop ::= SETUP_LOOP \e__come_froms . 
sstmt ::= sstmt . RETURN_LAST
sstmt ::= stmt . 
stmt ::= assign . 
stmt ::= call_stmt . 
stmt ::= continue . 
stmt ::= expr_stmt . 
stmt ::= ifelsestmt . 
stmt ::= ifstmt . 
stmt ::= ifstmtl . 
stmts ::= sstmt . 
stmts ::= stmts . sstmt
stmts ::= stmts sstmt . 
store ::= STORE_FAST . 
store ::= expr . STORE_ATTR
store ::= expr STORE_ATTR . 
store ::= store_subscript . 
store_subscript ::= expr . expr STORE_SUBSCR
store_subscript ::= expr expr . STORE_SUBSCR
store_subscript ::= expr expr STORE_SUBSCR . 
subscript ::= expr . expr BINARY_SUBSCR
subscript ::= expr expr . BINARY_SUBSCR
subscript2 ::= expr . expr DUP_TOP_TWO BINARY_SUBSCR
subscript2 ::= expr expr . DUP_TOP_TWO BINARY_SUBSCR
suite_stmts ::= _stmts . 
suite_stmts_opt ::= suite_stmts . 
testexpr ::= testfalse . 
testexpr ::= testtrue . 
testexpr_cf ::= testexpr . come_froms
testexprl ::= testfalsel . 
testfalse ::= and_not . 
testfalse ::= expr . jmp_false
testfalse ::= expr jmp_false . 
testfalse_not_and ::= and . jmp_true come_froms
testfalse_not_and ::= expr . jmp_false expr jmp_true COME_FROM
testfalse_not_and ::= expr jmp_false . expr jmp_true COME_FROM
testfalse_not_and ::= expr jmp_false expr . jmp_true COME_FROM
testfalse_not_and ::= expr jmp_false expr jmp_true . COME_FROM
testfalse_not_or ::= expr . jmp_false expr jmp_false COME_FROM
testfalse_not_or ::= expr jmp_false . expr jmp_false COME_FROM
testfalse_not_or ::= expr jmp_false expr . jmp_false COME_FROM
testfalse_not_or ::= expr jmp_false expr jmp_false . COME_FROM
testfalsel ::= expr . jmp_true
testfalsel ::= expr jmp_true . 
testtrue ::= expr . jmp_true
testtrue ::= expr jmp_true . 
tryfinally36 ::= SETUP_FINALLY . returns COME_FROM_FINALLY \e_suite_stmts_opt END_FINALLY
tryfinally36 ::= SETUP_FINALLY . returns COME_FROM_FINALLY suite_stmts
tryfinally36 ::= SETUP_FINALLY . returns COME_FROM_FINALLY suite_stmts_opt END_FINALLY
tryfinally_return_stmt ::= SETUP_FINALLY . suite_stmts_opt POP_BLOCK LOAD_CONST COME_FROM_FINALLY
tryfinally_return_stmt ::= SETUP_FINALLY \e_suite_stmts_opt . POP_BLOCK LOAD_CONST COME_FROM_FINALLY
tryfinally_return_stmt ::= SETUP_FINALLY suite_stmts_opt . POP_BLOCK LOAD_CONST COME_FROM_FINALLY
tryfinallystmt ::= SETUP_FINALLY . suite_stmts_opt POP_BLOCK LOAD_CONST COME_FROM_FINALLY \e_suite_stmts_opt END_FINALLY
tryfinallystmt ::= SETUP_FINALLY . suite_stmts_opt POP_BLOCK LOAD_CONST COME_FROM_FINALLY suite_stmts_opt END_FINALLY
tryfinallystmt ::= SETUP_FINALLY \e_suite_stmts_opt . POP_BLOCK LOAD_CONST COME_FROM_FINALLY \e_suite_stmts_opt END_FINALLY
tryfinallystmt ::= SETUP_FINALLY \e_suite_stmts_opt . POP_BLOCK LOAD_CONST COME_FROM_FINALLY suite_stmts_opt END_FINALLY
tryfinallystmt ::= SETUP_FINALLY suite_stmts_opt . POP_BLOCK LOAD_CONST COME_FROM_FINALLY \e_suite_stmts_opt END_FINALLY
tryfinallystmt ::= SETUP_FINALLY suite_stmts_opt . POP_BLOCK LOAD_CONST COME_FROM_FINALLY suite_stmts_opt END_FINALLY
tuple ::= expr . expr BUILD_TUPLE_2
tuple ::= expr expr . BUILD_TUPLE_2
tuple ::= expr expr BUILD_TUPLE_2 . 
unary_not ::= expr . UNARY_NOT
unary_op ::= expr . unary_operator
while1elsestmt ::= setup_loop . l_stmts JUMP_BACK POP_BLOCK else_suite COME_FROM_LOOP
while1elsestmt ::= setup_loop . l_stmts JUMP_BACK \e__come_froms POP_BLOCK else_suitel COME_FROM_LOOP
while1elsestmt ::= setup_loop . l_stmts JUMP_BACK _come_froms POP_BLOCK else_suitel COME_FROM_LOOP
while1elsestmt ::= setup_loop . l_stmts JUMP_BACK else_suite COME_FROM_LOOP
while1elsestmt ::= setup_loop . l_stmts JUMP_BACK else_suitel
while1stmt ::= setup_loop . l_stmts COME_FROM JUMP_BACK COME_FROM_LOOP
while1stmt ::= setup_loop . l_stmts COME_FROM JUMP_BACK POP_BLOCK COME_FROM_LOOP
while1stmt ::= setup_loop . l_stmts COME_FROM_LOOP
while1stmt ::= setup_loop . l_stmts COME_FROM_LOOP JUMP_BACK POP_BLOCK COME_FROM_LOOP
while1stmt ::= setup_loop . l_stmts POP_BLOCK COME_FROM_LOOP
whileTruestmt ::= SETUP_LOOP . l_stmts_opt JUMP_BACK COME_FROM_LOOP
whileTruestmt ::= SETUP_LOOP \e_l_stmts_opt . JUMP_BACK COME_FROM_LOOP
whileTruestmt ::= setup_loop . l_stmts_opt JUMP_BACK POP_BLOCK \e__come_froms
whileTruestmt ::= setup_loop . l_stmts_opt JUMP_BACK POP_BLOCK _come_froms
whileTruestmt ::= setup_loop \e_l_stmts_opt . JUMP_BACK POP_BLOCK \e__come_froms
whileTruestmt ::= setup_loop \e_l_stmts_opt . JUMP_BACK POP_BLOCK _come_froms
whileelsestmt ::= setup_loop . testexpr \e_l_stmts_opt JUMP_BACK POP_BLOCK else_suitel COME_FROM
whileelsestmt ::= setup_loop . testexpr \e_l_stmts_opt JUMP_BACK POP_BLOCK else_suitel COME_FROM_LOOP
whileelsestmt ::= setup_loop . testexpr l_stmts_opt JUMP_BACK POP_BLOCK else_suitel COME_FROM
whileelsestmt ::= setup_loop . testexpr l_stmts_opt JUMP_BACK POP_BLOCK else_suitel COME_FROM_LOOP
whilestmt ::= setup_loop . testexpr \e_l_stmts_opt COME_FROM JUMP_BACK POP_BLOCK COME_FROM_LOOP
whilestmt ::= setup_loop . testexpr \e_l_stmts_opt JUMP_BACK POP_BLOCK COME_FROM_LOOP
whilestmt ::= setup_loop . testexpr \e_l_stmts_opt JUMP_BACK come_froms POP_BLOCK
whilestmt ::= setup_loop . testexpr \e_l_stmts_opt JUMP_BACK come_froms POP_BLOCK COME_FROM_LOOP
whilestmt ::= setup_loop . testexpr \e_l_stmts_opt come_froms JUMP_BACK come_froms POP_BLOCK COME_FROM_LOOP
whilestmt ::= setup_loop . testexpr l_stmts_opt COME_FROM JUMP_BACK POP_BLOCK COME_FROM_LOOP
whilestmt ::= setup_loop . testexpr l_stmts_opt JUMP_BACK POP_BLOCK COME_FROM_LOOP
whilestmt ::= setup_loop . testexpr l_stmts_opt JUMP_BACK come_froms POP_BLOCK
whilestmt ::= setup_loop . testexpr l_stmts_opt JUMP_BACK come_froms POP_BLOCK COME_FROM_LOOP
whilestmt ::= setup_loop . testexpr l_stmts_opt come_froms JUMP_BACK come_froms POP_BLOCK COME_FROM_LOOP
whilestmt ::= setup_loop . testexpr returns POP_BLOCK COME_FROM_LOOP
whilestmt ::= setup_loop . testexpr returns come_froms POP_BLOCK COME_FROM_LOOP
yield ::= expr . YIELD_VALUE
yield_from ::= expr . GET_YIELD_FROM_ITER LOAD_CONST YIELD_FROM
Instruction context:
   
 L. 104       264  LOAD_GLOBAL              logger
                 266  LOAD_METHOD              info
                 268  LOAD_STR                 'Trying to load unavailable STATISTIC resource: {}'
                 270  LOAD_FAST                'statistics_data'
                 272  LOAD_ATTR                name_hash
                 274  CALL_METHOD_2         2  '2 positional arguments'
                 276  POP_TOP          
               278_0  COME_FROM           248  '248'
                 278  JUMP_BACK            54  'to 54'
->               280  POP_BLOCK        
               282_0  COME_FROM_LOOP       48  '48'
                 282  POP_BLOCK        
                 284  LOAD_CONST               None
               286_0  COME_FROM_FINALLY     0  '0'
from protocolbuffers import SimObjectAttributes_pb2 as protocols
import services, sims, sims4.log, statistics.base_statistic_tracker
from sims.sim_info_lod import SimInfoLODLevel
logger = sims4.log.Logger('Statistic')

class StatisticTracker(statistics.base_statistic_tracker.BaseStatisticTracker):
    __slots__ = '_monetary_value_statistics'

    def __init__(self, owner=None):
        super().__init__(owner)
        self._monetary_value_statistics = []

    def save(self):
        self.check_for_unneeded_initial_statistics()
        save_list = []
        if self._statistics is not None:
            for stat_type, stat in self._statistics.items():
                if stat_type.persisted:
                    try:
                        statistic_data = protocols.Statistic()
                        statistic_data.name_hash = stat_type.guid64
                        if stat is not None:
                            statistic_data.value = stat.get_saved_value()
                        else:
                            statistic_data.ClearField('value')
                        save_list.append(statistic_data)
                    except Exception as e:
                        try:
                            logger.exception('Exception {} thrown while trying to save stat {}', e, stat, owner='rez')
                        finally:
                            e = None
                            del e

        return save_list

    def load--- This code section failed: ---

 L.  60       0_2  SETUP_FINALLY       286  'to 286'

 L.  61         4  LOAD_GLOBAL              services
                6  LOAD_METHOD              get_instance_manager
                8  LOAD_GLOBAL              sims4
               10  LOAD_ATTR                resources
               12  LOAD_ATTR                Types
               14  LOAD_ATTR                STATISTIC
               16  CALL_METHOD_1         1  '1 positional argument'
               18  STORE_FAST               'statistics_manager'

 L.  62        20  LOAD_GLOBAL              isinstance
               22  LOAD_FAST                'self'
               24  LOAD_ATTR                _owner
               26  LOAD_GLOBAL              sims
               28  LOAD_ATTR                sim_info
               30  LOAD_ATTR                SimInfo
               32  CALL_FUNCTION_2       2  '2 positional arguments'
               34  POP_JUMP_IF_FALSE    44  'to 44'
               36  LOAD_FAST                'self'
               38  LOAD_ATTR                _owner
               40  LOAD_ATTR                lod
               42  JUMP_FORWARD         46  'to 46'
             44_0  COME_FROM            34  '34'
               44  LOAD_CONST               None
             46_0  COME_FROM            42  '42'
               46  STORE_FAST               'owner_lod'

 L.  63        48  SETUP_LOOP          282  'to 282'
               50  LOAD_FAST                'statistics'
               52  GET_ITER         
             54_0  COME_FROM           152  '152'
               54  FOR_ITER            280  'to 280'
               56  STORE_FAST               'statistics_data'

 L.  66        58  LOAD_FAST                'statistics_manager'
               60  LOAD_METHOD              get
               62  LOAD_FAST                'statistics_data'
               64  LOAD_ATTR                name_hash
               66  CALL_METHOD_1         1  '1 positional argument'
               68  STORE_FAST               'stat_cls'

 L.  68        70  LOAD_FAST                'stat_cls'
               72  LOAD_CONST               None
               74  COMPARE_OP               is-not
            76_78  POP_JUMP_IF_FALSE   264  'to 264'

 L.  69        80  LOAD_FAST                'self'
               82  LOAD_METHOD              _should_add_commodity_from_gallery
               84  LOAD_FAST                'stat_cls'
               86  LOAD_FAST                'skip_load'
               88  CALL_METHOD_2         2  '2 positional arguments'
               90  POP_JUMP_IF_TRUE     94  'to 94'

 L.  72        92  CONTINUE             54  'to 54'
             94_0  COME_FROM            90  '90'

 L.  74        94  LOAD_FAST                'stat_cls'
               96  LOAD_ATTR                persisted
               98  POP_JUMP_IF_TRUE    102  'to 102'

 L.  75       100  CONTINUE             54  'to 54'
            102_0  COME_FROM            98  '98'

 L.  77       102  LOAD_FAST                'self'
              104  LOAD_ATTR                statistics_to_skip_load
              106  LOAD_CONST               None
              108  COMPARE_OP               is-not
              110  POP_JUMP_IF_FALSE   124  'to 124'

 L.  78       112  LOAD_FAST                'stat_cls'
              114  LOAD_FAST                'self'
              116  LOAD_ATTR                statistics_to_skip_load
              118  COMPARE_OP               in
              120  POP_JUMP_IF_FALSE   124  'to 124'

 L.  79       122  CONTINUE             54  'to 54'
            124_0  COME_FROM           120  '120'
            124_1  COME_FROM           110  '110'

 L.  83       124  LOAD_FAST                'owner_lod'
              126  LOAD_CONST               None
              128  COMPARE_OP               is-not
              130  POP_JUMP_IF_FALSE   194  'to 194'
              132  LOAD_FAST                'owner_lod'
              134  LOAD_FAST                'stat_cls'
              136  LOAD_ATTR                min_lod_value
              138  COMPARE_OP               <
              140  POP_JUMP_IF_FALSE   194  'to 194'

 L.  84       142  LOAD_FAST                'stat_cls'
              144  LOAD_ATTR                min_lod_value
              146  LOAD_GLOBAL              SimInfoLODLevel
              148  LOAD_ATTR                ACTIVE
              150  COMPARE_OP               ==
              152  POP_JUMP_IF_FALSE    54  'to 54'

 L.  85       154  LOAD_FAST                'self'
              156  LOAD_ATTR                _delayed_active_lod_statistics
              158  LOAD_CONST               None
              160  COMPARE_OP               is
              162  POP_JUMP_IF_FALSE   172  'to 172'

 L.  86       164  LOAD_GLOBAL              list
              166  CALL_FUNCTION_0       0  '0 positional arguments'
              168  LOAD_FAST                'self'
              170  STORE_ATTR               _delayed_active_lod_statistics
            172_0  COME_FROM           162  '162'

 L.  87       172  LOAD_FAST                'self'
              174  LOAD_ATTR                _delayed_active_lod_statistics
              176  LOAD_METHOD              append
              178  LOAD_FAST                'statistics_data'
              180  LOAD_ATTR                name_hash
              182  LOAD_FAST                'statistics_data'
              184  LOAD_ATTR                value
              186  BUILD_TUPLE_2         2 
              188  CALL_METHOD_1         1  '1 positional argument'
              190  POP_TOP          

 L.  88       192  CONTINUE             54  'to 54'
            194_0  COME_FROM           140  '140'
            194_1  COME_FROM           130  '130'

 L.  91       194  LOAD_FAST                'statistics_data'
              196  LOAD_METHOD              HasField
              198  LOAD_STR                 'value'
              200  CALL_METHOD_1         1  '1 positional argument'
              202  POP_JUMP_IF_FALSE   224  'to 224'

 L.  92       204  LOAD_FAST                'self'
              206  LOAD_ATTR                set_value
              208  LOAD_FAST                'stat_cls'
              210  LOAD_FAST                'statistics_data'
              212  LOAD_ATTR                value
              214  LOAD_CONST               True
              216  LOAD_CONST               ('from_load',)
              218  CALL_FUNCTION_KW_3     3  '3 total positional and keyword args'
              220  POP_TOP          
              222  JUMP_FORWARD        262  'to 262'
            224_0  COME_FROM           202  '202'

 L.  96       224  LOAD_FAST                'self'
              226  LOAD_ATTR                _statistics
              228  LOAD_CONST               None
              230  COMPARE_OP               is
              232  POP_JUMP_IF_FALSE   240  'to 240'

 L.  97       234  BUILD_MAP_0           0 
              236  LOAD_FAST                'self'
              238  STORE_ATTR               _statistics
            240_0  COME_FROM           232  '232'

 L. 101       240  LOAD_FAST                'stat_cls'
              242  LOAD_FAST                'self'
              244  LOAD_ATTR                _statistics
              246  COMPARE_OP               not-in
          248_250  POP_JUMP_IF_FALSE   278  'to 278'

 L. 102       252  LOAD_CONST               None
              254  LOAD_FAST                'self'
              256  LOAD_ATTR                _statistics
              258  LOAD_FAST                'stat_cls'
              260  STORE_SUBSCR     
            262_0  COME_FROM           222  '222'
              262  JUMP_BACK            54  'to 54'
            264_0  COME_FROM            76  '76'

 L. 104       264  LOAD_GLOBAL              logger
              266  LOAD_METHOD              info
              268  LOAD_STR                 'Trying to load unavailable STATISTIC resource: {}'
              270  LOAD_FAST                'statistics_data'
              272  LOAD_ATTR                name_hash
              274  CALL_METHOD_2         2  '2 positional arguments'
              276  POP_TOP          
            278_0  COME_FROM           248  '248'
              278  JUMP_BACK            54  'to 54'
              280  POP_BLOCK        
            282_0  COME_FROM_LOOP       48  '48'
              282  POP_BLOCK        
              284  LOAD_CONST               None
            286_0  COME_FROM_FINALLY     0  '0'

 L. 106       286  LOAD_CONST               None
              288  LOAD_FAST                'self'
              290  STORE_ATTR               statistics_to_skip_load
              292  END_FINALLY      

 L. 107       294  LOAD_FAST                'self'
              296  LOAD_METHOD              check_for_unneeded_initial_statistics
              298  CALL_METHOD_0         0  '0 positional arguments'
              300  POP_TOP          

Parse error at or near `POP_BLOCK' instruction at offset 280

    def add_statistic(self, stat_type, **kwargs):
        stat = (super().add_statistic)(stat_type, **kwargs)
        if stat is not None:
            if stat.apply_value_to_object_cost:
                if stat not in self._monetary_value_statistics:
                    self._monetary_value_statistics.append(stat)
        return stat

    def remove_statistic(self, stat_type, on_destroy=False):
        if self.has_statistic(stat_type):
            stat = self._statistics[stat_type]
            if stat is not None:
                if stat.apply_value_to_object_cost:
                    if stat in self._monetary_value_statistics:
                        self._monetary_value_statistics.remove(stat)
        super().remove_statisticstat_typeon_destroy

    def get_monetary_value_statistics(self):
        return self._monetary_value_statistics
