# uncompyle6 version 3.9.0
# Python bytecode version base 3.7.0 (3394)
# Decompiled from: Python 3.7.16 (default, Dec  7 2022, 01:12:33) 
# [GCC 11.3.0]
# Embedded file name: T:\InGame\Gameplay\Scripts\Server\fame\squad_situation.py
# Compiled at: 2018-10-08 22:45:16
# Size of source mod 2**32: 6274 bytes

-- Stacks of completed symbols:
START ::= |- stmts . 
_come_froms ::= \e__come_froms . COME_FROM
_come_froms ::= \e__come_froms . COME_FROM_LOOP
_come_froms ::= \e__come_froms COME_FROM . 
_come_froms ::= _come_froms . COME_FROM
_come_froms ::= _come_froms . COME_FROM_LOOP
_ifstmts_jump ::= \e_c_stmts_opt . COME_FROM
_ifstmts_jump ::= \e_c_stmts_opt . ELSE
_ifstmts_jump ::= \e_c_stmts_opt . JUMP_ABSOLUTE JUMP_FORWARD \e__come_froms
_ifstmts_jump ::= \e_c_stmts_opt . JUMP_ABSOLUTE JUMP_FORWARD _come_froms
_ifstmts_jump ::= \e_c_stmts_opt . come_froms
_ifstmts_jump ::= c_stmts_opt . COME_FROM
_ifstmts_jump ::= c_stmts_opt . ELSE
_ifstmts_jump ::= c_stmts_opt . JUMP_ABSOLUTE JUMP_FORWARD \e__come_froms
_ifstmts_jump ::= c_stmts_opt . JUMP_ABSOLUTE JUMP_FORWARD _come_froms
_ifstmts_jump ::= c_stmts_opt . come_froms
_ifstmts_jump ::= c_stmts_opt COME_FROM . 
_ifstmts_jump ::= c_stmts_opt come_froms . 
_ifstmts_jumpl ::= _ifstmts_jump . 
_ifstmts_jumpl ::= c_stmts . JUMP_BACK
_stmts ::= _stmts . stmt
_stmts ::= _stmts stmt . 
_stmts ::= stmt . 
and ::= expr . JUMP_IF_FALSE_OR_POP expr \e_come_from_opt
and ::= expr . JUMP_IF_FALSE_OR_POP expr come_from_opt
and ::= expr . jifop_come_from expr
and ::= expr . jmp_false expr
and ::= expr . jmp_false expr COME_FROM
and ::= expr . jmp_false expr jmp_false
and ::= expr jmp_false . expr
and ::= expr jmp_false . expr COME_FROM
and ::= expr jmp_false . expr jmp_false
and ::= expr jmp_false expr . 
and ::= expr jmp_false expr . COME_FROM
and ::= expr jmp_false expr . jmp_false
and_not ::= expr . jmp_false expr POP_JUMP_IF_TRUE
and_not ::= expr jmp_false . expr POP_JUMP_IF_TRUE
and_not ::= expr jmp_false expr . POP_JUMP_IF_TRUE
assert2 ::= expr . jmp_true LOAD_GLOBAL expr CALL_FUNCTION_1 RAISE_VARARGS_1
assign ::= expr . DUP_TOP designList
assign ::= expr . store
assign ::= expr store . 
assign2 ::= expr . expr ROT_TWO store store
assign2 ::= expr expr . ROT_TWO store store
assign3 ::= expr . expr expr ROT_THREE ROT_TWO store store store
assign3 ::= expr expr . expr ROT_THREE ROT_TWO store store store
assign3 ::= expr expr expr . ROT_THREE ROT_TWO store store store
async_for_stmt ::= setup_loop . expr GET_AITER LOAD_CONST YIELD_FROM SETUP_EXCEPT GET_ANEXT LOAD_CONST YIELD_FROM store POP_BLOCK JUMP_FORWARD COME_FROM_EXCEPT DUP_TOP LOAD_GLOBAL COMPARE_OP POP_JUMP_IF_FALSE POP_TOP POP_TOP POP_TOP POP_EXCEPT POP_BLOCK JUMP_ABSOLUTE END_FINALLY COME_FROM for_block POP_BLOCK COME_FROM_LOOP
async_for_stmt ::= setup_loop . expr GET_AITER SETUP_EXCEPT GET_ANEXT LOAD_CONST YIELD_FROM store POP_BLOCK JUMP_FORWARD COME_FROM_EXCEPT DUP_TOP LOAD_GLOBAL COMPARE_OP POP_JUMP_IF_TRUE END_FINALLY COME_FROM for_block COME_FROM POP_TOP POP_TOP POP_TOP POP_EXCEPT POP_TOP POP_BLOCK COME_FROM_LOOP
async_for_stmt ::= setup_loop expr . GET_AITER LOAD_CONST YIELD_FROM SETUP_EXCEPT GET_ANEXT LOAD_CONST YIELD_FROM store POP_BLOCK JUMP_FORWARD COME_FROM_EXCEPT DUP_TOP LOAD_GLOBAL COMPARE_OP POP_JUMP_IF_FALSE POP_TOP POP_TOP POP_TOP POP_EXCEPT POP_BLOCK JUMP_ABSOLUTE END_FINALLY COME_FROM for_block POP_BLOCK COME_FROM_LOOP
async_for_stmt ::= setup_loop expr . GET_AITER SETUP_EXCEPT GET_ANEXT LOAD_CONST YIELD_FROM store POP_BLOCK JUMP_FORWARD COME_FROM_EXCEPT DUP_TOP LOAD_GLOBAL COMPARE_OP POP_JUMP_IF_TRUE END_FINALLY COME_FROM for_block COME_FROM POP_TOP POP_TOP POP_TOP POP_EXCEPT POP_TOP POP_BLOCK COME_FROM_LOOP
async_for_stmt37 ::= setup_loop . expr GET_AITER \e__come_froms SETUP_EXCEPT GET_ANEXT LOAD_CONST YIELD_FROM store POP_BLOCK JUMP_BACK COME_FROM_EXCEPT DUP_TOP LOAD_GLOBAL COMPARE_OP POP_JUMP_IF_TRUE END_FINALLY for_block COME_FROM POP_TOP POP_TOP POP_TOP POP_EXCEPT POP_TOP POP_BLOCK COME_FROM_LOOP
async_for_stmt37 ::= setup_loop . expr GET_AITER _come_froms SETUP_EXCEPT GET_ANEXT LOAD_CONST YIELD_FROM store POP_BLOCK JUMP_BACK COME_FROM_EXCEPT DUP_TOP LOAD_GLOBAL COMPARE_OP POP_JUMP_IF_TRUE END_FINALLY for_block COME_FROM POP_TOP POP_TOP POP_TOP POP_EXCEPT POP_TOP POP_BLOCK COME_FROM_LOOP
async_for_stmt37 ::= setup_loop expr . GET_AITER \e__come_froms SETUP_EXCEPT GET_ANEXT LOAD_CONST YIELD_FROM store POP_BLOCK JUMP_BACK COME_FROM_EXCEPT DUP_TOP LOAD_GLOBAL COMPARE_OP POP_JUMP_IF_TRUE END_FINALLY for_block COME_FROM POP_TOP POP_TOP POP_TOP POP_EXCEPT POP_TOP POP_BLOCK COME_FROM_LOOP
async_for_stmt37 ::= setup_loop expr . GET_AITER _come_froms SETUP_EXCEPT GET_ANEXT LOAD_CONST YIELD_FROM store POP_BLOCK JUMP_BACK COME_FROM_EXCEPT DUP_TOP LOAD_GLOBAL COMPARE_OP POP_JUMP_IF_TRUE END_FINALLY for_block COME_FROM POP_TOP POP_TOP POP_TOP POP_EXCEPT POP_TOP POP_BLOCK COME_FROM_LOOP
async_forelse_stmt ::= setup_loop . expr GET_AITER \e__come_froms SETUP_EXCEPT GET_ANEXT LOAD_CONST YIELD_FROM store POP_BLOCK JUMP_FORWARD COME_FROM_EXCEPT DUP_TOP LOAD_GLOBAL COMPARE_OP POP_JUMP_IF_TRUE END_FINALLY COME_FROM for_block COME_FROM POP_TOP POP_TOP POP_TOP POP_EXCEPT POP_TOP POP_BLOCK else_suite COME_FROM_LOOP
async_forelse_stmt ::= setup_loop . expr GET_AITER _come_froms SETUP_EXCEPT GET_ANEXT LOAD_CONST YIELD_FROM store POP_BLOCK JUMP_FORWARD COME_FROM_EXCEPT DUP_TOP LOAD_GLOBAL COMPARE_OP POP_JUMP_IF_TRUE END_FINALLY COME_FROM for_block COME_FROM POP_TOP POP_TOP POP_TOP POP_EXCEPT POP_TOP POP_BLOCK else_suite COME_FROM_LOOP
async_forelse_stmt ::= setup_loop expr . GET_AITER \e__come_froms SETUP_EXCEPT GET_ANEXT LOAD_CONST YIELD_FROM store POP_BLOCK JUMP_FORWARD COME_FROM_EXCEPT DUP_TOP LOAD_GLOBAL COMPARE_OP POP_JUMP_IF_TRUE END_FINALLY COME_FROM for_block COME_FROM POP_TOP POP_TOP POP_TOP POP_EXCEPT POP_TOP POP_BLOCK else_suite COME_FROM_LOOP
async_forelse_stmt ::= setup_loop expr . GET_AITER _come_froms SETUP_EXCEPT GET_ANEXT LOAD_CONST YIELD_FROM store POP_BLOCK JUMP_FORWARD COME_FROM_EXCEPT DUP_TOP LOAD_GLOBAL COMPARE_OP POP_JUMP_IF_TRUE END_FINALLY COME_FROM for_block COME_FROM POP_TOP POP_TOP POP_TOP POP_EXCEPT POP_TOP POP_BLOCK else_suite COME_FROM_LOOP
attribute ::= expr . LOAD_ATTR
attribute ::= expr LOAD_ATTR . 
attribute37 ::= expr . LOAD_METHOD
attribute37 ::= expr LOAD_METHOD . 
aug_assign1 ::= expr . expr inplace_op ROT_THREE STORE_SUBSCR
aug_assign1 ::= expr . expr inplace_op store
aug_assign1 ::= expr expr . inplace_op ROT_THREE STORE_SUBSCR
aug_assign1 ::= expr expr . inplace_op store
aug_assign2 ::= expr . DUP_TOP LOAD_ATTR expr inplace_op ROT_TWO STORE_ATTR
await_expr ::= expr . GET_AWAITABLE LOAD_CONST YIELD_FROM
bin_op ::= expr . expr binary_operator
bin_op ::= expr expr . binary_operator
c_stmts ::= _stmts . 
c_stmts ::= _stmts . lastc_stmt
c_stmts_opt ::= c_stmts . 
call ::= expr . CALL_FUNCTION_0
call ::= expr . CALL_METHOD_0
call ::= expr . expr CALL_METHOD_1
call ::= expr . expr expr CALL_METHOD_2
call ::= expr . pos_arg CALL_FUNCTION_1
call ::= expr . pos_arg pos_arg pos_arg CALL_FUNCTION_3
call ::= expr CALL_FUNCTION_0 . 
call ::= expr CALL_METHOD_0 . 
call ::= expr expr . CALL_METHOD_1
call ::= expr expr . expr CALL_METHOD_2
call ::= expr expr CALL_METHOD_1 . 
call ::= expr expr expr . CALL_METHOD_2
call ::= expr expr expr CALL_METHOD_2 . 
call ::= expr pos_arg . CALL_FUNCTION_1
call ::= expr pos_arg . pos_arg pos_arg CALL_FUNCTION_3
call ::= expr pos_arg pos_arg . pos_arg CALL_FUNCTION_3
call ::= expr pos_arg pos_arg pos_arg . CALL_FUNCTION_3
call_ex_kw4 ::= expr . expr expr CALL_FUNCTION_EX_KW
call_ex_kw4 ::= expr expr . expr CALL_FUNCTION_EX_KW
call_ex_kw4 ::= expr expr expr . CALL_FUNCTION_EX_KW
call_kw36 ::= expr . expr expr LOAD_CONST CALL_FUNCTION_KW_2
call_kw36 ::= expr . expr expr expr LOAD_CONST CALL_FUNCTION_KW_3
call_kw36 ::= expr . expr expr expr expr expr expr expr LOAD_CONST CALL_FUNCTION_KW_7
call_kw36 ::= expr expr . expr LOAD_CONST CALL_FUNCTION_KW_2
call_kw36 ::= expr expr . expr expr LOAD_CONST CALL_FUNCTION_KW_3
call_kw36 ::= expr expr . expr expr expr expr expr expr LOAD_CONST CALL_FUNCTION_KW_7
call_kw36 ::= expr expr expr . LOAD_CONST CALL_FUNCTION_KW_2
call_kw36 ::= expr expr expr . expr LOAD_CONST CALL_FUNCTION_KW_3
call_kw36 ::= expr expr expr . expr expr expr expr expr LOAD_CONST CALL_FUNCTION_KW_7
call_kw36 ::= expr expr expr LOAD_CONST . CALL_FUNCTION_KW_2
call_kw36 ::= expr expr expr expr . LOAD_CONST CALL_FUNCTION_KW_3
call_kw36 ::= expr expr expr expr . expr expr expr expr LOAD_CONST CALL_FUNCTION_KW_7
call_kw36 ::= expr expr expr expr LOAD_CONST . CALL_FUNCTION_KW_3
call_kw36 ::= expr expr expr expr expr . expr expr expr LOAD_CONST CALL_FUNCTION_KW_7
call_kw36 ::= expr expr expr expr expr expr . expr expr LOAD_CONST CALL_FUNCTION_KW_7
call_kw36 ::= expr expr expr expr expr expr expr . expr LOAD_CONST CALL_FUNCTION_KW_7
call_kw36 ::= expr expr expr expr expr expr expr expr . LOAD_CONST CALL_FUNCTION_KW_7
call_kw36 ::= expr expr expr expr expr expr expr expr LOAD_CONST . CALL_FUNCTION_KW_7
call_kw36 ::= expr expr expr expr expr expr expr expr LOAD_CONST CALL_FUNCTION_KW_7 . 
call_stmt ::= expr . POP_TOP
call_stmt ::= expr POP_TOP . 
cf_jf_else ::= come_froms . JUMP_FORWARD ELSE
cf_jump_back ::= COME_FROM . JUMP_BACK
classdefdeco1 ::= expr . classdefdeco1 CALL_FUNCTION_1
classdefdeco1 ::= expr . classdefdeco2 CALL_FUNCTION_1
come_from_loops ::= \e_come_from_loops . COME_FROM_LOOP
come_from_opt ::= COME_FROM . 
come_froms ::= COME_FROM . 
come_froms ::= come_froms . COME_FROM
come_froms ::= come_froms COME_FROM . 
compare ::= compare_single . 
compare_chained ::= expr . compare_chained1 ROT_TWO POP_TOP \e__come_froms
compare_chained ::= expr . compare_chained1 ROT_TWO POP_TOP _come_froms
compare_chained1 ::= expr . DUP_TOP ROT_THREE COMPARE_OP JUMP_IF_FALSE_OR_POP compare_chained1 COME_FROM
compare_chained1 ::= expr . DUP_TOP ROT_THREE COMPARE_OP JUMP_IF_FALSE_OR_POP compare_chained2 COME_FROM
compare_chained1_false_37 ::= expr . DUP_TOP ROT_THREE COMPARE_OP POP_JUMP_IF_FALSE compare_chained2b_false_37 POP_TOP _jump COME_FROM
compare_chained1_false_37 ::= expr . DUP_TOP ROT_THREE COMPARE_OP POP_JUMP_IF_FALSE compare_chained2c_37 POP_TOP JUMP_FORWARD COME_FROM
compare_chained1a_37 ::= expr . DUP_TOP ROT_THREE COMPARE_OP POP_JUMP_IF_FALSE
compare_chained1a_37 ::= expr . DUP_TOP ROT_THREE COMPARE_OP POP_JUMP_IF_FALSE compare_chained2a_37 COME_FROM POP_TOP COME_FROM
compare_chained1b_false_37 ::= expr . DUP_TOP ROT_THREE COMPARE_OP POP_JUMP_IF_FALSE compare_chained2b_false_37 POP_TOP _jump COME_FROM
compare_chained1c_37 ::= expr . DUP_TOP ROT_THREE COMPARE_OP POP_JUMP_IF_FALSE compare_chained2a_37 POP_TOP
compare_chained2_false_37 ::= expr . DUP_TOP ROT_THREE COMPARE_OP POP_JUMP_IF_FALSE compare_chained2a_false_37 POP_TOP JUMP_BACK COME_FROM
compare_chained37 ::= expr . compare_chained1a_37
compare_chained37 ::= expr . compare_chained1c_37
compare_chained37_false ::= expr . compare_chained1_false_37
compare_chained37_false ::= expr . compare_chained1b_false_37
compare_chained37_false ::= expr . compare_chained2_false_37
compare_single ::= expr . expr COMPARE_OP
compare_single ::= expr expr . COMPARE_OP
compare_single ::= expr expr COMPARE_OP . 
continues ::= _stmts . lastl_stmt continue
continues ::= _stmts lastl_stmt . continue
continues ::= lastl_stmt . continue
dict ::= expr . expr expr expr LOAD_CONST BUILD_CONST_KEY_MAP_4
dict ::= expr expr . expr expr LOAD_CONST BUILD_CONST_KEY_MAP_4
dict ::= expr expr expr . expr LOAD_CONST BUILD_CONST_KEY_MAP_4
dict ::= expr expr expr expr . LOAD_CONST BUILD_CONST_KEY_MAP_4
dict ::= expr expr expr expr LOAD_CONST . BUILD_CONST_KEY_MAP_4
else_suite ::= suite_stmts . 
else_suite_opt ::= else_suite . 
else_suitec ::= c_stmts . 
expr ::= LOAD_CONST . 
expr ::= LOAD_FAST . 
expr ::= LOAD_GLOBAL . 
expr ::= attribute . 
expr ::= attribute37 . 
expr ::= call . 
expr ::= call_kw36 . 
expr ::= compare . 
expr ::= get_iter . 
expr_jit ::= expr . JUMP_IF_TRUE
expr_jitop ::= expr . JUMP_IF_TRUE_OR_POP
expr_jt ::= expr . jmp_true
expr_pjit ::= expr . POP_JUMP_IF_TRUE
expr_pjit_come_from ::= expr . POP_JUMP_IF_TRUE COME_FROM
expr_stmt ::= expr . POP_TOP
expr_stmt ::= expr POP_TOP . 
for ::= setup_loop . expr get_for_iter store for_block POP_BLOCK
for ::= setup_loop . expr get_for_iter store for_block POP_BLOCK COME_FROM_LOOP
for ::= setup_loop . expr get_for_iter store for_block POP_BLOCK NOP COME_FROM_LOOP
for ::= setup_loop expr . get_for_iter store for_block POP_BLOCK
for ::= setup_loop expr . get_for_iter store for_block POP_BLOCK COME_FROM_LOOP
for ::= setup_loop expr . get_for_iter store for_block POP_BLOCK NOP COME_FROM_LOOP
for ::= setup_loop expr get_for_iter . store for_block POP_BLOCK
for ::= setup_loop expr get_for_iter . store for_block POP_BLOCK COME_FROM_LOOP
for ::= setup_loop expr get_for_iter . store for_block POP_BLOCK NOP COME_FROM_LOOP
for ::= setup_loop expr get_for_iter store . for_block POP_BLOCK
for ::= setup_loop expr get_for_iter store . for_block POP_BLOCK COME_FROM_LOOP
for ::= setup_loop expr get_for_iter store . for_block POP_BLOCK NOP COME_FROM_LOOP
for ::= setup_loop expr get_for_iter store for_block . POP_BLOCK
for ::= setup_loop expr get_for_iter store for_block . POP_BLOCK COME_FROM_LOOP
for ::= setup_loop expr get_for_iter store for_block . POP_BLOCK NOP COME_FROM_LOOP
for ::= setup_loop expr get_for_iter store for_block POP_BLOCK . 
for ::= setup_loop expr get_for_iter store for_block POP_BLOCK . COME_FROM_LOOP
for ::= setup_loop expr get_for_iter store for_block POP_BLOCK . NOP COME_FROM_LOOP
for_block ::= \e_l_stmts_opt . COME_FROM_LOOP JUMP_BACK
for_block ::= \e_l_stmts_opt . _come_froms JUMP_BACK
for_block ::= \e_l_stmts_opt . come_from_loops JUMP_BACK
for_block ::= \e_l_stmts_opt \e__come_froms . JUMP_BACK
for_block ::= \e_l_stmts_opt \e_come_from_loops . JUMP_BACK
for_block ::= l_stmts . 
for_block ::= l_stmts . JUMP_BACK
for_block ::= l_stmts JUMP_BACK . 
for_block ::= l_stmts_opt . COME_FROM_LOOP JUMP_BACK
for_block ::= l_stmts_opt . _come_froms JUMP_BACK
for_block ::= l_stmts_opt . come_from_loops JUMP_BACK
for_block ::= l_stmts_opt \e__come_froms . JUMP_BACK
for_block ::= l_stmts_opt \e__come_froms JUMP_BACK . 
for_block ::= l_stmts_opt \e_come_from_loops . JUMP_BACK
for_block ::= l_stmts_opt \e_come_from_loops JUMP_BACK . 
forelselaststmt ::= SETUP_LOOP . expr get_for_iter store for_block POP_BLOCK else_suitec \e__come_froms
forelselaststmt ::= SETUP_LOOP . expr get_for_iter store for_block POP_BLOCK else_suitec _come_froms
forelselaststmt ::= SETUP_LOOP expr . get_for_iter store for_block POP_BLOCK else_suitec \e__come_froms
forelselaststmt ::= SETUP_LOOP expr . get_for_iter store for_block POP_BLOCK else_suitec _come_froms
forelselaststmt ::= SETUP_LOOP expr get_for_iter . store for_block POP_BLOCK else_suitec \e__come_froms
forelselaststmt ::= SETUP_LOOP expr get_for_iter . store for_block POP_BLOCK else_suitec _come_froms
forelselaststmt ::= SETUP_LOOP expr get_for_iter store . for_block POP_BLOCK else_suitec \e__come_froms
forelselaststmt ::= SETUP_LOOP expr get_for_iter store . for_block POP_BLOCK else_suitec _come_froms
forelselaststmt ::= SETUP_LOOP expr get_for_iter store for_block . POP_BLOCK else_suitec \e__come_froms
forelselaststmt ::= SETUP_LOOP expr get_for_iter store for_block . POP_BLOCK else_suitec _come_froms
forelselaststmt ::= SETUP_LOOP expr get_for_iter store for_block POP_BLOCK . else_suitec \e__come_froms
forelselaststmt ::= SETUP_LOOP expr get_for_iter store for_block POP_BLOCK . else_suitec _come_froms
forelselaststmt ::= setup_loop . expr get_for_iter store for_block POP_BLOCK else_suitec COME_FROM_LOOP
forelselaststmt ::= setup_loop expr . get_for_iter store for_block POP_BLOCK else_suitec COME_FROM_LOOP
forelselaststmt ::= setup_loop expr get_for_iter . store for_block POP_BLOCK else_suitec COME_FROM_LOOP
forelselaststmt ::= setup_loop expr get_for_iter store . for_block POP_BLOCK else_suitec COME_FROM_LOOP
forelselaststmt ::= setup_loop expr get_for_iter store for_block . POP_BLOCK else_suitec COME_FROM_LOOP
forelselaststmt ::= setup_loop expr get_for_iter store for_block POP_BLOCK . else_suitec COME_FROM_LOOP
forelselaststmtl ::= SETUP_LOOP . expr get_for_iter store for_block POP_BLOCK else_suitel \e__come_froms
forelselaststmtl ::= SETUP_LOOP . expr get_for_iter store for_block POP_BLOCK else_suitel _come_froms
forelselaststmtl ::= SETUP_LOOP expr . get_for_iter store for_block POP_BLOCK else_suitel \e__come_froms
forelselaststmtl ::= SETUP_LOOP expr . get_for_iter store for_block POP_BLOCK else_suitel _come_froms
forelselaststmtl ::= SETUP_LOOP expr get_for_iter . store for_block POP_BLOCK else_suitel \e__come_froms
forelselaststmtl ::= SETUP_LOOP expr get_for_iter . store for_block POP_BLOCK else_suitel _come_froms
forelselaststmtl ::= SETUP_LOOP expr get_for_iter store . for_block POP_BLOCK else_suitel \e__come_froms
forelselaststmtl ::= SETUP_LOOP expr get_for_iter store . for_block POP_BLOCK else_suitel _come_froms
forelselaststmtl ::= SETUP_LOOP expr get_for_iter store for_block . POP_BLOCK else_suitel \e__come_froms
forelselaststmtl ::= SETUP_LOOP expr get_for_iter store for_block . POP_BLOCK else_suitel _come_froms
forelselaststmtl ::= SETUP_LOOP expr get_for_iter store for_block POP_BLOCK . else_suitel \e__come_froms
forelselaststmtl ::= SETUP_LOOP expr get_for_iter store for_block POP_BLOCK . else_suitel _come_froms
forelselaststmtl ::= setup_loop . expr get_for_iter store for_block POP_BLOCK else_suitel COME_FROM_LOOP
forelselaststmtl ::= setup_loop expr . get_for_iter store for_block POP_BLOCK else_suitel COME_FROM_LOOP
forelselaststmtl ::= setup_loop expr get_for_iter . store for_block POP_BLOCK else_suitel COME_FROM_LOOP
forelselaststmtl ::= setup_loop expr get_for_iter store . for_block POP_BLOCK else_suitel COME_FROM_LOOP
forelselaststmtl ::= setup_loop expr get_for_iter store for_block . POP_BLOCK else_suitel COME_FROM_LOOP
forelselaststmtl ::= setup_loop expr get_for_iter store for_block POP_BLOCK . else_suitel COME_FROM_LOOP
forelsestmt ::= SETUP_LOOP . expr get_for_iter store for_block POP_BLOCK else_suite \e__come_froms
forelsestmt ::= SETUP_LOOP . expr get_for_iter store for_block POP_BLOCK else_suite _come_froms
forelsestmt ::= SETUP_LOOP expr . get_for_iter store for_block POP_BLOCK else_suite \e__come_froms
forelsestmt ::= SETUP_LOOP expr . get_for_iter store for_block POP_BLOCK else_suite _come_froms
forelsestmt ::= SETUP_LOOP expr get_for_iter . store for_block POP_BLOCK else_suite \e__come_froms
forelsestmt ::= SETUP_LOOP expr get_for_iter . store for_block POP_BLOCK else_suite _come_froms
forelsestmt ::= SETUP_LOOP expr get_for_iter store . for_block POP_BLOCK else_suite \e__come_froms
forelsestmt ::= SETUP_LOOP expr get_for_iter store . for_block POP_BLOCK else_suite _come_froms
forelsestmt ::= SETUP_LOOP expr get_for_iter store for_block . POP_BLOCK else_suite \e__come_froms
forelsestmt ::= SETUP_LOOP expr get_for_iter store for_block . POP_BLOCK else_suite _come_froms
forelsestmt ::= SETUP_LOOP expr get_for_iter store for_block POP_BLOCK . else_suite \e__come_froms
forelsestmt ::= SETUP_LOOP expr get_for_iter store for_block POP_BLOCK . else_suite _come_froms
forelsestmt ::= setup_loop . expr get_for_iter store for_block POP_BLOCK else_suite COME_FROM_LOOP
forelsestmt ::= setup_loop expr . get_for_iter store for_block POP_BLOCK else_suite COME_FROM_LOOP
forelsestmt ::= setup_loop expr get_for_iter . store for_block POP_BLOCK else_suite COME_FROM_LOOP
forelsestmt ::= setup_loop expr get_for_iter store . for_block POP_BLOCK else_suite COME_FROM_LOOP
forelsestmt ::= setup_loop expr get_for_iter store for_block . POP_BLOCK else_suite COME_FROM_LOOP
forelsestmt ::= setup_loop expr get_for_iter store for_block POP_BLOCK . else_suite COME_FROM_LOOP
get_for_iter ::= GET_ITER . _come_froms FOR_ITER
get_for_iter ::= GET_ITER \e__come_froms . FOR_ITER
get_for_iter ::= GET_ITER \e__come_froms FOR_ITER . 
get_iter ::= expr . GET_ITER
get_iter ::= expr GET_ITER . 
if_exp ::= expr . jmp_false expr jf_cf expr COME_FROM
if_exp ::= expr . jmp_false expr jump_absolute_else expr
if_exp ::= expr jmp_false . expr jf_cf expr COME_FROM
if_exp ::= expr jmp_false . expr jump_absolute_else expr
if_exp ::= expr jmp_false expr . jf_cf expr COME_FROM
if_exp ::= expr jmp_false expr . jump_absolute_else expr
if_exp37 ::= expr . expr jf_cfs expr COME_FROM
if_exp37 ::= expr expr . jf_cfs expr COME_FROM
if_exp_37b ::= expr . jmp_false expr POP_JUMP_IF_FALSE jump_forward_else expr
if_exp_37b ::= expr jmp_false . expr POP_JUMP_IF_FALSE jump_forward_else expr
if_exp_37b ::= expr jmp_false expr . POP_JUMP_IF_FALSE jump_forward_else expr
if_exp_lambda ::= expr . jmp_false expr return_if_lambda return_stmt_lambda LAMBDA_MARKER
if_exp_lambda ::= expr jmp_false . expr return_if_lambda return_stmt_lambda LAMBDA_MARKER
if_exp_lambda ::= expr jmp_false expr . return_if_lambda return_stmt_lambda LAMBDA_MARKER
if_exp_not ::= expr . jmp_true expr jump_forward_else expr COME_FROM
if_exp_not_lambda ::= expr . jmp_true expr return_if_lambda return_stmt_lambda LAMBDA_MARKER
if_exp_true ::= expr . JUMP_FORWARD expr COME_FROM
ifelsestmt ::= testexpr . c_stmts come_froms else_suite come_froms
ifelsestmt ::= testexpr . c_stmts_opt JUMP_FORWARD else_suite \e__come_froms
ifelsestmt ::= testexpr . c_stmts_opt JUMP_FORWARD else_suite \e_opt_come_from_except
ifelsestmt ::= testexpr . c_stmts_opt JUMP_FORWARD else_suite _come_froms
ifelsestmt ::= testexpr . c_stmts_opt JUMP_FORWARD else_suite opt_come_from_except
ifelsestmt ::= testexpr . c_stmts_opt jf_cfs else_suite \e_opt_come_from_except
ifelsestmt ::= testexpr . c_stmts_opt jf_cfs else_suite opt_come_from_except
ifelsestmt ::= testexpr . c_stmts_opt jump_forward_else else_suite \e__come_froms
ifelsestmt ::= testexpr . c_stmts_opt jump_forward_else else_suite _come_froms
ifelsestmt ::= testexpr . stmts jf_cfs \e_else_suite_opt \e_opt_come_from_except
ifelsestmt ::= testexpr . stmts jf_cfs \e_else_suite_opt opt_come_from_except
ifelsestmt ::= testexpr . stmts jf_cfs else_suite_opt \e_opt_come_from_except
ifelsestmt ::= testexpr . stmts jf_cfs else_suite_opt opt_come_from_except
ifelsestmt ::= testexpr \e_c_stmts_opt . JUMP_FORWARD else_suite \e__come_froms
ifelsestmt ::= testexpr \e_c_stmts_opt . JUMP_FORWARD else_suite \e_opt_come_from_except
ifelsestmt ::= testexpr \e_c_stmts_opt . JUMP_FORWARD else_suite _come_froms
ifelsestmt ::= testexpr \e_c_stmts_opt . JUMP_FORWARD else_suite opt_come_from_except
ifelsestmt ::= testexpr \e_c_stmts_opt . jf_cfs else_suite \e_opt_come_from_except
ifelsestmt ::= testexpr \e_c_stmts_opt . jf_cfs else_suite opt_come_from_except
ifelsestmt ::= testexpr \e_c_stmts_opt . jump_forward_else else_suite \e__come_froms
ifelsestmt ::= testexpr \e_c_stmts_opt . jump_forward_else else_suite _come_froms
ifelsestmt ::= testexpr c_stmts . come_froms else_suite come_froms
ifelsestmt ::= testexpr c_stmts come_froms . else_suite come_froms
ifelsestmt ::= testexpr c_stmts_opt . JUMP_FORWARD else_suite \e__come_froms
ifelsestmt ::= testexpr c_stmts_opt . JUMP_FORWARD else_suite \e_opt_come_from_except
ifelsestmt ::= testexpr c_stmts_opt . JUMP_FORWARD else_suite _come_froms
ifelsestmt ::= testexpr c_stmts_opt . JUMP_FORWARD else_suite opt_come_from_except
ifelsestmt ::= testexpr c_stmts_opt . jf_cfs else_suite \e_opt_come_from_except
ifelsestmt ::= testexpr c_stmts_opt . jf_cfs else_suite opt_come_from_except
ifelsestmt ::= testexpr c_stmts_opt . jump_forward_else else_suite \e__come_froms
ifelsestmt ::= testexpr c_stmts_opt . jump_forward_else else_suite _come_froms
ifelsestmt ::= testexpr c_stmts_opt JUMP_FORWARD . else_suite \e__come_froms
ifelsestmt ::= testexpr c_stmts_opt JUMP_FORWARD . else_suite \e_opt_come_from_except
ifelsestmt ::= testexpr c_stmts_opt JUMP_FORWARD . else_suite _come_froms
ifelsestmt ::= testexpr c_stmts_opt JUMP_FORWARD . else_suite opt_come_from_except
ifelsestmt ::= testexpr c_stmts_opt jf_cfs . else_suite \e_opt_come_from_except
ifelsestmt ::= testexpr c_stmts_opt jf_cfs . else_suite opt_come_from_except
ifelsestmt ::= testexpr c_stmts_opt jf_cfs else_suite . opt_come_from_except
ifelsestmt ::= testexpr c_stmts_opt jf_cfs else_suite \e_opt_come_from_except . 
ifelsestmt ::= testexpr c_stmts_opt jf_cfs else_suite opt_come_from_except . 
ifelsestmt ::= testexpr c_stmts_opt jump_forward_else . else_suite \e__come_froms
ifelsestmt ::= testexpr c_stmts_opt jump_forward_else . else_suite _come_froms
ifelsestmt ::= testexpr c_stmts_opt jump_forward_else else_suite . _come_froms
ifelsestmt ::= testexpr c_stmts_opt jump_forward_else else_suite \e__come_froms . 
ifelsestmt ::= testexpr c_stmts_opt jump_forward_else else_suite _come_froms . 
ifelsestmt ::= testexpr stmts . jf_cfs \e_else_suite_opt \e_opt_come_from_except
ifelsestmt ::= testexpr stmts . jf_cfs \e_else_suite_opt opt_come_from_except
ifelsestmt ::= testexpr stmts . jf_cfs else_suite_opt \e_opt_come_from_except
ifelsestmt ::= testexpr stmts . jf_cfs else_suite_opt opt_come_from_except
ifelsestmt ::= testexpr stmts jf_cfs . else_suite_opt \e_opt_come_from_except
ifelsestmt ::= testexpr stmts jf_cfs . else_suite_opt opt_come_from_except
ifelsestmt ::= testexpr stmts jf_cfs \e_else_suite_opt . opt_come_from_except
ifelsestmt ::= testexpr stmts jf_cfs \e_else_suite_opt \e_opt_come_from_except . 
ifelsestmt ::= testexpr stmts jf_cfs \e_else_suite_opt opt_come_from_except . 
ifelsestmt ::= testexpr stmts jf_cfs else_suite_opt . opt_come_from_except
ifelsestmt ::= testexpr stmts jf_cfs else_suite_opt \e_opt_come_from_except . 
ifelsestmt ::= testexpr stmts jf_cfs else_suite_opt opt_come_from_except . 
ifelsestmtl ::= testexpr . c_stmts_opt cf_jf_else else_suitel
ifelsestmtl ::= testexpr . c_stmts_opt cf_jump_back else_suitel
ifelsestmtl ::= testexpr . c_stmts_opt jb_cfs else_suitel
ifelsestmtl ::= testexpr . c_stmts_opt jb_else else_suitel
ifelsestmtl ::= testexpr . c_stmts_opt jump_forward_else else_suitec
ifelsestmtl ::= testexpr \e_c_stmts_opt . cf_jf_else else_suitel
ifelsestmtl ::= testexpr \e_c_stmts_opt . cf_jump_back else_suitel
ifelsestmtl ::= testexpr \e_c_stmts_opt . jb_cfs else_suitel
ifelsestmtl ::= testexpr \e_c_stmts_opt . jb_else else_suitel
ifelsestmtl ::= testexpr \e_c_stmts_opt . jump_forward_else else_suitec
ifelsestmtl ::= testexpr c_stmts_opt . cf_jf_else else_suitel
ifelsestmtl ::= testexpr c_stmts_opt . cf_jump_back else_suitel
ifelsestmtl ::= testexpr c_stmts_opt . jb_cfs else_suitel
ifelsestmtl ::= testexpr c_stmts_opt . jb_else else_suitel
ifelsestmtl ::= testexpr c_stmts_opt . jump_forward_else else_suitec
ifelsestmtl ::= testexpr c_stmts_opt jump_forward_else . else_suitec
ifelsestmtl ::= testexpr c_stmts_opt jump_forward_else else_suitec . 
ifelsestmtr ::= testexpr . return_if_stmts returns
iflaststmtl ::= testexpr . c_stmts
iflaststmtl ::= testexpr . c_stmts JUMP_BACK
iflaststmtl ::= testexpr . c_stmts JUMP_BACK COME_FROM_LOOP
iflaststmtl ::= testexpr . c_stmts JUMP_BACK POP_BLOCK
iflaststmtl ::= testexpr c_stmts . 
iflaststmtl ::= testexpr c_stmts . JUMP_BACK
iflaststmtl ::= testexpr c_stmts . JUMP_BACK COME_FROM_LOOP
iflaststmtl ::= testexpr c_stmts . JUMP_BACK POP_BLOCK
ifstmt ::= testexpr . _ifstmts_jump
ifstmt ::= testexpr _ifstmts_jump . 
ifstmtl ::= testexpr . _ifstmts_jumpl
ifstmtl ::= testexpr _ifstmts_jumpl . 
jb_cfs ::= \e_come_from_opt . JUMP_BACK come_froms
jb_cfs ::= come_from_opt . JUMP_BACK come_froms
jf_cfs ::= JUMP_FORWARD . _come_froms
jf_cfs ::= JUMP_FORWARD \e__come_froms . 
jf_cfs ::= JUMP_FORWARD _come_froms . 
jmp_false ::= POP_JUMP_IF_FALSE . 
jump_forward_else ::= JUMP_FORWARD . 
jump_forward_else ::= JUMP_FORWARD . COME_FROM
jump_forward_else ::= JUMP_FORWARD . ELSE
jump_forward_else ::= JUMP_FORWARD COME_FROM . 
l_stmts ::= _stmts . 
l_stmts ::= _stmts . lastl_stmt
l_stmts ::= l_stmts . lstmt
l_stmts ::= l_stmts lstmt . 
l_stmts ::= lstmt . 
l_stmts_opt ::= l_stmts . 
lastl_stmt ::= ifelsestmtl . 
lastl_stmt ::= iflaststmtl . 
list ::= expr . BUILD_LIST_1
lstmt ::= stmt . 
mkfuncdeco ::= expr . mkfuncdeco CALL_FUNCTION_1
mkfuncdeco ::= expr . mkfuncdeco0 CALL_FUNCTION_1
opt_come_from_except ::= _come_froms . 
pos_arg ::= expr . 
ret_and ::= expr . JUMP_IF_FALSE_OR_POP return_expr_or_cond COME_FROM
ret_or ::= expr . JUMP_IF_TRUE_OR_POP return_expr_or_cond COME_FROM
return ::= return_expr . RETURN_END_IF
return ::= return_expr . RETURN_VALUE
return ::= return_expr . RETURN_VALUE COME_FROM
return_expr ::= expr . 
return_expr_lambda ::= return_expr . RETURN_VALUE_LAMBDA
return_expr_lambda ::= return_expr . RETURN_VALUE_LAMBDA LAMBDA_MARKER
return_if_stmt ::= return_expr . RETURN_END_IF
return_if_stmt ::= return_expr . RETURN_END_IF POP_BLOCK
return_if_stmts ::= _stmts . return_if_stmt \e__come_froms
return_if_stmts ::= _stmts . return_if_stmt _come_froms
returns ::= _stmts . return
returns ::= _stmts . return_if_stmt
setup_loop ::= SETUP_LOOP . _come_froms
setup_loop ::= SETUP_LOOP \e__come_froms . 
sstmt ::= sstmt . RETURN_LAST
sstmt ::= stmt . 
stmt ::= assign . 
stmt ::= call_stmt . 
stmt ::= expr_stmt . 
stmt ::= for . 
stmt ::= ifelsestmt . 
stmts ::= sstmt . 
stmts ::= stmts . sstmt
stmts ::= stmts sstmt . 
store ::= STORE_FAST . 
store ::= expr . STORE_ATTR
store ::= expr STORE_ATTR . 
store_subscript ::= expr . expr STORE_SUBSCR
store_subscript ::= expr expr . STORE_SUBSCR
subscript ::= expr . expr BINARY_SUBSCR
subscript ::= expr expr . BINARY_SUBSCR
subscript2 ::= expr . expr DUP_TOP_TWO BINARY_SUBSCR
subscript2 ::= expr expr . DUP_TOP_TWO BINARY_SUBSCR
suite_stmts ::= _stmts . 
testexpr ::= testfalse . 
testexpr_cf ::= testexpr . come_froms
testfalse ::= expr . jmp_false
testfalse ::= expr jmp_false . 
testfalse_not_and ::= expr . jmp_false expr jmp_true COME_FROM
testfalse_not_and ::= expr jmp_false . expr jmp_true COME_FROM
testfalse_not_and ::= expr jmp_false expr . jmp_true COME_FROM
testfalse_not_or ::= expr . jmp_false expr jmp_false COME_FROM
testfalse_not_or ::= expr jmp_false . expr jmp_false COME_FROM
testfalse_not_or ::= expr jmp_false expr . jmp_false COME_FROM
testfalsel ::= expr . jmp_true
testtrue ::= expr . jmp_true
unary_not ::= expr . UNARY_NOT
unary_op ::= expr . unary_operator
while1elsestmt ::= setup_loop . l_stmts JUMP_BACK POP_BLOCK else_suite COME_FROM_LOOP
while1elsestmt ::= setup_loop . l_stmts JUMP_BACK \e__come_froms POP_BLOCK else_suitel COME_FROM_LOOP
while1elsestmt ::= setup_loop . l_stmts JUMP_BACK _come_froms POP_BLOCK else_suitel COME_FROM_LOOP
while1elsestmt ::= setup_loop . l_stmts JUMP_BACK else_suite COME_FROM_LOOP
while1elsestmt ::= setup_loop . l_stmts JUMP_BACK else_suitel
while1stmt ::= setup_loop . l_stmts COME_FROM JUMP_BACK COME_FROM_LOOP
while1stmt ::= setup_loop . l_stmts COME_FROM JUMP_BACK POP_BLOCK COME_FROM_LOOP
while1stmt ::= setup_loop . l_stmts COME_FROM_LOOP
while1stmt ::= setup_loop . l_stmts COME_FROM_LOOP JUMP_BACK POP_BLOCK COME_FROM_LOOP
while1stmt ::= setup_loop . l_stmts POP_BLOCK COME_FROM_LOOP
whileTruestmt ::= SETUP_LOOP . l_stmts_opt JUMP_BACK COME_FROM_LOOP
whileTruestmt ::= SETUP_LOOP \e_l_stmts_opt . JUMP_BACK COME_FROM_LOOP
whileTruestmt ::= setup_loop . l_stmts_opt JUMP_BACK POP_BLOCK \e__come_froms
whileTruestmt ::= setup_loop . l_stmts_opt JUMP_BACK POP_BLOCK _come_froms
whileTruestmt ::= setup_loop \e_l_stmts_opt . JUMP_BACK POP_BLOCK \e__come_froms
whileTruestmt ::= setup_loop \e_l_stmts_opt . JUMP_BACK POP_BLOCK _come_froms
whileelsestmt ::= setup_loop . testexpr \e_l_stmts_opt JUMP_BACK POP_BLOCK else_suitel COME_FROM
whileelsestmt ::= setup_loop . testexpr \e_l_stmts_opt JUMP_BACK POP_BLOCK else_suitel COME_FROM_LOOP
whileelsestmt ::= setup_loop . testexpr l_stmts_opt JUMP_BACK POP_BLOCK else_suitel COME_FROM
whileelsestmt ::= setup_loop . testexpr l_stmts_opt JUMP_BACK POP_BLOCK else_suitel COME_FROM_LOOP
whilestmt ::= setup_loop . testexpr \e_l_stmts_opt COME_FROM JUMP_BACK POP_BLOCK COME_FROM_LOOP
whilestmt ::= setup_loop . testexpr \e_l_stmts_opt JUMP_BACK POP_BLOCK COME_FROM_LOOP
whilestmt ::= setup_loop . testexpr \e_l_stmts_opt JUMP_BACK come_froms POP_BLOCK
whilestmt ::= setup_loop . testexpr \e_l_stmts_opt JUMP_BACK come_froms POP_BLOCK COME_FROM_LOOP
whilestmt ::= setup_loop . testexpr \e_l_stmts_opt come_froms JUMP_BACK come_froms POP_BLOCK COME_FROM_LOOP
whilestmt ::= setup_loop . testexpr l_stmts_opt COME_FROM JUMP_BACK POP_BLOCK COME_FROM_LOOP
whilestmt ::= setup_loop . testexpr l_stmts_opt JUMP_BACK POP_BLOCK COME_FROM_LOOP
whilestmt ::= setup_loop . testexpr l_stmts_opt JUMP_BACK come_froms POP_BLOCK
whilestmt ::= setup_loop . testexpr l_stmts_opt JUMP_BACK come_froms POP_BLOCK COME_FROM_LOOP
whilestmt ::= setup_loop . testexpr l_stmts_opt come_froms JUMP_BACK come_froms POP_BLOCK COME_FROM_LOOP
whilestmt ::= setup_loop . testexpr returns POP_BLOCK COME_FROM_LOOP
whilestmt ::= setup_loop . testexpr returns come_froms POP_BLOCK COME_FROM_LOOP
yield ::= expr . YIELD_VALUE
yield_from ::= expr . GET_YIELD_FROM_ITER LOAD_CONST YIELD_FROM
Instruction context:
   
 L. 100       166  LOAD_FAST                'self'
                 168  LOAD_METHOD              _fixup_sims_outfit
                 170  LOAD_FAST                'sim'
                 172  CALL_METHOD_1         1  '1 positional argument'
                 174  POP_TOP          
               176_0  COME_FROM           164  '164'
->             176_1  COME_FROM            86  '86'
from interactions.context import InteractionContext, QueueInsertStrategy
from sims.outfits.outfit_enums import OutfitCategory, BodyTypeFlag
from sims4.tuning.tunable import TunableReference
from situations.base_situation import _RequestUserData
from situations.bouncer.bouncer_request import BouncerRequest
from situations.bouncer.bouncer_types import BouncerRequestPriority
from situations.situation import Situation
from situations.situation_complex import SituationComplexCommon, CommonSituationState, SituationStateData
import interactions.priority, services, sims4.resources

class _BeInSquadState(CommonSituationState):
    pass


class SquadSituation(SituationComplexCommon):
    INSTANCE_TUNABLES = {'_be_in_squad_state':_BeInSquadState.TunableFactory(description='\n            The situation state used for sims in this situation.\n            ',
       tuning_group=SituationComplexCommon.SITUATION_STATE_GROUP,
       display_name='01_be_in_squad_state'), 
     'leader_job':TunableReference(description='\n            The job that the leader will have. This will be used to identify\n            the leader.\n            ',
       manager=services.get_instance_manager(sims4.resources.Types.SITUATION_JOB)), 
     'squad_member_job':TunableReference(description='\n            The job that each member of the squad will get when they are added\n            to this situation.\n            ',
       manager=services.get_instance_manager(sims4.resources.Types.SITUATION_JOB)), 
     'ensemble_type':TunableReference(description='    \n            The type of ensemble you want the squad to start.\n            ',
       manager=services.get_instance_manager(sims4.resources.Types.ENSEMBLE))}
    REMOVE_INSTANCE_TUNABLES = Situation.NON_USER_FACING_REMOVE_INSTANCE_TUNABLES

    def __init__(self, *args, **kwargs):
        (super().__init__)(*args, **kwargs)
        self._ensemble = None

    @classmethod
    def _states(cls):
        return [SituationStateData(1, _BeInSquadState, factory=(cls._be_in_squad_state))]

    @classmethod
    def _get_tuned_job_and_default_role_state_tuples(cls):
        return list(cls._be_in_squad_state._tuned_values.job_and_role_changes.items())

    @classmethod
    def default_job(cls):
        pass

    def start_situation(self):
        super().start_situation()
        self._change_state(self._be_in_squad_state())

    def _on_set_sim_job--- This code section failed: ---

 L.  79         0  LOAD_GLOBAL              super
                2  CALL_FUNCTION_0       0  '0 positional arguments'
                4  LOAD_METHOD              _on_set_sim_job
                6  LOAD_FAST                'sim'
                8  LOAD_FAST                'job_type'
               10  CALL_METHOD_2         2  '2 positional arguments'
               12  POP_TOP          

 L.  80        14  LOAD_FAST                'job_type'
               16  LOAD_FAST                'self'
               18  LOAD_ATTR                leader_job
               20  COMPARE_OP               is
               22  POP_JUMP_IF_FALSE    88  'to 88'

 L.  81        24  SETUP_LOOP          176  'to 176'
               26  LOAD_FAST                'sim'
               28  LOAD_ATTR                sim_info
               30  LOAD_ATTR                squad_members
               32  GET_ITER         
               34  FOR_ITER             84  'to 84'
               36  STORE_FAST               'sim_info_id'

 L.  82        38  LOAD_GLOBAL              BouncerRequest
               40  LOAD_FAST                'self'

 L.  83        42  LOAD_GLOBAL              _RequestUserData
               44  CALL_FUNCTION_0       0  '0 positional arguments'

 L.  84        46  LOAD_FAST                'sim_info_id'

 L.  85        48  LOAD_FAST                'self'
               50  LOAD_ATTR                squad_member_job

 L.  86        52  LOAD_GLOBAL              BouncerRequestPriority
               54  LOAD_ATTR                BACKGROUND_HIGH

 L.  87        56  LOAD_CONST               False

 L.  88        58  LOAD_FAST                'self'
               60  LOAD_ATTR                exclusivity
               62  LOAD_CONST               ('callback_data', 'requested_sim_id', 'job_type', 'request_priority', 'user_facing', 'exclusivity')
               64  CALL_FUNCTION_KW_7     7  '7 total positional and keyword args'
               66  STORE_FAST               'request'

 L.  90        68  LOAD_FAST                'self'
               70  LOAD_ATTR                manager
               72  LOAD_ATTR                bouncer
               74  LOAD_METHOD              submit_request
               76  LOAD_FAST                'request'
               78  CALL_METHOD_1         1  '1 positional argument'
               80  POP_TOP          
               82  JUMP_BACK            34  'to 34'
               84  POP_BLOCK        
               86  JUMP_FORWARD        176  'to 176'
             88_0  COME_FROM            22  '22'

 L.  92        88  LOAD_FAST                'self'
               90  LOAD_ATTR                _ensemble
               92  LOAD_CONST               None
               94  COMPARE_OP               is
               96  POP_JUMP_IF_FALSE   144  'to 144'

 L.  93        98  LOAD_GLOBAL              services
              100  LOAD_METHOD              ensemble_service
              102  CALL_METHOD_0         0  '0 positional arguments'
              104  LOAD_METHOD              create_ensemble
              106  LOAD_FAST                'self'
              108  LOAD_ATTR                ensemble_type

 L.  94       110  LOAD_FAST                'self'
              112  LOAD_ATTR                _situation_sims
              114  LOAD_METHOD              keys
              116  CALL_METHOD_0         0  '0 positional arguments'
              118  CALL_METHOD_2         2  '2 positional arguments'
              120  POP_TOP          

 L.  95       122  LOAD_GLOBAL              services
              124  LOAD_METHOD              ensemble_service
              126  CALL_METHOD_0         0  '0 positional arguments'
              128  LOAD_METHOD              get_ensemble_for_sim
              130  LOAD_FAST                'self'
              132  LOAD_ATTR                ensemble_type
              134  LOAD_FAST                'sim'
              136  CALL_METHOD_2         2  '2 positional arguments'
              138  LOAD_FAST                'self'
              140  STORE_ATTR               _ensemble
              142  JUMP_FORWARD        156  'to 156'
            144_0  COME_FROM            96  '96'

 L.  98       144  LOAD_FAST                'self'
              146  LOAD_ATTR                _ensemble
              148  LOAD_METHOD              add_sim_to_ensemble
              150  LOAD_FAST                'sim'
              152  CALL_METHOD_1         1  '1 positional argument'
              154  POP_TOP          
            156_0  COME_FROM           142  '142'

 L.  99       156  LOAD_FAST                'job_type'
              158  LOAD_ATTR                job_uniform
              160  LOAD_CONST               None
              162  COMPARE_OP               is
              164  POP_JUMP_IF_FALSE   176  'to 176'

 L. 100       166  LOAD_FAST                'self'
              168  LOAD_METHOD              _fixup_sims_outfit
              170  LOAD_FAST                'sim'
              172  CALL_METHOD_1         1  '1 positional argument'
              174  POP_TOP          
            176_0  COME_FROM           164  '164'
            176_1  COME_FROM            86  '86'
            176_2  COME_FROM_LOOP       24  '24'

Parse error at or near `COME_FROM' instruction at offset 176_1

    def _fixup_sims_outfit(self, sim):
        sim_info = sim.sim_info
        if sim_info.is_child_or_younger:
            return
        leader_sim_info = self.requesting_sim_info
        if sim_info.species != leader_sim_info.species or sim_info.clothing_preference_gender != leader_sim_info.clothing_preference_gender:
            return
        leader_current_outfit = leader_sim_info.get_current_outfit()
        if leader_current_outfit[0] == OutfitCategory.BATHING:
            leader_current_outfit = (
             OutfitCategory.EVERYDAY, 0)
        else:
            with leader_sim_info.set_temporary_outfit_flags(leader_current_outfit[0], leader_current_outfit[1], BodyTypeFlag.CLOTHING_ALL):
                sim_info.generate_merged_outfit(leader_sim_info, (OutfitCategory.SITUATION, 0), (sim_info.get_current_outfit()), leader_current_outfit, preserve_outfit_flags=True)
            if not self.manager.sim_being_created is sim:
                services.current_zone().is_zone_running or sim.set_current_outfit((OutfitCategory.SITUATION, 0))
            else:
                context = InteractionContext(sim, (InteractionContext.SOURCE_SCRIPT),
                  (interactions.priority.Priority.High),
                  insert_strategy=(QueueInsertStrategy.NEXT),
                  bucket=(interactions.context.InteractionBucketType.DEFAULT))
                sim.push_super_affordance(self.CHANGE_TO_SITUATION_OUTFIT, None, context)

    def on_remove(self):
        super().on_remove()
        if self._ensemble is not None:
            self._ensemble.end_ensemble()
            self._ensemble = None
