# uncompyle6 version 3.9.0
# Python bytecode version base 3.7.0 (3394)
# Decompiled from: Python 3.7.16 (default, Dec  7 2022, 01:12:33) 
# [GCC 11.3.0]
# Embedded file name: T:\InGame\Gameplay\Scripts\Server\interactions\privacy_handlers.py
# Compiled at: 2022-05-09 23:32:13
# Size of source mod 2**32: 7548 bytes

-- Stacks of completed symbols:
START ::= |- stmts . 
_come_froms ::= \e__come_froms . COME_FROM
_come_froms ::= \e__come_froms . COME_FROM_LOOP
_come_froms ::= \e__come_froms COME_FROM . 
_come_froms ::= \e__come_froms COME_FROM_LOOP . 
_come_froms ::= _come_froms . COME_FROM
_come_froms ::= _come_froms . COME_FROM_LOOP
_come_froms ::= _come_froms COME_FROM . 
_ifstmts_jump ::= \e_c_stmts_opt . COME_FROM
_ifstmts_jump ::= \e_c_stmts_opt . ELSE
_ifstmts_jump ::= \e_c_stmts_opt . JUMP_ABSOLUTE JUMP_FORWARD \e__come_froms
_ifstmts_jump ::= \e_c_stmts_opt . JUMP_ABSOLUTE JUMP_FORWARD _come_froms
_ifstmts_jump ::= \e_c_stmts_opt . come_froms
_ifstmts_jump ::= c_stmts_opt . COME_FROM
_ifstmts_jump ::= c_stmts_opt . ELSE
_ifstmts_jump ::= c_stmts_opt . JUMP_ABSOLUTE JUMP_FORWARD \e__come_froms
_ifstmts_jump ::= c_stmts_opt . JUMP_ABSOLUTE JUMP_FORWARD _come_froms
_ifstmts_jump ::= c_stmts_opt . come_froms
_ifstmts_jumpl ::= c_stmts . JUMP_BACK
_ifstmts_jumpl ::= c_stmts JUMP_BACK . 
_stmts ::= _stmts . stmt
_stmts ::= _stmts stmt . 
_stmts ::= stmt . 
and ::= expr . JUMP_IF_FALSE_OR_POP expr \e_come_from_opt
and ::= expr . JUMP_IF_FALSE_OR_POP expr come_from_opt
and ::= expr . jifop_come_from expr
and ::= expr . jmp_false expr
and ::= expr . jmp_false expr COME_FROM
and ::= expr . jmp_false expr jmp_false
and ::= expr jmp_false . expr
and ::= expr jmp_false . expr COME_FROM
and ::= expr jmp_false . expr jmp_false
and ::= expr jmp_false expr . 
and ::= expr jmp_false expr . COME_FROM
and ::= expr jmp_false expr . jmp_false
and ::= expr jmp_false expr jmp_false . 
and_not ::= expr . jmp_false expr POP_JUMP_IF_TRUE
and_not ::= expr jmp_false . expr POP_JUMP_IF_TRUE
and_not ::= expr jmp_false expr . POP_JUMP_IF_TRUE
assert2 ::= expr . jmp_true LOAD_GLOBAL expr CALL_FUNCTION_1 RAISE_VARARGS_1
assign ::= expr . DUP_TOP designList
assign ::= expr . store
assign ::= expr store . 
assign2 ::= expr . expr ROT_TWO store store
assign2 ::= expr expr . ROT_TWO store store
assign3 ::= expr . expr expr ROT_THREE ROT_TWO store store store
assign3 ::= expr expr . expr ROT_THREE ROT_TWO store store store
assign3 ::= expr expr expr . ROT_THREE ROT_TWO store store store
async_for_stmt ::= setup_loop . expr GET_AITER LOAD_CONST YIELD_FROM SETUP_EXCEPT GET_ANEXT LOAD_CONST YIELD_FROM store POP_BLOCK JUMP_FORWARD COME_FROM_EXCEPT DUP_TOP LOAD_GLOBAL COMPARE_OP POP_JUMP_IF_FALSE POP_TOP POP_TOP POP_TOP POP_EXCEPT POP_BLOCK JUMP_ABSOLUTE END_FINALLY COME_FROM for_block POP_BLOCK COME_FROM_LOOP
async_for_stmt ::= setup_loop . expr GET_AITER SETUP_EXCEPT GET_ANEXT LOAD_CONST YIELD_FROM store POP_BLOCK JUMP_FORWARD COME_FROM_EXCEPT DUP_TOP LOAD_GLOBAL COMPARE_OP POP_JUMP_IF_TRUE END_FINALLY COME_FROM for_block COME_FROM POP_TOP POP_TOP POP_TOP POP_EXCEPT POP_TOP POP_BLOCK COME_FROM_LOOP
async_for_stmt ::= setup_loop expr . GET_AITER LOAD_CONST YIELD_FROM SETUP_EXCEPT GET_ANEXT LOAD_CONST YIELD_FROM store POP_BLOCK JUMP_FORWARD COME_FROM_EXCEPT DUP_TOP LOAD_GLOBAL COMPARE_OP POP_JUMP_IF_FALSE POP_TOP POP_TOP POP_TOP POP_EXCEPT POP_BLOCK JUMP_ABSOLUTE END_FINALLY COME_FROM for_block POP_BLOCK COME_FROM_LOOP
async_for_stmt ::= setup_loop expr . GET_AITER SETUP_EXCEPT GET_ANEXT LOAD_CONST YIELD_FROM store POP_BLOCK JUMP_FORWARD COME_FROM_EXCEPT DUP_TOP LOAD_GLOBAL COMPARE_OP POP_JUMP_IF_TRUE END_FINALLY COME_FROM for_block COME_FROM POP_TOP POP_TOP POP_TOP POP_EXCEPT POP_TOP POP_BLOCK COME_FROM_LOOP
async_for_stmt37 ::= setup_loop . expr GET_AITER \e__come_froms SETUP_EXCEPT GET_ANEXT LOAD_CONST YIELD_FROM store POP_BLOCK JUMP_BACK COME_FROM_EXCEPT DUP_TOP LOAD_GLOBAL COMPARE_OP POP_JUMP_IF_TRUE END_FINALLY for_block COME_FROM POP_TOP POP_TOP POP_TOP POP_EXCEPT POP_TOP POP_BLOCK COME_FROM_LOOP
async_for_stmt37 ::= setup_loop . expr GET_AITER _come_froms SETUP_EXCEPT GET_ANEXT LOAD_CONST YIELD_FROM store POP_BLOCK JUMP_BACK COME_FROM_EXCEPT DUP_TOP LOAD_GLOBAL COMPARE_OP POP_JUMP_IF_TRUE END_FINALLY for_block COME_FROM POP_TOP POP_TOP POP_TOP POP_EXCEPT POP_TOP POP_BLOCK COME_FROM_LOOP
async_for_stmt37 ::= setup_loop expr . GET_AITER \e__come_froms SETUP_EXCEPT GET_ANEXT LOAD_CONST YIELD_FROM store POP_BLOCK JUMP_BACK COME_FROM_EXCEPT DUP_TOP LOAD_GLOBAL COMPARE_OP POP_JUMP_IF_TRUE END_FINALLY for_block COME_FROM POP_TOP POP_TOP POP_TOP POP_EXCEPT POP_TOP POP_BLOCK COME_FROM_LOOP
async_for_stmt37 ::= setup_loop expr . GET_AITER _come_froms SETUP_EXCEPT GET_ANEXT LOAD_CONST YIELD_FROM store POP_BLOCK JUMP_BACK COME_FROM_EXCEPT DUP_TOP LOAD_GLOBAL COMPARE_OP POP_JUMP_IF_TRUE END_FINALLY for_block COME_FROM POP_TOP POP_TOP POP_TOP POP_EXCEPT POP_TOP POP_BLOCK COME_FROM_LOOP
async_forelse_stmt ::= setup_loop . expr GET_AITER \e__come_froms SETUP_EXCEPT GET_ANEXT LOAD_CONST YIELD_FROM store POP_BLOCK JUMP_FORWARD COME_FROM_EXCEPT DUP_TOP LOAD_GLOBAL COMPARE_OP POP_JUMP_IF_TRUE END_FINALLY COME_FROM for_block COME_FROM POP_TOP POP_TOP POP_TOP POP_EXCEPT POP_TOP POP_BLOCK else_suite COME_FROM_LOOP
async_forelse_stmt ::= setup_loop . expr GET_AITER _come_froms SETUP_EXCEPT GET_ANEXT LOAD_CONST YIELD_FROM store POP_BLOCK JUMP_FORWARD COME_FROM_EXCEPT DUP_TOP LOAD_GLOBAL COMPARE_OP POP_JUMP_IF_TRUE END_FINALLY COME_FROM for_block COME_FROM POP_TOP POP_TOP POP_TOP POP_EXCEPT POP_TOP POP_BLOCK else_suite COME_FROM_LOOP
async_forelse_stmt ::= setup_loop expr . GET_AITER \e__come_froms SETUP_EXCEPT GET_ANEXT LOAD_CONST YIELD_FROM store POP_BLOCK JUMP_FORWARD COME_FROM_EXCEPT DUP_TOP LOAD_GLOBAL COMPARE_OP POP_JUMP_IF_TRUE END_FINALLY COME_FROM for_block COME_FROM POP_TOP POP_TOP POP_TOP POP_EXCEPT POP_TOP POP_BLOCK else_suite COME_FROM_LOOP
async_forelse_stmt ::= setup_loop expr . GET_AITER _come_froms SETUP_EXCEPT GET_ANEXT LOAD_CONST YIELD_FROM store POP_BLOCK JUMP_FORWARD COME_FROM_EXCEPT DUP_TOP LOAD_GLOBAL COMPARE_OP POP_JUMP_IF_TRUE END_FINALLY COME_FROM for_block COME_FROM POP_TOP POP_TOP POP_TOP POP_EXCEPT POP_TOP POP_BLOCK else_suite COME_FROM_LOOP
attribute ::= expr . LOAD_ATTR
attribute ::= expr LOAD_ATTR . 
attribute37 ::= expr . LOAD_METHOD
attribute37 ::= expr LOAD_METHOD . 
aug_assign1 ::= expr . expr inplace_op ROT_THREE STORE_SUBSCR
aug_assign1 ::= expr . expr inplace_op store
aug_assign1 ::= expr expr . inplace_op ROT_THREE STORE_SUBSCR
aug_assign1 ::= expr expr . inplace_op store
aug_assign2 ::= expr . DUP_TOP LOAD_ATTR expr inplace_op ROT_TWO STORE_ATTR
await_expr ::= expr . GET_AWAITABLE LOAD_CONST YIELD_FROM
bin_op ::= expr . expr binary_operator
bin_op ::= expr expr . binary_operator
break ::= BREAK_LOOP . 
c_stmts ::= _stmts . 
c_stmts ::= _stmts . lastc_stmt
c_stmts ::= lastc_stmt . 
c_stmts_opt ::= c_stmts . 
call ::= expr . CALL_FUNCTION_0
call ::= expr . CALL_METHOD_0
call ::= expr . expr CALL_METHOD_1
call ::= expr . expr expr expr CALL_METHOD_3
call ::= expr . pos_arg CALL_FUNCTION_1
call ::= expr . pos_arg pos_arg CALL_FUNCTION_2
call ::= expr . pos_arg pos_arg pos_arg CALL_FUNCTION_3
call ::= expr CALL_METHOD_0 . 
call ::= expr expr . CALL_METHOD_1
call ::= expr expr . expr expr CALL_METHOD_3
call ::= expr expr CALL_METHOD_1 . 
call ::= expr expr expr . expr CALL_METHOD_3
call ::= expr expr expr expr . CALL_METHOD_3
call ::= expr expr expr expr CALL_METHOD_3 . 
call ::= expr pos_arg . CALL_FUNCTION_1
call ::= expr pos_arg . pos_arg CALL_FUNCTION_2
call ::= expr pos_arg . pos_arg pos_arg CALL_FUNCTION_3
call ::= expr pos_arg CALL_FUNCTION_1 . 
call ::= expr pos_arg pos_arg . CALL_FUNCTION_2
call ::= expr pos_arg pos_arg . pos_arg CALL_FUNCTION_3
call ::= expr pos_arg pos_arg pos_arg . CALL_FUNCTION_3
call_kw36 ::= expr . expr LOAD_CONST CALL_FUNCTION_KW_1
call_kw36 ::= expr . expr expr LOAD_CONST CALL_FUNCTION_KW_2
call_kw36 ::= expr . expr expr expr LOAD_CONST CALL_FUNCTION_KW_3
call_kw36 ::= expr expr . LOAD_CONST CALL_FUNCTION_KW_1
call_kw36 ::= expr expr . expr LOAD_CONST CALL_FUNCTION_KW_2
call_kw36 ::= expr expr . expr expr LOAD_CONST CALL_FUNCTION_KW_3
call_kw36 ::= expr expr expr . LOAD_CONST CALL_FUNCTION_KW_2
call_kw36 ::= expr expr expr . expr LOAD_CONST CALL_FUNCTION_KW_3
call_kw36 ::= expr expr expr expr . LOAD_CONST CALL_FUNCTION_KW_3
call_stmt ::= expr . POP_TOP
call_stmt ::= expr POP_TOP . 
classdefdeco1 ::= expr . classdefdeco1 CALL_FUNCTION_1
classdefdeco1 ::= expr . classdefdeco2 CALL_FUNCTION_1
come_from_loops ::= \e_come_from_loops . COME_FROM_LOOP
come_from_loops ::= \e_come_from_loops COME_FROM_LOOP . 
come_from_loops ::= come_from_loops . COME_FROM_LOOP
come_froms ::= COME_FROM . 
come_froms ::= come_froms . COME_FROM
come_froms ::= come_froms COME_FROM . 
compare ::= compare_single . 
compare_chained ::= expr . compare_chained1 ROT_TWO POP_TOP \e__come_froms
compare_chained ::= expr . compare_chained1 ROT_TWO POP_TOP _come_froms
compare_chained1 ::= expr . DUP_TOP ROT_THREE COMPARE_OP JUMP_IF_FALSE_OR_POP compare_chained1 COME_FROM
compare_chained1 ::= expr . DUP_TOP ROT_THREE COMPARE_OP JUMP_IF_FALSE_OR_POP compare_chained2 COME_FROM
compare_chained1_false_37 ::= expr . DUP_TOP ROT_THREE COMPARE_OP POP_JUMP_IF_FALSE compare_chained2b_false_37 POP_TOP _jump COME_FROM
compare_chained1_false_37 ::= expr . DUP_TOP ROT_THREE COMPARE_OP POP_JUMP_IF_FALSE compare_chained2c_37 POP_TOP JUMP_FORWARD COME_FROM
compare_chained1a_37 ::= expr . DUP_TOP ROT_THREE COMPARE_OP POP_JUMP_IF_FALSE
compare_chained1a_37 ::= expr . DUP_TOP ROT_THREE COMPARE_OP POP_JUMP_IF_FALSE compare_chained2a_37 COME_FROM POP_TOP COME_FROM
compare_chained1b_false_37 ::= expr . DUP_TOP ROT_THREE COMPARE_OP POP_JUMP_IF_FALSE compare_chained2b_false_37 POP_TOP _jump COME_FROM
compare_chained1c_37 ::= expr . DUP_TOP ROT_THREE COMPARE_OP POP_JUMP_IF_FALSE compare_chained2a_37 POP_TOP
compare_chained2_false_37 ::= expr . DUP_TOP ROT_THREE COMPARE_OP POP_JUMP_IF_FALSE compare_chained2a_false_37 POP_TOP JUMP_BACK COME_FROM
compare_chained37 ::= expr . compare_chained1a_37
compare_chained37 ::= expr . compare_chained1c_37
compare_chained37_false ::= expr . compare_chained1_false_37
compare_chained37_false ::= expr . compare_chained1b_false_37
compare_chained37_false ::= expr . compare_chained2_false_37
compare_single ::= expr . expr COMPARE_OP
compare_single ::= expr expr . COMPARE_OP
compare_single ::= expr expr COMPARE_OP . 
continues ::= _stmts . lastl_stmt continue
continues ::= lastl_stmt . continue
dict ::= expr . expr LOAD_CONST BUILD_CONST_KEY_MAP_2
dict ::= expr . expr expr LOAD_CONST BUILD_CONST_KEY_MAP_3
dict ::= expr . expr expr expr expr LOAD_CONST BUILD_CONST_KEY_MAP_5
dict ::= expr . expr expr expr expr expr expr expr expr expr expr LOAD_CONST BUILD_CONST_KEY_MAP_11
dict ::= expr expr . LOAD_CONST BUILD_CONST_KEY_MAP_2
dict ::= expr expr . expr LOAD_CONST BUILD_CONST_KEY_MAP_3
dict ::= expr expr . expr expr expr LOAD_CONST BUILD_CONST_KEY_MAP_5
dict ::= expr expr . expr expr expr expr expr expr expr expr expr LOAD_CONST BUILD_CONST_KEY_MAP_11
dict ::= expr expr expr . LOAD_CONST BUILD_CONST_KEY_MAP_3
dict ::= expr expr expr . expr expr LOAD_CONST BUILD_CONST_KEY_MAP_5
dict ::= expr expr expr . expr expr expr expr expr expr expr expr LOAD_CONST BUILD_CONST_KEY_MAP_11
dict ::= expr expr expr expr . expr LOAD_CONST BUILD_CONST_KEY_MAP_5
dict ::= expr expr expr expr . expr expr expr expr expr expr expr LOAD_CONST BUILD_CONST_KEY_MAP_11
dict ::= kvlist_1 . 
else_suite ::= suite_stmts . 
else_suitel ::= l_stmts . 
expr ::= LOAD_FAST . 
expr ::= LOAD_GLOBAL . 
expr ::= LOAD_STR . 
expr ::= and . 
expr ::= attribute . 
expr ::= attribute37 . 
expr ::= call . 
expr ::= compare . 
expr ::= dict . 
expr ::= get_iter . 
expr ::= if_exp . 
expr ::= list . 
expr ::= listcomp . 
expr ::= subscript . 
expr_jit ::= expr . JUMP_IF_TRUE
expr_jitop ::= expr . JUMP_IF_TRUE_OR_POP
expr_jt ::= expr . jmp_true
expr_pjit ::= expr . POP_JUMP_IF_TRUE
expr_pjit_come_from ::= expr . POP_JUMP_IF_TRUE COME_FROM
expr_stmt ::= expr . POP_TOP
expr_stmt ::= expr POP_TOP . 
for ::= setup_loop . expr get_for_iter store for_block POP_BLOCK
for ::= setup_loop . expr get_for_iter store for_block POP_BLOCK COME_FROM_LOOP
for ::= setup_loop . expr get_for_iter store for_block POP_BLOCK NOP COME_FROM_LOOP
for ::= setup_loop expr . get_for_iter store for_block POP_BLOCK
for ::= setup_loop expr . get_for_iter store for_block POP_BLOCK COME_FROM_LOOP
for ::= setup_loop expr . get_for_iter store for_block POP_BLOCK NOP COME_FROM_LOOP
for ::= setup_loop expr get_for_iter . store for_block POP_BLOCK
for ::= setup_loop expr get_for_iter . store for_block POP_BLOCK COME_FROM_LOOP
for ::= setup_loop expr get_for_iter . store for_block POP_BLOCK NOP COME_FROM_LOOP
for ::= setup_loop expr get_for_iter store . for_block POP_BLOCK
for ::= setup_loop expr get_for_iter store . for_block POP_BLOCK COME_FROM_LOOP
for ::= setup_loop expr get_for_iter store . for_block POP_BLOCK NOP COME_FROM_LOOP
for ::= setup_loop expr get_for_iter store for_block . POP_BLOCK
for ::= setup_loop expr get_for_iter store for_block . POP_BLOCK COME_FROM_LOOP
for ::= setup_loop expr get_for_iter store for_block . POP_BLOCK NOP COME_FROM_LOOP
for ::= setup_loop expr get_for_iter store for_block POP_BLOCK . 
for ::= setup_loop expr get_for_iter store for_block POP_BLOCK . COME_FROM_LOOP
for ::= setup_loop expr get_for_iter store for_block POP_BLOCK . NOP COME_FROM_LOOP
for ::= setup_loop expr get_for_iter store for_block POP_BLOCK COME_FROM_LOOP . 
for_block ::= \e_l_stmts_opt . COME_FROM_LOOP JUMP_BACK
for_block ::= \e_l_stmts_opt . _come_froms JUMP_BACK
for_block ::= \e_l_stmts_opt . come_from_loops JUMP_BACK
for_block ::= \e_l_stmts_opt \e__come_froms . JUMP_BACK
for_block ::= \e_l_stmts_opt \e_come_from_loops . JUMP_BACK
for_block ::= l_stmts . 
for_block ::= l_stmts . JUMP_BACK
for_block ::= l_stmts JUMP_BACK . 
for_block ::= l_stmts_opt . COME_FROM_LOOP JUMP_BACK
for_block ::= l_stmts_opt . _come_froms JUMP_BACK
for_block ::= l_stmts_opt . come_from_loops JUMP_BACK
for_block ::= l_stmts_opt COME_FROM_LOOP . JUMP_BACK
for_block ::= l_stmts_opt \e__come_froms . JUMP_BACK
for_block ::= l_stmts_opt \e__come_froms JUMP_BACK . 
for_block ::= l_stmts_opt \e_come_from_loops . JUMP_BACK
for_block ::= l_stmts_opt \e_come_from_loops JUMP_BACK . 
for_block ::= l_stmts_opt _come_froms . JUMP_BACK
for_block ::= l_stmts_opt _come_froms JUMP_BACK . 
for_block ::= l_stmts_opt come_from_loops . JUMP_BACK
forelsestmt ::= SETUP_LOOP . expr get_for_iter store for_block POP_BLOCK else_suite \e__come_froms
forelsestmt ::= SETUP_LOOP . expr get_for_iter store for_block POP_BLOCK else_suite _come_froms
forelsestmt ::= SETUP_LOOP expr . get_for_iter store for_block POP_BLOCK else_suite \e__come_froms
forelsestmt ::= SETUP_LOOP expr . get_for_iter store for_block POP_BLOCK else_suite _come_froms
forelsestmt ::= SETUP_LOOP expr get_for_iter . store for_block POP_BLOCK else_suite \e__come_froms
forelsestmt ::= SETUP_LOOP expr get_for_iter . store for_block POP_BLOCK else_suite _come_froms
forelsestmt ::= SETUP_LOOP expr get_for_iter store . for_block POP_BLOCK else_suite \e__come_froms
forelsestmt ::= SETUP_LOOP expr get_for_iter store . for_block POP_BLOCK else_suite _come_froms
forelsestmt ::= SETUP_LOOP expr get_for_iter store for_block . POP_BLOCK else_suite \e__come_froms
forelsestmt ::= SETUP_LOOP expr get_for_iter store for_block . POP_BLOCK else_suite _come_froms
forelsestmt ::= SETUP_LOOP expr get_for_iter store for_block POP_BLOCK . else_suite \e__come_froms
forelsestmt ::= SETUP_LOOP expr get_for_iter store for_block POP_BLOCK . else_suite _come_froms
forelsestmt ::= SETUP_LOOP expr get_for_iter store for_block POP_BLOCK else_suite . _come_froms
forelsestmt ::= SETUP_LOOP expr get_for_iter store for_block POP_BLOCK else_suite \e__come_froms . 
forelsestmt ::= SETUP_LOOP expr get_for_iter store for_block POP_BLOCK else_suite _come_froms . 
forelsestmt ::= setup_loop . expr get_for_iter store for_block POP_BLOCK else_suite COME_FROM_LOOP
forelsestmt ::= setup_loop expr . get_for_iter store for_block POP_BLOCK else_suite COME_FROM_LOOP
forelsestmt ::= setup_loop expr get_for_iter . store for_block POP_BLOCK else_suite COME_FROM_LOOP
forelsestmt ::= setup_loop expr get_for_iter store . for_block POP_BLOCK else_suite COME_FROM_LOOP
forelsestmt ::= setup_loop expr get_for_iter store for_block . POP_BLOCK else_suite COME_FROM_LOOP
forelsestmt ::= setup_loop expr get_for_iter store for_block POP_BLOCK . else_suite COME_FROM_LOOP
forelsestmt ::= setup_loop expr get_for_iter store for_block POP_BLOCK else_suite . COME_FROM_LOOP
forelsestmt ::= setup_loop expr get_for_iter store for_block POP_BLOCK else_suite COME_FROM_LOOP . 
generator_exp ::= load_closure . load_genexpr LOAD_STR MAKE_FUNCTION_0 expr GET_ITER CALL_FUNCTION_1
generator_exp ::= load_closure . load_genexpr LOAD_STR MAKE_FUNCTION_8 expr GET_ITER CALL_FUNCTION_1
get_for_iter ::= GET_ITER . _come_froms FOR_ITER
get_for_iter ::= GET_ITER \e__come_froms . FOR_ITER
get_for_iter ::= GET_ITER \e__come_froms FOR_ITER . 
get_for_iter ::= GET_ITER _come_froms . FOR_ITER
get_for_iter ::= GET_ITER _come_froms FOR_ITER . 
get_iter ::= expr . GET_ITER
get_iter ::= expr GET_ITER . 
if_exp ::= expr . jmp_false expr jf_cf expr COME_FROM
if_exp ::= expr . jmp_false expr jump_absolute_else expr
if_exp ::= expr jmp_false . expr jf_cf expr COME_FROM
if_exp ::= expr jmp_false . expr jump_absolute_else expr
if_exp ::= expr jmp_false expr . jf_cf expr COME_FROM
if_exp ::= expr jmp_false expr . jump_absolute_else expr
if_exp ::= expr jmp_false expr jf_cf . expr COME_FROM
if_exp ::= expr jmp_false expr jf_cf expr . COME_FROM
if_exp ::= expr jmp_false expr jf_cf expr COME_FROM . 
if_exp37 ::= expr . expr jf_cfs expr COME_FROM
if_exp37 ::= expr expr . jf_cfs expr COME_FROM
if_exp_37b ::= expr . jmp_false expr POP_JUMP_IF_FALSE jump_forward_else expr
if_exp_37b ::= expr jmp_false . expr POP_JUMP_IF_FALSE jump_forward_else expr
if_exp_37b ::= expr jmp_false expr . POP_JUMP_IF_FALSE jump_forward_else expr
if_exp_37b ::= expr jmp_false expr POP_JUMP_IF_FALSE . jump_forward_else expr
if_exp_lambda ::= expr . jmp_false expr return_if_lambda return_stmt_lambda LAMBDA_MARKER
if_exp_lambda ::= expr jmp_false . expr return_if_lambda return_stmt_lambda LAMBDA_MARKER
if_exp_lambda ::= expr jmp_false expr . return_if_lambda return_stmt_lambda LAMBDA_MARKER
if_exp_not ::= expr . jmp_true expr jump_forward_else expr COME_FROM
if_exp_not_lambda ::= expr . jmp_true expr return_if_lambda return_stmt_lambda LAMBDA_MARKER
if_exp_true ::= expr . JUMP_FORWARD expr COME_FROM
if_exp_true ::= expr JUMP_FORWARD . expr COME_FROM
ifelsestmt ::= testexpr . c_stmts come_froms else_suite come_froms
ifelsestmt ::= testexpr . c_stmts_opt JUMP_FORWARD else_suite \e__come_froms
ifelsestmt ::= testexpr . c_stmts_opt JUMP_FORWARD else_suite \e_opt_come_from_except
ifelsestmt ::= testexpr . c_stmts_opt JUMP_FORWARD else_suite _come_froms
ifelsestmt ::= testexpr . c_stmts_opt JUMP_FORWARD else_suite opt_come_from_except
ifelsestmt ::= testexpr . c_stmts_opt jf_cfs else_suite \e_opt_come_from_except
ifelsestmt ::= testexpr . c_stmts_opt jf_cfs else_suite opt_come_from_except
ifelsestmt ::= testexpr . c_stmts_opt jump_forward_else else_suite \e__come_froms
ifelsestmt ::= testexpr . c_stmts_opt jump_forward_else else_suite _come_froms
ifelsestmt ::= testexpr . stmts jf_cfs \e_else_suite_opt \e_opt_come_from_except
ifelsestmt ::= testexpr . stmts jf_cfs \e_else_suite_opt opt_come_from_except
ifelsestmt ::= testexpr . stmts jf_cfs else_suite_opt \e_opt_come_from_except
ifelsestmt ::= testexpr . stmts jf_cfs else_suite_opt opt_come_from_except
ifelsestmt ::= testexpr \e_c_stmts_opt . JUMP_FORWARD else_suite \e__come_froms
ifelsestmt ::= testexpr \e_c_stmts_opt . JUMP_FORWARD else_suite \e_opt_come_from_except
ifelsestmt ::= testexpr \e_c_stmts_opt . JUMP_FORWARD else_suite _come_froms
ifelsestmt ::= testexpr \e_c_stmts_opt . JUMP_FORWARD else_suite opt_come_from_except
ifelsestmt ::= testexpr \e_c_stmts_opt . jf_cfs else_suite \e_opt_come_from_except
ifelsestmt ::= testexpr \e_c_stmts_opt . jf_cfs else_suite opt_come_from_except
ifelsestmt ::= testexpr \e_c_stmts_opt . jump_forward_else else_suite \e__come_froms
ifelsestmt ::= testexpr \e_c_stmts_opt . jump_forward_else else_suite _come_froms
ifelsestmt ::= testexpr c_stmts . come_froms else_suite come_froms
ifelsestmt ::= testexpr c_stmts_opt . JUMP_FORWARD else_suite \e__come_froms
ifelsestmt ::= testexpr c_stmts_opt . JUMP_FORWARD else_suite \e_opt_come_from_except
ifelsestmt ::= testexpr c_stmts_opt . JUMP_FORWARD else_suite _come_froms
ifelsestmt ::= testexpr c_stmts_opt . JUMP_FORWARD else_suite opt_come_from_except
ifelsestmt ::= testexpr c_stmts_opt . jf_cfs else_suite \e_opt_come_from_except
ifelsestmt ::= testexpr c_stmts_opt . jf_cfs else_suite opt_come_from_except
ifelsestmt ::= testexpr c_stmts_opt . jump_forward_else else_suite \e__come_froms
ifelsestmt ::= testexpr c_stmts_opt . jump_forward_else else_suite _come_froms
ifelsestmt ::= testexpr stmts . jf_cfs \e_else_suite_opt \e_opt_come_from_except
ifelsestmt ::= testexpr stmts . jf_cfs \e_else_suite_opt opt_come_from_except
ifelsestmt ::= testexpr stmts . jf_cfs else_suite_opt \e_opt_come_from_except
ifelsestmt ::= testexpr stmts . jf_cfs else_suite_opt opt_come_from_except
ifelsestmtc ::= testexpr . c_stmts_opt JUMP_ABSOLUTE else_suitec
ifelsestmtc ::= testexpr . c_stmts_opt JUMP_FORWARD else_suitec
ifelsestmtc ::= testexpr . c_stmts_opt jump_absolute_else else_suitec
ifelsestmtc ::= testexpr \e_c_stmts_opt . JUMP_ABSOLUTE else_suitec
ifelsestmtc ::= testexpr \e_c_stmts_opt . JUMP_FORWARD else_suitec
ifelsestmtc ::= testexpr \e_c_stmts_opt . jump_absolute_else else_suitec
ifelsestmtc ::= testexpr c_stmts_opt . JUMP_ABSOLUTE else_suitec
ifelsestmtc ::= testexpr c_stmts_opt . JUMP_FORWARD else_suitec
ifelsestmtc ::= testexpr c_stmts_opt . jump_absolute_else else_suitec
ifelsestmtc ::= testexpr c_stmts_opt jump_absolute_else . else_suitec
ifelsestmtl ::= testexpr . c_stmts_opt cf_jf_else else_suitel
ifelsestmtl ::= testexpr . c_stmts_opt cf_jump_back else_suitel
ifelsestmtl ::= testexpr . c_stmts_opt jb_cfs else_suitel
ifelsestmtl ::= testexpr . c_stmts_opt jb_else else_suitel
ifelsestmtl ::= testexpr . c_stmts_opt jump_forward_else else_suitec
ifelsestmtl ::= testexpr \e_c_stmts_opt . cf_jf_else else_suitel
ifelsestmtl ::= testexpr \e_c_stmts_opt . cf_jump_back else_suitel
ifelsestmtl ::= testexpr \e_c_stmts_opt . jb_cfs else_suitel
ifelsestmtl ::= testexpr \e_c_stmts_opt . jb_else else_suitel
ifelsestmtl ::= testexpr \e_c_stmts_opt . jump_forward_else else_suitec
ifelsestmtl ::= testexpr c_stmts_opt . cf_jf_else else_suitel
ifelsestmtl ::= testexpr c_stmts_opt . cf_jump_back else_suitel
ifelsestmtl ::= testexpr c_stmts_opt . jb_cfs else_suitel
ifelsestmtl ::= testexpr c_stmts_opt . jb_else else_suitel
ifelsestmtl ::= testexpr c_stmts_opt . jump_forward_else else_suitec
ifelsestmtl ::= testexpr c_stmts_opt jb_cfs . else_suitel
ifelsestmtl ::= testexpr c_stmts_opt jb_cfs else_suitel . 
ifelsestmtl ::= testexpr c_stmts_opt jb_else . else_suitel
ifelsestmtr ::= testexpr . return_if_stmts returns
iflaststmt ::= testexpr . c_stmts
iflaststmt ::= testexpr . c_stmts JUMP_ABSOLUTE
iflaststmt ::= testexpr . c_stmts_opt JUMP_FORWARD
iflaststmt ::= testexpr \e_c_stmts_opt . JUMP_FORWARD
iflaststmt ::= testexpr c_stmts . 
iflaststmt ::= testexpr c_stmts . JUMP_ABSOLUTE
iflaststmt ::= testexpr c_stmts_opt . JUMP_FORWARD
iflaststmtl ::= testexpr . c_stmts
iflaststmtl ::= testexpr . c_stmts JUMP_BACK
iflaststmtl ::= testexpr . c_stmts JUMP_BACK COME_FROM_LOOP
iflaststmtl ::= testexpr . c_stmts JUMP_BACK POP_BLOCK
iflaststmtl ::= testexpr c_stmts . 
iflaststmtl ::= testexpr c_stmts . JUMP_BACK
iflaststmtl ::= testexpr c_stmts . JUMP_BACK COME_FROM_LOOP
iflaststmtl ::= testexpr c_stmts . JUMP_BACK POP_BLOCK
iflaststmtl ::= testexpr c_stmts JUMP_BACK . 
iflaststmtl ::= testexpr c_stmts JUMP_BACK . COME_FROM_LOOP
iflaststmtl ::= testexpr c_stmts JUMP_BACK . POP_BLOCK
iflaststmtl ::= testexpr c_stmts JUMP_BACK POP_BLOCK . 
ifstmt ::= testexpr . _ifstmts_jump
ifstmtl ::= testexpr . _ifstmts_jumpl
ifstmtl ::= testexpr _ifstmts_jumpl . 
jb_cfs ::= \e_come_from_opt . JUMP_BACK come_froms
jb_cfs ::= \e_come_from_opt JUMP_BACK . come_froms
jb_cfs ::= \e_come_from_opt JUMP_BACK come_froms . 
jb_else ::= JUMP_BACK . COME_FROM
jb_else ::= JUMP_BACK . ELSE
jb_else ::= JUMP_BACK COME_FROM . 
jf_cf ::= JUMP_FORWARD . COME_FROM
jf_cf ::= JUMP_FORWARD COME_FROM . 
jmp_false ::= POP_JUMP_IF_FALSE . 
jump_absolute_else ::= jb_else . 
kvlist_1 ::= expr . expr BUILD_MAP_1
kvlist_1 ::= expr expr . BUILD_MAP_1
kvlist_1 ::= expr expr BUILD_MAP_1 . 
l_stmts ::= _stmts . 
l_stmts ::= _stmts . lastl_stmt
l_stmts ::= l_stmts . lstmt
l_stmts ::= l_stmts lstmt . 
l_stmts ::= lastl_stmt . 
l_stmts ::= lastl_stmt . come_froms l_stmts
l_stmts ::= lastl_stmt come_froms . l_stmts
l_stmts ::= lastl_stmt come_froms l_stmts . 
l_stmts ::= lstmt . 
l_stmts_opt ::= l_stmts . 
lambda_body ::= expr . LOAD_LAMBDA LOAD_STR MAKE_FUNCTION_1
lambda_body ::= load_closure . LOAD_LAMBDA LOAD_STR MAKE_FUNCTION_8
lastc_stmt ::= iflaststmt . 
lastl_stmt ::= ifelsestmtl . 
lastl_stmt ::= iflaststmtl . 
list ::= expr . BUILD_LIST_1
list ::= expr BUILD_LIST_1 . 
listcomp ::= LOAD_LISTCOMP . LOAD_STR MAKE_FUNCTION_0 expr GET_ITER CALL_FUNCTION_1
listcomp ::= LOAD_LISTCOMP LOAD_STR . MAKE_FUNCTION_0 expr GET_ITER CALL_FUNCTION_1
listcomp ::= LOAD_LISTCOMP LOAD_STR MAKE_FUNCTION_0 . expr GET_ITER CALL_FUNCTION_1
listcomp ::= LOAD_LISTCOMP LOAD_STR MAKE_FUNCTION_0 expr . GET_ITER CALL_FUNCTION_1
listcomp ::= LOAD_LISTCOMP LOAD_STR MAKE_FUNCTION_0 expr GET_ITER . CALL_FUNCTION_1
listcomp ::= LOAD_LISTCOMP LOAD_STR MAKE_FUNCTION_0 expr GET_ITER CALL_FUNCTION_1 . 
listcomp ::= load_closure . LOAD_LISTCOMP LOAD_STR MAKE_FUNCTION_0 expr GET_ITER CALL_FUNCTION_1
load_closure ::= LOAD_CLOSURE . 
load_closure ::= LOAD_CLOSURE . BUILD_TUPLE_1
load_closure ::= LOAD_CLOSURE BUILD_TUPLE_1 . 
load_closure ::= load_closure . LOAD_CLOSURE
load_genexpr ::= BUILD_TUPLE_1 . LOAD_GENEXPR LOAD_STR
lstmt ::= stmt . 
mkfunc ::= expr . LOAD_CODE LOAD_STR MAKE_FUNCTION_1
mkfunc ::= load_closure . LOAD_CODE LOAD_STR MAKE_FUNCTION_8
mkfuncdeco ::= expr . mkfuncdeco CALL_FUNCTION_1
mkfuncdeco ::= expr . mkfuncdeco0 CALL_FUNCTION_1
or ::= and . jitop_come_from_expr COME_FROM
pos_arg ::= expr . 
ret_and ::= expr . JUMP_IF_FALSE_OR_POP return_expr_or_cond COME_FROM
ret_or ::= expr . JUMP_IF_TRUE_OR_POP return_expr_or_cond COME_FROM
return ::= return_expr . RETURN_END_IF
return ::= return_expr . RETURN_VALUE
return ::= return_expr . RETURN_VALUE COME_FROM
return_closure ::= LOAD_CLOSURE . DUP_TOP STORE_NAME RETURN_VALUE RETURN_LAST
return_closure ::= LOAD_CLOSURE . RETURN_VALUE RETURN_LAST
return_expr ::= expr . 
return_expr_lambda ::= return_expr . RETURN_VALUE_LAMBDA
return_expr_lambda ::= return_expr . RETURN_VALUE_LAMBDA LAMBDA_MARKER
return_if_stmt ::= return_expr . RETURN_END_IF
return_if_stmt ::= return_expr . RETURN_END_IF POP_BLOCK
return_if_stmts ::= _stmts . return_if_stmt \e__come_froms
return_if_stmts ::= _stmts . return_if_stmt _come_froms
returns ::= _stmts . return
returns ::= _stmts . return_if_stmt
setup_loop ::= SETUP_LOOP . _come_froms
setup_loop ::= SETUP_LOOP \e__come_froms . 
sstmt ::= sstmt . RETURN_LAST
sstmt ::= stmt . 
stmt ::= assign . 
stmt ::= break . 
stmt ::= call_stmt . 
stmt ::= expr_stmt . 
stmt ::= for . 
stmt ::= forelsestmt . 
stmt ::= ifstmtl . 
stmts ::= sstmt . 
stmts ::= stmts . sstmt
stmts ::= stmts sstmt . 
store ::= STORE_FAST . 
store ::= expr . STORE_ATTR
store ::= store_subscript . 
store ::= unpack . 
store_subscript ::= expr . expr STORE_SUBSCR
store_subscript ::= expr expr . STORE_SUBSCR
store_subscript ::= expr expr STORE_SUBSCR . 
subscript ::= expr . expr BINARY_SUBSCR
subscript ::= expr expr . BINARY_SUBSCR
subscript ::= expr expr BINARY_SUBSCR . 
subscript2 ::= expr . expr DUP_TOP_TWO BINARY_SUBSCR
subscript2 ::= expr expr . DUP_TOP_TWO BINARY_SUBSCR
suite_stmts ::= _stmts . 
testexpr ::= testfalse . 
testexpr_cf ::= testexpr . come_froms
testfalse ::= expr . jmp_false
testfalse ::= expr jmp_false . 
testfalse_not_and ::= and . jmp_true come_froms
testfalse_not_and ::= expr . jmp_false expr jmp_true COME_FROM
testfalse_not_and ::= expr jmp_false . expr jmp_true COME_FROM
testfalse_not_and ::= expr jmp_false expr . jmp_true COME_FROM
testfalse_not_or ::= expr . jmp_false expr jmp_false COME_FROM
testfalse_not_or ::= expr jmp_false . expr jmp_false COME_FROM
testfalse_not_or ::= expr jmp_false expr . jmp_false COME_FROM
testfalse_not_or ::= expr jmp_false expr jmp_false . COME_FROM
testfalsel ::= expr . jmp_true
testtrue ::= expr . jmp_true
unary_not ::= expr . UNARY_NOT
unary_op ::= expr . unary_operator
unpack ::= UNPACK_SEQUENCE_2 . store store
unpack ::= UNPACK_SEQUENCE_2 store . store
unpack ::= UNPACK_SEQUENCE_2 store store . 
while1elsestmt ::= setup_loop . l_stmts JUMP_BACK POP_BLOCK else_suite COME_FROM_LOOP
while1elsestmt ::= setup_loop . l_stmts JUMP_BACK \e__come_froms POP_BLOCK else_suitel COME_FROM_LOOP
while1elsestmt ::= setup_loop . l_stmts JUMP_BACK _come_froms POP_BLOCK else_suitel COME_FROM_LOOP
while1elsestmt ::= setup_loop . l_stmts JUMP_BACK else_suite COME_FROM_LOOP
while1elsestmt ::= setup_loop . l_stmts JUMP_BACK else_suitel
while1stmt ::= setup_loop . l_stmts COME_FROM JUMP_BACK COME_FROM_LOOP
while1stmt ::= setup_loop . l_stmts COME_FROM JUMP_BACK POP_BLOCK COME_FROM_LOOP
while1stmt ::= setup_loop . l_stmts COME_FROM_LOOP
while1stmt ::= setup_loop . l_stmts COME_FROM_LOOP JUMP_BACK POP_BLOCK COME_FROM_LOOP
while1stmt ::= setup_loop . l_stmts POP_BLOCK COME_FROM_LOOP
whileTruestmt ::= SETUP_LOOP . l_stmts_opt JUMP_BACK COME_FROM_LOOP
whileTruestmt ::= SETUP_LOOP \e_l_stmts_opt . JUMP_BACK COME_FROM_LOOP
whileTruestmt ::= setup_loop . l_stmts_opt JUMP_BACK POP_BLOCK \e__come_froms
whileTruestmt ::= setup_loop . l_stmts_opt JUMP_BACK POP_BLOCK _come_froms
whileTruestmt ::= setup_loop \e_l_stmts_opt . JUMP_BACK POP_BLOCK \e__come_froms
whileTruestmt ::= setup_loop \e_l_stmts_opt . JUMP_BACK POP_BLOCK _come_froms
whileelsestmt ::= setup_loop . testexpr \e_l_stmts_opt JUMP_BACK POP_BLOCK else_suitel COME_FROM
whileelsestmt ::= setup_loop . testexpr \e_l_stmts_opt JUMP_BACK POP_BLOCK else_suitel COME_FROM_LOOP
whileelsestmt ::= setup_loop . testexpr l_stmts_opt JUMP_BACK POP_BLOCK else_suitel COME_FROM
whileelsestmt ::= setup_loop . testexpr l_stmts_opt JUMP_BACK POP_BLOCK else_suitel COME_FROM_LOOP
whilestmt ::= setup_loop . testexpr \e_l_stmts_opt COME_FROM JUMP_BACK POP_BLOCK COME_FROM_LOOP
whilestmt ::= setup_loop . testexpr \e_l_stmts_opt JUMP_BACK POP_BLOCK COME_FROM_LOOP
whilestmt ::= setup_loop . testexpr \e_l_stmts_opt JUMP_BACK come_froms POP_BLOCK
whilestmt ::= setup_loop . testexpr \e_l_stmts_opt JUMP_BACK come_froms POP_BLOCK COME_FROM_LOOP
whilestmt ::= setup_loop . testexpr \e_l_stmts_opt come_froms JUMP_BACK come_froms POP_BLOCK COME_FROM_LOOP
whilestmt ::= setup_loop . testexpr l_stmts_opt COME_FROM JUMP_BACK POP_BLOCK COME_FROM_LOOP
whilestmt ::= setup_loop . testexpr l_stmts_opt JUMP_BACK POP_BLOCK COME_FROM_LOOP
whilestmt ::= setup_loop . testexpr l_stmts_opt JUMP_BACK come_froms POP_BLOCK
whilestmt ::= setup_loop . testexpr l_stmts_opt JUMP_BACK come_froms POP_BLOCK COME_FROM_LOOP
whilestmt ::= setup_loop . testexpr l_stmts_opt come_froms JUMP_BACK come_froms POP_BLOCK COME_FROM_LOOP
whilestmt ::= setup_loop . testexpr returns POP_BLOCK COME_FROM_LOOP
whilestmt ::= setup_loop . testexpr returns come_froms POP_BLOCK COME_FROM_LOOP
with ::= expr . SETUP_WITH POP_TOP \e_suite_stmts_opt COME_FROM_WITH WITH_CLEANUP_START WITH_CLEANUP_FINISH END_FINALLY
with ::= expr . SETUP_WITH POP_TOP \e_suite_stmts_opt COME_FROM_WITH with_suffix
with ::= expr . SETUP_WITH POP_TOP \e_suite_stmts_opt POP_BLOCK LOAD_CONST COME_FROM_WITH with_suffix
with ::= expr . SETUP_WITH POP_TOP \e_suite_stmts_opt POP_BLOCK LOAD_CONST WITH_CLEANUP_START WITH_CLEANUP_FINISH END_FINALLY
with ::= expr . SETUP_WITH POP_TOP \e_suite_stmts_opt POP_BLOCK LOAD_CONST with_suffix
with ::= expr . SETUP_WITH POP_TOP suite_stmts_opt COME_FROM_WITH WITH_CLEANUP_START WITH_CLEANUP_FINISH END_FINALLY
with ::= expr . SETUP_WITH POP_TOP suite_stmts_opt COME_FROM_WITH with_suffix
with ::= expr . SETUP_WITH POP_TOP suite_stmts_opt POP_BLOCK LOAD_CONST COME_FROM_WITH with_suffix
with ::= expr . SETUP_WITH POP_TOP suite_stmts_opt POP_BLOCK LOAD_CONST WITH_CLEANUP_START WITH_CLEANUP_FINISH END_FINALLY
with ::= expr . SETUP_WITH POP_TOP suite_stmts_opt POP_BLOCK LOAD_CONST with_suffix
withasstmt ::= expr . SETUP_WITH store \e_suite_stmts_opt COME_FROM_WITH WITH_CLEANUP_START WITH_CLEANUP_FINISH END_FINALLY
withasstmt ::= expr . SETUP_WITH store \e_suite_stmts_opt COME_FROM_WITH with_suffix
withasstmt ::= expr . SETUP_WITH store \e_suite_stmts_opt POP_BLOCK LOAD_CONST COME_FROM_WITH with_suffix
withasstmt ::= expr . SETUP_WITH store suite_stmts_opt COME_FROM_WITH WITH_CLEANUP_START WITH_CLEANUP_FINISH END_FINALLY
withasstmt ::= expr . SETUP_WITH store suite_stmts_opt COME_FROM_WITH with_suffix
withasstmt ::= expr . SETUP_WITH store suite_stmts_opt POP_BLOCK LOAD_CONST COME_FROM_WITH with_suffix
yield ::= expr . YIELD_VALUE
yield_from ::= expr . GET_YIELD_FROM_ITER LOAD_CONST YIELD_FROM
Instruction context:
   
 L. 123       252  LOAD_CLOSURE             'active_instances'
                 254  BUILD_TUPLE_1         1 
->               256  LOAD_DICTCOMP            '<code_object <dictcomp>>'
                 258  LOAD_STR                 'populate_violators.<locals>.<dictcomp>'
                 260  MAKE_FUNCTION_8          'closure'
                 262  LOAD_GLOBAL              privacy_instance_to_violators
                 264  LOAD_METHOD              items
                 266  CALL_METHOD_0         0  '0 positional arguments'
                 268  GET_ITER         
                 270  CALL_FUNCTION_1       1  '1 positional argument'
import services, gsi_handlers, weakref, sims4
from timeit import itertools
from routing import FootprintType
from gsi_handlers.gsi_utils import parse_filter_to_list
from sims4.gsi.dispatcher import GsiHandler
from sims4.gsi.schema import GsiGridSchema
ACTIVE_FILTER = 'Is Active'
HAS_VIOLATORS_FILTER = 'Has Current Violators'
NO_VIOLATORS_STR = 'No Current Violators'
privacy_management_schema = GsiGridSchema(label='Privacy Management')
privacy_management_schema.add_field('is_active', label='Is Active', width=0.02)
privacy_management_schema.add_field('privacy_interaction', label='Privacy Interaction', width=0.05)
privacy_management_schema.add_field('sim_violators', label='Current Sim Violators', width=0.05)
privacy_management_schema.add_field('vehicle_violators', label='Current Vehicle Violators', width=0.05)
privacy_management_schema.add_field('late_violators', label='Late Privacy Violators', width=0.05)
privacy_management_schema.add_field('all_past_violators', label='All Past Instance Violators', width=0.055)
privacy_management_schema.add_field('privacy_violators', label='Privacy Violators', width=0.05)
privacy_management_schema.add_field('central_object', label='Central Object', width=0.05)
privacy_management_schema.add_field('has_shooed', label='Has Shooed', width=0.03)
privacy_management_schema.add_field('max_los', label='Max Line of Sight Radius', width=0.05)
privacy_management_schema.add_field('shoo_cons', label='Shoo Constraint Radius', width=0.05)
privacy_management_schema.add_field('privacy_discouragement_cost', label='Privacy Discouragement Cost', width=0.055)
with privacy_management_schema.add_has_many('privacy_constraints', GsiGridSchema, label='Constraints') as (sub_schema):
    sub_schema.add_field('cost', label='Cost')
    sub_schema.add_field('enabled', label='Enabled')
    sub_schema.add_field('footprint_id', label='Footprint Id')
    sub_schema.add_field('footprint_type', label='Footprint Type')
    sub_schema.add_field('polygon', label='Polygon')
with privacy_management_schema.add_has_many('affordances', GsiGridSchema, label='Affordances') as (sub_schema):
    sub_schema.add_field('embarrassed_affordance', label='Embarrassed Affordance')
    sub_schema.add_field('post_route_affordance', label='Post Route Affordance')
with privacy_management_schema.add_has_many('allowed', GsiGridSchema, label='Allowed/Exempt Sims') as (sub_schema):
    sub_schema.add_field('allowed_sims', label='Allowed Sims')
    sub_schema.add_field('disallowed_sims', label='Disallowed Sims')
    sub_schema.add_field('exempt_sims', label='Sims Exempt From Shooing')
privacy_management_schema.add_filter(ACTIVE_FILTER)
privacy_management_schema.add_filter(HAS_VIOLATORS_FILTER)
with sims4.reload.protected(globals()):
    privacy_instance_to_violators = weakref.WeakKeyDictionary()

@GsiHandler('privacy_management', privacy_management_schema)
def generate_privacy_management_data(filter=None):
    privacy_management_data = []
    active_instances = []
    filter_list = parse_filter_to_list(filter)
    privacy_service = services.privacy_service()
    if privacy_service is None:
        return privacy_management_data
    for instance in privacy_service._privacy_instances:
        if instance.is_active:
            active_instances.append(instance)
        if not filter_list is None:
            if ACTIVE_FILTER not in filter_list:
                if instance.is_active:
                    continue
            if filter_list is not None:
                if HAS_VIOLATORS_FILTER in filter_list:
                    if not instance.find_violating_vehicles():
                        if not instance.find_violating_sims():
                            if not instance._late_violators:
                                continue
            entry = {'is_active':str(instance.is_active), 
             'max_los':str(instance._max_line_of_sight_radius), 
             'has_shooed':str(instance.has_shooed), 
             'privacy_violators':str(instance.privacy_violators), 
             'privacy_discouragement_cost':str(instance.privacy_discouragement_cost), 
             'privacy_interaction':str(instance._interaction), 
             'central_object':str(instance.central_object), 
             'shoo_cons':str(instance._shoo_constraint_radius or instance._SHOO_CONSTRAINT_RADIUS), 
             'affordances':{'embarrassed_affordance':str(instance._embarrassed_affordance or instance._EMBARRASSED_AFFORDANCE), 
              'post_route_affordance':str(instance._post_route_affordance)}, 
             'allowed':{'allowed_sims':gsi_handlers.gsi_utils.format_object_list_names(instance._allowed_sims) if instance._allowed_sims else 'None', 
              'disallowed_sims':gsi_handlers.gsi_utils.format_object_list_names(instance._disallowed_sims) if instance._disallowed_sims else 'None', 
              'exempt_sims':gsi_handlers.gsi_utils.format_object_list_names(instance._exempt_sims) if instance._exempt_sims else 'None'}, 
             'privacy_constraints':[]}
            populate_violators(entry, instance, active_instances)
            for constraint in instance._privacy_constraints:
                constraint_type = next((constraint_type for constraint_type, value in vars(FootprintType).items() if value == constraint.footprint_type))
                entry['privacy_constraints'].append({'cost':str(constraint.cost),  'enabled':str(constraint.enabled), 
                 'footprint_id':str(constraint.footprint_id), 
                 'footprint_type':str(constraint_type), 
                 'polygon':str(constraint.polygon)})

            privacy_management_data.append(entry)

    return privacy_management_data


def populate_violators--- This code section failed: ---

 L. 105         0  LOAD_FAST                'instance'
                2  LOAD_METHOD              find_violating_sims
                4  CALL_METHOD_0         0  '0 positional arguments'
                6  POP_JUMP_IF_FALSE    24  'to 24'
                8  LOAD_GLOBAL              gsi_handlers
               10  LOAD_ATTR                gsi_utils
               12  LOAD_METHOD              format_object_list_names
               14  LOAD_FAST                'instance'
               16  LOAD_METHOD              find_violating_sims
               18  CALL_METHOD_0         0  '0 positional arguments'
               20  CALL_METHOD_1         1  '1 positional argument'
               22  JUMP_FORWARD         26  'to 26'
             24_0  COME_FROM             6  '6'
               24  LOAD_GLOBAL              NO_VIOLATORS_STR
             26_0  COME_FROM            22  '22'
               26  LOAD_FAST                'entry'
               28  LOAD_STR                 'sim_violators'
               30  STORE_SUBSCR     

 L. 106        32  LOAD_FAST                'instance'
               34  LOAD_ATTR                _late_violators
               36  POP_JUMP_IF_FALSE    52  'to 52'
               38  LOAD_GLOBAL              gsi_handlers
               40  LOAD_ATTR                gsi_utils
               42  LOAD_METHOD              format_object_list_names
               44  LOAD_FAST                'instance'
               46  LOAD_ATTR                _late_violators
               48  CALL_METHOD_1         1  '1 positional argument'
               50  JUMP_FORWARD         54  'to 54'
             52_0  COME_FROM            36  '36'
               52  LOAD_GLOBAL              NO_VIOLATORS_STR
             54_0  COME_FROM            50  '50'
               54  LOAD_FAST                'entry'
               56  LOAD_STR                 'late_violators'
               58  STORE_SUBSCR     

 L. 107        60  LOAD_FAST                'instance'
               62  LOAD_METHOD              find_violating_vehicles
               64  CALL_METHOD_0         0  '0 positional arguments'
               66  POP_JUMP_IF_FALSE    84  'to 84'
               68  LOAD_GLOBAL              gsi_handlers
               70  LOAD_ATTR                gsi_utils
               72  LOAD_METHOD              format_object_list_names
               74  LOAD_FAST                'instance'
               76  LOAD_METHOD              find_violating_vehicles
               78  CALL_METHOD_0         0  '0 positional arguments'
               80  CALL_METHOD_1         1  '1 positional argument'
               82  JUMP_FORWARD         86  'to 86'
             84_0  COME_FROM            66  '66'
               84  LOAD_GLOBAL              NO_VIOLATORS_STR
             86_0  COME_FROM            82  '82'
               86  LOAD_FAST                'entry'
               88  LOAD_STR                 'vehicle_violators'
               90  STORE_SUBSCR     

 L. 109        92  SETUP_LOOP          194  'to 194'
               94  LOAD_GLOBAL              itertools
               96  LOAD_METHOD              chain
               98  LOAD_FAST                'instance'
              100  LOAD_METHOD              find_violating_sims
              102  CALL_METHOD_0         0  '0 positional arguments'
              104  LOAD_FAST                'instance'
              106  LOAD_METHOD              find_violating_vehicles
              108  CALL_METHOD_0         0  '0 positional arguments'
              110  LOAD_FAST                'instance'
              112  LOAD_ATTR                _late_violators
              114  CALL_METHOD_3         3  '3 positional arguments'
              116  GET_ITER         
              118  FOR_ITER            192  'to 192'
              120  STORE_FAST               'violator'

 L. 110       122  LOAD_GLOBAL              privacy_instance_to_violators
              124  POP_JUMP_IF_FALSE   170  'to 170'
              126  LOAD_FAST                'instance'
              128  LOAD_GLOBAL              privacy_instance_to_violators
              130  COMPARE_OP               in
              132  POP_JUMP_IF_FALSE   170  'to 170'

 L. 111       134  LOAD_GLOBAL              str
              136  LOAD_FAST                'violator'
              138  CALL_FUNCTION_1       1  '1 positional argument'
              140  LOAD_GLOBAL              privacy_instance_to_violators
              142  LOAD_FAST                'instance'
              144  BINARY_SUBSCR    
              146  COMPARE_OP               not-in
              148  POP_JUMP_IF_FALSE   190  'to 190'

 L. 112       150  LOAD_GLOBAL              privacy_instance_to_violators
              152  LOAD_FAST                'instance'
              154  BINARY_SUBSCR    
              156  LOAD_METHOD              append
              158  LOAD_GLOBAL              str
              160  LOAD_FAST                'violator'
              162  CALL_FUNCTION_1       1  '1 positional argument'
              164  CALL_METHOD_1         1  '1 positional argument'
              166  POP_TOP          
              168  JUMP_BACK           118  'to 118'
            170_0  COME_FROM           132  '132'
            170_1  COME_FROM           124  '124'

 L. 114       170  LOAD_GLOBAL              privacy_instance_to_violators
              172  LOAD_METHOD              update
              174  LOAD_FAST                'instance'
              176  LOAD_GLOBAL              str
              178  LOAD_FAST                'violator'
              180  CALL_FUNCTION_1       1  '1 positional argument'
              182  BUILD_LIST_1          1 
              184  BUILD_MAP_1           1 
              186  CALL_METHOD_1         1  '1 positional argument'
              188  POP_TOP          
            190_0  COME_FROM           148  '148'
              190  JUMP_BACK           118  'to 118'
              192  POP_BLOCK        
            194_0  COME_FROM_LOOP       92  '92'

 L. 116       194  SETUP_LOOP          252  'to 252'
              196  LOAD_GLOBAL              privacy_instance_to_violators
              198  LOAD_METHOD              items
              200  CALL_METHOD_0         0  '0 positional arguments'
              202  GET_ITER         
            204_0  COME_FROM           218  '218'
              204  FOR_ITER            242  'to 242'
              206  UNPACK_SEQUENCE_2     2 
              208  STORE_FAST               'key'
              210  STORE_FAST               'value'

 L. 117       212  LOAD_FAST                'key'
              214  LOAD_FAST                'instance'
              216  COMPARE_OP               is
              218  POP_JUMP_IF_FALSE   204  'to 204'

 L. 118       220  LOAD_LISTCOMP            '<code_object <listcomp>>'
              222  LOAD_STR                 'populate_violators.<locals>.<listcomp>'
              224  MAKE_FUNCTION_0          'Neither defaults, keyword-only args, annotations, nor closures'
              226  LOAD_FAST                'value'
              228  GET_ITER         
              230  CALL_FUNCTION_1       1  '1 positional argument'
              232  LOAD_FAST                'entry'
              234  LOAD_STR                 'all_past_violators'
              236  STORE_SUBSCR     

 L. 119       238  BREAK_LOOP       
              240  JUMP_BACK           204  'to 204'
              242  POP_BLOCK        

 L. 121       244  LOAD_GLOBAL              NO_VIOLATORS_STR
              246  LOAD_FAST                'entry'
              248  LOAD_STR                 'all_past_violators'
              250  STORE_SUBSCR     
            252_0  COME_FROM_LOOP      194  '194'

 L. 123       252  LOAD_CLOSURE             'active_instances'
              254  BUILD_TUPLE_1         1 
              256  LOAD_DICTCOMP            '<code_object <dictcomp>>'
              258  LOAD_STR                 'populate_violators.<locals>.<dictcomp>'
              260  MAKE_FUNCTION_8          'closure'
              262  LOAD_GLOBAL              privacy_instance_to_violators
              264  LOAD_METHOD              items
              266  CALL_METHOD_0         0  '0 positional arguments'
              268  GET_ITER         
              270  CALL_FUNCTION_1       1  '1 positional argument'
              272  STORE_GLOBAL             privacy_instance_to_violators

Parse error at or near `LOAD_DICTCOMP' instruction at offset 256


# global privacy_instance_to_violators ## Warning: Unused global
