# uncompyle6 version 3.9.0
# Python bytecode version base 3.7.0 (3394)
# Decompiled from: Python 3.7.16 (default, Dec  7 2022, 01:12:33) 
# [GCC 11.3.0]
# Embedded file name: T:\InGame\Gameplay\Scripts\Server\socials\jigs\jig_type_animation.py
# Compiled at: 2019-01-30 18:11:20
# Size of source mod 2**32: 9087 bytes

-- Stacks of completed symbols:
START ::= |- stmts . 
_come_froms ::= \e__come_froms . COME_FROM
_come_froms ::= \e__come_froms . COME_FROM_LOOP
_come_froms ::= \e__come_froms COME_FROM . 
_come_froms ::= _come_froms . COME_FROM
_come_froms ::= _come_froms . COME_FROM_LOOP
_ifstmts_jump ::= \e_c_stmts_opt . COME_FROM
_ifstmts_jump ::= \e_c_stmts_opt . ELSE
_ifstmts_jump ::= \e_c_stmts_opt . JUMP_ABSOLUTE JUMP_FORWARD \e__come_froms
_ifstmts_jump ::= \e_c_stmts_opt . JUMP_ABSOLUTE JUMP_FORWARD _come_froms
_ifstmts_jump ::= \e_c_stmts_opt . come_froms
_ifstmts_jump ::= c_stmts_opt . COME_FROM
_ifstmts_jump ::= c_stmts_opt . ELSE
_ifstmts_jump ::= c_stmts_opt . JUMP_ABSOLUTE JUMP_FORWARD \e__come_froms
_ifstmts_jump ::= c_stmts_opt . JUMP_ABSOLUTE JUMP_FORWARD _come_froms
_ifstmts_jump ::= c_stmts_opt . come_froms
_ifstmts_jump ::= c_stmts_opt COME_FROM . 
_ifstmts_jump ::= c_stmts_opt come_froms . 
_ifstmts_jumpl ::= _ifstmts_jump . 
_ifstmts_jumpl ::= c_stmts . JUMP_BACK
_stmts ::= _stmts . stmt
_stmts ::= stmt . 
and ::= expr . JUMP_IF_FALSE_OR_POP expr \e_come_from_opt
and ::= expr . JUMP_IF_FALSE_OR_POP expr come_from_opt
and ::= expr . jifop_come_from expr
and ::= expr . jmp_false expr
and ::= expr . jmp_false expr COME_FROM
and ::= expr . jmp_false expr jmp_false
and_not ::= expr . jmp_false expr POP_JUMP_IF_TRUE
assert2 ::= expr . jmp_true LOAD_GLOBAL expr CALL_FUNCTION_1 RAISE_VARARGS_1
assert2 ::= expr jmp_true . LOAD_GLOBAL expr CALL_FUNCTION_1 RAISE_VARARGS_1
assert_invert ::= testtrue . LOAD_GLOBAL RAISE_VARARGS_1
assign ::= expr . DUP_TOP designList
assign ::= expr . store
assign ::= expr store . 
assign2 ::= expr . expr ROT_TWO store store
assign2 ::= expr expr . ROT_TWO store store
assign3 ::= expr . expr expr ROT_THREE ROT_TWO store store store
assign3 ::= expr expr . expr ROT_THREE ROT_TWO store store store
assign3 ::= expr expr expr . ROT_THREE ROT_TWO store store store
async_for_stmt ::= setup_loop . expr GET_AITER LOAD_CONST YIELD_FROM SETUP_EXCEPT GET_ANEXT LOAD_CONST YIELD_FROM store POP_BLOCK JUMP_FORWARD COME_FROM_EXCEPT DUP_TOP LOAD_GLOBAL COMPARE_OP POP_JUMP_IF_FALSE POP_TOP POP_TOP POP_TOP POP_EXCEPT POP_BLOCK JUMP_ABSOLUTE END_FINALLY COME_FROM for_block POP_BLOCK COME_FROM_LOOP
async_for_stmt ::= setup_loop . expr GET_AITER SETUP_EXCEPT GET_ANEXT LOAD_CONST YIELD_FROM store POP_BLOCK JUMP_FORWARD COME_FROM_EXCEPT DUP_TOP LOAD_GLOBAL COMPARE_OP POP_JUMP_IF_TRUE END_FINALLY COME_FROM for_block COME_FROM POP_TOP POP_TOP POP_TOP POP_EXCEPT POP_TOP POP_BLOCK COME_FROM_LOOP
async_for_stmt ::= setup_loop expr . GET_AITER LOAD_CONST YIELD_FROM SETUP_EXCEPT GET_ANEXT LOAD_CONST YIELD_FROM store POP_BLOCK JUMP_FORWARD COME_FROM_EXCEPT DUP_TOP LOAD_GLOBAL COMPARE_OP POP_JUMP_IF_FALSE POP_TOP POP_TOP POP_TOP POP_EXCEPT POP_BLOCK JUMP_ABSOLUTE END_FINALLY COME_FROM for_block POP_BLOCK COME_FROM_LOOP
async_for_stmt ::= setup_loop expr . GET_AITER SETUP_EXCEPT GET_ANEXT LOAD_CONST YIELD_FROM store POP_BLOCK JUMP_FORWARD COME_FROM_EXCEPT DUP_TOP LOAD_GLOBAL COMPARE_OP POP_JUMP_IF_TRUE END_FINALLY COME_FROM for_block COME_FROM POP_TOP POP_TOP POP_TOP POP_EXCEPT POP_TOP POP_BLOCK COME_FROM_LOOP
async_for_stmt37 ::= setup_loop . expr GET_AITER \e__come_froms SETUP_EXCEPT GET_ANEXT LOAD_CONST YIELD_FROM store POP_BLOCK JUMP_BACK COME_FROM_EXCEPT DUP_TOP LOAD_GLOBAL COMPARE_OP POP_JUMP_IF_TRUE END_FINALLY for_block COME_FROM POP_TOP POP_TOP POP_TOP POP_EXCEPT POP_TOP POP_BLOCK COME_FROM_LOOP
async_for_stmt37 ::= setup_loop . expr GET_AITER _come_froms SETUP_EXCEPT GET_ANEXT LOAD_CONST YIELD_FROM store POP_BLOCK JUMP_BACK COME_FROM_EXCEPT DUP_TOP LOAD_GLOBAL COMPARE_OP POP_JUMP_IF_TRUE END_FINALLY for_block COME_FROM POP_TOP POP_TOP POP_TOP POP_EXCEPT POP_TOP POP_BLOCK COME_FROM_LOOP
async_for_stmt37 ::= setup_loop expr . GET_AITER \e__come_froms SETUP_EXCEPT GET_ANEXT LOAD_CONST YIELD_FROM store POP_BLOCK JUMP_BACK COME_FROM_EXCEPT DUP_TOP LOAD_GLOBAL COMPARE_OP POP_JUMP_IF_TRUE END_FINALLY for_block COME_FROM POP_TOP POP_TOP POP_TOP POP_EXCEPT POP_TOP POP_BLOCK COME_FROM_LOOP
async_for_stmt37 ::= setup_loop expr . GET_AITER _come_froms SETUP_EXCEPT GET_ANEXT LOAD_CONST YIELD_FROM store POP_BLOCK JUMP_BACK COME_FROM_EXCEPT DUP_TOP LOAD_GLOBAL COMPARE_OP POP_JUMP_IF_TRUE END_FINALLY for_block COME_FROM POP_TOP POP_TOP POP_TOP POP_EXCEPT POP_TOP POP_BLOCK COME_FROM_LOOP
async_forelse_stmt ::= setup_loop . expr GET_AITER \e__come_froms SETUP_EXCEPT GET_ANEXT LOAD_CONST YIELD_FROM store POP_BLOCK JUMP_FORWARD COME_FROM_EXCEPT DUP_TOP LOAD_GLOBAL COMPARE_OP POP_JUMP_IF_TRUE END_FINALLY COME_FROM for_block COME_FROM POP_TOP POP_TOP POP_TOP POP_EXCEPT POP_TOP POP_BLOCK else_suite COME_FROM_LOOP
async_forelse_stmt ::= setup_loop . expr GET_AITER _come_froms SETUP_EXCEPT GET_ANEXT LOAD_CONST YIELD_FROM store POP_BLOCK JUMP_FORWARD COME_FROM_EXCEPT DUP_TOP LOAD_GLOBAL COMPARE_OP POP_JUMP_IF_TRUE END_FINALLY COME_FROM for_block COME_FROM POP_TOP POP_TOP POP_TOP POP_EXCEPT POP_TOP POP_BLOCK else_suite COME_FROM_LOOP
async_forelse_stmt ::= setup_loop expr . GET_AITER \e__come_froms SETUP_EXCEPT GET_ANEXT LOAD_CONST YIELD_FROM store POP_BLOCK JUMP_FORWARD COME_FROM_EXCEPT DUP_TOP LOAD_GLOBAL COMPARE_OP POP_JUMP_IF_TRUE END_FINALLY COME_FROM for_block COME_FROM POP_TOP POP_TOP POP_TOP POP_EXCEPT POP_TOP POP_BLOCK else_suite COME_FROM_LOOP
async_forelse_stmt ::= setup_loop expr . GET_AITER _come_froms SETUP_EXCEPT GET_ANEXT LOAD_CONST YIELD_FROM store POP_BLOCK JUMP_FORWARD COME_FROM_EXCEPT DUP_TOP LOAD_GLOBAL COMPARE_OP POP_JUMP_IF_TRUE END_FINALLY COME_FROM for_block COME_FROM POP_TOP POP_TOP POP_TOP POP_EXCEPT POP_TOP POP_BLOCK else_suite COME_FROM_LOOP
attribute ::= expr . LOAD_ATTR
attribute ::= expr LOAD_ATTR . 
attribute37 ::= expr . LOAD_METHOD
attribute37 ::= expr LOAD_METHOD . 
aug_assign1 ::= expr . expr inplace_op ROT_THREE STORE_SUBSCR
aug_assign1 ::= expr . expr inplace_op store
aug_assign1 ::= expr expr . inplace_op ROT_THREE STORE_SUBSCR
aug_assign1 ::= expr expr . inplace_op store
aug_assign2 ::= expr . DUP_TOP LOAD_ATTR expr inplace_op ROT_TWO STORE_ATTR
await_expr ::= expr . GET_AWAITABLE LOAD_CONST YIELD_FROM
bin_op ::= expr . expr binary_operator
bin_op ::= expr expr . binary_operator
c_stmts ::= _stmts . 
c_stmts ::= _stmts . lastc_stmt
c_stmts ::= continues . 
c_stmts_opt ::= c_stmts . 
call ::= expr . CALL_FUNCTION_0
call ::= expr . CALL_METHOD_0
call ::= expr . expr CALL_METHOD_1
call ::= expr . expr expr CALL_METHOD_2
call ::= expr . pos_arg CALL_FUNCTION_1
call ::= expr . pos_arg pos_arg CALL_FUNCTION_2
call ::= expr . pos_arg pos_arg pos_arg CALL_FUNCTION_3
call ::= expr . pos_arg pos_arg pos_arg pos_arg CALL_FUNCTION_4
call ::= expr expr . CALL_METHOD_1
call ::= expr expr . expr CALL_METHOD_2
call ::= expr expr CALL_METHOD_1 . 
call ::= expr expr expr . CALL_METHOD_2
call ::= expr pos_arg . CALL_FUNCTION_1
call ::= expr pos_arg . pos_arg CALL_FUNCTION_2
call ::= expr pos_arg . pos_arg pos_arg CALL_FUNCTION_3
call ::= expr pos_arg . pos_arg pos_arg pos_arg CALL_FUNCTION_4
call ::= expr pos_arg pos_arg . CALL_FUNCTION_2
call ::= expr pos_arg pos_arg . pos_arg CALL_FUNCTION_3
call ::= expr pos_arg pos_arg . pos_arg pos_arg CALL_FUNCTION_4
call ::= expr pos_arg pos_arg CALL_FUNCTION_2 . 
call ::= expr pos_arg pos_arg pos_arg . CALL_FUNCTION_3
call ::= expr pos_arg pos_arg pos_arg . pos_arg CALL_FUNCTION_4
call ::= expr pos_arg pos_arg pos_arg pos_arg . CALL_FUNCTION_4
call_kw36 ::= expr . expr expr LOAD_CONST CALL_FUNCTION_KW_2
call_kw36 ::= expr . expr expr expr LOAD_CONST CALL_FUNCTION_KW_3
call_kw36 ::= expr . expr expr expr expr LOAD_CONST CALL_FUNCTION_KW_4
call_kw36 ::= expr expr . expr LOAD_CONST CALL_FUNCTION_KW_2
call_kw36 ::= expr expr . expr expr LOAD_CONST CALL_FUNCTION_KW_3
call_kw36 ::= expr expr . expr expr expr LOAD_CONST CALL_FUNCTION_KW_4
call_kw36 ::= expr expr expr . LOAD_CONST CALL_FUNCTION_KW_2
call_kw36 ::= expr expr expr . expr LOAD_CONST CALL_FUNCTION_KW_3
call_kw36 ::= expr expr expr . expr expr LOAD_CONST CALL_FUNCTION_KW_4
call_kw36 ::= expr expr expr expr . LOAD_CONST CALL_FUNCTION_KW_3
call_kw36 ::= expr expr expr expr . expr LOAD_CONST CALL_FUNCTION_KW_4
call_kw36 ::= expr expr expr expr expr . LOAD_CONST CALL_FUNCTION_KW_4
call_stmt ::= expr . POP_TOP
cf_jf_else ::= come_froms . JUMP_FORWARD ELSE
cf_jump_back ::= COME_FROM . JUMP_BACK
classdefdeco1 ::= expr . classdefdeco1 CALL_FUNCTION_1
classdefdeco1 ::= expr . classdefdeco2 CALL_FUNCTION_1
come_from_loops ::= \e_come_from_loops . COME_FROM_LOOP
come_from_opt ::= COME_FROM . 
come_froms ::= COME_FROM . 
come_froms ::= come_froms . COME_FROM
compare_chained ::= expr . compare_chained1 ROT_TWO POP_TOP \e__come_froms
compare_chained ::= expr . compare_chained1 ROT_TWO POP_TOP _come_froms
compare_chained1 ::= expr . DUP_TOP ROT_THREE COMPARE_OP JUMP_IF_FALSE_OR_POP compare_chained1 COME_FROM
compare_chained1 ::= expr . DUP_TOP ROT_THREE COMPARE_OP JUMP_IF_FALSE_OR_POP compare_chained2 COME_FROM
compare_chained1_false_37 ::= expr . DUP_TOP ROT_THREE COMPARE_OP POP_JUMP_IF_FALSE compare_chained2b_false_37 POP_TOP _jump COME_FROM
compare_chained1_false_37 ::= expr . DUP_TOP ROT_THREE COMPARE_OP POP_JUMP_IF_FALSE compare_chained2c_37 POP_TOP JUMP_FORWARD COME_FROM
compare_chained1a_37 ::= expr . DUP_TOP ROT_THREE COMPARE_OP POP_JUMP_IF_FALSE
compare_chained1a_37 ::= expr . DUP_TOP ROT_THREE COMPARE_OP POP_JUMP_IF_FALSE compare_chained2a_37 COME_FROM POP_TOP COME_FROM
compare_chained1b_false_37 ::= expr . DUP_TOP ROT_THREE COMPARE_OP POP_JUMP_IF_FALSE compare_chained2b_false_37 POP_TOP _jump COME_FROM
compare_chained1c_37 ::= expr . DUP_TOP ROT_THREE COMPARE_OP POP_JUMP_IF_FALSE compare_chained2a_37 POP_TOP
compare_chained2_false_37 ::= expr . DUP_TOP ROT_THREE COMPARE_OP POP_JUMP_IF_FALSE compare_chained2a_false_37 POP_TOP JUMP_BACK COME_FROM
compare_chained37 ::= expr . compare_chained1a_37
compare_chained37 ::= expr . compare_chained1c_37
compare_chained37_false ::= expr . compare_chained1_false_37
compare_chained37_false ::= expr . compare_chained1b_false_37
compare_chained37_false ::= expr . compare_chained2_false_37
compare_single ::= expr . expr COMPARE_OP
compare_single ::= expr expr . COMPARE_OP
continue ::= CONTINUE . 
continues ::= _stmts . lastl_stmt continue
continues ::= continue . 
continues ::= lastl_stmt . continue
dict ::= expr . expr expr LOAD_CONST BUILD_CONST_KEY_MAP_3
dict ::= expr expr . expr LOAD_CONST BUILD_CONST_KEY_MAP_3
dict ::= expr expr expr . LOAD_CONST BUILD_CONST_KEY_MAP_3
dict ::= kvlist_4 . 
expr ::= LOAD_DEREF . 
expr ::= LOAD_FAST . 
expr ::= LOAD_GLOBAL . 
expr ::= LOAD_STR . 
expr ::= attribute . 
expr ::= attribute37 . 
expr ::= call . 
expr ::= dict . 
expr ::= get_iter . 
expr ::= tuple . 
expr_jit ::= expr . JUMP_IF_TRUE
expr_jitop ::= expr . JUMP_IF_TRUE_OR_POP
expr_jt ::= expr . jmp_true
expr_jt ::= expr jmp_true . 
expr_pjit ::= expr . POP_JUMP_IF_TRUE
expr_pjit ::= expr POP_JUMP_IF_TRUE . 
expr_pjit_come_from ::= expr . POP_JUMP_IF_TRUE COME_FROM
expr_pjit_come_from ::= expr POP_JUMP_IF_TRUE . COME_FROM
expr_stmt ::= expr . POP_TOP
for ::= setup_loop . expr get_for_iter store for_block POP_BLOCK
for ::= setup_loop . expr get_for_iter store for_block POP_BLOCK COME_FROM_LOOP
for ::= setup_loop . expr get_for_iter store for_block POP_BLOCK NOP COME_FROM_LOOP
for ::= setup_loop expr . get_for_iter store for_block POP_BLOCK
for ::= setup_loop expr . get_for_iter store for_block POP_BLOCK COME_FROM_LOOP
for ::= setup_loop expr . get_for_iter store for_block POP_BLOCK NOP COME_FROM_LOOP
for ::= setup_loop expr get_for_iter . store for_block POP_BLOCK
for ::= setup_loop expr get_for_iter . store for_block POP_BLOCK COME_FROM_LOOP
for ::= setup_loop expr get_for_iter . store for_block POP_BLOCK NOP COME_FROM_LOOP
for ::= setup_loop expr get_for_iter store . for_block POP_BLOCK
for ::= setup_loop expr get_for_iter store . for_block POP_BLOCK COME_FROM_LOOP
for ::= setup_loop expr get_for_iter store . for_block POP_BLOCK NOP COME_FROM_LOOP
for ::= setup_loop expr get_for_iter store for_block . POP_BLOCK
for ::= setup_loop expr get_for_iter store for_block . POP_BLOCK COME_FROM_LOOP
for ::= setup_loop expr get_for_iter store for_block . POP_BLOCK NOP COME_FROM_LOOP
for_block ::= \e_l_stmts_opt . COME_FROM_LOOP JUMP_BACK
for_block ::= \e_l_stmts_opt . _come_froms JUMP_BACK
for_block ::= \e_l_stmts_opt . come_from_loops JUMP_BACK
for_block ::= \e_l_stmts_opt \e__come_froms . JUMP_BACK
for_block ::= \e_l_stmts_opt \e_come_from_loops . JUMP_BACK
for_block ::= l_stmts . 
for_block ::= l_stmts . JUMP_BACK
for_block ::= l_stmts_opt . COME_FROM_LOOP JUMP_BACK
for_block ::= l_stmts_opt . _come_froms JUMP_BACK
for_block ::= l_stmts_opt . come_from_loops JUMP_BACK
for_block ::= l_stmts_opt \e__come_froms . JUMP_BACK
for_block ::= l_stmts_opt \e_come_from_loops . JUMP_BACK
for_block ::= l_stmts_opt _come_froms . JUMP_BACK
forelselaststmtl ::= SETUP_LOOP . expr get_for_iter store for_block POP_BLOCK else_suitel \e__come_froms
forelselaststmtl ::= SETUP_LOOP . expr get_for_iter store for_block POP_BLOCK else_suitel _come_froms
forelselaststmtl ::= SETUP_LOOP expr . get_for_iter store for_block POP_BLOCK else_suitel \e__come_froms
forelselaststmtl ::= SETUP_LOOP expr . get_for_iter store for_block POP_BLOCK else_suitel _come_froms
forelselaststmtl ::= SETUP_LOOP expr get_for_iter . store for_block POP_BLOCK else_suitel \e__come_froms
forelselaststmtl ::= SETUP_LOOP expr get_for_iter . store for_block POP_BLOCK else_suitel _come_froms
forelselaststmtl ::= SETUP_LOOP expr get_for_iter store . for_block POP_BLOCK else_suitel \e__come_froms
forelselaststmtl ::= SETUP_LOOP expr get_for_iter store . for_block POP_BLOCK else_suitel _come_froms
forelselaststmtl ::= SETUP_LOOP expr get_for_iter store for_block . POP_BLOCK else_suitel \e__come_froms
forelselaststmtl ::= SETUP_LOOP expr get_for_iter store for_block . POP_BLOCK else_suitel _come_froms
forelselaststmtl ::= setup_loop . expr get_for_iter store for_block POP_BLOCK else_suitel COME_FROM_LOOP
forelselaststmtl ::= setup_loop expr . get_for_iter store for_block POP_BLOCK else_suitel COME_FROM_LOOP
forelselaststmtl ::= setup_loop expr get_for_iter . store for_block POP_BLOCK else_suitel COME_FROM_LOOP
forelselaststmtl ::= setup_loop expr get_for_iter store . for_block POP_BLOCK else_suitel COME_FROM_LOOP
forelselaststmtl ::= setup_loop expr get_for_iter store for_block . POP_BLOCK else_suitel COME_FROM_LOOP
forelsestmt ::= SETUP_LOOP . expr get_for_iter store for_block POP_BLOCK else_suite \e__come_froms
forelsestmt ::= SETUP_LOOP . expr get_for_iter store for_block POP_BLOCK else_suite _come_froms
forelsestmt ::= SETUP_LOOP expr . get_for_iter store for_block POP_BLOCK else_suite \e__come_froms
forelsestmt ::= SETUP_LOOP expr . get_for_iter store for_block POP_BLOCK else_suite _come_froms
forelsestmt ::= SETUP_LOOP expr get_for_iter . store for_block POP_BLOCK else_suite \e__come_froms
forelsestmt ::= SETUP_LOOP expr get_for_iter . store for_block POP_BLOCK else_suite _come_froms
forelsestmt ::= SETUP_LOOP expr get_for_iter store . for_block POP_BLOCK else_suite \e__come_froms
forelsestmt ::= SETUP_LOOP expr get_for_iter store . for_block POP_BLOCK else_suite _come_froms
forelsestmt ::= SETUP_LOOP expr get_for_iter store for_block . POP_BLOCK else_suite \e__come_froms
forelsestmt ::= SETUP_LOOP expr get_for_iter store for_block . POP_BLOCK else_suite _come_froms
forelsestmt ::= setup_loop . expr get_for_iter store for_block POP_BLOCK else_suite COME_FROM_LOOP
forelsestmt ::= setup_loop expr . get_for_iter store for_block POP_BLOCK else_suite COME_FROM_LOOP
forelsestmt ::= setup_loop expr get_for_iter . store for_block POP_BLOCK else_suite COME_FROM_LOOP
forelsestmt ::= setup_loop expr get_for_iter store . for_block POP_BLOCK else_suite COME_FROM_LOOP
forelsestmt ::= setup_loop expr get_for_iter store for_block . POP_BLOCK else_suite COME_FROM_LOOP
generator_exp ::= load_closure . load_genexpr LOAD_STR MAKE_FUNCTION_8 expr GET_ITER CALL_FUNCTION_1
get_for_iter ::= GET_ITER . _come_froms FOR_ITER
get_for_iter ::= GET_ITER \e__come_froms . FOR_ITER
get_for_iter ::= GET_ITER \e__come_froms FOR_ITER . 
get_iter ::= expr . GET_ITER
get_iter ::= expr GET_ITER . 
if_exp ::= expr . jmp_false expr jf_cf expr COME_FROM
if_exp ::= expr . jmp_false expr jump_absolute_else expr
if_exp37 ::= expr . expr jf_cfs expr COME_FROM
if_exp37 ::= expr expr . jf_cfs expr COME_FROM
if_exp_37b ::= expr . jmp_false expr POP_JUMP_IF_FALSE jump_forward_else expr
if_exp_lambda ::= expr . jmp_false expr return_if_lambda return_stmt_lambda LAMBDA_MARKER
if_exp_not ::= expr . jmp_true expr jump_forward_else expr COME_FROM
if_exp_not ::= expr jmp_true . expr jump_forward_else expr COME_FROM
if_exp_not_lambda ::= expr . jmp_true expr return_if_lambda return_stmt_lambda LAMBDA_MARKER
if_exp_not_lambda ::= expr jmp_true . expr return_if_lambda return_stmt_lambda LAMBDA_MARKER
if_exp_true ::= expr . JUMP_FORWARD expr COME_FROM
ifelsestmt ::= testexpr . c_stmts come_froms else_suite come_froms
ifelsestmt ::= testexpr . c_stmts_opt JUMP_FORWARD else_suite \e__come_froms
ifelsestmt ::= testexpr . c_stmts_opt JUMP_FORWARD else_suite \e_opt_come_from_except
ifelsestmt ::= testexpr . c_stmts_opt JUMP_FORWARD else_suite _come_froms
ifelsestmt ::= testexpr . c_stmts_opt JUMP_FORWARD else_suite opt_come_from_except
ifelsestmt ::= testexpr . c_stmts_opt jf_cfs else_suite \e_opt_come_from_except
ifelsestmt ::= testexpr . c_stmts_opt jf_cfs else_suite opt_come_from_except
ifelsestmt ::= testexpr . c_stmts_opt jump_forward_else else_suite \e__come_froms
ifelsestmt ::= testexpr . c_stmts_opt jump_forward_else else_suite _come_froms
ifelsestmt ::= testexpr . stmts jf_cfs \e_else_suite_opt \e_opt_come_from_except
ifelsestmt ::= testexpr . stmts jf_cfs \e_else_suite_opt opt_come_from_except
ifelsestmt ::= testexpr . stmts jf_cfs else_suite_opt \e_opt_come_from_except
ifelsestmt ::= testexpr . stmts jf_cfs else_suite_opt opt_come_from_except
ifelsestmt ::= testexpr \e_c_stmts_opt . JUMP_FORWARD else_suite \e__come_froms
ifelsestmt ::= testexpr \e_c_stmts_opt . JUMP_FORWARD else_suite \e_opt_come_from_except
ifelsestmt ::= testexpr \e_c_stmts_opt . JUMP_FORWARD else_suite _come_froms
ifelsestmt ::= testexpr \e_c_stmts_opt . JUMP_FORWARD else_suite opt_come_from_except
ifelsestmt ::= testexpr \e_c_stmts_opt . jf_cfs else_suite \e_opt_come_from_except
ifelsestmt ::= testexpr \e_c_stmts_opt . jf_cfs else_suite opt_come_from_except
ifelsestmt ::= testexpr \e_c_stmts_opt . jump_forward_else else_suite \e__come_froms
ifelsestmt ::= testexpr \e_c_stmts_opt . jump_forward_else else_suite _come_froms
ifelsestmt ::= testexpr c_stmts . come_froms else_suite come_froms
ifelsestmt ::= testexpr c_stmts come_froms . else_suite come_froms
ifelsestmt ::= testexpr c_stmts_opt . JUMP_FORWARD else_suite \e__come_froms
ifelsestmt ::= testexpr c_stmts_opt . JUMP_FORWARD else_suite \e_opt_come_from_except
ifelsestmt ::= testexpr c_stmts_opt . JUMP_FORWARD else_suite _come_froms
ifelsestmt ::= testexpr c_stmts_opt . JUMP_FORWARD else_suite opt_come_from_except
ifelsestmt ::= testexpr c_stmts_opt . jf_cfs else_suite \e_opt_come_from_except
ifelsestmt ::= testexpr c_stmts_opt . jf_cfs else_suite opt_come_from_except
ifelsestmt ::= testexpr c_stmts_opt . jump_forward_else else_suite \e__come_froms
ifelsestmt ::= testexpr c_stmts_opt . jump_forward_else else_suite _come_froms
ifelsestmt ::= testexpr stmts . jf_cfs \e_else_suite_opt \e_opt_come_from_except
ifelsestmt ::= testexpr stmts . jf_cfs \e_else_suite_opt opt_come_from_except
ifelsestmt ::= testexpr stmts . jf_cfs else_suite_opt \e_opt_come_from_except
ifelsestmt ::= testexpr stmts . jf_cfs else_suite_opt opt_come_from_except
ifelsestmtl ::= testexpr . c_stmts_opt cf_jf_else else_suitel
ifelsestmtl ::= testexpr . c_stmts_opt cf_jump_back else_suitel
ifelsestmtl ::= testexpr . c_stmts_opt jb_cfs else_suitel
ifelsestmtl ::= testexpr . c_stmts_opt jb_else else_suitel
ifelsestmtl ::= testexpr . c_stmts_opt jump_forward_else else_suitec
ifelsestmtl ::= testexpr \e_c_stmts_opt . cf_jf_else else_suitel
ifelsestmtl ::= testexpr \e_c_stmts_opt . cf_jump_back else_suitel
ifelsestmtl ::= testexpr \e_c_stmts_opt . jb_cfs else_suitel
ifelsestmtl ::= testexpr \e_c_stmts_opt . jb_else else_suitel
ifelsestmtl ::= testexpr \e_c_stmts_opt . jump_forward_else else_suitec
ifelsestmtl ::= testexpr c_stmts_opt . cf_jf_else else_suitel
ifelsestmtl ::= testexpr c_stmts_opt . cf_jump_back else_suitel
ifelsestmtl ::= testexpr c_stmts_opt . jb_cfs else_suitel
ifelsestmtl ::= testexpr c_stmts_opt . jb_else else_suitel
ifelsestmtl ::= testexpr c_stmts_opt . jump_forward_else else_suitec
iflaststmtl ::= testexpr . c_stmts
iflaststmtl ::= testexpr . c_stmts JUMP_BACK
iflaststmtl ::= testexpr . c_stmts JUMP_BACK COME_FROM_LOOP
iflaststmtl ::= testexpr . c_stmts JUMP_BACK POP_BLOCK
iflaststmtl ::= testexpr c_stmts . 
iflaststmtl ::= testexpr c_stmts . JUMP_BACK
iflaststmtl ::= testexpr c_stmts . JUMP_BACK COME_FROM_LOOP
iflaststmtl ::= testexpr c_stmts . JUMP_BACK POP_BLOCK
iflaststmtl ::= testexprl . c_stmts JUMP_BACK
iflaststmtl ::= testexprl . c_stmts JUMP_BACK COME_FROM_LOOP
iflaststmtl ::= testexprl . c_stmts JUMP_BACK POP_BLOCK
iflaststmtl ::= testexprl c_stmts . JUMP_BACK
iflaststmtl ::= testexprl c_stmts . JUMP_BACK COME_FROM_LOOP
iflaststmtl ::= testexprl c_stmts . JUMP_BACK POP_BLOCK
ifstmt ::= testexpr . _ifstmts_jump
ifstmt ::= testexpr _ifstmts_jump . 
ifstmtl ::= testexpr . _ifstmts_jumpl
ifstmtl ::= testexpr _ifstmts_jumpl . 
jb_cfs ::= \e_come_from_opt . JUMP_BACK come_froms
jb_cfs ::= come_from_opt . JUMP_BACK come_froms
jmp_true ::= POP_JUMP_IF_TRUE . 
kvlist_4 ::= expr . expr expr expr expr expr expr expr BUILD_MAP_4
kvlist_4 ::= expr expr . expr expr expr expr expr expr BUILD_MAP_4
kvlist_4 ::= expr expr expr . expr expr expr expr expr BUILD_MAP_4
kvlist_4 ::= expr expr expr expr . expr expr expr expr BUILD_MAP_4
kvlist_4 ::= expr expr expr expr expr . expr expr expr BUILD_MAP_4
kvlist_4 ::= expr expr expr expr expr expr . expr expr BUILD_MAP_4
kvlist_4 ::= expr expr expr expr expr expr expr . expr BUILD_MAP_4
kvlist_4 ::= expr expr expr expr expr expr expr expr . BUILD_MAP_4
kvlist_4 ::= expr expr expr expr expr expr expr expr BUILD_MAP_4 . 
l_stmts ::= _stmts . 
l_stmts ::= _stmts . lastl_stmt
l_stmts ::= l_stmts . lstmt
l_stmts ::= lastl_stmt . 
l_stmts ::= lastl_stmt . come_froms l_stmts
l_stmts ::= lastl_stmt come_froms . l_stmts
l_stmts ::= lstmt . 
l_stmts_opt ::= l_stmts . 
lambda_body ::= expr . LOAD_LAMBDA LOAD_STR MAKE_FUNCTION_1
lambda_body ::= load_closure . LOAD_LAMBDA LOAD_STR MAKE_FUNCTION_8
lastl_stmt ::= iflaststmtl . 
load_closure ::= LOAD_CLOSURE . 
load_closure ::= LOAD_CLOSURE . BUILD_TUPLE_1
load_closure ::= LOAD_CLOSURE BUILD_TUPLE_1 . 
load_closure ::= load_closure . LOAD_CLOSURE
load_genexpr ::= BUILD_TUPLE_1 . LOAD_GENEXPR LOAD_STR
lstmt ::= stmt . 
mkfunc ::= expr . LOAD_CODE LOAD_STR MAKE_FUNCTION_1
mkfunc ::= load_closure . LOAD_CODE LOAD_STR MAKE_FUNCTION_8
mkfuncdeco ::= expr . mkfuncdeco CALL_FUNCTION_1
mkfuncdeco ::= expr . mkfuncdeco0 CALL_FUNCTION_1
or ::= expr_jt . expr
or ::= expr_jt . expr COME_FROM
or ::= expr_pjit . expr POP_JUMP_IF_FALSE COME_FROM
pos_arg ::= expr . 
ret_and ::= expr . JUMP_IF_FALSE_OR_POP return_expr_or_cond COME_FROM
ret_or ::= expr . JUMP_IF_TRUE_OR_POP return_expr_or_cond COME_FROM
return ::= return_expr . RETURN_END_IF
return ::= return_expr . RETURN_VALUE
return ::= return_expr . RETURN_VALUE COME_FROM
return_expr ::= expr . 
return_expr_lambda ::= return_expr . RETURN_VALUE_LAMBDA
return_expr_lambda ::= return_expr . RETURN_VALUE_LAMBDA LAMBDA_MARKER
return_if_stmt ::= return_expr . RETURN_END_IF
return_if_stmt ::= return_expr . RETURN_END_IF POP_BLOCK
return_if_stmts ::= _stmts . return_if_stmt \e__come_froms
return_if_stmts ::= _stmts . return_if_stmt _come_froms
returns ::= _stmts . return
returns ::= _stmts . return_if_stmt
setup_loop ::= SETUP_LOOP . _come_froms
setup_loop ::= SETUP_LOOP \e__come_froms . 
sstmt ::= sstmt . RETURN_LAST
sstmt ::= stmt . 
stmt ::= assign . 
stmt ::= continue . 
stmt ::= ifstmt . 
stmt ::= ifstmtl . 
stmts ::= sstmt . 
stmts ::= stmts . sstmt
stmts ::= stmts sstmt . 
store ::= STORE_DEREF . 
store ::= STORE_FAST . 
store ::= expr . STORE_ATTR
store ::= unpack . 
store_subscript ::= expr . expr STORE_SUBSCR
store_subscript ::= expr expr . STORE_SUBSCR
subscript ::= expr . expr BINARY_SUBSCR
subscript ::= expr expr . BINARY_SUBSCR
subscript2 ::= expr . expr DUP_TOP_TWO BINARY_SUBSCR
subscript2 ::= expr expr . DUP_TOP_TWO BINARY_SUBSCR
testexpr ::= testtrue . 
testexpr_cf ::= testexpr . come_froms
testexprl ::= testfalsel . 
testfalse ::= expr . jmp_false
testfalse_not_and ::= expr . jmp_false expr jmp_true COME_FROM
testfalse_not_or ::= expr . jmp_false expr jmp_false COME_FROM
testfalsel ::= expr . jmp_true
testfalsel ::= expr jmp_true . 
testtrue ::= expr . jmp_true
testtrue ::= expr jmp_true . 
tuple ::= expr . expr BUILD_TUPLE_2
tuple ::= expr expr . BUILD_TUPLE_2
tuple ::= expr expr BUILD_TUPLE_2 . 
unary_not ::= expr . UNARY_NOT
unary_op ::= expr . unary_operator
unpack ::= UNPACK_SEQUENCE_2 . store store
unpack ::= UNPACK_SEQUENCE_2 store . store
unpack ::= UNPACK_SEQUENCE_2 store store . 
while1elsestmt ::= setup_loop . l_stmts JUMP_BACK POP_BLOCK else_suite COME_FROM_LOOP
while1elsestmt ::= setup_loop . l_stmts JUMP_BACK \e__come_froms POP_BLOCK else_suitel COME_FROM_LOOP
while1elsestmt ::= setup_loop . l_stmts JUMP_BACK _come_froms POP_BLOCK else_suitel COME_FROM_LOOP
while1elsestmt ::= setup_loop . l_stmts JUMP_BACK else_suite COME_FROM_LOOP
while1elsestmt ::= setup_loop . l_stmts JUMP_BACK else_suitel
while1stmt ::= setup_loop . l_stmts COME_FROM JUMP_BACK COME_FROM_LOOP
while1stmt ::= setup_loop . l_stmts COME_FROM JUMP_BACK POP_BLOCK COME_FROM_LOOP
while1stmt ::= setup_loop . l_stmts COME_FROM_LOOP
while1stmt ::= setup_loop . l_stmts COME_FROM_LOOP JUMP_BACK POP_BLOCK COME_FROM_LOOP
while1stmt ::= setup_loop . l_stmts POP_BLOCK COME_FROM_LOOP
whileTruestmt ::= SETUP_LOOP . l_stmts_opt JUMP_BACK COME_FROM_LOOP
whileTruestmt ::= SETUP_LOOP \e_l_stmts_opt . JUMP_BACK COME_FROM_LOOP
whileTruestmt ::= setup_loop . l_stmts_opt JUMP_BACK POP_BLOCK \e__come_froms
whileTruestmt ::= setup_loop . l_stmts_opt JUMP_BACK POP_BLOCK _come_froms
whileTruestmt ::= setup_loop \e_l_stmts_opt . JUMP_BACK POP_BLOCK \e__come_froms
whileTruestmt ::= setup_loop \e_l_stmts_opt . JUMP_BACK POP_BLOCK _come_froms
whileelsestmt ::= setup_loop . testexpr \e_l_stmts_opt JUMP_BACK POP_BLOCK else_suitel COME_FROM
whileelsestmt ::= setup_loop . testexpr \e_l_stmts_opt JUMP_BACK POP_BLOCK else_suitel COME_FROM_LOOP
whileelsestmt ::= setup_loop . testexpr l_stmts_opt JUMP_BACK POP_BLOCK else_suitel COME_FROM
whileelsestmt ::= setup_loop . testexpr l_stmts_opt JUMP_BACK POP_BLOCK else_suitel COME_FROM_LOOP
whilestmt ::= setup_loop . testexpr \e_l_stmts_opt COME_FROM JUMP_BACK POP_BLOCK COME_FROM_LOOP
whilestmt ::= setup_loop . testexpr \e_l_stmts_opt JUMP_BACK POP_BLOCK COME_FROM_LOOP
whilestmt ::= setup_loop . testexpr \e_l_stmts_opt JUMP_BACK come_froms POP_BLOCK
whilestmt ::= setup_loop . testexpr \e_l_stmts_opt JUMP_BACK come_froms POP_BLOCK COME_FROM_LOOP
whilestmt ::= setup_loop . testexpr \e_l_stmts_opt come_froms JUMP_BACK come_froms POP_BLOCK COME_FROM_LOOP
whilestmt ::= setup_loop . testexpr l_stmts_opt COME_FROM JUMP_BACK POP_BLOCK COME_FROM_LOOP
whilestmt ::= setup_loop . testexpr l_stmts_opt JUMP_BACK POP_BLOCK COME_FROM_LOOP
whilestmt ::= setup_loop . testexpr l_stmts_opt JUMP_BACK come_froms POP_BLOCK
whilestmt ::= setup_loop . testexpr l_stmts_opt JUMP_BACK come_froms POP_BLOCK COME_FROM_LOOP
whilestmt ::= setup_loop . testexpr l_stmts_opt come_froms JUMP_BACK come_froms POP_BLOCK COME_FROM_LOOP
whilestmt ::= setup_loop . testexpr returns POP_BLOCK COME_FROM_LOOP
whilestmt ::= setup_loop . testexpr returns come_froms POP_BLOCK COME_FROM_LOOP
yield ::= expr . YIELD_VALUE
yield_from ::= expr . GET_YIELD_FROM_ITER LOAD_CONST YIELD_FROM
Instruction context:
   
 L. 136       128  LOAD_GLOBAL              frozendict
                 130  LOAD_CLOSURE             'locked_params'
                 132  BUILD_TUPLE_1         1 
->               134  LOAD_DICTCOMP            '<code_object <dictcomp>>'
                 136  LOAD_STR                 'SocialJigAnimation._get_available_transforms_gen.<locals>.<dictcomp>'
                 138  MAKE_FUNCTION_8          'closure'
                 140  LOAD_FAST                'param_sequence'
                 142  LOAD_METHOD              items
                 144  CALL_METHOD_0         0  '0 positional arguments'
                 146  GET_ITER         
                 148  CALL_FUNCTION_1       1  '1 positional argument'
                 150  CALL_FUNCTION_1       1  '1 positional argument'
                 152  STORE_FAST               'jig_params'
from _math import Vector2, Transform, Vector3
from animation import get_throwaway_animation_context
from animation.animation_utils import StubActor
from animation.asm import create_asm, do_params_match
from interactions.utils.animation_reference import TunableAnimationReference
from postures import PostureTrack
from routing import FootprintType
from sims.sim_info_types import SpeciesExtended
from sims4.collections import frozendict
from sims4.geometry import PolygonFootprint
from sims4.math import yaw_quaternion_to_angle
from sims4.tuning.tunable import AutoFactoryInit, HasTunableSingletonFactory, Tunable
from socials.jigs.jig_utils import get_default_reserve_space, generate_jig_polygon, _generate_poly_points

class SocialJigAnimation(AutoFactoryInit, HasTunableSingletonFactory):

    @staticmethod
    def on_tunable_loaded_callback(instance_class, tunable_name, source, value):
        animation_element = value.canonical_animation
        asm_key = animation_element.asm_key
        actor_name = animation_element.actor_name
        target_name = animation_element.target_name
        state_name = animation_element.begin_states[0]
        actor = StubActor(1)
        target = StubActor(2)
        animation_context = get_throwaway_animation_context()
        asm = create_asm(asm_key, context=animation_context)
        asm.set_actor(actor_name, actor)
        asm.set_actor(target_name, target)
        for posture_manifest_entry in asm.get_supported_postures_for_actor(actor_name).get_constraint_version():
            for posture_type in posture_manifest_entry.posture_types:
                if posture_type.mobile:
                    break
            else:
                continue

            break
        else:
            posture_type = None

        available_transforms = []
        if posture_type is not None:
            posture = posture_type(actor, None, (PostureTrack.BODY), animation_context=animation_context)
            boundary_conditions = asm.get_boundary_conditions_list(actor, state_name, posture=posture, target=target)
            for _, slots_to_params_entry in boundary_conditions:
                if not slots_to_params_entry:
                    continue
                for boundary_condition_entry, param_sequences_entry in slots_to_params_entry:
                    relative_transform, _, _, _ = boundary_condition_entry.get_transforms(asm, target)
                    available_transforms.append((param_sequences_entry, relative_transform))

        setattr(value, 'available_transforms', available_transforms)

    FACTORY_TUNABLES = {'canonical_animation':TunableAnimationReference(description="\n            The canonical animation element used to generate social positioning\n            for this group.\n            \n            The animation must include a target actor (such as 'y') whose\n            relative positioning from an actor, such as 'x' defines the\n            positioning.\n            ",
       callback=None), 
     'reverse_actor_sim_orientation':Tunable(description='\n            If checked then we will reverse the orientation of the actor Sim\n            when generating this jig. \n            ',
       tunable_type=bool,
       default=False), 
     'callback':on_tunable_loaded_callback}

    def _get_available_transforms_gen--- This code section failed: ---

 L. 115         0  LOAD_FAST                'self'
                2  LOAD_ATTR                canonical_animation
                4  STORE_FAST               'animation_element'

 L. 117         6  LOAD_FAST                'animation_element'
                8  LOAD_ATTR                actor_name
               10  STORE_FAST               'actor_name'

 L. 118        12  LOAD_FAST                'animation_element'
               14  LOAD_ATTR                target_name
               16  STORE_FAST               'target_name'

 L. 122        18  LOAD_FAST                'actor'
               20  LOAD_ATTR                age
               22  LOAD_ATTR                age_for_animation_cache
               24  STORE_FAST               'actor_age'

 L. 123        26  LOAD_FAST                'target'
               28  LOAD_ATTR                age
               30  LOAD_ATTR                age_for_animation_cache
               32  STORE_FAST               'target_age'

 L. 126        34  LOAD_STR                 'species'
               36  LOAD_FAST                'actor_name'
               38  BUILD_TUPLE_2         2 
               40  LOAD_GLOBAL              SpeciesExtended
               42  LOAD_METHOD              get_animation_species_param
               44  LOAD_FAST                'actor'
               46  LOAD_ATTR                extended_species
               48  CALL_METHOD_1         1  '1 positional argument'

 L. 127        50  LOAD_STR                 'age'
               52  LOAD_FAST                'actor_name'
               54  BUILD_TUPLE_2         2 
               56  LOAD_FAST                'actor_age'
               58  LOAD_ATTR                animation_age_param

 L. 128        60  LOAD_STR                 'species'
               62  LOAD_FAST                'target_name'
               64  BUILD_TUPLE_2         2 
               66  LOAD_GLOBAL              SpeciesExtended
               68  LOAD_METHOD              get_animation_species_param
               70  LOAD_FAST                'target'
               72  LOAD_ATTR                extended_species
               74  CALL_METHOD_1         1  '1 positional argument'

 L. 129        76  LOAD_STR                 'age'
               78  LOAD_FAST                'target_name'
               80  BUILD_TUPLE_2         2 
               82  LOAD_FAST                'target_age'
               84  LOAD_ATTR                animation_age_param
               86  BUILD_MAP_4           4 
               88  STORE_DEREF              'locked_params'

 L. 132        90  SETUP_LOOP          172  'to 172'
               92  LOAD_FAST                'self'
               94  LOAD_ATTR                available_transforms
               96  GET_ITER         
               98  FOR_ITER            170  'to 170'
              100  UNPACK_SEQUENCE_2     2 
              102  STORE_FAST               'param_sequences'
              104  STORE_FAST               'transform'

 L. 133       106  SETUP_LOOP          168  'to 168'
              108  LOAD_FAST                'param_sequences'
              110  GET_ITER         
              112  FOR_ITER            166  'to 166'
              114  STORE_FAST               'param_sequence'

 L. 134       116  LOAD_GLOBAL              do_params_match
              118  LOAD_FAST                'param_sequence'
              120  LOAD_DEREF               'locked_params'
              122  CALL_FUNCTION_2       2  '2 positional arguments'
              124  POP_JUMP_IF_TRUE    128  'to 128'

 L. 135       126  CONTINUE            112  'to 112'
            128_0  COME_FROM           124  '124'

 L. 136       128  LOAD_GLOBAL              frozendict
              130  LOAD_CLOSURE             'locked_params'
              132  BUILD_TUPLE_1         1 
              134  LOAD_DICTCOMP            '<code_object <dictcomp>>'
              136  LOAD_STR                 'SocialJigAnimation._get_available_transforms_gen.<locals>.<dictcomp>'
              138  MAKE_FUNCTION_8          'closure'
              140  LOAD_FAST                'param_sequence'
              142  LOAD_METHOD              items
              144  CALL_METHOD_0         0  '0 positional arguments'
              146  GET_ITER         
              148  CALL_FUNCTION_1       1  '1 positional argument'
              150  CALL_FUNCTION_1       1  '1 positional argument'
              152  STORE_FAST               'jig_params'

 L. 137       154  LOAD_FAST                'transform'
              156  LOAD_FAST                'jig_params'
              158  BUILD_TUPLE_2         2 
              160  YIELD_VALUE      
              162  POP_TOP          
              164  JUMP_BACK           112  'to 112'
              166  POP_BLOCK        
            168_0  COME_FROM_LOOP      106  '106'
              168  JUMP_BACK            98  'to 98'
              170  POP_BLOCK        
            172_0  COME_FROM_LOOP       90  '90'

Parse error at or near `LOAD_DICTCOMP' instruction at offset 134

    def get_transforms_gen(self, actor, target, fallback_routing_surface=None, fgl_kwargs=None, **kwargs):
        reserved_space_a = get_default_reserve_spaceactor.speciesactor.age
        reserved_space_b = get_default_reserve_spacetarget.speciestarget.age
        fgl_kwargs = fgl_kwargs if fgl_kwargs is not None else {}
        ignored_objects = {actor.id, target.id}
        ignored_ids = fgl_kwargs.get('ignored_object_ids')
        if ignored_ids is not None:
            ignored_objects.update(ignored_ids)
        fgl_kwargs['ignored_object_ids'] = ignored_objects
        for transform, jig_params in self._get_available_transforms_gen(actor, target):
            actor_angle = yaw_quaternion_to_angle(transform.orientation)
            translation_a, orientation_a, translation_b, orientation_b, routing_surface = generate_jig_polygon(actor.location, transform.translation, actor_angle, target.location, Vector2.ZERO(), 0,
 reserved_space_a.left, reserved_space_a.right, reserved_space_a.front, reserved_space_a.back,
 reserved_space_b.left, reserved_space_b.right, reserved_space_b.front, reserved_space_b.back, fallback_routing_surface=fallback_routing_surface, 
             reverse_nonreletive_sim_orientation=self.reverse_actor_sim_orientation, **fgl_kwargs)
            if translation_a is None:
                continue
            yield (
             Transformtranslation_aorientation_a, Transformtranslation_borientation_b, routing_surface, jig_params)

    def get_footprint_polygon(self, sim_a, sim_b, sim_a_transform, sim_b_transform, routing_surface):
        reserved_space_a = get_default_reserve_spacesim_a.speciessim_a.age
        reserved_space_b = get_default_reserve_spacesim_b.speciessim_b.age
        polygon = _generate_poly_points(sim_a_transform.translation, sim_a_transform.orientation.transform_vector(Vector3.Z_AXIS()), sim_b_transform.translation, sim_b_transform.orientation.transform_vector(Vector3.Z_AXIS()), reserved_space_a.left, reserved_space_a.right, reserved_space_a.front, reserved_space_a.back, reserved_space_b.left, reserved_space_b.right, reserved_space_b.front, reserved_space_b.back)
        return PolygonFootprint(polygon, routing_surface=(sim_a.routing_surface), cost=25, footprint_type=(FootprintType.FOOTPRINT_TYPE_OBJECT), enabled=True)
