# uncompyle6 version 3.9.0
# Python bytecode version base 3.7.0 (3394)
# Decompiled from: Python 3.7.16 (default, Dec  7 2022, 01:12:33) 
# [GCC 11.3.0]
# Embedded file name: T:\InGame\Gameplay\Scripts\Server\venues\civic_policies\venue_civic_policy_commands.py
# Compiled at: 2020-10-02 16:44:04
# Size of source mod 2**32: 6364 bytes

-- Stacks of completed symbols:
START ::= |- stmts . 
_ifstmts_jump ::= COME_FROM . c_stmts come_froms
_ifstmts_jump ::= \e_c_stmts_opt . COME_FROM
_ifstmts_jump ::= \e_c_stmts_opt . ELSE
_ifstmts_jump ::= \e_c_stmts_opt . JUMP_ABSOLUTE JUMP_FORWARD \e__come_froms
_ifstmts_jump ::= \e_c_stmts_opt . JUMP_ABSOLUTE JUMP_FORWARD _come_froms
_ifstmts_jump ::= \e_c_stmts_opt . come_froms
_ifstmts_jump ::= \e_c_stmts_opt COME_FROM . 
_ifstmts_jump ::= \e_c_stmts_opt come_froms . 
_ifstmts_jumpl ::= COME_FROM . c_stmts JUMP_BACK
_ifstmts_jumpl ::= COME_FROM . c_stmts JUMP_FORWARD
_stmts ::= _stmts . stmt
_stmts ::= _stmts stmt . 
_stmts ::= stmt . 
and ::= expr . JUMP_IF_FALSE_OR_POP expr \e_come_from_opt
and ::= expr . JUMP_IF_FALSE_OR_POP expr come_from_opt
and ::= expr . jifop_come_from expr
and ::= expr . jmp_false expr
and ::= expr . jmp_false expr COME_FROM
and ::= expr . jmp_false expr jmp_false
and_not ::= expr . jmp_false expr POP_JUMP_IF_TRUE
assert2 ::= expr . jmp_true LOAD_GLOBAL expr CALL_FUNCTION_1 RAISE_VARARGS_1
assert2 ::= expr jmp_true . LOAD_GLOBAL expr CALL_FUNCTION_1 RAISE_VARARGS_1
assert_invert ::= testtrue . LOAD_GLOBAL RAISE_VARARGS_1
assign ::= expr . DUP_TOP designList
assign ::= expr . store
assign ::= expr store . 
assign2 ::= expr . expr ROT_TWO store store
assign2 ::= expr expr . ROT_TWO store store
assign3 ::= expr . expr expr ROT_THREE ROT_TWO store store store
assign3 ::= expr expr . expr ROT_THREE ROT_TWO store store store
assign3 ::= expr expr expr . ROT_THREE ROT_TWO store store store
attribute ::= expr . LOAD_ATTR
attribute ::= expr LOAD_ATTR . 
attribute37 ::= expr . LOAD_METHOD
attribute37 ::= expr LOAD_METHOD . 
aug_assign1 ::= expr . expr inplace_op ROT_THREE STORE_SUBSCR
aug_assign1 ::= expr . expr inplace_op store
aug_assign1 ::= expr expr . inplace_op ROT_THREE STORE_SUBSCR
aug_assign1 ::= expr expr . inplace_op store
aug_assign2 ::= expr . DUP_TOP LOAD_ATTR expr inplace_op ROT_TWO STORE_ATTR
await_expr ::= expr . GET_AWAITABLE LOAD_CONST YIELD_FROM
bin_op ::= expr . expr binary_operator
bin_op ::= expr expr . binary_operator
c_stmts ::= _stmts . 
c_stmts ::= _stmts . lastc_stmt
c_stmts_opt ::= c_stmts . 
call ::= expr . CALL_METHOD_0
call ::= expr . expr CALL_METHOD_1
call ::= expr . expr expr CALL_METHOD_2
call ::= expr . pos_arg CALL_FUNCTION_1
call ::= expr CALL_METHOD_0 . 
call ::= expr expr . CALL_METHOD_1
call ::= expr expr . expr CALL_METHOD_2
call ::= expr expr CALL_METHOD_1 . 
call ::= expr expr expr . CALL_METHOD_2
call ::= expr expr expr CALL_METHOD_2 . 
call ::= expr pos_arg . CALL_FUNCTION_1
call_kw36 ::= expr . expr expr expr LOAD_CONST CALL_FUNCTION_KW_3
call_kw36 ::= expr expr . expr expr LOAD_CONST CALL_FUNCTION_KW_3
call_kw36 ::= expr expr expr . expr LOAD_CONST CALL_FUNCTION_KW_3
call_stmt ::= expr . POP_TOP
call_stmt ::= expr POP_TOP . 
cf_jf_else ::= come_froms . JUMP_FORWARD ELSE
cf_jump_back ::= COME_FROM . JUMP_BACK
classdefdeco1 ::= expr . classdefdeco1 CALL_FUNCTION_1
classdefdeco1 ::= expr . classdefdeco2 CALL_FUNCTION_1
come_from_opt ::= COME_FROM . 
come_froms ::= COME_FROM . 
come_froms ::= come_froms . COME_FROM
come_froms ::= come_froms COME_FROM . 
compare ::= compare_single . 
compare_chained ::= expr . compare_chained1 ROT_TWO POP_TOP \e__come_froms
compare_chained ::= expr . compare_chained1 ROT_TWO POP_TOP _come_froms
compare_chained1 ::= expr . DUP_TOP ROT_THREE COMPARE_OP JUMP_IF_FALSE_OR_POP compare_chained1 COME_FROM
compare_chained1 ::= expr . DUP_TOP ROT_THREE COMPARE_OP JUMP_IF_FALSE_OR_POP compare_chained2 COME_FROM
compare_chained1_false_37 ::= expr . DUP_TOP ROT_THREE COMPARE_OP POP_JUMP_IF_FALSE compare_chained2b_false_37 POP_TOP _jump COME_FROM
compare_chained1_false_37 ::= expr . DUP_TOP ROT_THREE COMPARE_OP POP_JUMP_IF_FALSE compare_chained2c_37 POP_TOP JUMP_FORWARD COME_FROM
compare_chained1a_37 ::= expr . DUP_TOP ROT_THREE COMPARE_OP POP_JUMP_IF_FALSE
compare_chained1a_37 ::= expr . DUP_TOP ROT_THREE COMPARE_OP POP_JUMP_IF_FALSE compare_chained2a_37 COME_FROM POP_TOP COME_FROM
compare_chained1b_false_37 ::= expr . DUP_TOP ROT_THREE COMPARE_OP POP_JUMP_IF_FALSE compare_chained2b_false_37 POP_TOP _jump COME_FROM
compare_chained1c_37 ::= expr . DUP_TOP ROT_THREE COMPARE_OP POP_JUMP_IF_FALSE compare_chained2a_37 POP_TOP
compare_chained2_false_37 ::= expr . DUP_TOP ROT_THREE COMPARE_OP POP_JUMP_IF_FALSE compare_chained2a_false_37 POP_TOP JUMP_BACK COME_FROM
compare_chained37 ::= expr . compare_chained1a_37
compare_chained37 ::= expr . compare_chained1c_37
compare_chained37_false ::= expr . compare_chained1_false_37
compare_chained37_false ::= expr . compare_chained1b_false_37
compare_chained37_false ::= expr . compare_chained2_false_37
compare_single ::= expr . expr COMPARE_OP
compare_single ::= expr expr . COMPARE_OP
compare_single ::= expr expr COMPARE_OP . 
continues ::= _stmts . lastl_stmt continue
dict ::= expr . LOAD_CONST BUILD_CONST_KEY_MAP_1
dict ::= expr . expr LOAD_CONST BUILD_CONST_KEY_MAP_2
dict ::= expr LOAD_CONST . BUILD_CONST_KEY_MAP_1
dict ::= expr expr . LOAD_CONST BUILD_CONST_KEY_MAP_2
expr ::= LOAD_CONST . 
expr ::= LOAD_FAST . 
expr ::= LOAD_GLOBAL . 
expr ::= LOAD_STR . 
expr ::= attribute . 
expr ::= attribute37 . 
expr ::= call . 
expr ::= compare . 
expr ::= or . 
expr_jit ::= expr . JUMP_IF_TRUE
expr_jitop ::= expr . JUMP_IF_TRUE_OR_POP
expr_jt ::= expr . jmp_true
expr_jt ::= expr jmp_true . 
expr_pjit ::= expr . POP_JUMP_IF_TRUE
expr_pjit ::= expr POP_JUMP_IF_TRUE . 
expr_pjit_come_from ::= expr . POP_JUMP_IF_TRUE COME_FROM
expr_pjit_come_from ::= expr POP_JUMP_IF_TRUE . COME_FROM
expr_pjit_come_from ::= expr POP_JUMP_IF_TRUE COME_FROM . 
expr_stmt ::= expr . POP_TOP
expr_stmt ::= expr POP_TOP . 
if_exp ::= expr . jmp_false expr jf_cf expr COME_FROM
if_exp ::= expr . jmp_false expr jump_absolute_else expr
if_exp37 ::= expr . expr jf_cfs expr COME_FROM
if_exp37 ::= expr expr . jf_cfs expr COME_FROM
if_exp_37b ::= expr . jmp_false expr POP_JUMP_IF_FALSE jump_forward_else expr
if_exp_lambda ::= expr . jmp_false expr return_if_lambda return_stmt_lambda LAMBDA_MARKER
if_exp_not ::= expr . jmp_true expr jump_forward_else expr COME_FROM
if_exp_not ::= expr jmp_true . expr jump_forward_else expr COME_FROM
if_exp_not ::= expr jmp_true expr . jump_forward_else expr COME_FROM
if_exp_not_lambda ::= expr . jmp_true expr return_if_lambda return_stmt_lambda LAMBDA_MARKER
if_exp_not_lambda ::= expr jmp_true . expr return_if_lambda return_stmt_lambda LAMBDA_MARKER
if_exp_not_lambda ::= expr jmp_true expr . return_if_lambda return_stmt_lambda LAMBDA_MARKER
if_exp_true ::= expr . JUMP_FORWARD expr COME_FROM
ifelsestmt ::= testexpr . c_stmts come_froms else_suite come_froms
ifelsestmt ::= testexpr . c_stmts_opt JUMP_FORWARD else_suite \e__come_froms
ifelsestmt ::= testexpr . c_stmts_opt JUMP_FORWARD else_suite \e_opt_come_from_except
ifelsestmt ::= testexpr . c_stmts_opt JUMP_FORWARD else_suite _come_froms
ifelsestmt ::= testexpr . c_stmts_opt JUMP_FORWARD else_suite opt_come_from_except
ifelsestmt ::= testexpr . c_stmts_opt jf_cfs else_suite \e_opt_come_from_except
ifelsestmt ::= testexpr . c_stmts_opt jf_cfs else_suite opt_come_from_except
ifelsestmt ::= testexpr . c_stmts_opt jump_forward_else else_suite \e__come_froms
ifelsestmt ::= testexpr . c_stmts_opt jump_forward_else else_suite _come_froms
ifelsestmt ::= testexpr . stmts jf_cfs \e_else_suite_opt \e_opt_come_from_except
ifelsestmt ::= testexpr . stmts jf_cfs \e_else_suite_opt opt_come_from_except
ifelsestmt ::= testexpr . stmts jf_cfs else_suite_opt \e_opt_come_from_except
ifelsestmt ::= testexpr . stmts jf_cfs else_suite_opt opt_come_from_except
ifelsestmt ::= testexpr \e_c_stmts_opt . JUMP_FORWARD else_suite \e__come_froms
ifelsestmt ::= testexpr \e_c_stmts_opt . JUMP_FORWARD else_suite \e_opt_come_from_except
ifelsestmt ::= testexpr \e_c_stmts_opt . JUMP_FORWARD else_suite _come_froms
ifelsestmt ::= testexpr \e_c_stmts_opt . JUMP_FORWARD else_suite opt_come_from_except
ifelsestmt ::= testexpr \e_c_stmts_opt . jf_cfs else_suite \e_opt_come_from_except
ifelsestmt ::= testexpr \e_c_stmts_opt . jf_cfs else_suite opt_come_from_except
ifelsestmt ::= testexpr \e_c_stmts_opt . jump_forward_else else_suite \e__come_froms
ifelsestmt ::= testexpr \e_c_stmts_opt . jump_forward_else else_suite _come_froms
ifelsestmtc ::= testexpr . c_stmts_opt JUMP_ABSOLUTE else_suitec
ifelsestmtc ::= testexpr . c_stmts_opt JUMP_FORWARD else_suitec
ifelsestmtc ::= testexpr . c_stmts_opt jump_absolute_else else_suitec
ifelsestmtc ::= testexpr \e_c_stmts_opt . JUMP_ABSOLUTE else_suitec
ifelsestmtc ::= testexpr \e_c_stmts_opt . JUMP_FORWARD else_suitec
ifelsestmtc ::= testexpr \e_c_stmts_opt . jump_absolute_else else_suitec
ifelsestmtl ::= testexpr . c_stmts_opt cf_jf_else else_suitel
ifelsestmtl ::= testexpr . c_stmts_opt cf_jump_back else_suitel
ifelsestmtl ::= testexpr . c_stmts_opt jb_cfs else_suitel
ifelsestmtl ::= testexpr . c_stmts_opt jb_else else_suitel
ifelsestmtl ::= testexpr . c_stmts_opt jump_forward_else else_suitec
ifelsestmtl ::= testexpr \e_c_stmts_opt . cf_jf_else else_suitel
ifelsestmtl ::= testexpr \e_c_stmts_opt . cf_jump_back else_suitel
ifelsestmtl ::= testexpr \e_c_stmts_opt . jb_cfs else_suitel
ifelsestmtl ::= testexpr \e_c_stmts_opt . jb_else else_suitel
ifelsestmtl ::= testexpr \e_c_stmts_opt . jump_forward_else else_suitec
ifelsestmtl ::= testexpr_cf . c_stmts_opt jb_else else_suitel
ifelsestmtl ::= testexpr_cf \e_c_stmts_opt . jb_else else_suitel
ifelsestmtl ::= testexpr_cf c_stmts_opt . jb_else else_suitel
ifelsestmtr ::= testexpr . return_if_stmts returns
iflaststmt ::= testexpr . c_stmts
iflaststmt ::= testexpr . c_stmts JUMP_ABSOLUTE
iflaststmt ::= testexpr . c_stmts_opt JUMP_FORWARD
iflaststmt ::= testexpr \e_c_stmts_opt . JUMP_FORWARD
iflaststmtl ::= testexpr . c_stmts
iflaststmtl ::= testexpr . c_stmts JUMP_BACK
iflaststmtl ::= testexpr . c_stmts JUMP_BACK COME_FROM_LOOP
iflaststmtl ::= testexpr . c_stmts JUMP_BACK POP_BLOCK
iflaststmtl ::= testexprl . c_stmts JUMP_BACK
iflaststmtl ::= testexprl . c_stmts JUMP_BACK COME_FROM_LOOP
iflaststmtl ::= testexprl . c_stmts JUMP_BACK POP_BLOCK
ifstmt ::= testexpr . _ifstmts_jump
ifstmtl ::= testexpr . _ifstmts_jumpl
jb_cfs ::= \e_come_from_opt . JUMP_BACK come_froms
jb_cfs ::= come_from_opt . JUMP_BACK come_froms
jmp_true ::= POP_JUMP_IF_TRUE . 
jump_absolute_else ::= come_froms . _jump COME_FROM
lambda_body ::= expr . LOAD_LAMBDA LOAD_STR MAKE_FUNCTION_1
lambda_body ::= expr . expr LOAD_LAMBDA LOAD_STR MAKE_FUNCTION_5
lambda_body ::= expr expr . LOAD_LAMBDA LOAD_STR MAKE_FUNCTION_5
mkfunc ::= expr . LOAD_CODE LOAD_STR MAKE_FUNCTION_1
mkfunc ::= expr . expr LOAD_CODE LOAD_STR MAKE_FUNCTION_5
mkfunc ::= expr expr . LOAD_CODE LOAD_STR MAKE_FUNCTION_5
mkfuncdeco ::= expr . mkfuncdeco CALL_FUNCTION_1
mkfuncdeco ::= expr . mkfuncdeco0 CALL_FUNCTION_1
or ::= expr_jt . expr
or ::= expr_jt . expr COME_FROM
or ::= expr_jt expr . 
or ::= expr_jt expr . COME_FROM
or ::= expr_pjit . expr POP_JUMP_IF_FALSE COME_FROM
or ::= expr_pjit expr . POP_JUMP_IF_FALSE COME_FROM
or ::= expr_pjit_come_from . expr
pos_arg ::= expr . 
ret_and ::= expr . JUMP_IF_FALSE_OR_POP return_expr_or_cond COME_FROM
ret_or ::= expr . JUMP_IF_TRUE_OR_POP return_expr_or_cond COME_FROM
return ::= return_expr . RETURN_END_IF
return ::= return_expr . RETURN_VALUE
return ::= return_expr . RETURN_VALUE COME_FROM
return_expr ::= expr . 
return_expr_lambda ::= return_expr . RETURN_VALUE_LAMBDA
return_expr_lambda ::= return_expr . RETURN_VALUE_LAMBDA LAMBDA_MARKER
return_if_stmt ::= return_expr . RETURN_END_IF
return_if_stmt ::= return_expr . RETURN_END_IF POP_BLOCK
sstmt ::= sstmt . RETURN_LAST
sstmt ::= stmt . 
stmt ::= assign . 
stmt ::= call_stmt . 
stmt ::= expr_stmt . 
stmts ::= sstmt . 
stmts ::= stmts . sstmt
store ::= STORE_FAST . 
store ::= expr . STORE_ATTR
store_subscript ::= expr . expr STORE_SUBSCR
store_subscript ::= expr expr . STORE_SUBSCR
subscript ::= expr . expr BINARY_SUBSCR
subscript ::= expr expr . BINARY_SUBSCR
subscript2 ::= expr . expr DUP_TOP_TWO BINARY_SUBSCR
subscript2 ::= expr expr . DUP_TOP_TWO BINARY_SUBSCR
testexpr ::= testtrue . 
testexpr_cf ::= testexpr . come_froms
testexpr_cf ::= testexpr come_froms . 
testexprl ::= testfalsel . 
testfalse ::= expr . jmp_false
testfalse ::= or . jmp_false COME_FROM
testfalse_not_and ::= expr . jmp_false expr jmp_true COME_FROM
testfalse_not_or ::= expr . jmp_false expr jmp_false COME_FROM
testfalsel ::= expr . jmp_true
testfalsel ::= expr jmp_true . 
testtrue ::= expr . jmp_true
testtrue ::= expr jmp_true . 
unary_not ::= expr . UNARY_NOT
unary_op ::= expr . unary_operator
yield ::= expr . YIELD_VALUE
yield_from ::= expr . GET_YIELD_FROM_ITER LOAD_CONST YIELD_FROM
Instruction context:
   
 L.  29        54  LOAD_GLOBAL              sims4
                  56  LOAD_ATTR                commands
                  58  LOAD_METHOD              cheat_output
                  60  LOAD_STR                 '{} not enacted'
                  62  LOAD_METHOD              format
                  64  LOAD_FAST                'policy'
                  66  CALL_METHOD_1         1  '1 positional argument'
                  68  LOAD_FAST                '_connection'
                  70  CALL_METHOD_2         2  '2 positional arguments'
                  72  POP_TOP          
->                74  JUMP_FORWARD         90  'to 90'
                76_0  COME_FROM            38  '38'

-- Stacks of completed symbols:
START ::= |- stmts . 
_ifstmts_jump ::= COME_FROM . c_stmts come_froms
_ifstmts_jump ::= \e_c_stmts_opt . COME_FROM
_ifstmts_jump ::= \e_c_stmts_opt . ELSE
_ifstmts_jump ::= \e_c_stmts_opt . JUMP_ABSOLUTE JUMP_FORWARD \e__come_froms
_ifstmts_jump ::= \e_c_stmts_opt . JUMP_ABSOLUTE JUMP_FORWARD _come_froms
_ifstmts_jump ::= \e_c_stmts_opt . come_froms
_ifstmts_jump ::= \e_c_stmts_opt COME_FROM . 
_ifstmts_jump ::= \e_c_stmts_opt come_froms . 
_ifstmts_jumpl ::= COME_FROM . c_stmts JUMP_BACK
_ifstmts_jumpl ::= COME_FROM . c_stmts JUMP_FORWARD
_stmts ::= _stmts . stmt
_stmts ::= _stmts stmt . 
_stmts ::= stmt . 
and ::= expr . JUMP_IF_FALSE_OR_POP expr \e_come_from_opt
and ::= expr . JUMP_IF_FALSE_OR_POP expr come_from_opt
and ::= expr . jifop_come_from expr
and ::= expr . jmp_false expr
and ::= expr . jmp_false expr COME_FROM
and ::= expr . jmp_false expr jmp_false
and_not ::= expr . jmp_false expr POP_JUMP_IF_TRUE
assert2 ::= expr . jmp_true LOAD_GLOBAL expr CALL_FUNCTION_1 RAISE_VARARGS_1
assert2 ::= expr jmp_true . LOAD_GLOBAL expr CALL_FUNCTION_1 RAISE_VARARGS_1
assert_invert ::= testtrue . LOAD_GLOBAL RAISE_VARARGS_1
assign ::= expr . DUP_TOP designList
assign ::= expr . store
assign ::= expr store . 
assign2 ::= expr . expr ROT_TWO store store
assign2 ::= expr expr . ROT_TWO store store
assign3 ::= expr . expr expr ROT_THREE ROT_TWO store store store
assign3 ::= expr expr . expr ROT_THREE ROT_TWO store store store
assign3 ::= expr expr expr . ROT_THREE ROT_TWO store store store
attribute ::= expr . LOAD_ATTR
attribute ::= expr LOAD_ATTR . 
attribute37 ::= expr . LOAD_METHOD
attribute37 ::= expr LOAD_METHOD . 
aug_assign1 ::= expr . expr inplace_op ROT_THREE STORE_SUBSCR
aug_assign1 ::= expr . expr inplace_op store
aug_assign1 ::= expr expr . inplace_op ROT_THREE STORE_SUBSCR
aug_assign1 ::= expr expr . inplace_op store
aug_assign2 ::= expr . DUP_TOP LOAD_ATTR expr inplace_op ROT_TWO STORE_ATTR
await_expr ::= expr . GET_AWAITABLE LOAD_CONST YIELD_FROM
bin_op ::= expr . expr binary_operator
bin_op ::= expr expr . binary_operator
c_stmts ::= _stmts . 
c_stmts ::= _stmts . lastc_stmt
c_stmts_opt ::= c_stmts . 
call ::= expr . CALL_METHOD_0
call ::= expr . expr CALL_METHOD_1
call ::= expr . expr expr CALL_METHOD_2
call ::= expr . pos_arg CALL_FUNCTION_1
call ::= expr CALL_METHOD_0 . 
call ::= expr expr . CALL_METHOD_1
call ::= expr expr . expr CALL_METHOD_2
call ::= expr expr CALL_METHOD_1 . 
call ::= expr expr expr . CALL_METHOD_2
call ::= expr expr expr CALL_METHOD_2 . 
call ::= expr pos_arg . CALL_FUNCTION_1
call_kw36 ::= expr . expr expr expr LOAD_CONST CALL_FUNCTION_KW_3
call_kw36 ::= expr expr . expr expr LOAD_CONST CALL_FUNCTION_KW_3
call_kw36 ::= expr expr expr . expr LOAD_CONST CALL_FUNCTION_KW_3
call_stmt ::= expr . POP_TOP
call_stmt ::= expr POP_TOP . 
cf_jf_else ::= come_froms . JUMP_FORWARD ELSE
cf_jump_back ::= COME_FROM . JUMP_BACK
classdefdeco1 ::= expr . classdefdeco1 CALL_FUNCTION_1
classdefdeco1 ::= expr . classdefdeco2 CALL_FUNCTION_1
come_from_opt ::= COME_FROM . 
come_froms ::= COME_FROM . 
come_froms ::= come_froms . COME_FROM
come_froms ::= come_froms COME_FROM . 
compare ::= compare_single . 
compare_chained ::= expr . compare_chained1 ROT_TWO POP_TOP \e__come_froms
compare_chained ::= expr . compare_chained1 ROT_TWO POP_TOP _come_froms
compare_chained1 ::= expr . DUP_TOP ROT_THREE COMPARE_OP JUMP_IF_FALSE_OR_POP compare_chained1 COME_FROM
compare_chained1 ::= expr . DUP_TOP ROT_THREE COMPARE_OP JUMP_IF_FALSE_OR_POP compare_chained2 COME_FROM
compare_chained1_false_37 ::= expr . DUP_TOP ROT_THREE COMPARE_OP POP_JUMP_IF_FALSE compare_chained2b_false_37 POP_TOP _jump COME_FROM
compare_chained1_false_37 ::= expr . DUP_TOP ROT_THREE COMPARE_OP POP_JUMP_IF_FALSE compare_chained2c_37 POP_TOP JUMP_FORWARD COME_FROM
compare_chained1a_37 ::= expr . DUP_TOP ROT_THREE COMPARE_OP POP_JUMP_IF_FALSE
compare_chained1a_37 ::= expr . DUP_TOP ROT_THREE COMPARE_OP POP_JUMP_IF_FALSE compare_chained2a_37 COME_FROM POP_TOP COME_FROM
compare_chained1b_false_37 ::= expr . DUP_TOP ROT_THREE COMPARE_OP POP_JUMP_IF_FALSE compare_chained2b_false_37 POP_TOP _jump COME_FROM
compare_chained1c_37 ::= expr . DUP_TOP ROT_THREE COMPARE_OP POP_JUMP_IF_FALSE compare_chained2a_37 POP_TOP
compare_chained2_false_37 ::= expr . DUP_TOP ROT_THREE COMPARE_OP POP_JUMP_IF_FALSE compare_chained2a_false_37 POP_TOP JUMP_BACK COME_FROM
compare_chained37 ::= expr . compare_chained1a_37
compare_chained37 ::= expr . compare_chained1c_37
compare_chained37_false ::= expr . compare_chained1_false_37
compare_chained37_false ::= expr . compare_chained1b_false_37
compare_chained37_false ::= expr . compare_chained2_false_37
compare_single ::= expr . expr COMPARE_OP
compare_single ::= expr expr . COMPARE_OP
compare_single ::= expr expr COMPARE_OP . 
continues ::= _stmts . lastl_stmt continue
dict ::= expr . LOAD_CONST BUILD_CONST_KEY_MAP_1
dict ::= expr . expr LOAD_CONST BUILD_CONST_KEY_MAP_2
dict ::= expr LOAD_CONST . BUILD_CONST_KEY_MAP_1
dict ::= expr expr . LOAD_CONST BUILD_CONST_KEY_MAP_2
expr ::= LOAD_CONST . 
expr ::= LOAD_FAST . 
expr ::= LOAD_GLOBAL . 
expr ::= LOAD_STR . 
expr ::= attribute . 
expr ::= attribute37 . 
expr ::= call . 
expr ::= compare . 
expr ::= or . 
expr_jit ::= expr . JUMP_IF_TRUE
expr_jitop ::= expr . JUMP_IF_TRUE_OR_POP
expr_jt ::= expr . jmp_true
expr_jt ::= expr jmp_true . 
expr_pjit ::= expr . POP_JUMP_IF_TRUE
expr_pjit ::= expr POP_JUMP_IF_TRUE . 
expr_pjit_come_from ::= expr . POP_JUMP_IF_TRUE COME_FROM
expr_pjit_come_from ::= expr POP_JUMP_IF_TRUE . COME_FROM
expr_pjit_come_from ::= expr POP_JUMP_IF_TRUE COME_FROM . 
expr_stmt ::= expr . POP_TOP
expr_stmt ::= expr POP_TOP . 
if_exp ::= expr . jmp_false expr jf_cf expr COME_FROM
if_exp ::= expr . jmp_false expr jump_absolute_else expr
if_exp37 ::= expr . expr jf_cfs expr COME_FROM
if_exp37 ::= expr expr . jf_cfs expr COME_FROM
if_exp_37b ::= expr . jmp_false expr POP_JUMP_IF_FALSE jump_forward_else expr
if_exp_lambda ::= expr . jmp_false expr return_if_lambda return_stmt_lambda LAMBDA_MARKER
if_exp_not ::= expr . jmp_true expr jump_forward_else expr COME_FROM
if_exp_not ::= expr jmp_true . expr jump_forward_else expr COME_FROM
if_exp_not ::= expr jmp_true expr . jump_forward_else expr COME_FROM
if_exp_not_lambda ::= expr . jmp_true expr return_if_lambda return_stmt_lambda LAMBDA_MARKER
if_exp_not_lambda ::= expr jmp_true . expr return_if_lambda return_stmt_lambda LAMBDA_MARKER
if_exp_not_lambda ::= expr jmp_true expr . return_if_lambda return_stmt_lambda LAMBDA_MARKER
if_exp_true ::= expr . JUMP_FORWARD expr COME_FROM
ifelsestmt ::= testexpr . c_stmts come_froms else_suite come_froms
ifelsestmt ::= testexpr . c_stmts_opt JUMP_FORWARD else_suite \e__come_froms
ifelsestmt ::= testexpr . c_stmts_opt JUMP_FORWARD else_suite \e_opt_come_from_except
ifelsestmt ::= testexpr . c_stmts_opt JUMP_FORWARD else_suite _come_froms
ifelsestmt ::= testexpr . c_stmts_opt JUMP_FORWARD else_suite opt_come_from_except
ifelsestmt ::= testexpr . c_stmts_opt jf_cfs else_suite \e_opt_come_from_except
ifelsestmt ::= testexpr . c_stmts_opt jf_cfs else_suite opt_come_from_except
ifelsestmt ::= testexpr . c_stmts_opt jump_forward_else else_suite \e__come_froms
ifelsestmt ::= testexpr . c_stmts_opt jump_forward_else else_suite _come_froms
ifelsestmt ::= testexpr . stmts jf_cfs \e_else_suite_opt \e_opt_come_from_except
ifelsestmt ::= testexpr . stmts jf_cfs \e_else_suite_opt opt_come_from_except
ifelsestmt ::= testexpr . stmts jf_cfs else_suite_opt \e_opt_come_from_except
ifelsestmt ::= testexpr . stmts jf_cfs else_suite_opt opt_come_from_except
ifelsestmt ::= testexpr \e_c_stmts_opt . JUMP_FORWARD else_suite \e__come_froms
ifelsestmt ::= testexpr \e_c_stmts_opt . JUMP_FORWARD else_suite \e_opt_come_from_except
ifelsestmt ::= testexpr \e_c_stmts_opt . JUMP_FORWARD else_suite _come_froms
ifelsestmt ::= testexpr \e_c_stmts_opt . JUMP_FORWARD else_suite opt_come_from_except
ifelsestmt ::= testexpr \e_c_stmts_opt . jf_cfs else_suite \e_opt_come_from_except
ifelsestmt ::= testexpr \e_c_stmts_opt . jf_cfs else_suite opt_come_from_except
ifelsestmt ::= testexpr \e_c_stmts_opt . jump_forward_else else_suite \e__come_froms
ifelsestmt ::= testexpr \e_c_stmts_opt . jump_forward_else else_suite _come_froms
ifelsestmtc ::= testexpr . c_stmts_opt JUMP_ABSOLUTE else_suitec
ifelsestmtc ::= testexpr . c_stmts_opt JUMP_FORWARD else_suitec
ifelsestmtc ::= testexpr . c_stmts_opt jump_absolute_else else_suitec
ifelsestmtc ::= testexpr \e_c_stmts_opt . JUMP_ABSOLUTE else_suitec
ifelsestmtc ::= testexpr \e_c_stmts_opt . JUMP_FORWARD else_suitec
ifelsestmtc ::= testexpr \e_c_stmts_opt . jump_absolute_else else_suitec
ifelsestmtl ::= testexpr . c_stmts_opt cf_jf_else else_suitel
ifelsestmtl ::= testexpr . c_stmts_opt cf_jump_back else_suitel
ifelsestmtl ::= testexpr . c_stmts_opt jb_cfs else_suitel
ifelsestmtl ::= testexpr . c_stmts_opt jb_else else_suitel
ifelsestmtl ::= testexpr . c_stmts_opt jump_forward_else else_suitec
ifelsestmtl ::= testexpr \e_c_stmts_opt . cf_jf_else else_suitel
ifelsestmtl ::= testexpr \e_c_stmts_opt . cf_jump_back else_suitel
ifelsestmtl ::= testexpr \e_c_stmts_opt . jb_cfs else_suitel
ifelsestmtl ::= testexpr \e_c_stmts_opt . jb_else else_suitel
ifelsestmtl ::= testexpr \e_c_stmts_opt . jump_forward_else else_suitec
ifelsestmtl ::= testexpr_cf . c_stmts_opt jb_else else_suitel
ifelsestmtl ::= testexpr_cf \e_c_stmts_opt . jb_else else_suitel
ifelsestmtl ::= testexpr_cf c_stmts_opt . jb_else else_suitel
ifelsestmtr ::= testexpr . return_if_stmts returns
iflaststmt ::= testexpr . c_stmts
iflaststmt ::= testexpr . c_stmts JUMP_ABSOLUTE
iflaststmt ::= testexpr . c_stmts_opt JUMP_FORWARD
iflaststmt ::= testexpr \e_c_stmts_opt . JUMP_FORWARD
iflaststmtl ::= testexpr . c_stmts
iflaststmtl ::= testexpr . c_stmts JUMP_BACK
iflaststmtl ::= testexpr . c_stmts JUMP_BACK COME_FROM_LOOP
iflaststmtl ::= testexpr . c_stmts JUMP_BACK POP_BLOCK
iflaststmtl ::= testexprl . c_stmts JUMP_BACK
iflaststmtl ::= testexprl . c_stmts JUMP_BACK COME_FROM_LOOP
iflaststmtl ::= testexprl . c_stmts JUMP_BACK POP_BLOCK
ifstmt ::= testexpr . _ifstmts_jump
ifstmtl ::= testexpr . _ifstmts_jumpl
jb_cfs ::= \e_come_from_opt . JUMP_BACK come_froms
jb_cfs ::= come_from_opt . JUMP_BACK come_froms
jmp_true ::= POP_JUMP_IF_TRUE . 
jump_absolute_else ::= come_froms . _jump COME_FROM
lambda_body ::= expr . LOAD_LAMBDA LOAD_STR MAKE_FUNCTION_1
lambda_body ::= expr . expr LOAD_LAMBDA LOAD_STR MAKE_FUNCTION_5
lambda_body ::= expr expr . LOAD_LAMBDA LOAD_STR MAKE_FUNCTION_5
mkfunc ::= expr . LOAD_CODE LOAD_STR MAKE_FUNCTION_1
mkfunc ::= expr . expr LOAD_CODE LOAD_STR MAKE_FUNCTION_5
mkfunc ::= expr expr . LOAD_CODE LOAD_STR MAKE_FUNCTION_5
mkfuncdeco ::= expr . mkfuncdeco CALL_FUNCTION_1
mkfuncdeco ::= expr . mkfuncdeco0 CALL_FUNCTION_1
or ::= expr_jt . expr
or ::= expr_jt . expr COME_FROM
or ::= expr_jt expr . 
or ::= expr_jt expr . COME_FROM
or ::= expr_pjit . expr POP_JUMP_IF_FALSE COME_FROM
or ::= expr_pjit expr . POP_JUMP_IF_FALSE COME_FROM
or ::= expr_pjit_come_from . expr
pos_arg ::= expr . 
ret_and ::= expr . JUMP_IF_FALSE_OR_POP return_expr_or_cond COME_FROM
ret_or ::= expr . JUMP_IF_TRUE_OR_POP return_expr_or_cond COME_FROM
return ::= return_expr . RETURN_END_IF
return ::= return_expr . RETURN_VALUE
return ::= return_expr . RETURN_VALUE COME_FROM
return_expr ::= expr . 
return_expr_lambda ::= return_expr . RETURN_VALUE_LAMBDA
return_expr_lambda ::= return_expr . RETURN_VALUE_LAMBDA LAMBDA_MARKER
return_if_stmt ::= return_expr . RETURN_END_IF
return_if_stmt ::= return_expr . RETURN_END_IF POP_BLOCK
sstmt ::= sstmt . RETURN_LAST
sstmt ::= stmt . 
stmt ::= assign . 
stmt ::= call_stmt . 
stmt ::= expr_stmt . 
stmts ::= sstmt . 
stmts ::= stmts . sstmt
store ::= STORE_FAST . 
store ::= expr . STORE_ATTR
store_subscript ::= expr . expr STORE_SUBSCR
store_subscript ::= expr expr . STORE_SUBSCR
subscript ::= expr . expr BINARY_SUBSCR
subscript ::= expr expr . BINARY_SUBSCR
subscript2 ::= expr . expr DUP_TOP_TWO BINARY_SUBSCR
subscript2 ::= expr expr . DUP_TOP_TWO BINARY_SUBSCR
testexpr ::= testtrue . 
testexpr_cf ::= testexpr . come_froms
testexpr_cf ::= testexpr come_froms . 
testexprl ::= testfalsel . 
testfalse ::= expr . jmp_false
testfalse ::= or . jmp_false COME_FROM
testfalse_not_and ::= expr . jmp_false expr jmp_true COME_FROM
testfalse_not_or ::= expr . jmp_false expr jmp_false COME_FROM
testfalsel ::= expr . jmp_true
testfalsel ::= expr jmp_true . 
testtrue ::= expr . jmp_true
testtrue ::= expr jmp_true . 
unary_not ::= expr . UNARY_NOT
unary_op ::= expr . unary_operator
yield ::= expr . YIELD_VALUE
yield_from ::= expr . GET_YIELD_FROM_ITER LOAD_CONST YIELD_FROM
Instruction context:
   
 L.  44        54  LOAD_GLOBAL              sims4
                  56  LOAD_ATTR                commands
                  58  LOAD_METHOD              cheat_output
                  60  LOAD_STR                 '{} not repealed'
                  62  LOAD_METHOD              format
                  64  LOAD_FAST                'policy'
                  66  CALL_METHOD_1         1  '1 positional argument'
                  68  LOAD_FAST                '_connection'
                  70  CALL_METHOD_2         2  '2 positional arguments'
                  72  POP_TOP          
->                74  JUMP_FORWARD         90  'to 90'
                76_0  COME_FROM            38  '38'

-- Stacks of completed symbols:
START ::= |- stmts . 
_ifstmts_jump ::= COME_FROM . c_stmts come_froms
_ifstmts_jump ::= \e_c_stmts_opt . COME_FROM
_ifstmts_jump ::= \e_c_stmts_opt . ELSE
_ifstmts_jump ::= \e_c_stmts_opt . JUMP_ABSOLUTE JUMP_FORWARD \e__come_froms
_ifstmts_jump ::= \e_c_stmts_opt . JUMP_ABSOLUTE JUMP_FORWARD _come_froms
_ifstmts_jump ::= \e_c_stmts_opt . come_froms
_ifstmts_jump ::= \e_c_stmts_opt COME_FROM . 
_ifstmts_jump ::= \e_c_stmts_opt come_froms . 
_ifstmts_jumpl ::= COME_FROM . c_stmts JUMP_BACK
_ifstmts_jumpl ::= COME_FROM . c_stmts JUMP_FORWARD
_stmts ::= _stmts . stmt
_stmts ::= _stmts stmt . 
_stmts ::= stmt . 
and ::= expr . JUMP_IF_FALSE_OR_POP expr \e_come_from_opt
and ::= expr . JUMP_IF_FALSE_OR_POP expr come_from_opt
and ::= expr . jifop_come_from expr
and ::= expr . jmp_false expr
and ::= expr . jmp_false expr COME_FROM
and ::= expr . jmp_false expr jmp_false
and_not ::= expr . jmp_false expr POP_JUMP_IF_TRUE
assert2 ::= expr . jmp_true LOAD_GLOBAL expr CALL_FUNCTION_1 RAISE_VARARGS_1
assert2 ::= expr jmp_true . LOAD_GLOBAL expr CALL_FUNCTION_1 RAISE_VARARGS_1
assert_invert ::= testtrue . LOAD_GLOBAL RAISE_VARARGS_1
assign ::= expr . DUP_TOP designList
assign ::= expr . store
assign ::= expr store . 
assign2 ::= expr . expr ROT_TWO store store
assign2 ::= expr expr . ROT_TWO store store
assign3 ::= expr . expr expr ROT_THREE ROT_TWO store store store
assign3 ::= expr expr . expr ROT_THREE ROT_TWO store store store
assign3 ::= expr expr expr . ROT_THREE ROT_TWO store store store
attribute ::= expr . LOAD_ATTR
attribute ::= expr LOAD_ATTR . 
attribute37 ::= expr . LOAD_METHOD
attribute37 ::= expr LOAD_METHOD . 
aug_assign1 ::= expr . expr inplace_op ROT_THREE STORE_SUBSCR
aug_assign1 ::= expr . expr inplace_op store
aug_assign1 ::= expr expr . inplace_op ROT_THREE STORE_SUBSCR
aug_assign1 ::= expr expr . inplace_op store
aug_assign2 ::= expr . DUP_TOP LOAD_ATTR expr inplace_op ROT_TWO STORE_ATTR
await_expr ::= expr . GET_AWAITABLE LOAD_CONST YIELD_FROM
bin_op ::= expr . expr binary_operator
bin_op ::= expr expr . binary_operator
c_stmts ::= _stmts . 
c_stmts ::= _stmts . lastc_stmt
c_stmts_opt ::= c_stmts . 
call ::= expr . CALL_METHOD_0
call ::= expr . expr CALL_METHOD_1
call ::= expr . expr expr CALL_METHOD_2
call ::= expr . pos_arg CALL_FUNCTION_1
call ::= expr CALL_METHOD_0 . 
call ::= expr expr . CALL_METHOD_1
call ::= expr expr . expr CALL_METHOD_2
call ::= expr expr CALL_METHOD_1 . 
call ::= expr expr expr . CALL_METHOD_2
call ::= expr expr expr CALL_METHOD_2 . 
call ::= expr pos_arg . CALL_FUNCTION_1
call ::= expr pos_arg CALL_FUNCTION_1 . 
call_kw36 ::= expr . expr expr expr LOAD_CONST CALL_FUNCTION_KW_3
call_kw36 ::= expr expr . expr expr LOAD_CONST CALL_FUNCTION_KW_3
call_kw36 ::= expr expr expr . expr LOAD_CONST CALL_FUNCTION_KW_3
call_stmt ::= expr . POP_TOP
call_stmt ::= expr POP_TOP . 
cf_jf_else ::= come_froms . JUMP_FORWARD ELSE
cf_jump_back ::= COME_FROM . JUMP_BACK
classdefdeco1 ::= expr . classdefdeco1 CALL_FUNCTION_1
classdefdeco1 ::= expr . classdefdeco2 CALL_FUNCTION_1
come_from_opt ::= COME_FROM . 
come_froms ::= COME_FROM . 
come_froms ::= come_froms . COME_FROM
come_froms ::= come_froms COME_FROM . 
compare ::= compare_single . 
compare_chained ::= expr . compare_chained1 ROT_TWO POP_TOP \e__come_froms
compare_chained ::= expr . compare_chained1 ROT_TWO POP_TOP _come_froms
compare_chained1 ::= expr . DUP_TOP ROT_THREE COMPARE_OP JUMP_IF_FALSE_OR_POP compare_chained1 COME_FROM
compare_chained1 ::= expr . DUP_TOP ROT_THREE COMPARE_OP JUMP_IF_FALSE_OR_POP compare_chained2 COME_FROM
compare_chained1_false_37 ::= expr . DUP_TOP ROT_THREE COMPARE_OP POP_JUMP_IF_FALSE compare_chained2b_false_37 POP_TOP _jump COME_FROM
compare_chained1_false_37 ::= expr . DUP_TOP ROT_THREE COMPARE_OP POP_JUMP_IF_FALSE compare_chained2c_37 POP_TOP JUMP_FORWARD COME_FROM
compare_chained1a_37 ::= expr . DUP_TOP ROT_THREE COMPARE_OP POP_JUMP_IF_FALSE
compare_chained1a_37 ::= expr . DUP_TOP ROT_THREE COMPARE_OP POP_JUMP_IF_FALSE compare_chained2a_37 COME_FROM POP_TOP COME_FROM
compare_chained1b_false_37 ::= expr . DUP_TOP ROT_THREE COMPARE_OP POP_JUMP_IF_FALSE compare_chained2b_false_37 POP_TOP _jump COME_FROM
compare_chained1c_37 ::= expr . DUP_TOP ROT_THREE COMPARE_OP POP_JUMP_IF_FALSE compare_chained2a_37 POP_TOP
compare_chained2_false_37 ::= expr . DUP_TOP ROT_THREE COMPARE_OP POP_JUMP_IF_FALSE compare_chained2a_false_37 POP_TOP JUMP_BACK COME_FROM
compare_chained37 ::= expr . compare_chained1a_37
compare_chained37 ::= expr . compare_chained1c_37
compare_chained37_false ::= expr . compare_chained1_false_37
compare_chained37_false ::= expr . compare_chained1b_false_37
compare_chained37_false ::= expr . compare_chained2_false_37
compare_single ::= expr . expr COMPARE_OP
compare_single ::= expr expr . COMPARE_OP
compare_single ::= expr expr COMPARE_OP . 
continues ::= _stmts . lastl_stmt continue
dict ::= expr . LOAD_CONST BUILD_CONST_KEY_MAP_1
dict ::= expr . expr LOAD_CONST BUILD_CONST_KEY_MAP_2
dict ::= expr LOAD_CONST . BUILD_CONST_KEY_MAP_1
dict ::= expr expr . LOAD_CONST BUILD_CONST_KEY_MAP_2
expr ::= LOAD_CONST . 
expr ::= LOAD_FAST . 
expr ::= LOAD_GLOBAL . 
expr ::= LOAD_STR . 
expr ::= attribute . 
expr ::= attribute37 . 
expr ::= call . 
expr ::= compare . 
expr ::= or . 
expr_jit ::= expr . JUMP_IF_TRUE
expr_jitop ::= expr . JUMP_IF_TRUE_OR_POP
expr_jt ::= expr . jmp_true
expr_jt ::= expr jmp_true . 
expr_pjit ::= expr . POP_JUMP_IF_TRUE
expr_pjit ::= expr POP_JUMP_IF_TRUE . 
expr_pjit_come_from ::= expr . POP_JUMP_IF_TRUE COME_FROM
expr_pjit_come_from ::= expr POP_JUMP_IF_TRUE . COME_FROM
expr_pjit_come_from ::= expr POP_JUMP_IF_TRUE COME_FROM . 
expr_stmt ::= expr . POP_TOP
expr_stmt ::= expr POP_TOP . 
if_exp ::= expr . jmp_false expr jf_cf expr COME_FROM
if_exp ::= expr . jmp_false expr jump_absolute_else expr
if_exp37 ::= expr . expr jf_cfs expr COME_FROM
if_exp37 ::= expr expr . jf_cfs expr COME_FROM
if_exp_37b ::= expr . jmp_false expr POP_JUMP_IF_FALSE jump_forward_else expr
if_exp_lambda ::= expr . jmp_false expr return_if_lambda return_stmt_lambda LAMBDA_MARKER
if_exp_not ::= expr . jmp_true expr jump_forward_else expr COME_FROM
if_exp_not ::= expr jmp_true . expr jump_forward_else expr COME_FROM
if_exp_not ::= expr jmp_true expr . jump_forward_else expr COME_FROM
if_exp_not_lambda ::= expr . jmp_true expr return_if_lambda return_stmt_lambda LAMBDA_MARKER
if_exp_not_lambda ::= expr jmp_true . expr return_if_lambda return_stmt_lambda LAMBDA_MARKER
if_exp_not_lambda ::= expr jmp_true expr . return_if_lambda return_stmt_lambda LAMBDA_MARKER
if_exp_true ::= expr . JUMP_FORWARD expr COME_FROM
ifelsestmt ::= testexpr . c_stmts come_froms else_suite come_froms
ifelsestmt ::= testexpr . c_stmts_opt JUMP_FORWARD else_suite \e__come_froms
ifelsestmt ::= testexpr . c_stmts_opt JUMP_FORWARD else_suite \e_opt_come_from_except
ifelsestmt ::= testexpr . c_stmts_opt JUMP_FORWARD else_suite _come_froms
ifelsestmt ::= testexpr . c_stmts_opt JUMP_FORWARD else_suite opt_come_from_except
ifelsestmt ::= testexpr . c_stmts_opt jf_cfs else_suite \e_opt_come_from_except
ifelsestmt ::= testexpr . c_stmts_opt jf_cfs else_suite opt_come_from_except
ifelsestmt ::= testexpr . c_stmts_opt jump_forward_else else_suite \e__come_froms
ifelsestmt ::= testexpr . c_stmts_opt jump_forward_else else_suite _come_froms
ifelsestmt ::= testexpr . stmts jf_cfs \e_else_suite_opt \e_opt_come_from_except
ifelsestmt ::= testexpr . stmts jf_cfs \e_else_suite_opt opt_come_from_except
ifelsestmt ::= testexpr . stmts jf_cfs else_suite_opt \e_opt_come_from_except
ifelsestmt ::= testexpr . stmts jf_cfs else_suite_opt opt_come_from_except
ifelsestmt ::= testexpr \e_c_stmts_opt . JUMP_FORWARD else_suite \e__come_froms
ifelsestmt ::= testexpr \e_c_stmts_opt . JUMP_FORWARD else_suite \e_opt_come_from_except
ifelsestmt ::= testexpr \e_c_stmts_opt . JUMP_FORWARD else_suite _come_froms
ifelsestmt ::= testexpr \e_c_stmts_opt . JUMP_FORWARD else_suite opt_come_from_except
ifelsestmt ::= testexpr \e_c_stmts_opt . jf_cfs else_suite \e_opt_come_from_except
ifelsestmt ::= testexpr \e_c_stmts_opt . jf_cfs else_suite opt_come_from_except
ifelsestmt ::= testexpr \e_c_stmts_opt . jump_forward_else else_suite \e__come_froms
ifelsestmt ::= testexpr \e_c_stmts_opt . jump_forward_else else_suite _come_froms
ifelsestmtc ::= testexpr . c_stmts_opt JUMP_ABSOLUTE else_suitec
ifelsestmtc ::= testexpr . c_stmts_opt JUMP_FORWARD else_suitec
ifelsestmtc ::= testexpr . c_stmts_opt jump_absolute_else else_suitec
ifelsestmtc ::= testexpr \e_c_stmts_opt . JUMP_ABSOLUTE else_suitec
ifelsestmtc ::= testexpr \e_c_stmts_opt . JUMP_FORWARD else_suitec
ifelsestmtc ::= testexpr \e_c_stmts_opt . jump_absolute_else else_suitec
ifelsestmtl ::= testexpr . c_stmts_opt cf_jf_else else_suitel
ifelsestmtl ::= testexpr . c_stmts_opt cf_jump_back else_suitel
ifelsestmtl ::= testexpr . c_stmts_opt jb_cfs else_suitel
ifelsestmtl ::= testexpr . c_stmts_opt jb_else else_suitel
ifelsestmtl ::= testexpr . c_stmts_opt jump_forward_else else_suitec
ifelsestmtl ::= testexpr \e_c_stmts_opt . cf_jf_else else_suitel
ifelsestmtl ::= testexpr \e_c_stmts_opt . cf_jump_back else_suitel
ifelsestmtl ::= testexpr \e_c_stmts_opt . jb_cfs else_suitel
ifelsestmtl ::= testexpr \e_c_stmts_opt . jb_else else_suitel
ifelsestmtl ::= testexpr \e_c_stmts_opt . jump_forward_else else_suitec
ifelsestmtl ::= testexpr_cf . c_stmts_opt jb_else else_suitel
ifelsestmtl ::= testexpr_cf \e_c_stmts_opt . jb_else else_suitel
ifelsestmtl ::= testexpr_cf c_stmts_opt . jb_else else_suitel
ifelsestmtr ::= testexpr . return_if_stmts returns
iflaststmt ::= testexpr . c_stmts
iflaststmt ::= testexpr . c_stmts JUMP_ABSOLUTE
iflaststmt ::= testexpr . c_stmts_opt JUMP_FORWARD
iflaststmt ::= testexpr \e_c_stmts_opt . JUMP_FORWARD
iflaststmtl ::= testexpr . c_stmts
iflaststmtl ::= testexpr . c_stmts JUMP_BACK
iflaststmtl ::= testexpr . c_stmts JUMP_BACK COME_FROM_LOOP
iflaststmtl ::= testexpr . c_stmts JUMP_BACK POP_BLOCK
iflaststmtl ::= testexprl . c_stmts JUMP_BACK
iflaststmtl ::= testexprl . c_stmts JUMP_BACK COME_FROM_LOOP
iflaststmtl ::= testexprl . c_stmts JUMP_BACK POP_BLOCK
ifstmt ::= testexpr . _ifstmts_jump
ifstmtl ::= testexpr . _ifstmts_jumpl
jb_cfs ::= \e_come_from_opt . JUMP_BACK come_froms
jb_cfs ::= come_from_opt . JUMP_BACK come_froms
jmp_true ::= POP_JUMP_IF_TRUE . 
jump_absolute_else ::= come_froms . _jump COME_FROM
lambda_body ::= expr . LOAD_LAMBDA LOAD_STR MAKE_FUNCTION_1
lambda_body ::= expr . expr LOAD_LAMBDA LOAD_STR MAKE_FUNCTION_5
lambda_body ::= expr expr . LOAD_LAMBDA LOAD_STR MAKE_FUNCTION_5
mkfunc ::= expr . LOAD_CODE LOAD_STR MAKE_FUNCTION_1
mkfunc ::= expr . expr LOAD_CODE LOAD_STR MAKE_FUNCTION_5
mkfunc ::= expr expr . LOAD_CODE LOAD_STR MAKE_FUNCTION_5
mkfuncdeco ::= expr . mkfuncdeco CALL_FUNCTION_1
mkfuncdeco ::= expr . mkfuncdeco0 CALL_FUNCTION_1
or ::= expr_jt . expr
or ::= expr_jt . expr COME_FROM
or ::= expr_jt expr . 
or ::= expr_jt expr . COME_FROM
or ::= expr_pjit . expr POP_JUMP_IF_FALSE COME_FROM
or ::= expr_pjit expr . POP_JUMP_IF_FALSE COME_FROM
or ::= expr_pjit_come_from . expr
pos_arg ::= expr . 
ret_and ::= expr . JUMP_IF_FALSE_OR_POP return_expr_or_cond COME_FROM
ret_or ::= expr . JUMP_IF_TRUE_OR_POP return_expr_or_cond COME_FROM
return ::= return_expr . RETURN_END_IF
return ::= return_expr . RETURN_VALUE
return ::= return_expr . RETURN_VALUE COME_FROM
return_expr ::= expr . 
return_expr_lambda ::= return_expr . RETURN_VALUE_LAMBDA
return_expr_lambda ::= return_expr . RETURN_VALUE_LAMBDA LAMBDA_MARKER
return_if_stmt ::= return_expr . RETURN_END_IF
return_if_stmt ::= return_expr . RETURN_END_IF POP_BLOCK
sstmt ::= sstmt . RETURN_LAST
sstmt ::= stmt . 
stmt ::= assign . 
stmt ::= call_stmt . 
stmt ::= expr_stmt . 
stmts ::= sstmt . 
stmts ::= stmts . sstmt
stmts ::= stmts sstmt . 
store ::= STORE_FAST . 
store ::= expr . STORE_ATTR
store_subscript ::= expr . expr STORE_SUBSCR
store_subscript ::= expr expr . STORE_SUBSCR
subscript ::= expr . expr BINARY_SUBSCR
subscript ::= expr expr . BINARY_SUBSCR
subscript2 ::= expr . expr DUP_TOP_TWO BINARY_SUBSCR
subscript2 ::= expr expr . DUP_TOP_TWO BINARY_SUBSCR
testexpr ::= testtrue . 
testexpr_cf ::= testexpr . come_froms
testexpr_cf ::= testexpr come_froms . 
testexprl ::= testfalsel . 
testfalse ::= expr . jmp_false
testfalse ::= or . jmp_false COME_FROM
testfalse_not_and ::= expr . jmp_false expr jmp_true COME_FROM
testfalse_not_or ::= expr . jmp_false expr jmp_false COME_FROM
testfalsel ::= expr . jmp_true
testfalsel ::= expr jmp_true . 
testtrue ::= expr . jmp_true
testtrue ::= expr jmp_true . 
unary_not ::= expr . UNARY_NOT
unary_op ::= expr . unary_operator
yield ::= expr . YIELD_VALUE
yield_from ::= expr . GET_YIELD_FROM_ITER LOAD_CONST YIELD_FROM
Instruction context:
   
 L.  60        70  LOAD_GLOBAL              sims4
                  72  LOAD_ATTR                commands
                  74  LOAD_METHOD              automation_output
                  76  LOAD_STR                 'Status; Result:Failed'
                  78  LOAD_FAST                '_connection'
                  80  CALL_METHOD_2         2  '2 positional arguments'
                  82  POP_TOP          
->                84  JUMP_FORWARD        100  'to 100'
                86_0  COME_FROM            48  '48'
import sims4
from civic_policies.base_civic_policy_utilities import CivicPolicyProviderListSelector, debug_automation_output_policy_name_list, debug_automation_output_vote_info
from distributor.ops import CommunityBoardDialog
from distributor.system import Distributor
from server_commands.argument_helpers import OptionalSimInfoParam, get_optional_target, TunableInstanceParam
from sims4.common import Pack
import services

@sims4.commands.Command('civic_policy.venue.enact', pack=(Pack.EP09), command_type=(sims4.commands.CommandType.Live))
def venue_civic_policy_enact--- This code section failed: ---

 L.  24         0  LOAD_GLOBAL              services
                2  LOAD_METHOD              venue_service
                4  CALL_METHOD_0         0  '0 positional arguments'
                6  LOAD_ATTR                source_venue
                8  STORE_FAST               'source_venue'

 L.  25        10  LOAD_FAST                'source_venue'
               12  LOAD_CONST               None
               14  COMPARE_OP               is
               16  POP_JUMP_IF_TRUE     40  'to 40'

 L.  26        18  LOAD_FAST                'source_venue'
               20  LOAD_ATTR                civic_policy_provider
               22  LOAD_CONST               None
               24  COMPARE_OP               is
               26  POP_JUMP_IF_TRUE     40  'to 40'

 L.  27        28  LOAD_FAST                'source_venue'
               30  LOAD_ATTR                civic_policy_provider
               32  LOAD_METHOD              enact
               34  LOAD_FAST                'policy'
               36  CALL_METHOD_1         1  '1 positional argument'
               38  POP_JUMP_IF_TRUE     76  'to 76'
             40_0  COME_FROM            26  '26'
             40_1  COME_FROM            16  '16'

 L.  28        40  LOAD_GLOBAL              sims4
               42  LOAD_ATTR                commands
               44  LOAD_METHOD              automation_output
               46  LOAD_STR                 'Status; Result:Failed'
               48  LOAD_FAST                '_connection'
               50  CALL_METHOD_2         2  '2 positional arguments'
               52  POP_TOP          

 L.  29        54  LOAD_GLOBAL              sims4
               56  LOAD_ATTR                commands
               58  LOAD_METHOD              cheat_output
               60  LOAD_STR                 '{} not enacted'
               62  LOAD_METHOD              format
               64  LOAD_FAST                'policy'
               66  CALL_METHOD_1         1  '1 positional argument'
               68  LOAD_FAST                '_connection'
               70  CALL_METHOD_2         2  '2 positional arguments'
               72  POP_TOP          
               74  JUMP_FORWARD         90  'to 90'
             76_0  COME_FROM            38  '38'

 L.  31        76  LOAD_GLOBAL              sims4
               78  LOAD_ATTR                commands
               80  LOAD_METHOD              automation_output
               82  LOAD_STR                 'Status; Result:Success'
               84  LOAD_FAST                '_connection'
               86  CALL_METHOD_2         2  '2 positional arguments'
               88  POP_TOP          
             90_0  COME_FROM            74  '74'

Parse error at or near `JUMP_FORWARD' instruction at offset 74


@sims4.commands.Command('civic_policy.venue.repeal', pack=(Pack.EP09), command_type=(sims4.commands.CommandType.Live))
def venue_civic_policy_repeal--- This code section failed: ---

 L.  39         0  LOAD_GLOBAL              services
                2  LOAD_METHOD              venue_service
                4  CALL_METHOD_0         0  '0 positional arguments'
                6  LOAD_ATTR                source_venue
                8  STORE_FAST               'source_venue'

 L.  40        10  LOAD_FAST                'source_venue'
               12  LOAD_CONST               None
               14  COMPARE_OP               is
               16  POP_JUMP_IF_TRUE     40  'to 40'

 L.  41        18  LOAD_FAST                'source_venue'
               20  LOAD_ATTR                civic_policy_provider
               22  LOAD_CONST               None
               24  COMPARE_OP               is
               26  POP_JUMP_IF_TRUE     40  'to 40'

 L.  42        28  LOAD_FAST                'source_venue'
               30  LOAD_ATTR                civic_policy_provider
               32  LOAD_METHOD              repeal
               34  LOAD_FAST                'policy'
               36  CALL_METHOD_1         1  '1 positional argument'
               38  POP_JUMP_IF_TRUE     76  'to 76'
             40_0  COME_FROM            26  '26'
             40_1  COME_FROM            16  '16'

 L.  43        40  LOAD_GLOBAL              sims4
               42  LOAD_ATTR                commands
               44  LOAD_METHOD              automation_output
               46  LOAD_STR                 'Status; Result:Failed'
               48  LOAD_FAST                '_connection'
               50  CALL_METHOD_2         2  '2 positional arguments'
               52  POP_TOP          

 L.  44        54  LOAD_GLOBAL              sims4
               56  LOAD_ATTR                commands
               58  LOAD_METHOD              cheat_output
               60  LOAD_STR                 '{} not repealed'
               62  LOAD_METHOD              format
               64  LOAD_FAST                'policy'
               66  CALL_METHOD_1         1  '1 positional argument'
               68  LOAD_FAST                '_connection'
               70  CALL_METHOD_2         2  '2 positional arguments'
               72  POP_TOP          
               74  JUMP_FORWARD         90  'to 90'
             76_0  COME_FROM            38  '38'

 L.  46        76  LOAD_GLOBAL              sims4
               78  LOAD_ATTR                commands
               80  LOAD_METHOD              automation_output
               82  LOAD_STR                 'Status; Result:Success'
               84  LOAD_FAST                '_connection'
               86  CALL_METHOD_2         2  '2 positional arguments'
               88  POP_TOP          
             90_0  COME_FROM            74  '74'

Parse error at or near `JUMP_FORWARD' instruction at offset 74


@sims4.commands.Command('civic_policy.venue.vote', pack=(Pack.EP09), command_type=(sims4.commands.CommandType.Live))
def venue_civic_policy_vote--- This code section failed: ---

 L.  54         0  LOAD_GLOBAL              int
                2  LOAD_FAST                'count'
                4  CALL_FUNCTION_1       1  '1 positional argument'
                6  STORE_FAST               'count'

 L.  55         8  LOAD_GLOBAL              services
               10  LOAD_METHOD              venue_service
               12  CALL_METHOD_0         0  '0 positional arguments'
               14  LOAD_ATTR                source_venue
               16  STORE_FAST               'source_venue'

 L.  56        18  LOAD_FAST                'source_venue'
               20  LOAD_CONST               None
               22  COMPARE_OP               is
               24  POP_JUMP_IF_TRUE     50  'to 50'

 L.  57        26  LOAD_FAST                'source_venue'
               28  LOAD_ATTR                civic_policy_provider
               30  LOAD_CONST               None
               32  COMPARE_OP               is
               34  POP_JUMP_IF_TRUE     50  'to 50'

 L.  58        36  LOAD_FAST                'source_venue'
               38  LOAD_ATTR                civic_policy_provider
               40  LOAD_METHOD              vote
               42  LOAD_FAST                'policy'
               44  LOAD_FAST                'count'
               46  CALL_METHOD_2         2  '2 positional arguments'
               48  POP_JUMP_IF_TRUE     86  'to 86'
             50_0  COME_FROM            34  '34'
             50_1  COME_FROM            24  '24'

 L.  59        50  LOAD_GLOBAL              sims4
               52  LOAD_ATTR                commands
               54  LOAD_METHOD              cheat_output
               56  LOAD_STR                 'Could not add vote to {}'
               58  LOAD_METHOD              format
               60  LOAD_FAST                'policy'
               62  CALL_METHOD_1         1  '1 positional argument'
               64  LOAD_FAST                '_connection'
               66  CALL_METHOD_2         2  '2 positional arguments'
               68  POP_TOP          

 L.  60        70  LOAD_GLOBAL              sims4
               72  LOAD_ATTR                commands
               74  LOAD_METHOD              automation_output
               76  LOAD_STR                 'Status; Result:Failed'
               78  LOAD_FAST                '_connection'
               80  CALL_METHOD_2         2  '2 positional arguments'
               82  POP_TOP          
               84  JUMP_FORWARD        100  'to 100'
             86_0  COME_FROM            48  '48'

 L.  62        86  LOAD_GLOBAL              sims4
               88  LOAD_ATTR                commands
               90  LOAD_METHOD              automation_output
               92  LOAD_STR                 'Status; Result:Success'
               94  LOAD_FAST                '_connection'
               96  CALL_METHOD_2         2  '2 positional arguments'
               98  POP_TOP          
            100_0  COME_FROM            84  '84'

Parse error at or near `JUMP_FORWARD' instruction at offset 84


@sims4.commands.Command('civic_policy.venue.force_end_voting', pack=(Pack.EP09), command_type=(sims4.commands.CommandType.Automation))
def venue_civic_policy_force_end_voting(_connection=None):
    source_venue = services.venue_service.source_venue
    if source_venue is None:
        return False
    provider = source_venue.civic_policy_provider
    if provider is None:
        return False

    def output_enacted_policy_list():
        policies = provider.get_enacted_policies
        for policy in policies:
            sims4.commands.cheat_output'    {}'.formatpolicy_connection

    sims4.commands.cheat_output'Before Enacted Policies'_connection
    output_enacted_policy_list()
    provider.close_voting
    sims4.commands.cheat_output'After Enacted Policies'_connection
    output_enacted_policy_list()


@sims4.commands.Command('civic_policy.venue.show_community_board', pack=(Pack.EP09), command_type=(sims4.commands.CommandType.Live))
def venue_civic_policy_show_community_board(opt_sim: OptionalSimInfoParam=None, opt_target_id: int=0, _connection=None):
    street_service = services.street_service
    if street_service is None:
        sims4.commands.automation_output'Pack not loaded'_connection
        sims4.commands.cheat_output'Pack not loaded'_connection
        return
    sim_info = get_optional_target(opt_sim, _connection, target_type=OptionalSimInfoParam)
    source_venue = services.venue_service.source_venue
    if source_venue is None:
        return
    provider = source_venue.civic_policy_provider
    if provider is None:
        return
    op = CommunityBoardDialog(provider, sim_info, opt_target_id)
    Distributor.instance.add_op_with_no_ownerop


@sims4.commands.Command('civic_policy.venue.policy_list', pack=(Pack.EP09), command_type=(sims4.commands.CommandType.Automation))
def civic_policy_list(selector: CivicPolicyProviderListSelector=None, _connection=None):
    source_venue = services.venue_service.source_venue
    if source_venue is None:
        return False
    provider = source_venue.civic_policy_provider
    if provider is None:
        return False
    debug_automation_output_policy_name_list(provider, selector, _connection)


@sims4.commands.Command('civic_policy.venue.vote_count', pack=(Pack.EP09), command_type=(sims4.commands.CommandType.Automation))
def street_civic_policy_vote_count(policy: TunableInstanceParam(sims4.resources.Types.SNIPPET), _connection=None):
    provider = None
    source_venue = services.venue_service.source_venue
    if source_venue is not None:
        provider = source_venue.civic_policy_provider
    debug_automation_output_vote_info(provider, policy, _connection)
