# uncompyle6 version 3.9.0
# Python bytecode version base 3.7.0 (3394)
# Decompiled from: Python 3.7.16 (default, Dec  7 2022, 01:12:33) 
# [GCC 11.3.0]
# Embedded file name: T:\InGame\Gameplay\Scripts\Server\interactions\utils\camera.py
# Compiled at: 2021-05-07 00:19:49
# Size of source mod 2**32: 6819 bytes

-- Stacks of completed symbols:
START ::= |- stmts . 
_come_froms ::= \e__come_froms . COME_FROM
_come_froms ::= \e__come_froms . COME_FROM_LOOP
_come_froms ::= \e__come_froms COME_FROM . 
_come_froms ::= _come_froms . COME_FROM
_come_froms ::= _come_froms . COME_FROM_LOOP
_ifstmts_jump ::= \e_c_stmts_opt . COME_FROM
_ifstmts_jump ::= \e_c_stmts_opt . ELSE
_ifstmts_jump ::= \e_c_stmts_opt . JUMP_ABSOLUTE JUMP_FORWARD \e__come_froms
_ifstmts_jump ::= \e_c_stmts_opt . JUMP_ABSOLUTE JUMP_FORWARD _come_froms
_ifstmts_jump ::= \e_c_stmts_opt . come_froms
_ifstmts_jump ::= c_stmts_opt . COME_FROM
_ifstmts_jump ::= c_stmts_opt . ELSE
_ifstmts_jump ::= c_stmts_opt . JUMP_ABSOLUTE JUMP_FORWARD \e__come_froms
_ifstmts_jump ::= c_stmts_opt . JUMP_ABSOLUTE JUMP_FORWARD _come_froms
_ifstmts_jump ::= c_stmts_opt . come_froms
_ifstmts_jump ::= c_stmts_opt COME_FROM . 
_ifstmts_jump ::= c_stmts_opt come_froms . 
_ifstmts_jumpl ::= _ifstmts_jump . 
_ifstmts_jumpl ::= c_stmts . JUMP_BACK
_ifstmts_jumpl ::= c_stmts JUMP_BACK . 
_lambda_body ::= lambda_body . 
_stmts ::= _stmts . stmt
_stmts ::= _stmts stmt . 
_stmts ::= stmt . 
and ::= expr . JUMP_IF_FALSE_OR_POP expr \e_come_from_opt
and ::= expr . JUMP_IF_FALSE_OR_POP expr come_from_opt
and ::= expr . jifop_come_from expr
and ::= expr . jmp_false expr
and ::= expr . jmp_false expr COME_FROM
and ::= expr . jmp_false expr jmp_false
and ::= expr jmp_false . expr
and ::= expr jmp_false . expr COME_FROM
and ::= expr jmp_false . expr jmp_false
and ::= expr jmp_false expr . 
and ::= expr jmp_false expr . COME_FROM
and ::= expr jmp_false expr . jmp_false
and_not ::= expr . jmp_false expr POP_JUMP_IF_TRUE
and_not ::= expr jmp_false . expr POP_JUMP_IF_TRUE
and_not ::= expr jmp_false expr . POP_JUMP_IF_TRUE
assert2 ::= expr . jmp_true LOAD_GLOBAL expr CALL_FUNCTION_1 RAISE_VARARGS_1
assign ::= expr . DUP_TOP designList
assign ::= expr . store
assign ::= expr store . 
assign2 ::= expr . expr ROT_TWO store store
assign2 ::= expr expr . ROT_TWO store store
assign3 ::= expr . expr expr ROT_THREE ROT_TWO store store store
assign3 ::= expr expr . expr ROT_THREE ROT_TWO store store store
assign3 ::= expr expr expr . ROT_THREE ROT_TWO store store store
async_for_stmt ::= setup_loop . expr GET_AITER LOAD_CONST YIELD_FROM SETUP_EXCEPT GET_ANEXT LOAD_CONST YIELD_FROM store POP_BLOCK JUMP_FORWARD COME_FROM_EXCEPT DUP_TOP LOAD_GLOBAL COMPARE_OP POP_JUMP_IF_FALSE POP_TOP POP_TOP POP_TOP POP_EXCEPT POP_BLOCK JUMP_ABSOLUTE END_FINALLY COME_FROM for_block POP_BLOCK COME_FROM_LOOP
async_for_stmt ::= setup_loop . expr GET_AITER SETUP_EXCEPT GET_ANEXT LOAD_CONST YIELD_FROM store POP_BLOCK JUMP_FORWARD COME_FROM_EXCEPT DUP_TOP LOAD_GLOBAL COMPARE_OP POP_JUMP_IF_TRUE END_FINALLY COME_FROM for_block COME_FROM POP_TOP POP_TOP POP_TOP POP_EXCEPT POP_TOP POP_BLOCK COME_FROM_LOOP
async_for_stmt ::= setup_loop expr . GET_AITER LOAD_CONST YIELD_FROM SETUP_EXCEPT GET_ANEXT LOAD_CONST YIELD_FROM store POP_BLOCK JUMP_FORWARD COME_FROM_EXCEPT DUP_TOP LOAD_GLOBAL COMPARE_OP POP_JUMP_IF_FALSE POP_TOP POP_TOP POP_TOP POP_EXCEPT POP_BLOCK JUMP_ABSOLUTE END_FINALLY COME_FROM for_block POP_BLOCK COME_FROM_LOOP
async_for_stmt ::= setup_loop expr . GET_AITER SETUP_EXCEPT GET_ANEXT LOAD_CONST YIELD_FROM store POP_BLOCK JUMP_FORWARD COME_FROM_EXCEPT DUP_TOP LOAD_GLOBAL COMPARE_OP POP_JUMP_IF_TRUE END_FINALLY COME_FROM for_block COME_FROM POP_TOP POP_TOP POP_TOP POP_EXCEPT POP_TOP POP_BLOCK COME_FROM_LOOP
async_for_stmt37 ::= setup_loop . expr GET_AITER \e__come_froms SETUP_EXCEPT GET_ANEXT LOAD_CONST YIELD_FROM store POP_BLOCK JUMP_BACK COME_FROM_EXCEPT DUP_TOP LOAD_GLOBAL COMPARE_OP POP_JUMP_IF_TRUE END_FINALLY for_block COME_FROM POP_TOP POP_TOP POP_TOP POP_EXCEPT POP_TOP POP_BLOCK COME_FROM_LOOP
async_for_stmt37 ::= setup_loop . expr GET_AITER _come_froms SETUP_EXCEPT GET_ANEXT LOAD_CONST YIELD_FROM store POP_BLOCK JUMP_BACK COME_FROM_EXCEPT DUP_TOP LOAD_GLOBAL COMPARE_OP POP_JUMP_IF_TRUE END_FINALLY for_block COME_FROM POP_TOP POP_TOP POP_TOP POP_EXCEPT POP_TOP POP_BLOCK COME_FROM_LOOP
async_for_stmt37 ::= setup_loop expr . GET_AITER \e__come_froms SETUP_EXCEPT GET_ANEXT LOAD_CONST YIELD_FROM store POP_BLOCK JUMP_BACK COME_FROM_EXCEPT DUP_TOP LOAD_GLOBAL COMPARE_OP POP_JUMP_IF_TRUE END_FINALLY for_block COME_FROM POP_TOP POP_TOP POP_TOP POP_EXCEPT POP_TOP POP_BLOCK COME_FROM_LOOP
async_for_stmt37 ::= setup_loop expr . GET_AITER _come_froms SETUP_EXCEPT GET_ANEXT LOAD_CONST YIELD_FROM store POP_BLOCK JUMP_BACK COME_FROM_EXCEPT DUP_TOP LOAD_GLOBAL COMPARE_OP POP_JUMP_IF_TRUE END_FINALLY for_block COME_FROM POP_TOP POP_TOP POP_TOP POP_EXCEPT POP_TOP POP_BLOCK COME_FROM_LOOP
async_forelse_stmt ::= setup_loop . expr GET_AITER \e__come_froms SETUP_EXCEPT GET_ANEXT LOAD_CONST YIELD_FROM store POP_BLOCK JUMP_FORWARD COME_FROM_EXCEPT DUP_TOP LOAD_GLOBAL COMPARE_OP POP_JUMP_IF_TRUE END_FINALLY COME_FROM for_block COME_FROM POP_TOP POP_TOP POP_TOP POP_EXCEPT POP_TOP POP_BLOCK else_suite COME_FROM_LOOP
async_forelse_stmt ::= setup_loop . expr GET_AITER _come_froms SETUP_EXCEPT GET_ANEXT LOAD_CONST YIELD_FROM store POP_BLOCK JUMP_FORWARD COME_FROM_EXCEPT DUP_TOP LOAD_GLOBAL COMPARE_OP POP_JUMP_IF_TRUE END_FINALLY COME_FROM for_block COME_FROM POP_TOP POP_TOP POP_TOP POP_EXCEPT POP_TOP POP_BLOCK else_suite COME_FROM_LOOP
async_forelse_stmt ::= setup_loop expr . GET_AITER \e__come_froms SETUP_EXCEPT GET_ANEXT LOAD_CONST YIELD_FROM store POP_BLOCK JUMP_FORWARD COME_FROM_EXCEPT DUP_TOP LOAD_GLOBAL COMPARE_OP POP_JUMP_IF_TRUE END_FINALLY COME_FROM for_block COME_FROM POP_TOP POP_TOP POP_TOP POP_EXCEPT POP_TOP POP_BLOCK else_suite COME_FROM_LOOP
async_forelse_stmt ::= setup_loop expr . GET_AITER _come_froms SETUP_EXCEPT GET_ANEXT LOAD_CONST YIELD_FROM store POP_BLOCK JUMP_FORWARD COME_FROM_EXCEPT DUP_TOP LOAD_GLOBAL COMPARE_OP POP_JUMP_IF_TRUE END_FINALLY COME_FROM for_block COME_FROM POP_TOP POP_TOP POP_TOP POP_EXCEPT POP_TOP POP_BLOCK else_suite COME_FROM_LOOP
attribute ::= expr . LOAD_ATTR
attribute ::= expr LOAD_ATTR . 
attribute37 ::= expr . LOAD_METHOD
attribute37 ::= expr LOAD_METHOD . 
aug_assign1 ::= expr . expr inplace_op ROT_THREE STORE_SUBSCR
aug_assign1 ::= expr . expr inplace_op store
aug_assign1 ::= expr expr . inplace_op ROT_THREE STORE_SUBSCR
aug_assign1 ::= expr expr . inplace_op store
aug_assign2 ::= expr . DUP_TOP LOAD_ATTR expr inplace_op ROT_TWO STORE_ATTR
await_expr ::= expr . GET_AWAITABLE LOAD_CONST YIELD_FROM
bin_op ::= expr . expr binary_operator
bin_op ::= expr expr . binary_operator
break ::= BREAK_LOOP . 
c_stmts ::= _stmts . 
c_stmts ::= _stmts . lastc_stmt
c_stmts_opt ::= c_stmts . 
call ::= expr . CALL_METHOD_0
call ::= expr . expr CALL_METHOD_1
call ::= expr . pos_arg pos_arg pos_arg pos_arg CALL_FUNCTION_4
call ::= expr . pos_arg pos_arg pos_arg pos_arg pos_arg CALL_FUNCTION_5
call ::= expr CALL_METHOD_0 . 
call ::= expr expr . CALL_METHOD_1
call ::= expr expr CALL_METHOD_1 . 
call ::= expr pos_arg . pos_arg pos_arg pos_arg CALL_FUNCTION_4
call ::= expr pos_arg . pos_arg pos_arg pos_arg pos_arg CALL_FUNCTION_5
call ::= expr pos_arg pos_arg . pos_arg pos_arg CALL_FUNCTION_4
call ::= expr pos_arg pos_arg . pos_arg pos_arg pos_arg CALL_FUNCTION_5
call ::= expr pos_arg pos_arg pos_arg . pos_arg CALL_FUNCTION_4
call ::= expr pos_arg pos_arg pos_arg . pos_arg pos_arg CALL_FUNCTION_5
call ::= expr pos_arg pos_arg pos_arg pos_arg . CALL_FUNCTION_4
call ::= expr pos_arg pos_arg pos_arg pos_arg . pos_arg CALL_FUNCTION_5
call_kw36 ::= expr . expr LOAD_CONST CALL_FUNCTION_KW_1
call_kw36 ::= expr . expr expr LOAD_CONST CALL_FUNCTION_KW_2
call_kw36 ::= expr . expr expr expr LOAD_CONST CALL_FUNCTION_KW_3
call_kw36 ::= expr expr . LOAD_CONST CALL_FUNCTION_KW_1
call_kw36 ::= expr expr . expr LOAD_CONST CALL_FUNCTION_KW_2
call_kw36 ::= expr expr . expr expr LOAD_CONST CALL_FUNCTION_KW_3
call_kw36 ::= expr expr LOAD_CONST . CALL_FUNCTION_KW_1
call_kw36 ::= expr expr expr . LOAD_CONST CALL_FUNCTION_KW_2
call_kw36 ::= expr expr expr . expr LOAD_CONST CALL_FUNCTION_KW_3
call_kw36 ::= expr expr expr LOAD_CONST . CALL_FUNCTION_KW_2
call_kw36 ::= expr expr expr expr . LOAD_CONST CALL_FUNCTION_KW_3
call_kw36 ::= expr expr expr expr LOAD_CONST . CALL_FUNCTION_KW_3
call_kw36 ::= expr expr expr expr LOAD_CONST CALL_FUNCTION_KW_3 . 
call_stmt ::= expr . POP_TOP
cf_jf_else ::= come_froms . JUMP_FORWARD ELSE
cf_jump_back ::= COME_FROM . JUMP_BACK
come_from_loops ::= \e_come_from_loops . COME_FROM_LOOP
come_from_opt ::= COME_FROM . 
come_froms ::= COME_FROM . 
come_froms ::= come_froms . COME_FROM
come_froms ::= come_froms COME_FROM . 
compare ::= compare_single . 
compare_chained ::= expr . compare_chained1 ROT_TWO POP_TOP \e__come_froms
compare_chained ::= expr . compare_chained1 ROT_TWO POP_TOP _come_froms
compare_chained1 ::= expr . DUP_TOP ROT_THREE COMPARE_OP JUMP_IF_FALSE_OR_POP compare_chained1 COME_FROM
compare_chained1 ::= expr . DUP_TOP ROT_THREE COMPARE_OP JUMP_IF_FALSE_OR_POP compare_chained2 COME_FROM
compare_chained1_false_37 ::= expr . DUP_TOP ROT_THREE COMPARE_OP POP_JUMP_IF_FALSE compare_chained2b_false_37 POP_TOP _jump COME_FROM
compare_chained1_false_37 ::= expr . DUP_TOP ROT_THREE COMPARE_OP POP_JUMP_IF_FALSE compare_chained2c_37 POP_TOP JUMP_FORWARD COME_FROM
compare_chained1a_37 ::= expr . DUP_TOP ROT_THREE COMPARE_OP POP_JUMP_IF_FALSE
compare_chained1a_37 ::= expr . DUP_TOP ROT_THREE COMPARE_OP POP_JUMP_IF_FALSE compare_chained2a_37 COME_FROM POP_TOP COME_FROM
compare_chained1b_false_37 ::= expr . DUP_TOP ROT_THREE COMPARE_OP POP_JUMP_IF_FALSE compare_chained2b_false_37 POP_TOP _jump COME_FROM
compare_chained1c_37 ::= expr . DUP_TOP ROT_THREE COMPARE_OP POP_JUMP_IF_FALSE compare_chained2a_37 POP_TOP
compare_chained2_false_37 ::= expr . DUP_TOP ROT_THREE COMPARE_OP POP_JUMP_IF_FALSE compare_chained2a_false_37 POP_TOP JUMP_BACK COME_FROM
compare_chained37 ::= expr . compare_chained1a_37
compare_chained37 ::= expr . compare_chained1c_37
compare_chained37_false ::= expr . compare_chained1_false_37
compare_chained37_false ::= expr . compare_chained1b_false_37
compare_chained37_false ::= expr . compare_chained2_false_37
compare_single ::= expr . expr COMPARE_OP
compare_single ::= expr expr . COMPARE_OP
compare_single ::= expr expr COMPARE_OP . 
continues ::= _stmts . lastl_stmt continue
continues ::= _stmts lastl_stmt . continue
dict ::= expr . expr expr expr expr LOAD_CONST BUILD_CONST_KEY_MAP_5
dict ::= expr expr . expr expr expr LOAD_CONST BUILD_CONST_KEY_MAP_5
dict ::= expr expr expr . expr expr LOAD_CONST BUILD_CONST_KEY_MAP_5
dict ::= expr expr expr expr . expr LOAD_CONST BUILD_CONST_KEY_MAP_5
dict ::= expr expr expr expr expr . LOAD_CONST BUILD_CONST_KEY_MAP_5
else_suite ::= suite_stmts . 
else_suite_opt ::= else_suite . 
expr ::= LOAD_CONST . 
expr ::= LOAD_FAST . 
expr ::= LOAD_GLOBAL . 
expr ::= _lambda_body . 
expr ::= attribute . 
expr ::= attribute37 . 
expr ::= call . 
expr ::= call_kw36 . 
expr ::= compare . 
expr ::= get_iter . 
expr_jit ::= expr . JUMP_IF_TRUE
expr_jitop ::= expr . JUMP_IF_TRUE_OR_POP
expr_jt ::= expr . jmp_true
expr_pjit ::= expr . POP_JUMP_IF_TRUE
expr_pjit_come_from ::= expr . POP_JUMP_IF_TRUE COME_FROM
expr_stmt ::= expr . POP_TOP
for ::= setup_loop . expr get_for_iter store for_block POP_BLOCK
for ::= setup_loop . expr get_for_iter store for_block POP_BLOCK COME_FROM_LOOP
for ::= setup_loop . expr get_for_iter store for_block POP_BLOCK NOP COME_FROM_LOOP
for ::= setup_loop expr . get_for_iter store for_block POP_BLOCK
for ::= setup_loop expr . get_for_iter store for_block POP_BLOCK COME_FROM_LOOP
for ::= setup_loop expr . get_for_iter store for_block POP_BLOCK NOP COME_FROM_LOOP
for ::= setup_loop expr get_for_iter . store for_block POP_BLOCK
for ::= setup_loop expr get_for_iter . store for_block POP_BLOCK COME_FROM_LOOP
for ::= setup_loop expr get_for_iter . store for_block POP_BLOCK NOP COME_FROM_LOOP
for ::= setup_loop expr get_for_iter store . for_block POP_BLOCK
for ::= setup_loop expr get_for_iter store . for_block POP_BLOCK COME_FROM_LOOP
for ::= setup_loop expr get_for_iter store . for_block POP_BLOCK NOP COME_FROM_LOOP
for ::= setup_loop expr get_for_iter store for_block . POP_BLOCK
for ::= setup_loop expr get_for_iter store for_block . POP_BLOCK COME_FROM_LOOP
for ::= setup_loop expr get_for_iter store for_block . POP_BLOCK NOP COME_FROM_LOOP
for ::= setup_loop expr get_for_iter store for_block POP_BLOCK . 
for ::= setup_loop expr get_for_iter store for_block POP_BLOCK . COME_FROM_LOOP
for ::= setup_loop expr get_for_iter store for_block POP_BLOCK . NOP COME_FROM_LOOP
for_block ::= \e_l_stmts_opt . COME_FROM_LOOP JUMP_BACK
for_block ::= \e_l_stmts_opt . _come_froms JUMP_BACK
for_block ::= \e_l_stmts_opt . come_from_loops JUMP_BACK
for_block ::= \e_l_stmts_opt \e__come_froms . JUMP_BACK
for_block ::= \e_l_stmts_opt \e_come_from_loops . JUMP_BACK
for_block ::= l_stmts . 
for_block ::= l_stmts . JUMP_BACK
for_block ::= l_stmts JUMP_BACK . 
for_block ::= l_stmts_opt . COME_FROM_LOOP JUMP_BACK
for_block ::= l_stmts_opt . _come_froms JUMP_BACK
for_block ::= l_stmts_opt . come_from_loops JUMP_BACK
for_block ::= l_stmts_opt \e__come_froms . JUMP_BACK
for_block ::= l_stmts_opt \e__come_froms JUMP_BACK . 
for_block ::= l_stmts_opt \e_come_from_loops . JUMP_BACK
for_block ::= l_stmts_opt \e_come_from_loops JUMP_BACK . 
forelselaststmt ::= SETUP_LOOP . expr get_for_iter store for_block POP_BLOCK else_suitec \e__come_froms
forelselaststmt ::= SETUP_LOOP . expr get_for_iter store for_block POP_BLOCK else_suitec _come_froms
forelselaststmt ::= SETUP_LOOP expr . get_for_iter store for_block POP_BLOCK else_suitec \e__come_froms
forelselaststmt ::= SETUP_LOOP expr . get_for_iter store for_block POP_BLOCK else_suitec _come_froms
forelselaststmt ::= SETUP_LOOP expr get_for_iter . store for_block POP_BLOCK else_suitec \e__come_froms
forelselaststmt ::= SETUP_LOOP expr get_for_iter . store for_block POP_BLOCK else_suitec _come_froms
forelselaststmt ::= SETUP_LOOP expr get_for_iter store . for_block POP_BLOCK else_suitec \e__come_froms
forelselaststmt ::= SETUP_LOOP expr get_for_iter store . for_block POP_BLOCK else_suitec _come_froms
forelselaststmt ::= SETUP_LOOP expr get_for_iter store for_block . POP_BLOCK else_suitec \e__come_froms
forelselaststmt ::= SETUP_LOOP expr get_for_iter store for_block . POP_BLOCK else_suitec _come_froms
forelselaststmt ::= SETUP_LOOP expr get_for_iter store for_block POP_BLOCK . else_suitec \e__come_froms
forelselaststmt ::= SETUP_LOOP expr get_for_iter store for_block POP_BLOCK . else_suitec _come_froms
forelselaststmt ::= setup_loop . expr get_for_iter store for_block POP_BLOCK else_suitec COME_FROM_LOOP
forelselaststmt ::= setup_loop expr . get_for_iter store for_block POP_BLOCK else_suitec COME_FROM_LOOP
forelselaststmt ::= setup_loop expr get_for_iter . store for_block POP_BLOCK else_suitec COME_FROM_LOOP
forelselaststmt ::= setup_loop expr get_for_iter store . for_block POP_BLOCK else_suitec COME_FROM_LOOP
forelselaststmt ::= setup_loop expr get_for_iter store for_block . POP_BLOCK else_suitec COME_FROM_LOOP
forelselaststmt ::= setup_loop expr get_for_iter store for_block POP_BLOCK . else_suitec COME_FROM_LOOP
forelselaststmtl ::= SETUP_LOOP . expr get_for_iter store for_block POP_BLOCK else_suitel \e__come_froms
forelselaststmtl ::= SETUP_LOOP . expr get_for_iter store for_block POP_BLOCK else_suitel _come_froms
forelselaststmtl ::= SETUP_LOOP expr . get_for_iter store for_block POP_BLOCK else_suitel \e__come_froms
forelselaststmtl ::= SETUP_LOOP expr . get_for_iter store for_block POP_BLOCK else_suitel _come_froms
forelselaststmtl ::= SETUP_LOOP expr get_for_iter . store for_block POP_BLOCK else_suitel \e__come_froms
forelselaststmtl ::= SETUP_LOOP expr get_for_iter . store for_block POP_BLOCK else_suitel _come_froms
forelselaststmtl ::= SETUP_LOOP expr get_for_iter store . for_block POP_BLOCK else_suitel \e__come_froms
forelselaststmtl ::= SETUP_LOOP expr get_for_iter store . for_block POP_BLOCK else_suitel _come_froms
forelselaststmtl ::= SETUP_LOOP expr get_for_iter store for_block . POP_BLOCK else_suitel \e__come_froms
forelselaststmtl ::= SETUP_LOOP expr get_for_iter store for_block . POP_BLOCK else_suitel _come_froms
forelselaststmtl ::= SETUP_LOOP expr get_for_iter store for_block POP_BLOCK . else_suitel \e__come_froms
forelselaststmtl ::= SETUP_LOOP expr get_for_iter store for_block POP_BLOCK . else_suitel _come_froms
forelselaststmtl ::= setup_loop . expr get_for_iter store for_block POP_BLOCK else_suitel COME_FROM_LOOP
forelselaststmtl ::= setup_loop expr . get_for_iter store for_block POP_BLOCK else_suitel COME_FROM_LOOP
forelselaststmtl ::= setup_loop expr get_for_iter . store for_block POP_BLOCK else_suitel COME_FROM_LOOP
forelselaststmtl ::= setup_loop expr get_for_iter store . for_block POP_BLOCK else_suitel COME_FROM_LOOP
forelselaststmtl ::= setup_loop expr get_for_iter store for_block . POP_BLOCK else_suitel COME_FROM_LOOP
forelselaststmtl ::= setup_loop expr get_for_iter store for_block POP_BLOCK . else_suitel COME_FROM_LOOP
forelsestmt ::= SETUP_LOOP . expr get_for_iter store for_block POP_BLOCK else_suite \e__come_froms
forelsestmt ::= SETUP_LOOP . expr get_for_iter store for_block POP_BLOCK else_suite _come_froms
forelsestmt ::= SETUP_LOOP expr . get_for_iter store for_block POP_BLOCK else_suite \e__come_froms
forelsestmt ::= SETUP_LOOP expr . get_for_iter store for_block POP_BLOCK else_suite _come_froms
forelsestmt ::= SETUP_LOOP expr get_for_iter . store for_block POP_BLOCK else_suite \e__come_froms
forelsestmt ::= SETUP_LOOP expr get_for_iter . store for_block POP_BLOCK else_suite _come_froms
forelsestmt ::= SETUP_LOOP expr get_for_iter store . for_block POP_BLOCK else_suite \e__come_froms
forelsestmt ::= SETUP_LOOP expr get_for_iter store . for_block POP_BLOCK else_suite _come_froms
forelsestmt ::= SETUP_LOOP expr get_for_iter store for_block . POP_BLOCK else_suite \e__come_froms
forelsestmt ::= SETUP_LOOP expr get_for_iter store for_block . POP_BLOCK else_suite _come_froms
forelsestmt ::= SETUP_LOOP expr get_for_iter store for_block POP_BLOCK . else_suite \e__come_froms
forelsestmt ::= SETUP_LOOP expr get_for_iter store for_block POP_BLOCK . else_suite _come_froms
forelsestmt ::= setup_loop . expr get_for_iter store for_block POP_BLOCK else_suite COME_FROM_LOOP
forelsestmt ::= setup_loop expr . get_for_iter store for_block POP_BLOCK else_suite COME_FROM_LOOP
forelsestmt ::= setup_loop expr get_for_iter . store for_block POP_BLOCK else_suite COME_FROM_LOOP
forelsestmt ::= setup_loop expr get_for_iter store . for_block POP_BLOCK else_suite COME_FROM_LOOP
forelsestmt ::= setup_loop expr get_for_iter store for_block . POP_BLOCK else_suite COME_FROM_LOOP
forelsestmt ::= setup_loop expr get_for_iter store for_block POP_BLOCK . else_suite COME_FROM_LOOP
get_for_iter ::= GET_ITER . _come_froms FOR_ITER
get_for_iter ::= GET_ITER \e__come_froms . FOR_ITER
get_for_iter ::= GET_ITER _come_froms . FOR_ITER
get_for_iter ::= GET_ITER _come_froms FOR_ITER . 
get_iter ::= expr . GET_ITER
get_iter ::= expr GET_ITER . 
if_exp ::= expr . jmp_false expr jf_cf expr COME_FROM
if_exp ::= expr . jmp_false expr jump_absolute_else expr
if_exp ::= expr jmp_false . expr jf_cf expr COME_FROM
if_exp ::= expr jmp_false . expr jump_absolute_else expr
if_exp ::= expr jmp_false expr . jf_cf expr COME_FROM
if_exp ::= expr jmp_false expr . jump_absolute_else expr
if_exp37 ::= expr . expr jf_cfs expr COME_FROM
if_exp37 ::= expr expr . jf_cfs expr COME_FROM
if_exp_37b ::= expr . jmp_false expr POP_JUMP_IF_FALSE jump_forward_else expr
if_exp_37b ::= expr jmp_false . expr POP_JUMP_IF_FALSE jump_forward_else expr
if_exp_37b ::= expr jmp_false expr . POP_JUMP_IF_FALSE jump_forward_else expr
if_exp_lambda ::= expr . jmp_false expr return_if_lambda return_stmt_lambda LAMBDA_MARKER
if_exp_lambda ::= expr jmp_false . expr return_if_lambda return_stmt_lambda LAMBDA_MARKER
if_exp_lambda ::= expr jmp_false expr . return_if_lambda return_stmt_lambda LAMBDA_MARKER
if_exp_not ::= expr . jmp_true expr jump_forward_else expr COME_FROM
if_exp_not_lambda ::= expr . jmp_true expr return_if_lambda return_stmt_lambda LAMBDA_MARKER
if_exp_true ::= expr . JUMP_FORWARD expr COME_FROM
ifelsestmt ::= testexpr . c_stmts come_froms else_suite come_froms
ifelsestmt ::= testexpr . c_stmts_opt JUMP_FORWARD else_suite \e__come_froms
ifelsestmt ::= testexpr . c_stmts_opt JUMP_FORWARD else_suite \e_opt_come_from_except
ifelsestmt ::= testexpr . c_stmts_opt JUMP_FORWARD else_suite _come_froms
ifelsestmt ::= testexpr . c_stmts_opt JUMP_FORWARD else_suite opt_come_from_except
ifelsestmt ::= testexpr . c_stmts_opt jf_cfs else_suite \e_opt_come_from_except
ifelsestmt ::= testexpr . c_stmts_opt jf_cfs else_suite opt_come_from_except
ifelsestmt ::= testexpr . c_stmts_opt jump_forward_else else_suite \e__come_froms
ifelsestmt ::= testexpr . c_stmts_opt jump_forward_else else_suite _come_froms
ifelsestmt ::= testexpr . stmts jf_cfs \e_else_suite_opt \e_opt_come_from_except
ifelsestmt ::= testexpr . stmts jf_cfs \e_else_suite_opt opt_come_from_except
ifelsestmt ::= testexpr . stmts jf_cfs else_suite_opt \e_opt_come_from_except
ifelsestmt ::= testexpr . stmts jf_cfs else_suite_opt opt_come_from_except
ifelsestmt ::= testexpr \e_c_stmts_opt . JUMP_FORWARD else_suite \e__come_froms
ifelsestmt ::= testexpr \e_c_stmts_opt . JUMP_FORWARD else_suite \e_opt_come_from_except
ifelsestmt ::= testexpr \e_c_stmts_opt . JUMP_FORWARD else_suite _come_froms
ifelsestmt ::= testexpr \e_c_stmts_opt . JUMP_FORWARD else_suite opt_come_from_except
ifelsestmt ::= testexpr \e_c_stmts_opt . jf_cfs else_suite \e_opt_come_from_except
ifelsestmt ::= testexpr \e_c_stmts_opt . jf_cfs else_suite opt_come_from_except
ifelsestmt ::= testexpr \e_c_stmts_opt . jump_forward_else else_suite \e__come_froms
ifelsestmt ::= testexpr \e_c_stmts_opt . jump_forward_else else_suite _come_froms
ifelsestmt ::= testexpr c_stmts . come_froms else_suite come_froms
ifelsestmt ::= testexpr c_stmts come_froms . else_suite come_froms
ifelsestmt ::= testexpr c_stmts_opt . JUMP_FORWARD else_suite \e__come_froms
ifelsestmt ::= testexpr c_stmts_opt . JUMP_FORWARD else_suite \e_opt_come_from_except
ifelsestmt ::= testexpr c_stmts_opt . JUMP_FORWARD else_suite _come_froms
ifelsestmt ::= testexpr c_stmts_opt . JUMP_FORWARD else_suite opt_come_from_except
ifelsestmt ::= testexpr c_stmts_opt . jf_cfs else_suite \e_opt_come_from_except
ifelsestmt ::= testexpr c_stmts_opt . jf_cfs else_suite opt_come_from_except
ifelsestmt ::= testexpr c_stmts_opt . jump_forward_else else_suite \e__come_froms
ifelsestmt ::= testexpr c_stmts_opt . jump_forward_else else_suite _come_froms
ifelsestmt ::= testexpr c_stmts_opt JUMP_FORWARD . else_suite \e__come_froms
ifelsestmt ::= testexpr c_stmts_opt JUMP_FORWARD . else_suite \e_opt_come_from_except
ifelsestmt ::= testexpr c_stmts_opt JUMP_FORWARD . else_suite _come_froms
ifelsestmt ::= testexpr c_stmts_opt JUMP_FORWARD . else_suite opt_come_from_except
ifelsestmt ::= testexpr c_stmts_opt jf_cfs . else_suite \e_opt_come_from_except
ifelsestmt ::= testexpr c_stmts_opt jf_cfs . else_suite opt_come_from_except
ifelsestmt ::= testexpr c_stmts_opt jf_cfs else_suite . opt_come_from_except
ifelsestmt ::= testexpr c_stmts_opt jf_cfs else_suite \e_opt_come_from_except . 
ifelsestmt ::= testexpr c_stmts_opt jump_forward_else . else_suite \e__come_froms
ifelsestmt ::= testexpr c_stmts_opt jump_forward_else . else_suite _come_froms
ifelsestmt ::= testexpr c_stmts_opt jump_forward_else else_suite . _come_froms
ifelsestmt ::= testexpr c_stmts_opt jump_forward_else else_suite \e__come_froms . 
ifelsestmt ::= testexpr stmts . jf_cfs \e_else_suite_opt \e_opt_come_from_except
ifelsestmt ::= testexpr stmts . jf_cfs \e_else_suite_opt opt_come_from_except
ifelsestmt ::= testexpr stmts . jf_cfs else_suite_opt \e_opt_come_from_except
ifelsestmt ::= testexpr stmts . jf_cfs else_suite_opt opt_come_from_except
ifelsestmt ::= testexpr stmts jf_cfs . else_suite_opt \e_opt_come_from_except
ifelsestmt ::= testexpr stmts jf_cfs . else_suite_opt opt_come_from_except
ifelsestmt ::= testexpr stmts jf_cfs \e_else_suite_opt . opt_come_from_except
ifelsestmt ::= testexpr stmts jf_cfs \e_else_suite_opt \e_opt_come_from_except . 
ifelsestmt ::= testexpr stmts jf_cfs \e_else_suite_opt opt_come_from_except . 
ifelsestmt ::= testexpr stmts jf_cfs else_suite_opt . opt_come_from_except
ifelsestmt ::= testexpr stmts jf_cfs else_suite_opt \e_opt_come_from_except . 
ifelsestmtl ::= testexpr . c_stmts_opt cf_jf_else else_suitel
ifelsestmtl ::= testexpr . c_stmts_opt cf_jump_back else_suitel
ifelsestmtl ::= testexpr . c_stmts_opt jb_cfs else_suitel
ifelsestmtl ::= testexpr . c_stmts_opt jb_else else_suitel
ifelsestmtl ::= testexpr . c_stmts_opt jump_forward_else else_suitec
ifelsestmtl ::= testexpr \e_c_stmts_opt . cf_jf_else else_suitel
ifelsestmtl ::= testexpr \e_c_stmts_opt . cf_jump_back else_suitel
ifelsestmtl ::= testexpr \e_c_stmts_opt . jb_cfs else_suitel
ifelsestmtl ::= testexpr \e_c_stmts_opt . jb_else else_suitel
ifelsestmtl ::= testexpr \e_c_stmts_opt . jump_forward_else else_suitec
ifelsestmtl ::= testexpr c_stmts_opt . cf_jf_else else_suitel
ifelsestmtl ::= testexpr c_stmts_opt . cf_jump_back else_suitel
ifelsestmtl ::= testexpr c_stmts_opt . jb_cfs else_suitel
ifelsestmtl ::= testexpr c_stmts_opt . jb_else else_suitel
ifelsestmtl ::= testexpr c_stmts_opt . jump_forward_else else_suitec
ifelsestmtr ::= testexpr . return_if_stmts returns
iflaststmtl ::= testexpr . c_stmts
iflaststmtl ::= testexpr . c_stmts JUMP_BACK
iflaststmtl ::= testexpr . c_stmts JUMP_BACK COME_FROM_LOOP
iflaststmtl ::= testexpr . c_stmts JUMP_BACK POP_BLOCK
iflaststmtl ::= testexpr c_stmts . 
iflaststmtl ::= testexpr c_stmts . JUMP_BACK
iflaststmtl ::= testexpr c_stmts . JUMP_BACK COME_FROM_LOOP
iflaststmtl ::= testexpr c_stmts . JUMP_BACK POP_BLOCK
iflaststmtl ::= testexpr c_stmts JUMP_BACK . 
iflaststmtl ::= testexpr c_stmts JUMP_BACK . COME_FROM_LOOP
iflaststmtl ::= testexpr c_stmts JUMP_BACK . POP_BLOCK
iflaststmtl ::= testexpr c_stmts JUMP_BACK POP_BLOCK . 
ifstmt ::= testexpr . _ifstmts_jump
ifstmt ::= testexpr _ifstmts_jump . 
ifstmtl ::= testexpr . _ifstmts_jumpl
ifstmtl ::= testexpr _ifstmts_jumpl . 
import ::= LOAD_CONST . LOAD_CONST alias
import_as37 ::= LOAD_CONST . LOAD_CONST importlist37 store POP_TOP
import_from ::= LOAD_CONST . LOAD_CONST IMPORT_NAME importlist POP_TOP
import_from ::= LOAD_CONST . LOAD_CONST importlist POP_TOP
import_from37 ::= LOAD_CONST . LOAD_CONST IMPORT_NAME_ATTR importlist37 POP_TOP
import_from_as37 ::= LOAD_CONST . LOAD_CONST import_from_attr37 store POP_TOP
import_from_star ::= LOAD_CONST . LOAD_CONST IMPORT_NAME IMPORT_STAR
import_from_star ::= LOAD_CONST . LOAD_CONST IMPORT_NAME_ATTR IMPORT_STAR
importmultiple ::= LOAD_CONST . LOAD_CONST alias imports_cont
jb_cfs ::= \e_come_from_opt . JUMP_BACK come_froms
jb_cfs ::= \e_come_from_opt JUMP_BACK . come_froms
jb_cfs ::= come_from_opt . JUMP_BACK come_froms
jb_else ::= JUMP_BACK . COME_FROM
jb_else ::= JUMP_BACK . ELSE
jf_cfs ::= JUMP_FORWARD . _come_froms
jf_cfs ::= JUMP_FORWARD \e__come_froms . 
jf_cfs ::= JUMP_FORWARD _come_froms . 
jmp_false ::= POP_JUMP_IF_FALSE . 
jump_forward_else ::= JUMP_FORWARD . 
jump_forward_else ::= JUMP_FORWARD . COME_FROM
jump_forward_else ::= JUMP_FORWARD . ELSE
jump_forward_else ::= JUMP_FORWARD COME_FROM . 
l_stmts ::= _stmts . 
l_stmts ::= _stmts . lastl_stmt
l_stmts ::= _stmts lastl_stmt . 
l_stmts ::= l_stmts . lstmt
l_stmts ::= l_stmts lstmt . 
l_stmts ::= lstmt . 
l_stmts_opt ::= l_stmts . 
lambda_body ::= LOAD_LAMBDA . LOAD_STR MAKE_FUNCTION_0
lambda_body ::= LOAD_LAMBDA LOAD_STR . MAKE_FUNCTION_0
lambda_body ::= LOAD_LAMBDA LOAD_STR MAKE_FUNCTION_0 . 
lastl_stmt ::= iflaststmtl . 
lstmt ::= stmt . 
mkfuncdeco ::= expr . mkfuncdeco CALL_FUNCTION_1
mkfuncdeco ::= expr . mkfuncdeco0 CALL_FUNCTION_1
opt_come_from_except ::= _come_froms . 
pos_arg ::= expr . 
ret_and ::= expr . JUMP_IF_FALSE_OR_POP return_expr_or_cond COME_FROM
ret_or ::= expr . JUMP_IF_TRUE_OR_POP return_expr_or_cond COME_FROM
return ::= return_expr . RETURN_END_IF
return ::= return_expr . RETURN_VALUE
return ::= return_expr . RETURN_VALUE COME_FROM
return ::= return_expr RETURN_VALUE . 
return ::= return_expr RETURN_VALUE . COME_FROM
return ::= return_expr RETURN_VALUE COME_FROM . 
return_expr ::= expr . 
return_expr_lambda ::= return_expr . RETURN_VALUE_LAMBDA
return_expr_lambda ::= return_expr . RETURN_VALUE_LAMBDA LAMBDA_MARKER
return_if_stmt ::= return_expr . RETURN_END_IF
return_if_stmt ::= return_expr . RETURN_END_IF POP_BLOCK
return_if_stmts ::= _stmts . return_if_stmt \e__come_froms
return_if_stmts ::= _stmts . return_if_stmt _come_froms
returns ::= _stmts . return
returns ::= _stmts . return_if_stmt
setup_loop ::= SETUP_LOOP . _come_froms
setup_loop ::= SETUP_LOOP \e__come_froms . 
sstmt ::= return . RETURN_LAST
sstmt ::= sstmt . RETURN_LAST
sstmt ::= stmt . 
stmt ::= assign . 
stmt ::= break . 
stmt ::= for . 
stmt ::= ifelsestmt . 
stmt ::= ifstmtl . 
stmt ::= return . 
stmts ::= sstmt . 
stmts ::= stmts . sstmt
stmts ::= stmts sstmt . 
store ::= STORE_FAST . 
store ::= expr . STORE_ATTR
store_subscript ::= expr . expr STORE_SUBSCR
store_subscript ::= expr expr . STORE_SUBSCR
subscript ::= expr . expr BINARY_SUBSCR
subscript ::= expr expr . BINARY_SUBSCR
subscript2 ::= expr . expr DUP_TOP_TWO BINARY_SUBSCR
subscript2 ::= expr expr . DUP_TOP_TWO BINARY_SUBSCR
suite_stmts ::= _stmts . 
testexpr ::= testfalse . 
testexpr_cf ::= testexpr . come_froms
testfalse ::= expr . jmp_false
testfalse ::= expr jmp_false . 
testfalse_not_and ::= expr . jmp_false expr jmp_true COME_FROM
testfalse_not_and ::= expr jmp_false . expr jmp_true COME_FROM
testfalse_not_and ::= expr jmp_false expr . jmp_true COME_FROM
testfalse_not_or ::= expr . jmp_false expr jmp_false COME_FROM
testfalse_not_or ::= expr jmp_false . expr jmp_false COME_FROM
testfalse_not_or ::= expr jmp_false expr . jmp_false COME_FROM
testfalsel ::= expr . jmp_true
testtrue ::= expr . jmp_true
unary_not ::= expr . UNARY_NOT
unary_op ::= expr . unary_operator
while1elsestmt ::= setup_loop . l_stmts JUMP_BACK POP_BLOCK else_suite COME_FROM_LOOP
while1elsestmt ::= setup_loop . l_stmts JUMP_BACK \e__come_froms POP_BLOCK else_suitel COME_FROM_LOOP
while1elsestmt ::= setup_loop . l_stmts JUMP_BACK _come_froms POP_BLOCK else_suitel COME_FROM_LOOP
while1elsestmt ::= setup_loop . l_stmts JUMP_BACK else_suite COME_FROM_LOOP
while1elsestmt ::= setup_loop . l_stmts JUMP_BACK else_suitel
while1stmt ::= setup_loop . l_stmts COME_FROM JUMP_BACK COME_FROM_LOOP
while1stmt ::= setup_loop . l_stmts COME_FROM JUMP_BACK POP_BLOCK COME_FROM_LOOP
while1stmt ::= setup_loop . l_stmts COME_FROM_LOOP
while1stmt ::= setup_loop . l_stmts COME_FROM_LOOP JUMP_BACK POP_BLOCK COME_FROM_LOOP
while1stmt ::= setup_loop . l_stmts POP_BLOCK COME_FROM_LOOP
whileTruestmt ::= SETUP_LOOP . l_stmts_opt JUMP_BACK COME_FROM_LOOP
whileTruestmt ::= SETUP_LOOP \e_l_stmts_opt . JUMP_BACK COME_FROM_LOOP
whileTruestmt ::= setup_loop . l_stmts_opt JUMP_BACK POP_BLOCK \e__come_froms
whileTruestmt ::= setup_loop . l_stmts_opt JUMP_BACK POP_BLOCK _come_froms
whileTruestmt ::= setup_loop \e_l_stmts_opt . JUMP_BACK POP_BLOCK \e__come_froms
whileTruestmt ::= setup_loop \e_l_stmts_opt . JUMP_BACK POP_BLOCK _come_froms
whileelsestmt ::= setup_loop . testexpr \e_l_stmts_opt JUMP_BACK POP_BLOCK else_suitel COME_FROM
whileelsestmt ::= setup_loop . testexpr \e_l_stmts_opt JUMP_BACK POP_BLOCK else_suitel COME_FROM_LOOP
whileelsestmt ::= setup_loop . testexpr l_stmts_opt JUMP_BACK POP_BLOCK else_suitel COME_FROM
whileelsestmt ::= setup_loop . testexpr l_stmts_opt JUMP_BACK POP_BLOCK else_suitel COME_FROM_LOOP
whilestmt ::= setup_loop . testexpr \e_l_stmts_opt COME_FROM JUMP_BACK POP_BLOCK COME_FROM_LOOP
whilestmt ::= setup_loop . testexpr \e_l_stmts_opt JUMP_BACK POP_BLOCK COME_FROM_LOOP
whilestmt ::= setup_loop . testexpr \e_l_stmts_opt JUMP_BACK come_froms POP_BLOCK
whilestmt ::= setup_loop . testexpr \e_l_stmts_opt JUMP_BACK come_froms POP_BLOCK COME_FROM_LOOP
whilestmt ::= setup_loop . testexpr \e_l_stmts_opt come_froms JUMP_BACK come_froms POP_BLOCK COME_FROM_LOOP
whilestmt ::= setup_loop . testexpr l_stmts_opt COME_FROM JUMP_BACK POP_BLOCK COME_FROM_LOOP
whilestmt ::= setup_loop . testexpr l_stmts_opt JUMP_BACK POP_BLOCK COME_FROM_LOOP
whilestmt ::= setup_loop . testexpr l_stmts_opt JUMP_BACK come_froms POP_BLOCK
whilestmt ::= setup_loop . testexpr l_stmts_opt JUMP_BACK come_froms POP_BLOCK COME_FROM_LOOP
whilestmt ::= setup_loop . testexpr l_stmts_opt come_froms JUMP_BACK come_froms POP_BLOCK COME_FROM_LOOP
whilestmt ::= setup_loop . testexpr returns POP_BLOCK COME_FROM_LOOP
whilestmt ::= setup_loop . testexpr returns come_froms POP_BLOCK COME_FROM_LOOP
yield ::= expr . YIELD_VALUE
yield_from ::= expr . GET_YIELD_FROM_ITER LOAD_CONST YIELD_FROM
Instruction context:
   
 L.  77        98  LOAD_CONST               None
                 100  RETURN_VALUE     
               102_0  COME_FROM            96  '96'
               102_1  COME_FROM            74  '74'
->             102_2  COME_FROM_LOOP       14  '14'
from camera import focus_on_sim, focus_on_object, shake_camera, focus_on_object_from_position, focus_on_lot, walls_up_override, focus_on_position
from interactions import ParticipantType
from interactions.utils.interaction_elements import XevtTriggeredElement
from objects.components.types import CAMERA_VIEW_COMPONENT
from sims4.tuning.tunable import TunableEnumEntry, Tunable, AutoFactoryInit, HasTunableFactory, HasTunableSingletonFactory, OptionalTunable, TunableRange, TunableRealSecond, TunablePackSafeReference
import services, sims4

class CameraFocusElement(XevtTriggeredElement, HasTunableFactory, AutoFactoryInit):
    FACTORY_TUNABLES = {'description':'\n            Focus the camera on the specified participant.\n            ', 
     'participant':TunableEnumEntry(description='\n            The participant of this interaction to focus the camera on.\n            \n            Should be some kind of object or Sim.  Can also be set to Lot\n            to do a thumbnail-style view of the lot.\n            ',
       tunable_type=ParticipantType,
       default=ParticipantType.Actor), 
     'follow':Tunable(description='\n            Whether or not the camera should stick to the focused participant.\n            ',
       tunable_type=bool,
       default=False), 
     'time_to_position':TunableRealSecond(description='\n            The amount of time given for the camera to move into position.\n            \n            Only applicable when participant type is Lot\n            ',
       default=1.0), 
     'sim_filter':OptionalTunable(description='\n            If enabled, this sim filter will be used as the camera subject \n            instead of the participant.\n            ',
       tunable=TunablePackSafeReference(description='\n                The filter used to find the desired Sim.\n                ',
       manager=(services.get_instance_manager(sims4.resources.Types.SIM_FILTER))))}

    def _do_behavior--- This code section failed: ---

 L.  63         0  LOAD_CONST               None
                2  STORE_FAST               'subject'

 L.  66         4  LOAD_FAST                'self'
                6  LOAD_ATTR                sim_filter
                8  LOAD_CONST               None
               10  COMPARE_OP               is-not
               12  POP_JUMP_IF_FALSE    76  'to 76'

 L.  67        14  SETUP_LOOP          102  'to 102'
               16  LOAD_GLOBAL              services
               18  LOAD_METHOD              sim_info_manager
               20  CALL_METHOD_0         0  '0 positional arguments'
               22  LOAD_METHOD              instanced_sims_gen
               24  CALL_METHOD_0         0  '0 positional arguments'
               26  GET_ITER         
             28_0  COME_FROM            62  '62'
               28  FOR_ITER             72  'to 72'
               30  STORE_FAST               'sim'

 L.  68        32  LOAD_GLOBAL              services
               34  LOAD_METHOD              sim_filter_service
               36  CALL_METHOD_0         0  '0 positional arguments'
               38  LOAD_ATTR                does_sim_match_filter
               40  LOAD_FAST                'sim'
               42  LOAD_ATTR                id

 L.  69        44  LOAD_FAST                'self'
               46  LOAD_ATTR                sim_filter

 L.  70        48  LOAD_LAMBDA              '<code_object <lambda>>'
               50  LOAD_STR                 'CameraFocusElement._do_behavior.<locals>.<lambda>'
               52  MAKE_FUNCTION_0          'Neither defaults, keyword-only args, annotations, nor closures'
               54  LOAD_CONST               ('sim_filter', 'gsi_source_fn')
               56  CALL_FUNCTION_KW_3     3  '3 total positional and keyword args'
               58  STORE_FAST               'matched'

 L.  71        60  LOAD_FAST                'matched'
               62  POP_JUMP_IF_FALSE    28  'to 28'

 L.  72        64  LOAD_FAST                'sim'
               66  STORE_FAST               'subject'

 L.  73        68  BREAK_LOOP       
               70  JUMP_BACK            28  'to 28'
               72  POP_BLOCK        
               74  JUMP_FORWARD        102  'to 102'
             76_0  COME_FROM            12  '12'

 L.  75        76  LOAD_FAST                'self'
               78  LOAD_ATTR                interaction
               80  LOAD_METHOD              get_participant
               82  LOAD_FAST                'self'
               84  LOAD_ATTR                participant
               86  CALL_METHOD_1         1  '1 positional argument'
               88  STORE_FAST               'subject'

 L.  76        90  LOAD_FAST                'subject'
               92  LOAD_CONST               None
               94  COMPARE_OP               is
               96  POP_JUMP_IF_FALSE   102  'to 102'

 L.  77        98  LOAD_CONST               None
              100  RETURN_VALUE     
            102_0  COME_FROM            96  '96'
            102_1  COME_FROM            74  '74'
            102_2  COME_FROM_LOOP       14  '14'

 L.  79       102  LOAD_FAST                'self'
              104  LOAD_ATTR                participant
              106  LOAD_GLOBAL              ParticipantType
              108  LOAD_ATTR                Lot
              110  COMPARE_OP               ==
              112  POP_JUMP_IF_FALSE   130  'to 130'

 L.  81       114  LOAD_GLOBAL              focus_on_lot
              116  LOAD_FAST                'self'
              118  LOAD_ATTR                time_to_position
              120  LOAD_CONST               ('lerp_time',)
              122  CALL_FUNCTION_KW_1     1  '1 total positional and keyword args'
              124  POP_TOP          

 L.  82       126  LOAD_CONST               None
              128  RETURN_VALUE     
            130_0  COME_FROM           112  '112'

 L.  84       130  LOAD_FAST                'subject'
              132  LOAD_METHOD              has_component
              134  LOAD_GLOBAL              CAMERA_VIEW_COMPONENT
              136  CALL_METHOD_1         1  '1 positional argument'
              138  POP_JUMP_IF_FALSE   162  'to 162'

 L.  85       140  LOAD_GLOBAL              focus_on_object_from_position
              142  LOAD_FAST                'subject'
              144  LOAD_ATTR                position

 L.  86       146  LOAD_FAST                'subject'
              148  LOAD_METHOD              get_camera_position
              150  CALL_METHOD_0         0  '0 positional arguments'
              152  LOAD_CONST               ('obj_position', 'camera_position')
              154  CALL_FUNCTION_KW_2     2  '2 total positional and keyword args'
              156  POP_TOP          

 L.  87       158  LOAD_CONST               None
              160  RETURN_VALUE     
            162_0  COME_FROM           138  '138'

 L.  89       162  LOAD_FAST                'subject'
              164  LOAD_ATTR                is_sim
              166  POP_JUMP_IF_FALSE   188  'to 188'

 L.  90       168  LOAD_GLOBAL              focus_on_sim
              170  LOAD_FAST                'subject'
              172  LOAD_FAST                'self'
              174  LOAD_ATTR                follow
              176  LOAD_FAST                'subject'
              178  LOAD_ATTR                client
              180  LOAD_CONST               ('sim', 'follow', 'client')
              182  CALL_FUNCTION_KW_3     3  '3 total positional and keyword args'
              184  POP_TOP          
              186  JUMP_FORWARD        234  'to 234'
            188_0  COME_FROM           166  '166'

 L.  91       188  LOAD_FAST                'subject'
              190  LOAD_METHOD              is_in_inventory
              192  CALL_METHOD_0         0  '0 positional arguments'
              194  POP_JUMP_IF_FALSE   220  'to 220'

 L.  92       196  LOAD_FAST                'subject'
              198  LOAD_ATTR                inventoryitem_component
              200  LOAD_ATTR                last_inventory_owner
              202  STORE_FAST               'inventory_owner'

 L.  93       204  LOAD_GLOBAL              focus_on_object
              206  LOAD_FAST                'inventory_owner'
              208  LOAD_FAST                'self'
              210  LOAD_ATTR                follow
              212  LOAD_CONST               ('object', 'follow')
              214  CALL_FUNCTION_KW_2     2  '2 total positional and keyword args'
              216  POP_TOP          
              218  JUMP_FORWARD        234  'to 234'
            220_0  COME_FROM           194  '194'

 L.  95       220  LOAD_GLOBAL              focus_on_object
              222  LOAD_FAST                'subject'
              224  LOAD_FAST                'self'
              226  LOAD_ATTR                follow
              228  LOAD_CONST               ('object', 'follow')
              230  CALL_FUNCTION_KW_2     2  '2 total positional and keyword args'
              232  POP_TOP          
            234_0  COME_FROM           218  '218'
            234_1  COME_FROM           186  '186'

Parse error at or near `COME_FROM_LOOP' instruction at offset 102_2


class SetWallsUpOverrideElement(XevtTriggeredElement, HasTunableFactory, AutoFactoryInit):
    FACTORY_TUNABLES = {'enable': Tunable(description='\n            Set to True to enable the override.  False to disable it.\n            \n            A user moving the camera manually will also cancel the override.\n            ',
                 tunable_type=bool,
                 default=True)}

    def _do_behavior(self):
        walls_up_override(walls_up=(self.enable))


class TunableCameraShake(HasTunableSingletonFactory, AutoFactoryInit):
    FACTORY_TUNABLES = {'duration':TunableRange(description='\n            Length of time this effect should occur, in seconds.\n            ',
       tunable_type=float,
       default=1.0,
       minimum=0.0), 
     'frequency':OptionalTunable(description='\n            The times per second that the effect should occur.\n            \n            Default value is 1.0\n            ',
       tunable=TunableRange(float, 1.0, minimum=0.0),
       disabled_name='use_default',
       enabled_name='specify'), 
     'amplitude':OptionalTunable(description='\n            Strength of the shake, in Sim meters.\n            \n            Default value is 1.0\n            ',
       tunable=TunableRange(float, 1.0, minimum=0.0),
       disabled_name='use_default',
       enabled_name='specify'), 
     'octaves':OptionalTunable(description='\n            Number of octaves for the shake.\n\n            Default value is 1\n            ',
       tunable=TunableRange(int, 1, minimum=0),
       disabled_name='use_default',
       enabled_name='specify'), 
     'fade_multiplier':OptionalTunable(description='\n            Adjusts the wave function, this can be set above 1.0 to introduce\n            a plateau for the shake effect.\n\n            Default value is 1.0\n            ',
       tunable=TunableRange(float, 1.0, minimum=1.0),
       disabled_name='use_default',
       enabled_name='specify')}

    def shake_camera(self):
        shake_camera((self.duration), frequency=(self.frequency),
          amplitude=(self.amplitude),
          octaves=(self.octaves),
          fade_multiplier=(self.fade_multiplier))
